{
  "type": "Feature",
  "properties": {
    "addr:full":"29726 Old Hwy 87 Buffalo WY 82834",
    "addr:housenumber":"29726",
    "addr:postcode":"82834",
    "addr:street":"Old Hwy 87 Buffalo Wy",
    "iso:country":"US",
    "sg:address":"29726 Old Hwy 87",
    "sg:city":"Buffalo",
    "sg:classifiers":[
        {
            "category":"Marine",
            "type":"Transportation"
        }
    ],
    "sg:phone":"+1 307 684 8665",
    "sg:postcode":"82834",
    "sg:province":"WY",
    "sg:tags":[
        "private",
        "contractor"
    ],
    "wof:name":"Jerry Wellborn",
    "wof:placetype":"venue"
},
  "geometry": {"coordinates":[-106.68779600000001,44.30878],"type":"Point"}
}