{
  "type": "Feature",
  "properties": {
    "iso:country":"US",
    "sg:address":"10580 Goose Egg Rd",
    "sg:city":"Casper",
    "sg:classifiers":[
        {
            "category":"Bars & Pubs",
            "type":"Food & Drink"
        }
    ],
    "sg:phone":"+1 307 473 8838",
    "sg:postcode":"82604",
    "sg:province":"WY",
    "sg:tags":[
        "drinking"
    ],
    "wof:name":"Goose Egg Inn",
    "wof:placetype":"venue"
},
  "geometry": {"coordinates":[-106.51999000000001,42.744458],"type":"Point"}
}