{
  "type": "Feature",
  "properties": {
    "iso:country":"US",
    "sg:address":"104 2nd St",
    "sg:city":"Ten Sleep",
    "sg:classifiers":[
        {
            "category":"Real Estate",
            "subcategory":"Real Estate Agent",
            "type":"Services"
        }
    ],
    "sg:phone":"+1 307 366 2208",
    "sg:postcode":"82442",
    "sg:province":"WY",
    "wof:name":"Hake Realty",
    "wof:placetype":"venue"
},
  "geometry": {"coordinates":[-107.45115300000001,44.033941],"type":"Point"}
}