{
  "type": "Feature",
  "properties": {
    "addr:full":"114 Monument Hill Rd Cody WY 82414",
    "addr:housenumber":"114",
    "addr:postcode":"82414",
    "addr:street":"Monument Hill Rd",
    "iso:country":"US",
    "sg:address":"114 Monument Hill Rd",
    "sg:city":"Cody",
    "sg:classifiers":[
        {
            "category":"Farming",
            "subcategory":"Livestock Farm",
            "type":"Manufacturing & Wholesale Goods"
        }
    ],
    "sg:phone":"+1 307 587 3992",
    "sg:postcode":"82414",
    "sg:province":"WY",
    "sg:tags":[
        "beef",
        "feedlot",
        "cattle"
    ],
    "wof:name":"Monument Hill Ranch",
    "wof:placetype":"venue"
},
  "geometry": {"coordinates":[-109.17503499999999,44.617464],"type":"Point"}
}