{
  "type": "Feature",
  "properties": {
    "iso:country":"US",
    "sg:address":"1409 Echeta Rd",
    "sg:city":"Gillette",
    "sg:classifiers":[
        {
            "category":"Mining & Drilling",
            "type":"Manufacturing & Wholesale Goods"
        }
    ],
    "sg:phone":"+1 307 682 0824",
    "sg:postcode":"82716",
    "sg:province":"WY",
    "sg:tags":[
        "oil",
        "well"
    ],
    "wof:name":"Gas-Tech",
    "wof:placetype":"venue"
},
  "geometry": {"coordinates":[-105.52424499999999,44.296502],"type":"Point"}
}