{
  "type": "Feature",
  "properties": {
    "addr:full":"104 Brookside Rd Wheatland WY 82201",
    "addr:housenumber":"104",
    "addr:postcode":"82201",
    "addr:street":"Brookside Rd Wheatland Wy",
    "iso:country":"US",
    "sg:address":"104 Brookside Rd",
    "sg:city":"Wheatland",
    "sg:classifiers":[
        {
            "category":"Farming",
            "subcategory":"Farm",
            "type":"Manufacturing & Wholesale Goods"
        }
    ],
    "sg:phone":"+1 307 322 2101",
    "sg:postcode":"82201",
    "sg:province":"WY",
    "sg:tags":[
        "crop",
        "general"
    ],
    "wof:name":"Ockinga Farms Inc",
    "wof:placetype":"venue"
},
  "geometry": {"coordinates":[-104.96301800000001,42.002076],"type":"Point"}
}