{
  "type": "Feature",
  "properties": {
    "iso:country":"US",
    "sg:address":"1636 S Mitchell St",
    "sg:city":"Casper",
    "sg:classifiers":[
        {
            "category":"Real Estate",
            "subcategory":"Surveying",
            "type":"Services"
        }
    ],
    "sg:phone":"+1 307 266 1624",
    "sg:postcode":"82601",
    "sg:province":"WY",
    "wof:name":"Forsythe Surveying",
    "wof:placetype":"venue"
},
  "geometry": {"coordinates":[-106.31522699999999,42.833726],"type":"Point"}
}