{
  "type": "Feature",
  "properties": {
    "addr:full":"900 S Grant St Casper WY 82601",
    "addr:housenumber":"900",
    "addr:postcode":"82601",
    "addr:street":"S Grant St",
    "iso:country":"US",
    "sg:address":"900 S Grant St",
    "sg:city":"Casper",
    "sg:classifiers":[
        {
            "category":"Organizations",
            "subcategory":"Religious Organization",
            "type":"Services"
        }
    ],
    "sg:phone":"+1 307 265 5711",
    "sg:postcode":"82601",
    "sg:province":"WY",
    "sg:tags":[
        "church"
    ],
    "wof:name":"Christ First Baptist Church",
    "wof:placetype":"venue"
},
  "geometry": {"coordinates":[-106.31957300000001,42.841792],"type":"Point"}
}