{
  "type": "Feature",
  "properties": {
    "iso:country":"US",
    "sg:address":"119 N Wheatland Hwy",
    "sg:city":"Wheatland",
    "sg:classifiers":[
        {
            "category":"Utilities",
            "subcategory":"Water",
            "type":"Services"
        }
    ],
    "sg:phone":"+1 307 322 9678",
    "sg:postcode":"82201",
    "sg:province":"WY",
    "sg:tags":[
        "system",
        "supply"
    ],
    "wof:name":"Price Pump Co",
    "wof:placetype":"venue"
},
  "geometry": {"coordinates":[-104.95166999999999,42.084309],"type":"Point"}
}