{
  "type": "Feature",
  "properties": {
    "iso:country":"US",
    "sg:address":"2486 Tranquility Rd",
    "sg:city":"Cheyenne",
    "sg:classifiers":[
        {
            "category":"Professional",
            "subcategory":"Business Services",
            "type":"Services"
        }
    ],
    "sg:phone":"+1 307 635 3531",
    "sg:postcode":"82009",
    "sg:province":"WY",
    "wof:name":"Bilstad and Lyman",
    "wof:placetype":"venue"
},
  "geometry": {"coordinates":[-104.78320100000001,41.178102],"type":"Point"}
}