{
  "type": "Feature",
  "properties": {
    "addr:full":"3777 Airport Pkwy Casper WY 82604",
    "addr:housenumber":"3777",
    "addr:postcode":"82604",
    "addr:street":"Airport Pkwy",
    "iso:country":"US",
    "sg:address":"3777 Airport Pkwy",
    "sg:city":"Casper",
    "sg:classifiers":[
        {
            "category":"Government",
            "subcategory":"Office",
            "type":"Public Place"
        }
    ],
    "sg:phone":"+1 307 472 8900",
    "sg:postcode":"82604",
    "sg:province":"WY",
    "sg:tags":[
        "station",
        "flight"
    ],
    "wof:name":"Automated Flight Service Stn",
    "wof:placetype":"venue"
},
  "geometry": {"coordinates":[-106.4628,42.893543],"type":"Point"}
}