{
  "type": "Feature",
  "properties": {
    "iso:country":"US",
    "sg:address":"473 E South St",
    "sg:city":"Powell",
    "sg:classifiers":[
        {
            "category":"Building & Trades",
            "subcategory":"Plumbing",
            "type":"Services"
        }
    ],
    "sg:phone":"+1 307 754 3978",
    "sg:postcode":"82435",
    "sg:province":"WY",
    "sg:tags":[
        "plumbing",
        "contractor"
    ],
    "wof:name":"4-H Plumbing & Heating",
    "wof:placetype":"venue"
},
  "geometry": {"coordinates":[-108.753264,44.750736],"type":"Point"}
}