{
  "type": "Feature",
  "properties": {
    "iso:country":"US",
    "sg:address":"286 Middle Prong Rd",
    "sg:city":"Gillette",
    "sg:classifiers":[
        {
            "category":"Farming",
            "subcategory":"Livestock Farm",
            "type":"Manufacturing & Wholesale Goods"
        }
    ],
    "sg:phone":"+1 307 682 9668",
    "sg:postcode":"82716",
    "sg:province":"WY",
    "sg:tags":[
        "animal",
        "general"
    ],
    "wof:name":"Wild Cat Water Well Service",
    "wof:placetype":"venue"
},
  "geometry": {"coordinates":[-105.74636599999999,44.614304],"type":"Point"}
}