{
  "type": "Feature",
  "properties": {
    "iso:country":"US",
    "sg:address":"21 Cozad Rd",
    "sg:city":"Wheatland",
    "sg:classifiers":[
        {
            "category":"Building & Trades",
            "subcategory":"Construction",
            "type":"Services"
        }
    ],
    "sg:phone":"+1 307 322 9139",
    "sg:postcode":"82201",
    "sg:province":"WY",
    "sg:tags":[
        "house",
        "family"
    ],
    "wof:name":"Gary Weber Building and Dev",
    "wof:placetype":"venue"
},
  "geometry": {"coordinates":[-104.958643,42.030809],"type":"Point"}
}