{
  "type": "Feature",
  "properties": {
    "iso:country":"US",
    "sg:address":"2406 Hillcrest Dr",
    "sg:city":"Gillette",
    "sg:classifiers":[
        {
            "category":"Insurance",
            "subcategory":"Insurance Agent",
            "type":"Services"
        }
    ],
    "sg:phone":"+1 307 686 3700",
    "sg:postcode":"82718",
    "sg:province":"WY",
    "wof:name":"Biggerstaff Insurance",
    "wof:placetype":"venue"
},
  "geometry": {"coordinates":[-105.525936,44.273558],"type":"Point"}
}