{
  "type": "Feature",
  "properties": {
    "iso:country":"US",
    "sg:address":"1511 Mydland Rd",
    "sg:city":"Sheridan",
    "sg:classifiers":[
        {
            "category":"Professional",
            "subcategory":"Business Services",
            "type":"Services"
        }
    ],
    "sg:phone":"+1 307 674 6388",
    "sg:postcode":"82801",
    "sg:province":"WY",
    "sg:tags":[
        "embroidery"
    ],
    "wof:name":"Watermelon Patch Embroidery",
    "wof:placetype":"venue"
},
  "geometry": {"coordinates":[-106.98755199999999,44.814417],"type":"Point"}
}