{
  "type": "Feature",
  "properties": {
    "iso:country":"US",
    "sg:address":"111 S Durbin St",
    "sg:city":"Casper",
    "sg:classifiers":[
        {
            "category":"Professional",
            "subcategory":"Research",
            "type":"Services"
        }
    ],
    "sg:phone":"+1 307 235 3421",
    "sg:postcode":"82601",
    "sg:province":"WY",
    "sg:tags":[
        "organization",
        "philanthropic",
        "noncommercial",
        "foundation"
    ],
    "wof:name":"Jason's Friends Foundation",
    "wof:placetype":"venue"
},
  "geometry": {"coordinates":[-106.322255,42.84886],"type":"Point"}
}