{
  "type": "Feature",
  "properties": {
    "addr:full":"799 Ln 9 Powell WY 82435",
    "addr:housenumber":"9",
    "addr:postcode":"82435",
    "addr:street":"799 Ln;Powell Wy",
    "iso:country":"US",
    "sg:address":"799 Ln 9",
    "sg:city":"Powell",
    "sg:classifiers":[
        {
            "category":"Mining & Drilling",
            "type":"Manufacturing & Wholesale Goods"
        }
    ],
    "sg:phone":"+1 307 754 5613",
    "sg:postcode":"82435",
    "sg:province":"WY",
    "sg:tags":[
        "field",
        "oil"
    ],
    "wof:name":"Tri County Pump Svc",
    "wof:placetype":"venue"
},
  "geometry": {"coordinates":[-108.771975,44.753768],"type":"Point"}
}