{
  "type": "Feature",
  "properties": {
    "iso:country":"US",
    "sg:address":"701 Sioux Ave",
    "sg:city":"Gillette",
    "sg:classifiers":[
        {
            "category":"Retail",
            "subcategory":"Repair Shop",
            "type":"Services"
        }
    ],
    "sg:phone":"+1 307 682 7659",
    "sg:postcode":"82718",
    "sg:province":"WY",
    "sg:tags":[
        "welding"
    ],
    "wof:name":"P E Fusion",
    "wof:placetype":"venue"
},
  "geometry": {"coordinates":[-105.49485799999999,44.259394],"type":"Point"}
}