{
  "type": "Feature",
  "properties": {
    "iso:country":"US",
    "sg:address":"517 Grant St",
    "sg:city":"Belle Fourche",
    "sg:classifiers":[
        {
            "category":"Health Services",
            "subcategory":"Chiropractor",
            "type":"Services"
        }
    ],
    "sg:phone":"+1 605 892 4909",
    "sg:postcode":"57717",
    "sg:province":"WY",
    "wof:name":"Stinton Chiropractic Clinic",
    "wof:placetype":"venue"
},
  "geometry": {"coordinates":[-103.853403,44.672541],"type":"Point"}
}