{
  "type": "Feature",
  "properties": {
    "iso:country":"US",
    "sg:address":"484 Fern Rd",
    "sg:city":"Evanston",
    "sg:classifiers":[
        {
            "category":"Mining & Drilling",
            "type":"Manufacturing & Wholesale Goods"
        }
    ],
    "sg:phone":"+1 307 789 2122",
    "sg:postcode":"82930",
    "sg:province":"WY",
    "sg:tags":[
        "field",
        "oil"
    ],
    "wof:name":"LJE",
    "wof:placetype":"venue"
},
  "geometry": {"coordinates":[-111.005009,41.361739],"type":"Point"}
}