{
  "type": "Feature",
  "properties": {
    "addr:full":"1901 Energy Ct Gillette WY 82718",
    "addr:housenumber":"1901",
    "addr:postcode":"82718",
    "addr:street":"Energy Ct",
    "iso:country":"US",
    "sg:address":"1901 Energy Ct",
    "sg:city":"Gillette",
    "sg:classifiers":[
        {
            "category":"Government",
            "subcategory":"Office",
            "type":"Public Place"
        }
    ],
    "sg:phone":"+1 307 682 2918",
    "sg:postcode":"82718",
    "sg:province":"WY",
    "sg:tags":[
        "state",
        "resource"
    ],
    "wof:name":"Developmental Disabilities",
    "wof:placetype":"venue"
},
  "geometry": {"coordinates":[-105.49254000000001,44.27727],"type":"Point"}
}