{
  "type": "Feature",
  "properties": {
    "iso:country":"US",
    "sg:address":"110 Ta Bi Dr",
    "sg:city":"Worland",
    "sg:classifiers":[
        {
            "category":"Retail",
            "subcategory":"Repair Shop",
            "type":"Services"
        }
    ],
    "sg:phone":"+1 307 347 9404",
    "sg:postcode":"82401",
    "sg:province":"WY",
    "sg:tags":[
        "lock",
        "locksmith"
    ],
    "wof:name":"Bill's Lock & Key",
    "wof:placetype":"venue"
},
  "geometry": {"coordinates":[-107.951976,43.980942],"type":"Point"}
}