{
  "type": "Feature",
  "properties": {
    "iso:country":"US",
    "sg:address":"7197 W Derick Dr",
    "sg:city":"Casper",
    "sg:classifiers":[
        {
            "category":"Manufacturing",
            "subcategory":"Metals",
            "type":"Manufacturing & Wholesale Goods"
        }
    ],
    "sg:phone":"+1 307 472 5757",
    "sg:postcode":"82604",
    "sg:province":"WY",
    "sg:tags":[
        "oilfield"
    ],
    "wof:name":"Dresser Industries",
    "wof:placetype":"venue"
},
  "geometry": {"coordinates":[-106.430734,42.872108],"type":"Point"}
}