{
  "type": "Feature",
  "properties": {
    "iso:country":"US",
    "sg:address":"409 6th St",
    "sg:city":"Rawlins",
    "sg:classifiers":[
        {
            "category":"Professional",
            "subcategory":"Computer Services",
            "type":"Services"
        }
    ],
    "sg:phone":"+1 307 324 2286",
    "sg:postcode":"82301",
    "sg:province":"WY",
    "sg:tags":[
        "internet"
    ],
    "wof:name":"Bresnan Communications",
    "wof:placetype":"venue"
},
  "geometry": {"coordinates":[-107.242153,41.789682],"type":"Point"}
}