{
  "type": "Feature",
  "properties": {
    "iso:country":"US",
    "sg:address":"220 E Main St",
    "sg:city":"Riverton",
    "sg:classifiers":[
        {
            "category":"Home & Garden",
            "subcategory":"Carpets & Floor Coverings",
            "type":"Retail Goods"
        }
    ],
    "sg:phone":"+1 307 856 8697",
    "sg:postcode":"82501",
    "sg:province":"WY",
    "sg:tags":[
        "wall",
        "window",
        "material"
    ],
    "wof:name":"Gale's Carpet One",
    "wof:placetype":"venue"
},
  "geometry": {"coordinates":[-108.38901300000001,43.024712],"type":"Point"}
}