{
  "type": "Feature",
  "properties": {
    "addr:full":"1021 Pulliam Ave Worland WY 82401",
    "addr:housenumber":"1021",
    "addr:postcode":"82401",
    "addr:street":"Pulliam Ave",
    "iso:country":"US",
    "sg:address":"1021 Pulliam Ave",
    "sg:city":"Worland",
    "sg:classifiers":[
        {
            "category":"Manufacturing",
            "subcategory":"Signs",
            "type":"Manufacturing & Wholesale Goods"
        }
    ],
    "sg:phone":"+1 307 347 8645",
    "sg:postcode":"82401",
    "sg:province":"WY",
    "sg:website":"www.sos-inc.org",
    "wof:name":"Sutherland's",
    "wof:placetype":"venue"
},
  "geometry": {"coordinates":[-107.95557100000001,44.018959],"type":"Point"}
}