{
  "type": "Feature",
  "properties": {
    "addr:full":"100 Wright St Thayne WY 83127",
    "addr:housenumber":"100",
    "addr:postcode":"83127",
    "addr:street":"Wright St Thayne Wy",
    "iso:country":"US",
    "sg:address":"100 Wright St",
    "sg:city":"Thayne",
    "sg:classifiers":[
        {
            "category":"Restaurant",
            "type":"Food & Drink"
        }
    ],
    "sg:phone":"+1 307 883 5050",
    "sg:postcode":"83127",
    "sg:province":"WY",
    "wof:name":"Tootsies Take Or Bake Pizza",
    "wof:placetype":"venue"
},
  "geometry": {"coordinates":[-111.00134,42.92048],"type":"Point"}
}