{
  "type": "Feature",
  "properties": {
    "addr:full":"640 Par Dr Gillette WY 82718",
    "addr:housenumber":"640",
    "addr:postcode":"82718",
    "addr:street":"Par Dr",
    "iso:country":"US",
    "sg:address":"640 Par Dr",
    "sg:city":"Gillette",
    "sg:classifiers":[
        {
            "category":"Real Estate",
            "subcategory":"Developer",
            "type":"Services"
        }
    ],
    "sg:phone":"+1 307 686 7631",
    "sg:postcode":"82718",
    "sg:province":"WY",
    "wof:name":"Cambria Development LLC",
    "wof:placetype":"venue"
},
  "geometry": {"coordinates":[-105.55614199999999,44.288954],"type":"Point"}
}