{
  "type": "Feature",
  "properties": {
    "iso:country":"US",
    "sg:address":"745 W Main St",
    "sg:city":"Lander",
    "sg:classifiers":[
        {
            "category":"Wholesale",
            "subcategory":"Medical Equipment & Supplies",
            "type":"Manufacturing & Wholesale Goods"
        }
    ],
    "sg:phone":"+1 307 335 7015",
    "sg:postcode":"82520",
    "sg:province":"WY",
    "sg:tags":[
        "physician",
        "surgeon"
    ],
    "wof:name":"Mc Rae's Downtown",
    "wof:placetype":"venue"
},
  "geometry": {"coordinates":[-108.745088,42.840561],"type":"Point"}
}