{
  "type": "Feature",
  "properties": {
    "addr:full":"1501 16th St Wheatland WY 82201",
    "addr:housenumber":"1501",
    "addr:postcode":"82201",
    "addr:street":"16Th St Wheatland Wy",
    "iso:country":"US",
    "sg:address":"1501 16th St",
    "sg:city":"Wheatland",
    "sg:classifiers":[
        {
            "category":"Autos & Motor Vehicles",
            "subcategory":"Auto Supplies",
            "type":"Retail Goods"
        }
    ],
    "sg:phone":"+1 307 322 3111",
    "sg:postcode":"82201",
    "sg:province":"WY",
    "sg:tags":[
        "parts"
    ],
    "wof:name":"NAPA Auto Parts",
    "wof:placetype":"venue"
},
  "geometry": {"coordinates":[-104.96308000000001,42.0625],"type":"Point"}
}