{
  "type": "Feature",
  "properties": {
    "iso:country":"US",
    "sg:address":"930 S Elm St",
    "sg:city":"Casper",
    "sg:classifiers":[
        {
            "category":"Education",
            "subcategory":"School",
            "type":"Public Place"
        }
    ],
    "sg:phone":"+1 307 577 0330",
    "sg:postcode":"82601",
    "sg:province":"WY",
    "wof:name":"Natrona County Sr High School",
    "wof:placetype":"venue"
},
  "geometry": {"coordinates":[-106.329376,42.840698],"type":"Point"}
}