{
  "type": "Feature",
  "properties": {
    "addr:full":"1621 Snyder Ave Cheyenne WY 82001",
    "addr:housenumber":"1621",
    "addr:postcode":"82001",
    "addr:street":"Snyder Ave",
    "iso:country":"US",
    "sg:address":"1621 Snyder Ave",
    "sg:city":"Cheyenne",
    "sg:classifiers":[
        {
            "category":"Retail",
            "subcategory":"Car Wash",
            "type":"Services"
        }
    ],
    "sg:phone":"+1 307 635 8043",
    "sg:postcode":"82001",
    "sg:province":"WY",
    "sg:tags":[
        "polishing",
        "washing"
    ],
    "wof:name":"Easy Way Car Wash",
    "wof:placetype":"venue"
},
  "geometry": {"coordinates":[-104.823493,41.130543],"type":"Point"}
}