{
  "type": "Feature",
  "properties": {
    "addr:full":"3808 Collins Rd Gillette WY 82718",
    "addr:housenumber":"3808",
    "addr:postcode":"82718",
    "addr:street":"Collins Rd",
    "iso:country":"US",
    "sg:address":"3808 Collins Rd",
    "sg:city":"Gillette",
    "sg:classifiers":[
        {
            "category":"Wholesale",
            "subcategory":"Machinery & Supplies",
            "type":"Manufacturing & Wholesale Goods"
        },
        {
            "category":"Autos & Motor Vehicles",
            "subcategory":"Recreational Vehicle Sales",
            "type":"Retail Goods"
        }
    ],
    "sg:phone":"+1 307 682 1492",
    "sg:postcode":"82718",
    "sg:province":"WY",
    "sg:tags":[
        "industrial",
        "cap",
        "equipment",
        "shell",
        "truck",
        "canopy"
    ],
    "wof:name":"Trucks & Industrial Supply Inc",
    "wof:placetype":"venue"
},
  "geometry": {"coordinates":[-105.448785,44.289901],"type":"Point"}
}