{
  "type": "Feature",
  "properties": {
    "iso:country":"US",
    "sg:address":"3915 Gannett St",
    "sg:city":"Casper",
    "sg:classifiers":[
        {
            "category":"Professional",
            "subcategory":"Detective & Security Services",
            "type":"Services"
        }
    ],
    "sg:phone":"+1 307 259 8668",
    "sg:postcode":"82609",
    "sg:province":"WY",
    "sg:tags":[
        "guard"
    ],
    "wof:name":"Kirk Buchholz",
    "wof:placetype":"venue"
},
  "geometry": {"coordinates":[-106.27103200000001,42.846671],"type":"Point"}
}