{
  "type": "Feature",
  "properties": {
    "addr:full":"334 Second West Pkwy Sheridan WY 82801",
    "addr:housenumber":"334",
    "addr:postcode":"82801",
    "addr:street":"Second West Pkwy Sheridan Wy",
    "iso:country":"US",
    "sg:address":"334 Second West Pkwy",
    "sg:city":"Sheridan",
    "sg:classifiers":[
        {
            "category":"Building & Trades",
            "subcategory":"Electrical",
            "type":"Services"
        }
    ],
    "sg:phone":"+1 307 673 1176",
    "sg:postcode":"82801",
    "sg:province":"WY",
    "sg:tags":[
        "electrical",
        "contractor"
    ],
    "wof:name":"Mountain West Electric LLC",
    "wof:placetype":"venue"
},
  "geometry": {"coordinates":[-106.98162600000001,44.80085],"type":"Point"}
}