{
  "type": "Feature",
  "properties": {
    "addr:full":"595 Uinta Dr Green River WY 82935",
    "addr:housenumber":"595",
    "addr:postcode":"82935",
    "addr:street":"Uinta Dr Green",
    "iso:country":"US",
    "sg:address":"595 Uinta Dr",
    "sg:city":"Green River",
    "sg:classifiers":[
        {
            "category":"Wholesale",
            "subcategory":"Machinery & Supplies",
            "type":"Manufacturing & Wholesale Goods"
        }
    ],
    "sg:phone":"+1 307 875 5200",
    "sg:postcode":"82935",
    "sg:province":"WY",
    "sg:tags":[
        "pump"
    ],
    "wof:name":"Power Service Inc",
    "wof:placetype":"venue"
},
  "geometry": {"coordinates":[-109.471732,41.513667],"type":"Point"}
}