{
  "type": "Feature",
  "properties": {
    "iso:country":"US",
    "sg:address":"2313 Soldier Springs Rd",
    "sg:city":"Laramie",
    "sg:classifiers":[
        {
            "category":"Travel",
            "subcategory":"Hotels & Motels",
            "type":"Entertainment"
        }
    ],
    "sg:phone":"+1 307 745 8424",
    "sg:postcode":"82070",
    "sg:province":"WY",
    "wof:name":"ERS Investment Inc",
    "wof:placetype":"venue"
},
  "geometry": {"coordinates":[-105.59318399999999,41.295368],"type":"Point"}
}