{
  "type": "Feature",
  "properties": {
    "addr:full":"205 Cottonwood Ln Gillette WY 82718",
    "addr:housenumber":"205",
    "addr:postcode":"82718",
    "addr:street":"Cottonwood Ln",
    "iso:country":"US",
    "sg:address":"205 Cottonwood Ln",
    "sg:city":"Gillette",
    "sg:classifiers":[
        {
            "category":"Shopping",
            "subcategory":"Gifts & Souvenirs",
            "type":"Retail Goods"
        }
    ],
    "sg:phone":"+1 307 682 2721",
    "sg:postcode":"82718",
    "sg:province":"WY",
    "wof:name":"Specialty Crafts Gifts",
    "wof:placetype":"venue"
},
  "geometry": {"coordinates":[-105.505954,44.277965],"type":"Point"}
}