{
  "type": "Feature",
  "properties": {
    "iso:country":"US",
    "sg:address":"125 Fairway Dr",
    "sg:city":"Riverton",
    "sg:classifiers":[
        {
            "category":"Professional",
            "subcategory":"Business Services",
            "type":"Services"
        }
    ],
    "sg:phone":"+1 307 857 3022",
    "sg:postcode":"82501",
    "sg:province":"WY",
    "wof:name":"Blue Rock Venture L L C",
    "wof:placetype":"venue"
},
  "geometry": {"coordinates":[-108.452956,43.023078],"type":"Point"}
}