{
  "type": "Feature",
  "properties": {
    "iso:country":"US",
    "sg:address":"3755 Moose Wilson Rd",
    "sg:city":"Wilson",
    "sg:classifiers":[
        {
            "category":"Travel",
            "subcategory":"Hotels & Motels",
            "type":"Entertainment"
        }
    ],
    "sg:phone":"+1 307 733 1981",
    "sg:postcode":"83014",
    "sg:province":"WY",
    "wof:name":"Painted Porch",
    "wof:placetype":"venue"
},
  "geometry": {"coordinates":[-110.84317,43.512453],"type":"Point"}
}