{
  "type": "Feature",
  "properties": {
    "addr:full":"707 Clarion Dr Gillette WY 82718",
    "addr:housenumber":"707",
    "addr:postcode":"82718",
    "addr:street":"Clarion Dr",
    "iso:country":"US",
    "sg:address":"707 Clarion Dr",
    "sg:city":"Gillette",
    "sg:classifiers":[
        {
            "category":"Freight",
            "type":"Transportation"
        }
    ],
    "sg:phone":"+1 307 682 6807",
    "sg:postcode":"82718",
    "sg:province":"WY",
    "sg:tags":[
        "operator",
        "local",
        "trucking"
    ],
    "wof:name":"High Desert Hotshot Service A",
    "wof:placetype":"venue"
},
  "geometry": {"coordinates":[-105.550566,44.28784],"type":"Point"}
}