{
  "type": "Feature",
  "properties": {
    "iso:country":"US",
    "sg:address":"1230 W 30th St",
    "sg:city":"Casper",
    "sg:classifiers":[
        {
            "category":"Building & Trades",
            "subcategory":"Construction",
            "type":"Services"
        }
    ],
    "sg:phone":"+1 307 234 5590",
    "sg:postcode":"82601",
    "sg:province":"WY",
    "sg:tags":[
        "general",
        "contractor"
    ],
    "wof:name":"Brownell Construction",
    "wof:placetype":"venue"
},
  "geometry": {"coordinates":[-106.3411,42.81892],"type":"Point"}
}