{
  "type": "Feature",
  "properties": {
    "addr:full":"1107 N Main St Sheridan WY 82801",
    "addr:housenumber":"1107",
    "addr:postcode":"82801",
    "addr:street":"N Main St",
    "iso:country":"US",
    "sg:address":"1107 N Main St",
    "sg:city":"Sheridan",
    "sg:classifiers":[
        {
            "category":"Home & Garden",
            "subcategory":"Building Materials",
            "type":"Retail Goods"
        }
    ],
    "sg:phone":"+1 307 673 1135",
    "sg:postcode":"82801",
    "sg:province":"WY",
    "sg:tags":[
        "windows"
    ],
    "wof:name":"Pella Window Store",
    "wof:placetype":"venue"
},
  "geometry": {"coordinates":[-106.95551500000001,44.809848],"type":"Point"}
}