{
  "type": "Feature",
  "properties": {
    "addr:full":"1975 Old Salt Creek Hwy Casper WY 82601",
    "addr:housenumber":"1975",
    "addr:postcode":"82601",
    "addr:street":"Old Salt Creek Hwy",
    "iso:country":"US",
    "sg:address":"1975 Old Salt Creek Hwy",
    "sg:city":"Casper",
    "sg:classifiers":[
        {
            "category":"Building & Trades",
            "subcategory":"Construction",
            "type":"Services"
        }
    ],
    "sg:phone":"+1 307 235 5690",
    "sg:postcode":"82601",
    "sg:province":"WY",
    "sg:tags":[
        "general",
        "contractor"
    ],
    "wof:name":"Caspar Building Systems Inc",
    "wof:placetype":"venue"
},
  "geometry": {"coordinates":[-106.353623,42.87666],"type":"Point"}
}