{
  "type": "Feature",
  "properties": {
    "iso:country":"US",
    "sg:address":"300 E Prosser Rd",
    "sg:city":"Cheyenne",
    "sg:classifiers":[
        {
            "category":"Building & Trades",
            "subcategory":"Construction",
            "type":"Services"
        }
    ],
    "sg:phone":"+1 307 637 4235",
    "sg:postcode":"82007",
    "sg:province":"WY",
    "sg:tags":[
        "concrete",
        "contractor"
    ],
    "wof:name":"Jerry Garcia Concrete Inc",
    "wof:placetype":"venue"
},
  "geometry": {"coordinates":[-104.798631,41.106011],"type":"Point"}
}