{
  "type": "Feature",
  "properties": {
    "iso:country":"US",
    "sg:address":"2509 E Monroe Ave",
    "sg:city":"Riverton",
    "sg:classifiers":[
        {
            "category":"Professional",
            "subcategory":"Business Services",
            "type":"Services"
        }
    ],
    "sg:phone":"+1 307 856 9302",
    "sg:postcode":"82501",
    "sg:province":"WY",
    "sg:tags":[
        "water",
        "treatment"
    ],
    "wof:name":"Culligan Water Conditioning",
    "wof:placetype":"venue"
},
  "geometry": {"coordinates":[-108.358367,43.019469],"type":"Point"}
}