{
  "type": "Feature",
  "properties": {
    "iso:country":"US",
    "sg:address":"1725 Sheridan Ave",
    "sg:city":"Cody",
    "sg:classifiers":[
        {
            "category":"Health Services",
            "subcategory":"Clinic",
            "type":"Services"
        }
    ],
    "sg:phone":"+1 307 587 4601",
    "sg:postcode":"82414",
    "sg:province":"WY",
    "sg:tags":[
        "home"
    ],
    "wof:name":"Hands 2 Help",
    "wof:placetype":"venue"
},
  "geometry": {"coordinates":[-109.05159,44.52614],"type":"Point"}
}