{
  "type": "Feature",
  "properties": {
    "addr:full":"2 N Main St Sheridan WY 82801",
    "addr:housenumber":"2",
    "addr:postcode":"82801",
    "addr:street":"N Main St",
    "iso:country":"US",
    "sg:address":"2 N Main St",
    "sg:city":"Sheridan",
    "sg:classifiers":[
        {
            "category":"Restaurant",
            "type":"Food & Drink"
        }
    ],
    "sg:phone":"+1 307 672 2224",
    "sg:postcode":"82801",
    "sg:province":"WY",
    "wof:name":"Taco Bell",
    "wof:placetype":"venue"
},
  "geometry": {"coordinates":[-106.95581,44.79814],"type":"Point"}
}