{
  "type": "Feature",
  "properties": {
    "iso:country":"US",
    "sg:address":"320 S Gillette Ave",
    "sg:city":"Gillette",
    "sg:classifiers":[
        {
            "category":"Food & Beverages",
            "subcategory":"Specialty",
            "type":"Retail Goods"
        }
    ],
    "sg:phone":"+1 307 682 7228",
    "sg:postcode":"82716",
    "sg:province":"WY",
    "sg:tags":[
        "health",
        "diet"
    ],
    "wof:name":"Jessen & Assoc",
    "wof:placetype":"venue"
},
  "geometry": {"coordinates":[-105.504047,44.291998],"type":"Point"}
}