{
  "type": "Feature",
  "properties": {
    "iso:country":"US",
    "sg:address":"610 S 6th St",
    "sg:city":"Thermopolis",
    "sg:classifiers":[
        {
            "category":"Manufacturing",
            "subcategory":"Printing",
            "type":"Manufacturing & Wholesale Goods"
        }
    ],
    "sg:phone":"+1 307 864 2133",
    "sg:postcode":"82443",
    "sg:province":"WY",
    "sg:tags":[
        "publisher"
    ],
    "wof:name":"Eastmans' Journal",
    "wof:placetype":"venue"
},
  "geometry": {"coordinates":[-108.212228,43.64043],"type":"Point"}
}