{
  "type": "Feature",
  "properties": {
    "addr:full":"100 E 2nd St Casper WY 82601",
    "addr:housenumber":"100",
    "addr:postcode":"82601",
    "addr:street":"E 2Nd St",
    "iso:country":"US",
    "sg:address":"100 E 2nd St",
    "sg:city":"Casper",
    "sg:classifiers":[
        {
            "category":"Restaurant",
            "type":"Food & Drink"
        }
    ],
    "sg:phone":"+1 307 266 3647",
    "sg:postcode":"82601",
    "sg:province":"WY",
    "sg:website":"www.wyomovies.com",
    "wof:name":"Movie Palace Inc",
    "wof:placetype":"venue"
},
  "geometry": {"coordinates":[-106.32375999999999,42.84872],"type":"Point"}
}