{
  "type": "Feature",
  "properties": {
    "iso:country":"US",
    "sg:address":"149 Stockyard Rd",
    "sg:city":"Buffalo",
    "sg:classifiers":[
        {
            "category":"Government",
            "subcategory":"Office",
            "type":"Public Place"
        },
        {
            "category":"Manufacturing",
            "subcategory":"Tools & Machinery",
            "type":"Manufacturing & Wholesale Goods"
        }
    ],
    "sg:phone":"+1 307 684 9010",
    "sg:postcode":"82834",
    "sg:province":"WY",
    "sg:tags":[
        "industry",
        "village",
        "mac",
        "mfg"
    ],
    "wof:name":"Buffalo City Waste Water Plant",
    "wof:placetype":"venue"
},
  "geometry": {"coordinates":[-106.67578899999999,44.349058],"type":"Point"}
}