{
  "type": "Feature",
  "properties": {
    "iso:country":"US",
    "sg:address":"2470 Dell Range Blvd",
    "sg:city":"Cheyenne",
    "sg:classifiers":[
        {
            "category":"Retail",
            "subcategory":"Auto Rental",
            "type":"Services"
        }
    ],
    "sg:phone":"+1 307 637 7066",
    "sg:postcode":"82009",
    "sg:province":"WY",
    "sg:tags":[
        "truck"
    ],
    "wof:name":"Ryder",
    "wof:placetype":"venue"
},
  "geometry": {"coordinates":[-104.780457,41.160239],"type":"Point"}
}