{
  "type": "Feature",
  "properties": {
    "iso:country":"US",
    "sg:address":"901 Trona Dr",
    "sg:city":"Green River",
    "sg:classifiers":[
        {
            "category":"Organizations",
            "subcategory":"Religious Organization",
            "type":"Services"
        }
    ],
    "sg:phone":"+1 307 875 2598",
    "sg:postcode":"82935",
    "sg:province":"WY",
    "wof:name":"Emmanuel Lutheran Church",
    "wof:placetype":"venue"
},
  "geometry": {"coordinates":[-109.47729,41.5363],"type":"Point"}
}