{
  "type": "Feature",
  "properties": {
    "iso:country":"US",
    "sg:address":"511 W Rams Horn St",
    "sg:city":"Dubois",
    "sg:classifiers":[
        {
            "category":"Travel",
            "subcategory":"Hotels & Motels",
            "type":"Entertainment"
        }
    ],
    "sg:phone":"+1 307 455 2540",
    "sg:postcode":"82513",
    "sg:province":"WY",
    "sg:website":"www.trailsendmotel.com",
    "wof:name":"Trail's End Motel",
    "wof:placetype":"venue"
},
  "geometry": {"coordinates":[-109.64017800000001,43.53543],"type":"Point"}
}