{
  "type": "Feature",
  "properties": {
    "addr:full":"328 E 3rd St Powell WY 82435",
    "addr:housenumber":"328",
    "addr:postcode":"82435",
    "addr:street":"E 3Rd St Powell Wy",
    "iso:country":"US",
    "sg:address":"328 E 3rd St",
    "sg:city":"Powell",
    "sg:classifiers":[
        {
            "category":"Education",
            "subcategory":"School",
            "type":"Public Place"
        }
    ],
    "sg:phone":"+1 307 754 2842",
    "sg:postcode":"82435",
    "sg:province":"WY",
    "wof:name":"Powell High School",
    "wof:placetype":"venue"
},
  "geometry": {"coordinates":[-108.755673,44.755429],"type":"Point"}
}