{
  "type": "Feature",
  "properties": {
    "iso:country":"US",
    "sg:address":"820 N 1 St",
    "sg:city":"Riverton",
    "sg:classifiers":[
        {
            "category":"Real Estate",
            "subcategory":"Real Estate Operator",
            "type":"Services"
        }
    ],
    "sg:phone":"+1 307 856 3514",
    "sg:postcode":"82501",
    "sg:province":"WY",
    "sg:tags":[
        "apartment"
    ],
    "wof:name":"Riverton Manor Apartments",
    "wof:placetype":"venue"
},
  "geometry": {"coordinates":[-108.39072899999999,43.031584],"type":"Point"}
}