{
  "type": "Feature",
  "properties": {
    "iso:country":"US",
    "sg:address":"710 Pulliam Ave",
    "sg:city":"Worland",
    "sg:classifiers":[
        {
            "category":"Manufacturing",
            "subcategory":"Signs",
            "type":"Manufacturing & Wholesale Goods"
        }
    ],
    "sg:phone":"+1 307 347 6263",
    "sg:postcode":"82401",
    "sg:province":"WY",
    "wof:name":"Askew Sign Co",
    "wof:placetype":"venue"
},
  "geometry": {"coordinates":[-107.95977000000001,44.01883],"type":"Point"}
}