{
  "type": "Feature",
  "properties": {
    "addr:full":"914 Jefferson St Douglas WY 82633",
    "addr:housenumber":"914",
    "addr:postcode":"82633",
    "addr:street":"Jefferson St Douglas Wy",
    "iso:country":"US",
    "sg:address":"914 Jefferson St",
    "sg:city":"Douglas",
    "sg:classifiers":[
        {
            "category":"Shopping",
            "type":"Retail Goods"
        }
    ],
    "sg:phone":"+1 307 358 3871",
    "sg:postcode":"82633",
    "sg:province":"WY",
    "sg:tags":[
        "fire",
        "extinguisher",
        "sales"
    ],
    "wof:name":"Tri County Fire & Safety",
    "wof:placetype":"venue"
},
  "geometry": {"coordinates":[-105.377725,42.748002],"type":"Point"}
}