{
  "type": "Feature",
  "properties": {
    "iso:country":"US",
    "sg:address":"5142 Sycamore Rd",
    "sg:city":"Cheyenne",
    "sg:classifiers":[
        {
            "category":"Building & Trades",
            "subcategory":"Construction",
            "type":"Services"
        }
    ],
    "sg:phone":"+1 307 778 4901",
    "sg:postcode":"82009",
    "sg:province":"WY",
    "sg:tags":[
        "contractor"
    ],
    "wof:name":"Elegant Exteriors",
    "wof:placetype":"venue"
},
  "geometry": {"coordinates":[-104.811667,41.167286],"type":"Point"}
}