{
  "type": "Feature",
  "properties": {
    "addr:full":"30 Stevenson Rd Laramie WY 82070",
    "addr:housenumber":"30",
    "addr:postcode":"82070",
    "addr:street":"Stevenson Rd",
    "iso:country":"US",
    "sg:address":"30 Stevenson Rd",
    "sg:city":"Laramie",
    "sg:classifiers":[
        {
            "category":"Professional",
            "type":"Services"
        }
    ],
    "sg:phone":"+1 307 745 9443",
    "sg:postcode":"82070",
    "sg:province":"WY",
    "wof:name":"Co Probe R & D Co LLC",
    "wof:placetype":"venue"
},
  "geometry": {"coordinates":[-105.544855,41.134218],"type":"Point"}
}