{
  "type": "Feature",
  "properties": {
    "iso:country":"US",
    "sg:address":"112 W 17th St",
    "sg:city":"Cheyenne",
    "sg:classifiers":[
        {
            "category":"Restaurant",
            "type":"Food & Drink"
        }
    ],
    "sg:phone":"+1 307 635 8686",
    "sg:postcode":"82001",
    "sg:province":"WY",
    "wof:name":"Grand Avenue Pizza",
    "wof:placetype":"venue"
},
  "geometry": {"coordinates":[-104.81577900000001,41.133737],"type":"Point"}
}