{
  "type": "Feature",
  "properties": {
    "iso:country":"US",
    "sg:address":"501 S Douglas Hwy",
    "sg:city":"Gillette",
    "sg:classifiers":[
        {
            "category":"Utilities",
            "subcategory":"Mobile Phone",
            "type":"Services"
        }
    ],
    "sg:phone":"+1 307 685 0298",
    "sg:postcode":"82716",
    "sg:province":"WY",
    "sg:tags":[
        "telephone",
        "cellular"
    ],
    "wof:name":"Roush's Cellular",
    "wof:placetype":"venue"
},
  "geometry": {"coordinates":[-105.49412,44.290299],"type":"Point"}
}