{
  "type": "Feature",
  "properties": {
    "iso:country":"US",
    "sg:address":"197 Pine Haven Rd",
    "sg:city":"Pine Haven",
    "sg:classifiers":[
        {
            "category":"Organizations",
            "subcategory":"Professional Association",
            "type":"Services"
        }
    ],
    "sg:phone":"+1 307 756 9757",
    "sg:postcode":"82721",
    "sg:province":"WY",
    "sg:tags":[
        "chambers",
        "commerce"
    ],
    "wof:name":"Pine Haven Chamber Of Commerce",
    "wof:placetype":"venue"
},
  "geometry": {"coordinates":[-104.811521,44.355173],"type":"Point"}
}