{
  "type": "Feature",
  "properties": {
    "addr:full":"118 W 5th St Sheridan WY 82801",
    "addr:housenumber":"118",
    "addr:postcode":"82801",
    "addr:street":"W 5Th St",
    "iso:country":"US",
    "sg:address":"118 W 5th St",
    "sg:city":"Sheridan",
    "sg:classifiers":[
        {
            "category":"Education",
            "subcategory":"School",
            "type":"Public Place"
        }
    ],
    "sg:phone":"+1 307 674 9588",
    "sg:postcode":"82801",
    "sg:province":"WY",
    "wof:name":"Sheridan Christian School",
    "wof:placetype":"venue"
},
  "geometry": {"coordinates":[-106.956495,44.806774],"type":"Point"}
}