{
  "type": "Feature",
  "properties": {
    "addr:full":"4001 Dorset St Casper WY 82609",
    "addr:housenumber":"4001",
    "addr:postcode":"82609",
    "addr:street":"Dorset St",
    "iso:country":"US",
    "sg:address":"4001 Dorset St",
    "sg:city":"Casper",
    "sg:classifiers":[
        {
            "category":"Shopping",
            "subcategory":"Clothing, Apparel, & Fashions",
            "type":"Retail Goods"
        }
    ],
    "sg:phone":"+1 307 235 2167",
    "sg:postcode":"82609",
    "sg:province":"WY",
    "wof:name":"Terrys T&T",
    "wof:placetype":"venue"
},
  "geometry": {"coordinates":[-106.27161,42.840599],"type":"Point"}
}