{
  "type": "Feature",
  "properties": {
    "iso:country":"US",
    "sg:address":"601 W 10th St",
    "sg:city":"Gillette",
    "sg:classifiers":[
        {
            "category":"Personal",
            "subcategory":"Beauty Salon",
            "type":"Services"
        }
    ],
    "sg:phone":"+1 307 687 0028",
    "sg:postcode":"82716",
    "sg:province":"WY",
    "sg:tags":[
        "shop"
    ],
    "wof:name":"Sandras Precision Hair Care",
    "wof:placetype":"venue"
},
  "geometry": {"coordinates":[-105.511563,44.285788],"type":"Point"}
}