{
  "type": "Feature",
  "properties": {
    "iso:country":"US",
    "sg:address":"1466 N Buck Creek Rd",
    "sg:city":"Casper",
    "sg:classifiers":[
        {
            "category":"Professional",
            "subcategory":"Management & Consulting",
            "type":"Services"
        }
    ],
    "sg:phone":"+1 307 577 4868",
    "sg:postcode":"82604",
    "sg:province":"WY",
    "wof:name":"Spencer Amend Consultaing LLC",
    "wof:placetype":"venue"
},
  "geometry": {"coordinates":[-106.44045,42.86349],"type":"Point"}
}