{
  "type": "Feature",
  "properties": {
    "addr:full":"521 E Main St Riverton WY 82501",
    "addr:housenumber":"521",
    "addr:postcode":"82501",
    "addr:street":"E Main St",
    "iso:country":"US",
    "sg:address":"521 E Main St",
    "sg:city":"Riverton",
    "sg:classifiers":[
        {
            "category":"Banks & Credit Unions",
            "subcategory":"Bank",
            "type":"Services"
        }
    ],
    "sg:phone":"+1 307 856 7079",
    "sg:postcode":"82501",
    "sg:province":"WY",
    "sg:tags":[
        "escrow"
    ],
    "wof:name":"Valley Escrow Inc",
    "wof:placetype":"venue"
},
  "geometry": {"coordinates":[-108.38458199999999,43.024582],"type":"Point"}
}