{
  "type": "Feature",
  "properties": {
    "iso:country":"US",
    "sg:address":"201 Canyon Rd",
    "sg:city":"Diamondville",
    "sg:classifiers":[
        {
            "category":"Health Services",
            "subcategory":"Doctor",
            "type":"Services"
        }
    ],
    "sg:phone":"+1 307 877 5944",
    "sg:postcode":"83101",
    "sg:province":"WY",
    "sg:tags":[
        "dentist"
    ],
    "wof:name":"Brent Nielson DDS",
    "wof:placetype":"venue"
},
  "geometry": {"coordinates":[-110.547487,41.795384],"type":"Point"}
}