{
  "type": "Feature",
  "properties": {
    "iso:country":"US",
    "sg:address":"3601 S Coffman Ave",
    "sg:city":"Casper",
    "sg:classifiers":[
        {
            "category":"Real Estate",
            "subcategory":"Real Estate Agent",
            "type":"Services"
        }
    ],
    "sg:phone":"+1 307 237 9000",
    "sg:postcode":"82604",
    "sg:province":"WY",
    "wof:name":"Bert L Stovall",
    "wof:placetype":"venue"
},
  "geometry": {"coordinates":[-106.344751,42.813015],"type":"Point"}
}