{
  "type": "Feature",
  "properties": {
    "iso:country":"US",
    "sg:address":"1901 Parkway Dr",
    "sg:city":"Casper",
    "sg:classifiers":[
        {
            "category":"Recreation",
            "type":"Entertainment"
        }
    ],
    "sg:phone":"+1 307 473 3050",
    "sg:postcode":"82609",
    "sg:province":"WY",
    "sg:tags":[
        "bingo",
        "game"
    ],
    "wof:name":"Prime Time Bingo LLC",
    "wof:placetype":"venue"
},
  "geometry": {"coordinates":[-106.27370000000001,42.83033],"type":"Point"}
}