{
  "type": "Feature",
  "properties": {
    "iso:country":"US",
    "sg:address":"6566 Clareton Hwy",
    "sg:city":"Gillette",
    "sg:phone":"+1 307 464 0315",
    "sg:postcode":"82732",
    "sg:province":"WY",
    "sg:tags":[
        "farm",
        "field",
        "corn",
        "crop"
    ],
    "wof:name":"Larry Dobrenz",
    "wof:placetype":"venue"
},
  "geometry": {"coordinates":[-105.464044,43.722925],"type":"Point"}
}