{
  "type": "Feature",
  "properties": {
    "iso:country":"US",
    "sg:address":"719 Washington Blvd",
    "sg:city":"Newcastle",
    "sg:classifiers":[
        {
            "category":"Banks & Credit Unions",
            "subcategory":"Bank",
            "type":"Services"
        }
    ],
    "sg:phone":"+1 307 746 4664",
    "sg:postcode":"82701",
    "sg:province":"WY",
    "sg:tags":[
        "cashing",
        "check"
    ],
    "wof:name":"Payday Lenders",
    "wof:placetype":"venue"
},
  "geometry": {"coordinates":[-104.19543899999999,43.848788],"type":"Point"}
}