{
  "type": "Feature",
  "properties": {
    "addr:full":"2810 Southern Dr Gillette WY 82718",
    "addr:housenumber":"2810",
    "addr:postcode":"82718",
    "addr:street":"Southern Dr",
    "iso:country":"US",
    "sg:address":"2810 Southern Dr",
    "sg:city":"Gillette",
    "sg:classifiers":[
        {
            "category":"Communications",
            "subcategory":"Radio Station",
            "type":"Services"
        }
    ],
    "sg:phone":"+1 307 578 5000",
    "sg:postcode":"82718",
    "sg:province":"WY",
    "wof:name":"Legend Cmmncations Wyoming LLC",
    "wof:placetype":"venue"
},
  "geometry": {"coordinates":[-105.53621200000001,44.246622],"type":"Point"}
}