{
  "type": "Feature",
  "properties": {
    "iso:country":"US",
    "sg:address":"2020 Carey Ave",
    "sg:city":"Cheyenne",
    "sg:classifiers":[
        {
            "category":"Professional",
            "subcategory":"Employment Agencies",
            "type":"Services"
        }
    ],
    "sg:phone":"+1 307 638 1675",
    "sg:postcode":"82001",
    "sg:province":"WY",
    "sg:tags":[
        "co",
        "fraternal"
    ],
    "wof:name":"Wyoming New Hire",
    "wof:placetype":"venue"
},
  "geometry": {"coordinates":[-104.819239,41.136538],"type":"Point"}
}