{
  "type": "Feature",
  "properties": {
    "addr:full":"1910 N Loop Ave Casper WY 82601",
    "addr:housenumber":"1910",
    "addr:postcode":"82601",
    "addr:street":"N Loop Ave",
    "iso:country":"US",
    "sg:address":"1910 N Loop Ave",
    "sg:city":"Casper",
    "sg:classifiers":[
        {
            "category":"Mining & Drilling",
            "type":"Manufacturing & Wholesale Goods"
        }
    ],
    "sg:phone":"+1 307 235 8609",
    "sg:postcode":"82601",
    "sg:province":"WY",
    "sg:tags":[
        "oil",
        "well"
    ],
    "sg:website":"www.elenburgexploration.com",
    "wof:name":"Elenburg Exploration Inc",
    "wof:placetype":"venue"
},
  "geometry": {"coordinates":[-106.348907,42.873454],"type":"Point"}
}