{
  "type": "Feature",
  "properties": {
    "addr:full":"5240 Poison Spider Rd Casper WY 82604",
    "addr:postcode":"5240;82604",
    "addr:street":"Spider Rd",
    "iso:country":"US",
    "sg:address":"5240 Poison Spider Rd",
    "sg:city":"Casper",
    "sg:classifiers":[
        {
            "category":"Autos & Motor Vehicles",
            "subcategory":"Automobile Sales",
            "type":"Retail Goods"
        },
        {
            "category":"Autos & Motor Vehicles",
            "subcategory":"Motorcycle Sales",
            "type":"Retail Goods"
        }
    ],
    "sg:phone":"+1 307 265 1600",
    "sg:postcode":"82604",
    "sg:province":"WY",
    "sg:tags":[
        "repair",
        "r",
        "snowmobile",
        "general"
    ],
    "wof:name":"USA Motor Sports",
    "wof:placetype":"venue"
},
  "geometry": {"coordinates":[-106.393427,42.845173],"type":"Point"}
}