{
  "type": "Feature",
  "properties": {
    "iso:country":"US",
    "sg:address":"605 S 6th St",
    "sg:city":"Thermopolis",
    "sg:classifiers":[
        {
            "category":"Travel",
            "subcategory":"Hotels & Motels",
            "type":"Entertainment"
        }
    ],
    "sg:phone":"+1 307 864 3155",
    "sg:postcode":"82443",
    "sg:province":"WY",
    "sg:website":"www.cactusinn.com",
    "wof:name":"Cactus Inn",
    "wof:placetype":"venue"
},
  "geometry": {"coordinates":[-108.212079,43.640501],"type":"Point"}
}