{
  "type": "Feature",
  "properties": {
    "iso:country":"US",
    "sg:address":"1071 Rd 9",
    "sg:city":"Powell",
    "sg:classifiers":[
        {
            "category":"Building & Trades",
            "subcategory":"Construction",
            "type":"Services"
        }
    ],
    "sg:phone":"+1 307 754 3584",
    "sg:postcode":"82435",
    "sg:province":"WY",
    "sg:tags":[
        "excavating",
        "contractor"
    ],
    "wof:name":"Ray's Dirt Svc Inc",
    "wof:placetype":"venue"
},
  "geometry": {"coordinates":[-108.759821,44.729215],"type":"Point"}
}