{
  "type": "Feature",
  "properties": {
    "addr:full":"9 Cody St Wright WY 82732",
    "addr:housenumber":"9",
    "addr:postcode":"82732",
    "addr:street":"Cody St Wright Wy",
    "iso:country":"US",
    "sg:address":"9 Cody St",
    "sg:city":"Wright",
    "sg:classifiers":[
        {
            "category":"Professional",
            "subcategory":"Business Services",
            "type":"Services"
        }
    ],
    "sg:phone":"+1 307 464 0605",
    "sg:postcode":"82732",
    "sg:province":"WY",
    "wof:name":"Energy Enterprise Services",
    "wof:placetype":"venue"
},
  "geometry": {"coordinates":[-105.476597,43.73741],"type":"Point"}
}