{
  "type": "Feature",
  "properties": {
    "iso:country":"US",
    "sg:address":"22 Dale Rd",
    "sg:city":"Boulder",
    "sg:classifiers":[
        {
            "category":"Retail",
            "subcategory":"Repair Shop",
            "type":"Services"
        },
        {
            "category":"Building & Trades",
            "subcategory":"Construction",
            "type":"Services"
        }
    ],
    "sg:phone":"+1 307 537 5263",
    "sg:postcode":"82941",
    "sg:province":"WY",
    "sg:tags":[
        "welding",
        "contractor"
    ],
    "wof:name":"Buck's Welding & Repair",
    "wof:placetype":"venue"
},
  "geometry": {"coordinates":[-109.742206,42.772158],"type":"Point"}
}