{
  "type": "Feature",
  "properties": {
    "iso:country":"US",
    "sg:address":"22 4th Ave",
    "sg:city":"Newcastle",
    "sg:classifiers":[
        {
            "category":"Real Estate",
            "subcategory":"Surveying",
            "type":"Services"
        }
    ],
    "sg:phone":"+1 307 746 2754",
    "sg:postcode":"82701",
    "sg:province":"WY",
    "sg:tags":[
        "surveyor"
    ],
    "wof:name":"High Plains Of Wyoming",
    "wof:placetype":"venue"
},
  "geometry": {"coordinates":[-104.22349699999999,43.851334],"type":"Point"}
}