{
  "type": "Feature",
  "properties": {
    "addr:full":"100 Center St Evanston WY 82930",
    "addr:housenumber":"100",
    "addr:postcode":"82930",
    "addr:street":"Center St",
    "iso:country":"US",
    "sg:address":"100 Center St",
    "sg:city":"Evanston",
    "sg:classifiers":[
        {
            "category":"Recreation",
            "type":"Entertainment"
        }
    ],
    "sg:phone":"+1 307 444 7664",
    "sg:postcode":"82930",
    "sg:province":"WY",
    "wof:name":"Striking Scorpion Enterprises",
    "wof:placetype":"venue"
},
  "geometry": {"coordinates":[-110.957703,41.260674],"type":"Point"}
}