{
  "type": "Feature",
  "properties": {
    "iso:country":"US",
    "sg:address":"1006 S Oak St",
    "sg:city":"Lusk",
    "sg:classifiers":[
        {
            "category":"Shopping",
            "subcategory":"Clothing, Apparel, & Fashions",
            "type":"Retail Goods"
        }
    ],
    "sg:phone":"+1 307 334 2746",
    "sg:postcode":"82225",
    "sg:province":"WY",
    "sg:tags":[
        "western"
    ],
    "wof:name":"True Hatters",
    "wof:placetype":"venue"
},
  "geometry": {"coordinates":[-104.44896,42.751999],"type":"Point"}
}