{
  "type": "Feature",
  "properties": {
    "iso:country":"US",
    "sg:address":"40 S Main St",
    "sg:city":"Sheridan",
    "sg:classifiers":[
        {
            "category":"Social Services",
            "type":"Services"
        }
    ],
    "sg:phone":"+1 307 672 6789",
    "sg:postcode":"82801",
    "sg:province":"WY",
    "sg:tags":[
        "counselor",
        "marriage",
        "family"
    ],
    "wof:name":"Lynn E Gordon Lpc",
    "wof:placetype":"venue"
},
  "geometry": {"coordinates":[-106.95588499999999,44.79688],"type":"Point"}
}