{
  "type": "Feature",
  "properties": {
    "addr:full":"201 Yellowstone Ave Cody WY 82414",
    "addr:housenumber":"201",
    "addr:postcode":"82414",
    "addr:street":"Yellowstone Ave",
    "iso:country":"US",
    "sg:address":"201 Yellowstone Ave",
    "sg:city":"Cody",
    "sg:classifiers":[
        {
            "category":"Professional",
            "type":"Services"
        }
    ],
    "sg:phone":"+1 307 587 6089",
    "sg:postcode":"82414",
    "sg:province":"WY",
    "sg:tags":[
        "establishment"
    ],
    "wof:name":"North Platte Community Therape",
    "wof:placetype":"venue"
},
  "geometry": {"coordinates":[-109.093473,44.515997],"type":"Point"}
}