{
  "type": "Feature",
  "properties": {
    "addr:full":"1150 W Flaming Gorge Way Green River WY 82935",
    "addr:housenumber":"1150",
    "addr:postcode":"82935",
    "addr:street":"W Flaming Gorge Way Green",
    "iso:country":"US",
    "sg:address":"1150 W Flaming Gorge Way",
    "sg:city":"Green River",
    "sg:classifiers":[
        {
            "category":"Food & Beverages",
            "subcategory":"Groceries & Convenience Stores",
            "type":"Retail Goods"
        }
    ],
    "sg:phone":"+1 307 875 2342",
    "sg:postcode":"82935",
    "sg:province":"WY",
    "wof:name":"Tri-Mart Texaco",
    "wof:placetype":"venue"
},
  "geometry": {"coordinates":[-109.479815,41.536849],"type":"Point"}
}