{
  "type": "Feature",
  "properties": {
    "addr:full":"1853 E 4th St Casper WY 82609",
    "addr:housenumber":"1853",
    "addr:postcode":"82609",
    "addr:street":"E 4Th St",
    "iso:country":"US",
    "sg:address":"1853 E 4th St",
    "sg:city":"Casper",
    "sg:classifiers":[
        {
            "category":"Government",
            "subcategory":"Fire Station",
            "type":"Public Place"
        }
    ],
    "sg:phone":"+1 307 235 8323",
    "sg:postcode":"82609",
    "sg:province":"WY",
    "sg:tags":[
        "department"
    ],
    "wof:name":"Casper Fire Dept",
    "wof:placetype":"venue"
},
  "geometry": {"coordinates":[-106.300167,42.846266],"type":"Point"}
}