{
  "type": "Feature",
  "properties": {
    "iso:country":"US",
    "sg:address":"4727 Powell Hwy",
    "sg:city":"Cody",
    "sg:classifiers":[
        {
            "category":"Farming",
            "subcategory":"Aquatic Farm",
            "type":"Manufacturing & Wholesale Goods"
        }
    ],
    "sg:phone":"+1 307 527 7446",
    "sg:postcode":"82414",
    "sg:province":"WY",
    "sg:tags":[
        "fish"
    ],
    "wof:name":"Wyoming Trout Ranch",
    "wof:placetype":"venue"
},
  "geometry": {"coordinates":[-108.980906,44.563663],"type":"Point"}
}