{
  "type": "Feature",
  "properties": {
    "addr:full":"310 Industrial Ave Casper WY 82601",
    "addr:housenumber":"310",
    "addr:postcode":"82601",
    "addr:street":"Industrial Ave",
    "iso:country":"US",
    "sg:address":"310 Industrial Ave",
    "sg:city":"Casper",
    "sg:classifiers":[
        {
            "category":"Retail",
            "subcategory":"Repair Shop",
            "type":"Services"
        }
    ],
    "sg:phone":"+1 307 234 9427",
    "sg:postcode":"82601",
    "sg:province":"WY",
    "sg:tags":[
        "refinishing",
        "furniture"
    ],
    "wof:name":"R F Woodcrafting",
    "wof:placetype":"venue"
},
  "geometry": {"coordinates":[-106.32956299999999,42.848316],"type":"Point"}
}