{
  "type": "Feature",
  "properties": {
    "iso:country":"US",
    "sg:address":"915 State Hwy 116",
    "sg:city":"Upton",
    "sg:classifiers":[
        {
            "category":"Professional",
            "type":"Services"
        }
    ],
    "sg:phone":"+1 307 468 2825",
    "sg:postcode":"82730",
    "sg:province":"WY",
    "sg:tags":[
        "establishment"
    ],
    "wof:name":"Upton Fire Hall",
    "wof:placetype":"venue"
},
  "geometry": {"coordinates":[-104.748711,44.019001],"type":"Point"}
}