{
  "type": "Feature",
  "properties": {
    "iso:country":"US",
    "sg:address":"2521 E Park Ave",
    "sg:city":"Laramie",
    "sg:classifiers":[
        {
            "category":"Social Services",
            "subcategory":"Child Care",
            "type":"Services"
        }
    ],
    "sg:phone":"+1 307 742 3370",
    "sg:postcode":"82070",
    "sg:province":"WY",
    "sg:tags":[
        "day"
    ],
    "wof:name":"Corthell Hill Day Care",
    "wof:placetype":"venue"
},
  "geometry": {"coordinates":[-105.56633600000001,41.299748],"type":"Point"}
}