{
  "type": "Feature",
  "properties": {
    "iso:country":"US",
    "sg:address":"2701 S Douglas Hwy",
    "sg:city":"Gillette",
    "sg:classifiers":[
        {
            "category":"Sports & Exercise",
            "subcategory":"Gym",
            "type":"Entertainment"
        }
    ],
    "sg:phone":"+1 307 686 7627",
    "sg:postcode":"82718",
    "sg:province":"WY",
    "sg:tags":[
        "club",
        "health",
        "studio",
        "gymnasium"
    ],
    "wof:name":"Club Energize",
    "wof:placetype":"venue"
},
  "geometry": {"coordinates":[-105.493814,44.269888],"type":"Point"}
}