{
  "type": "Feature",
  "properties": {
    "iso:country":"US",
    "sg:address":"2610 S Douglas Hwy",
    "sg:city":"Gillette",
    "sg:classifiers":[
        {
            "category":"Home & Garden",
            "subcategory":"Hardware",
            "type":"Retail Goods"
        }
    ],
    "sg:phone":"+1 307 687 1166",
    "sg:postcode":"82718",
    "sg:province":"WY",
    "wof:name":"Ace Hardware",
    "wof:placetype":"venue"
},
  "geometry": {"coordinates":[-105.493994,44.270908],"type":"Point"}
}