{
  "type": "Feature",
  "properties": {
    "addr:full":"1212 Ridge Rd Cheyenne WY 82001",
    "addr:housenumber":"1212",
    "addr:postcode":"82001",
    "addr:street":"Ridge Rd",
    "iso:country":"US",
    "sg:address":"1212 Ridge Rd",
    "sg:city":"Cheyenne",
    "sg:classifiers":[
        {
            "category":"Shopping",
            "subcategory":"Bicycles & Sporting Goods",
            "type":"Retail Goods"
        }
    ],
    "sg:phone":"+1 307 637 7498",
    "sg:postcode":"82001",
    "sg:province":"WY",
    "sg:tags":[
        "equipment",
        "archery",
        "supply"
    ],
    "wof:name":"Bullseye Archery",
    "wof:placetype":"venue"
},
  "geometry": {"coordinates":[-104.76858,41.138234],"type":"Point"}
}