{
  "type": "Feature",
  "properties": {
    "iso:country":"US",
    "sg:address":"531 N Front St",
    "sg:city":"Rock Springs",
    "sg:classifiers":[
        {
            "category":"Professional",
            "subcategory":"Lawyer & Legal Services",
            "type":"Services"
        }
    ],
    "sg:phone":"+1 307 382 7700",
    "sg:postcode":"82901",
    "sg:province":"WY",
    "sg:tags":[
        "attorney"
    ],
    "wof:name":"Kaumo Law Office",
    "wof:placetype":"venue"
},
  "geometry": {"coordinates":[-109.219646,41.587793],"type":"Point"}
}