{
  "type": "Feature",
  "properties": {
    "iso:country":"US",
    "sg:address":"5 Rd 2Abn",
    "sg:city":"Cody",
    "sg:classifiers":[
        {
            "category":"Retail",
            "subcategory":"Repair Shop",
            "type":"Services"
        }
    ],
    "sg:phone":"+1 307 587 9443",
    "sg:postcode":"82414",
    "sg:province":"WY",
    "sg:tags":[
        "taxidermist"
    ],
    "sg:website":"www.jamesmarsico.com",
    "wof:name":"Mountain Valley Artistry",
    "wof:placetype":"venue"
},
  "geometry": {"coordinates":[-109.074684,44.554029],"type":"Point"}
}