{
  "type": "Feature",
  "properties": {
    "addr:full":"854 5th Ave Belle Fourche WY 57717",
    "addr:housenumber":"854",
    "addr:postcode":"57717",
    "addr:street":"5Th Ave",
    "iso:country":"US",
    "sg:address":"854 5th Ave",
    "sg:city":"Belle Fourche",
    "sg:classifiers":[
        {
            "category":"Autos & Motor Vehicles",
            "subcategory":"Fuel & Gas Station",
            "type":"Retail Goods"
        }
    ],
    "sg:phone":"+1 605 892 2981",
    "sg:postcode":"57717",
    "sg:province":"WY",
    "sg:tags":[
        "oil"
    ],
    "wof:name":"Harris's Service Station",
    "wof:placetype":"venue"
},
  "geometry": {"coordinates":[-103.85359699999999,44.668908],"type":"Point"}
}