{
  "type": "Feature",
  "properties": {
    "addr:full":"400 S Kendrick Ave Gillette WY 82716",
    "addr:housenumber":"400",
    "addr:postcode":"82716",
    "addr:street":"S Kendrick Ave",
    "iso:country":"US",
    "sg:address":"400 S Kendrick Ave",
    "sg:city":"Gillette",
    "sg:classifiers":[
        {
            "category":"Health Services",
            "subcategory":"Doctor",
            "type":"Services"
        }
    ],
    "sg:phone":"+1 307 686 1605",
    "sg:postcode":"82716",
    "sg:province":"WY",
    "wof:name":"McGarvin Larry H DDS",
    "wof:placetype":"venue"
},
  "geometry": {"coordinates":[-105.50248000000001,44.29123],"type":"Point"}
}