{
  "type": "Feature",
  "properties": {
    "iso:country":"US",
    "sg:address":"821 Illinois St",
    "sg:city":"Sheridan",
    "sg:classifiers":[
        {
            "category":"Building & Trades",
            "subcategory":"Cleaning & Sanitation",
            "type":"Services"
        }
    ],
    "sg:phone":"+1 307 672 9851",
    "sg:postcode":"82801",
    "sg:province":"WY",
    "sg:tags":[
        "help",
        "maintenance",
        "supply"
    ],
    "wof:name":"American Maid",
    "wof:placetype":"venue"
},
  "geometry": {"coordinates":[-106.949708,44.789437],"type":"Point"}
}