{
  "type": "Feature",
  "properties": {
    "iso:country":"US",
    "sg:address":"1330 Hillcrest Dr",
    "sg:city":"Lander",
    "sg:classifiers":[
        {
            "category":"Social Services",
            "subcategory":"Child Care",
            "type":"Services"
        }
    ],
    "sg:phone":"+1 307 335 8141",
    "sg:postcode":"82520",
    "sg:province":"WY",
    "sg:tags":[
        "day"
    ],
    "wof:name":"Mops",
    "wof:placetype":"venue"
},
  "geometry": {"coordinates":[-108.734527,42.82015],"type":"Point"}
}