{
  "type": "Feature",
  "properties": {
    "iso:country":"US",
    "sg:address":"622 W Spruce St",
    "sg:city":"Rawlins",
    "sg:classifiers":[
        {
            "category":"Autos & Motor Vehicles",
            "subcategory":"Automobile Sales",
            "type":"Retail Goods"
        }
    ],
    "sg:phone":"+1 307 324 3434",
    "sg:postcode":"82301",
    "sg:province":"WY",
    "sg:tags":[
        "body",
        "repair",
        "general"
    ],
    "sg:website":"www.fremontmotors.com",
    "wof:name":"Fremont Motors Of Rawlins",
    "wof:placetype":"venue"
},
  "geometry": {"coordinates":[-107.24269099999999,41.790108],"type":"Point"}
}