{
  "type": "Feature",
  "properties": {
    "addr:full":"311 Fish Hatchery Rd Story WY 82842",
    "addr:housenumber":"311",
    "addr:postcode":"82842",
    "addr:street":"Fish Hatchery Rd Story Wy",
    "iso:country":"US",
    "sg:address":"311 Fish Hatchery Rd",
    "sg:city":"Story",
    "sg:classifiers":[
        {
            "category":"Government",
            "subcategory":"Office",
            "type":"Public Place"
        }
    ],
    "sg:phone":"+1 307 683 2234",
    "sg:postcode":"82842",
    "sg:province":"WY",
    "sg:tags":[
        "state"
    ],
    "wof:name":"Fish Hatchery",
    "wof:placetype":"venue"
},
  "geometry": {"coordinates":[-106.92673000000001,44.56558],"type":"Point"}
}