{
  "type": "Feature",
  "properties": {
    "addr:full":"1849 Terra Ave Sheridan WY 82801",
    "addr:housenumber":"1849",
    "addr:postcode":"82801",
    "addr:street":"Terra Ave",
    "iso:country":"US",
    "sg:address":"1849 Terra Ave",
    "sg:city":"Sheridan",
    "sg:classifiers":[
        {
            "category":"Professional",
            "subcategory":"Engineering",
            "type":"Services"
        }
    ],
    "sg:phone":"+1 307 672 0761",
    "sg:postcode":"82801",
    "sg:province":"WY",
    "sg:tags":[
        "management"
    ],
    "sg:website":"www.wwcengineering.com",
    "wof:name":"WWC Engineering",
    "wof:placetype":"venue"
},
  "geometry": {"coordinates":[-106.946015,44.777228],"type":"Point"}
}