{
  "type": "Feature",
  "properties": {
    "iso:country":"US",
    "sg:address":"211 W Main St",
    "sg:city":"Lovell",
    "sg:classifiers":[
        {
            "category":"Professional",
            "type":"Services"
        }
    ],
    "sg:phone":"+1 307 548 7923",
    "sg:postcode":"82431",
    "sg:province":"WY",
    "sg:tags":[
        "establishment"
    ],
    "wof:name":"Maverik Tank Monitor",
    "wof:placetype":"venue"
},
  "geometry": {"coordinates":[-108.399508,44.837622],"type":"Point"}
}