{
  "type": "Feature",
  "properties": {
    "iso:country":"US",
    "sg:address":"1660 W Berger Ln",
    "sg:city":"Jackson",
    "sg:phone":"+1 307 733 3769",
    "sg:postcode":"83001",
    "sg:province":"WY",
    "sg:tags":[
        "gas"
    ],
    "wof:name":"Ameri Gas Inc",
    "wof:placetype":"venue"
},
  "geometry": {"coordinates":[-110.797206,43.460228],"type":"Point"}
}