{
  "type": "Feature",
  "properties": {
    "addr:full":"101 N 3rd St E Riverton WY 82501",
    "addr:housenumber":"101",
    "addr:postcode":"82501",
    "addr:street":"N 3Rd St",
    "iso:country":"US",
    "sg:address":"101 N 3rd St E",
    "sg:city":"Riverton",
    "sg:classifiers":[
        {
            "category":"Health Services",
            "subcategory":"Nursing And Care Facility",
            "type":"Services"
        }
    ],
    "sg:phone":"+1 307 857 6969",
    "sg:postcode":"82501",
    "sg:province":"WY",
    "sg:tags":[
        "home",
        "retirement",
        "community"
    ],
    "wof:name":"Teton Sertoma Inc",
    "wof:placetype":"venue"
},
  "geometry": {"coordinates":[-108.387766,43.025721],"type":"Point"}
}