{
  "type": "Feature",
  "properties": {
    "iso:country":"US",
    "sg:address":"715 Arapahoe Ave",
    "sg:city":"Gillette",
    "sg:classifiers":[
        {
            "category":"Freight",
            "type":"Transportation"
        }
    ],
    "sg:phone":"+1 307 682 4707",
    "sg:postcode":"82718",
    "sg:province":"WY",
    "sg:tags":[
        "special"
    ],
    "wof:name":"Dry Storage",
    "wof:placetype":"venue"
},
  "geometry": {"coordinates":[-105.4941,44.257108],"type":"Point"}
}