{
  "type": "Feature",
  "properties": {
    "iso:country":"US",
    "sg:address":"1305 Echeta Rd",
    "sg:city":"Gillette",
    "sg:classifiers":[
        {
            "category":"Mining & Drilling",
            "type":"Manufacturing & Wholesale Goods"
        }
    ],
    "sg:phone":"+1 307 685 6630",
    "sg:postcode":"82716",
    "sg:province":"WY",
    "sg:tags":[
        "development",
        "gas",
        "oil",
        "exploration"
    ],
    "wof:name":"Powder River Svc",
    "wof:placetype":"venue"
},
  "geometry": {"coordinates":[-105.52056,44.296084],"type":"Point"}
}