{
  "type": "Feature",
  "properties": {
    "iso:country":"US",
    "sg:address":"20 Shoshone Ave",
    "sg:city":"Green River",
    "sg:classifiers":[
        {
            "category":"Insurance",
            "subcategory":"Insurance Agent",
            "type":"Services"
        }
    ],
    "sg:phone":"+1 307 875 2171",
    "sg:postcode":"82935",
    "sg:province":"WY",
    "wof:name":"American General Finance Inc",
    "wof:placetype":"venue"
},
  "geometry": {"coordinates":[-109.47340199999999,41.509262],"type":"Point"}
}