{
  "type": "Feature",
  "properties": {
    "iso:country":"US",
    "sg:address":"4000 E 15th St",
    "sg:city":"Casper",
    "sg:classifiers":[
        {
            "category":"Government",
            "subcategory":"Fire Station",
            "type":"Public Place"
        }
    ],
    "sg:phone":"+1 307 235 8325",
    "sg:postcode":"82609",
    "sg:province":"WY",
    "sg:tags":[
        "department"
    ],
    "wof:name":"Casper Fire Dept",
    "wof:placetype":"venue"
},
  "geometry": {"coordinates":[-106.273882,42.835674],"type":"Point"}
}