{
  "type": "Feature",
  "properties": {
    "iso:country":"US",
    "sg:address":"3705 E Lincolnway",
    "sg:city":"Cheyenne",
    "sg:classifiers":[
        {
            "category":"Restaurant",
            "type":"Food & Drink"
        }
    ],
    "sg:phone":"+1 307 638 2108",
    "sg:postcode":"82001",
    "sg:province":"WY",
    "sg:tags":[
        "eating"
    ],
    "wof:name":"Smoke N Peppers",
    "wof:placetype":"venue"
},
  "geometry": {"coordinates":[-104.76468199999999,41.140017],"type":"Point"}
}