{
  "type": "Feature",
  "properties": {
    "iso:country":"US",
    "sg:address":"3753 E Lincolnway",
    "sg:city":"Cheyenne",
    "sg:classifiers":[
        {
            "category":"Restaurant",
            "type":"Food & Drink"
        }
    ],
    "sg:menulink":"http://www.allmenus.com/wy/cheyenne/20876-parkway-pizza/menu/",
    "sg:phone":"+1 307 778 2949",
    "sg:postcode":"82001",
    "sg:province":"WY",
    "sg:tags":[
        "american",
        "pizza"
    ],
    "wof:name":"Parkway Pizza",
    "wof:placetype":"venue"
},
  "geometry": {"coordinates":[-104.76545400000001,41.139603],"type":"Point"}
}