{
  "type": "Feature",
  "properties": {
    "iso:country":"US",
    "sg:address":"924 Horse Creek Rd",
    "sg:city":"Dubois",
    "sg:classifiers":[
        {
            "category":"Building & Trades",
            "subcategory":"Construction",
            "type":"Services"
        }
    ],
    "sg:phone":"+1 307 455 3494",
    "sg:postcode":"82513",
    "sg:province":"WY",
    "sg:tags":[
        "underground",
        "trenching",
        "contractor"
    ],
    "wof:name":"R & D Backhoe Svc",
    "wof:placetype":"venue"
},
  "geometry": {"coordinates":[-109.630779,43.587843],"type":"Point"}
}