{
  "type": "Feature",
  "properties": {
    "addr:full":"589 Pape Rd Daniel WY 83115",
    "addr:housenumber":"589",
    "addr:postcode":"83115",
    "addr:street":"Pape Rd Daniel Wy",
    "iso:country":"US",
    "sg:address":"589 Pape Rd",
    "sg:city":"Daniel",
    "sg:classifiers":[
        {
            "category":"Building & Trades",
            "subcategory":"Construction",
            "type":"Services"
        }
    ],
    "sg:phone":"+1 307 859 8237",
    "sg:postcode":"83115",
    "sg:province":"WY",
    "sg:tags":[
        "general",
        "contractor"
    ],
    "wof:name":"M L Mc Loughlin & SONS LLC",
    "wof:placetype":"venue"
},
  "geometry": {"coordinates":[-110.122525,42.967708],"type":"Point"}
}