{
  "type": "Feature",
  "properties": {
    "iso:country":"US",
    "sg:address":"1805 E 2nd St",
    "sg:city":"Casper",
    "sg:classifiers":[
        {
            "category":"Banks & Credit Unions",
            "subcategory":"Bank",
            "type":"Services"
        }
    ],
    "sg:phone":"+1 307 472 3580",
    "sg:postcode":"82601",
    "sg:province":"WY",
    "sg:tags":[
        "mortgage"
    ],
    "wof:name":"Amcentral Mortgage",
    "wof:placetype":"venue"
},
  "geometry": {"coordinates":[-106.300444,42.848686],"type":"Point"}
}