{
  "type": "Feature",
  "properties": {
    "iso:country":"US",
    "sg:address":"3440 Navarre Rd",
    "sg:city":"Casper",
    "sg:classifiers":[
        {
            "category":"Professional",
            "subcategory":"Management & Consulting",
            "type":"Services"
        }
    ],
    "sg:phone":"+1 307 472 0775",
    "sg:postcode":"82604",
    "sg:province":"WY",
    "sg:tags":[
        "consultant",
        "business"
    ],
    "wof:name":"Mel Klaus Consulting",
    "wof:placetype":"venue"
},
  "geometry": {"coordinates":[-106.35019699999999,42.816806],"type":"Point"}
}