{
  "type": "Feature",
  "properties": {
    "iso:country":"US",
    "sg:address":"110 W 2nd St",
    "sg:city":"Casper",
    "sg:classifiers":[
        {
            "category":"Professional",
            "subcategory":"Management & Consulting",
            "type":"Services"
        }
    ],
    "sg:phone":"+1 307 473 2703",
    "sg:postcode":"82601",
    "sg:province":"WY",
    "sg:tags":[
        "consultant",
        "business"
    ],
    "wof:name":"Business Resource Group",
    "wof:placetype":"venue"
},
  "geometry": {"coordinates":[-106.326486,42.848758],"type":"Point"}
}