{
  "type": "Feature",
  "properties": {
    "addr:full":"1022 Crear Ln Pinedale WY 82941",
    "addr:housenumber":"1022",
    "addr:postcode":"82941",
    "addr:street":"Crear Ln",
    "iso:country":"US",
    "sg:address":"1022 Crear Ln",
    "sg:city":"Pinedale",
    "sg:classifiers":[
        {
            "category":"Building & Trades",
            "subcategory":"Construction",
            "type":"Services"
        }
    ],
    "sg:phone":"+1 307 367 2534",
    "sg:postcode":"82941",
    "sg:province":"WY",
    "sg:tags":[
        "general",
        "contractor"
    ],
    "wof:name":"Myles Hopkins Construction",
    "wof:placetype":"venue"
},
  "geometry": {"coordinates":[-109.86682999999999,42.87621],"type":"Point"}
}