{
  "type": "Feature",
  "properties": {
    "iso:country":"US",
    "sg:address":"416 S Elm St",
    "sg:city":"Lusk",
    "sg:classifiers":[
        {
            "category":"Government",
            "subcategory":"Police Station",
            "type":"Public Place"
        }
    ],
    "sg:phone":"+1 307 334 2240",
    "sg:postcode":"82225",
    "sg:province":"WY",
    "sg:tags":[
        "sheriff"
    ],
    "wof:name":"Niobrara County Sheriff Dept",
    "wof:placetype":"venue"
},
  "geometry": {"coordinates":[-104.45089299999999,42.761057],"type":"Point"}
}