{
  "type": "Feature",
  "properties": {
    "addr:full":"800 Stocktrail Ave Gillette WY 82716",
    "addr:housenumber":"800",
    "addr:postcode":"82716",
    "addr:street":"Stocktrail Ave",
    "iso:country":"US",
    "sg:address":"800 Stocktrail Ave",
    "sg:city":"Gillette",
    "sg:classifiers":[
        {
            "category":"Social Services",
            "subcategory":"Child Care",
            "type":"Services"
        }
    ],
    "sg:phone":"+1 307 682 5413",
    "sg:postcode":"82716",
    "sg:province":"WY",
    "wof:name":"Kinderkids Child Care Ctr",
    "wof:placetype":"venue"
},
  "geometry": {"coordinates":[-105.5146,44.28751],"type":"Point"}
}