{
  "type": "Feature",
  "properties": {
    "iso:country":"US",
    "sg:address":"1517 Walnut",
    "sg:city":"Cheyenne",
    "sg:classifiers":[
        {
            "category":"Organizations",
            "subcategory":"Religious Organization",
            "type":"Services"
        }
    ],
    "sg:phone":"+1 307 634 3864",
    "sg:postcode":"82001",
    "sg:province":"WY",
    "sg:tags":[
        "church"
    ],
    "wof:name":"Miracle Valley Assembly Of God",
    "wof:placetype":"venue"
},
  "geometry": {"coordinates":[-104.783281,41.139033],"type":"Point"}
}