{
  "type": "Feature",
  "properties": {
    "addr:full":"2219 Garrett St Cheyenne WY 82001",
    "addr:housenumber":"2219",
    "addr:postcode":"82001",
    "addr:street":"Garrett St",
    "iso:country":"US",
    "sg:address":"2219 Garrett St",
    "sg:city":"Cheyenne",
    "sg:classifiers":[
        {
            "category":"Retail",
            "subcategory":"Laundry & Dry Cleaning",
            "type":"Services"
        },
        {
            "category":"Shopping",
            "subcategory":"Clothing, Apparel, & Fashions",
            "type":"Retail Goods"
        }
    ],
    "sg:phone":"+1 307 778 8621",
    "sg:postcode":"82001",
    "sg:province":"WY",
    "sg:tags":[
        "tailor",
        "alteration"
    ],
    "wof:name":"Alteration's Maria",
    "wof:placetype":"venue"
},
  "geometry": {"coordinates":[-104.79019,41.143253],"type":"Point"}
}