{
  "type": "Feature",
  "properties": {
    "iso:country":"US",
    "sg:address":"722 S Sheridan Ave",
    "sg:city":"Sheridan",
    "sg:classifiers":[
        {
            "category":"Shopping",
            "subcategory":"Bicycles & Sporting Goods",
            "type":"Retail Goods"
        }
    ],
    "sg:phone":"+1 307 674 9277",
    "sg:postcode":"82801",
    "sg:province":"WY",
    "sg:tags":[
        "gun",
        "gunsmith"
    ],
    "wof:name":"Down Range Gunsmithing",
    "wof:placetype":"venue"
},
  "geometry": {"coordinates":[-106.948308,44.790168],"type":"Point"}
}