{
  "type": "Feature",
  "properties": {
    "addr:full":"455 Targhee Towne Rd Driggs WY 83422",
    "addr:housenumber":"455",
    "addr:postcode":"83422",
    "addr:street":"Targhee Towne Rd",
    "iso:country":"US",
    "sg:address":"455 Targhee Towne Rd",
    "sg:city":"Driggs",
    "sg:classifiers":[
        {
            "category":"Professional",
            "subcategory":"Management & Consulting",
            "type":"Services"
        }
    ],
    "sg:phone":"+1 307 353 2238",
    "sg:postcode":"83422",
    "sg:province":"WY",
    "sg:tags":[
        "environmental"
    ],
    "wof:name":"Alta Solutions & Strategies",
    "wof:placetype":"venue"
},
  "geometry": {"coordinates":[-111.038068,43.760464],"type":"Point"}
}