{
  "type": "Feature",
  "properties": {
    "iso:country":"US",
    "sg:address":"721 State Hwy 230",
    "sg:city":"Laramie",
    "sg:classifiers":[
        {
            "category":"Organizations",
            "subcategory":"Religious Organization",
            "type":"Services"
        }
    ],
    "sg:phone":"+1 307 721 5017",
    "sg:postcode":"82070",
    "sg:province":"WY",
    "sg:tags":[
        "church"
    ],
    "wof:name":"Snowy Range Baptist Church",
    "wof:placetype":"venue"
},
  "geometry": {"coordinates":[-105.713939,41.249453],"type":"Point"}
}