{
  "type": "Feature",
  "properties": {
    "iso:country":"US",
    "sg:address":"201 N Main St",
    "sg:city":"Sheridan",
    "sg:classifiers":[
        {
            "category":"Professional",
            "subcategory":"Art Services",
            "type":"Services"
        }
    ],
    "sg:phone":"+1 307 674 8808",
    "sg:postcode":"82801",
    "sg:province":"WY",
    "sg:tags":[
        "graphic",
        "designer"
    ],
    "wof:name":"Bighorn Design",
    "wof:placetype":"venue"
},
  "geometry": {"coordinates":[-106.95574999999999,44.80067],"type":"Point"}
}