{
  "type": "Feature",
  "properties": {
    "addr:full":"1313 Monroe St Douglas WY 82633",
    "addr:housenumber":"1313",
    "addr:postcode":"82633",
    "addr:street":"Monroe St Douglas Wy",
    "iso:country":"US",
    "sg:address":"1313 Monroe St",
    "sg:city":"Douglas",
    "sg:classifiers":[
        {
            "category":"Organizations",
            "subcategory":"Community Association",
            "type":"Services"
        }
    ],
    "sg:phone":"+1 307 358 6453",
    "sg:postcode":"82633",
    "sg:province":"WY",
    "wof:name":"Douglas Lodge 15",
    "wof:placetype":"venue"
},
  "geometry": {"coordinates":[-105.405081,42.75649],"type":"Point"}
}