{
  "type": "Feature",
  "properties": {
    "iso:country":"US",
    "sg:address":"6220 E Pershing Blvd",
    "sg:city":"Cheyenne",
    "sg:classifiers":[
        {
            "category":"Autos & Motor Vehicles",
            "subcategory":"Automobile Sales",
            "type":"Retail Goods"
        }
    ],
    "sg:phone":"+1 307 634 4800",
    "sg:postcode":"82001",
    "sg:province":"WY",
    "sg:tags":[
        "used"
    ],
    "wof:name":"Bee Back Motors Inc",
    "wof:placetype":"venue"
},
  "geometry": {"coordinates":[-104.738467,41.145382],"type":"Point"}
}