{
  "type": "Feature",
  "properties": {
    "iso:country":"US",
    "sg:address":"1101 N Broadway Ave",
    "sg:city":"Riverton",
    "sg:classifiers":[
        {
            "category":"Organizations",
            "subcategory":"Religious Organization",
            "type":"Services"
        }
    ],
    "sg:phone":"+1 307 856 5181",
    "sg:postcode":"82501",
    "sg:province":"WY",
    "sg:tags":[
        "church"
    ],
    "wof:name":"United Presbyterian",
    "wof:placetype":"venue"
},
  "geometry": {"coordinates":[-108.38640700000001,43.037417],"type":"Point"}
}