{
  "type": "Feature",
  "properties": {
    "iso:country":"US",
    "sg:address":"4521 University Rd",
    "sg:city":"Gillette",
    "sg:classifiers":[
        {
            "category":"Shopping",
            "type":"Retail Goods"
        }
    ],
    "sg:phone":"+1 307 687 7789",
    "sg:postcode":"82718",
    "sg:province":"WY",
    "sg:tags":[
        "trophy",
        "merchandise",
        "medal",
        "business",
        "award"
    ],
    "wof:name":"Suzi's Trophies & Awards",
    "wof:placetype":"venue"
},
  "geometry": {"coordinates":[-105.437185,44.287512],"type":"Point"}
}