{
  "type": "Feature",
  "properties": {
    "addr:full":"615 Hamilton St Douglas WY 82633",
    "addr:housenumber":"615",
    "addr:postcode":"82633",
    "addr:street":"Hamilton St Douglas Wy",
    "iso:country":"US",
    "sg:address":"615 Hamilton St",
    "sg:city":"Douglas",
    "sg:classifiers":[
        {
            "category":"Education",
            "subcategory":"School",
            "type":"Public Place"
        }
    ],
    "sg:phone":"+1 307 358 4874",
    "sg:postcode":"82633",
    "sg:province":"WY",
    "sg:tags":[
        "academic",
        "special"
    ],
    "sg:website":"www.ccsd1.k12.wy.us",
    "wof:name":"Student Support Svc",
    "wof:placetype":"venue"
},
  "geometry": {"coordinates":[-105.379355,42.751149],"type":"Point"}
}