{
  "type": "Feature",
  "properties": {
    "iso:country":"US",
    "sg:address":"350 S Ash St",
    "sg:city":"Casper",
    "sg:classifiers":[
        {
            "category":"Organizations",
            "subcategory":"Non-profit Organization",
            "type":"Services"
        }
    ],
    "sg:phone":"+1 307 232 0159",
    "sg:postcode":"82601",
    "sg:province":"WY",
    "wof:name":"Childrens Advocacy Project",
    "wof:placetype":"venue"
},
  "geometry": {"coordinates":[-106.328045,42.847733],"type":"Point"}
}