{
  "type": "Feature",
  "properties": {
    "iso:country":"US",
    "sg:address":"1200 E 20th St",
    "sg:city":"Cheyenne",
    "sg:classifiers":[
        {
            "category":"Professional",
            "subcategory":"Employment Agencies",
            "type":"Services"
        }
    ],
    "sg:phone":"+1 307 635 8731",
    "sg:postcode":"82001",
    "sg:province":"WY",
    "sg:tags":[
        "help",
        "contractor"
    ],
    "wof:name":"Management Recruiters Intl",
    "wof:placetype":"venue"
},
  "geometry": {"coordinates":[-104.803032,41.141698],"type":"Point"}
}