{
  "type": "Feature",
  "properties": {
    "iso:country":"US",
    "sg:address":"1708 Stampede Ave",
    "sg:city":"Cody",
    "sg:classifiers":[
        {
            "category":"Health Services",
            "subcategory":"Optometrist",
            "type":"Services"
        }
    ],
    "sg:phone":"+1 307 587 2404",
    "sg:postcode":"82414",
    "sg:province":"WY",
    "wof:name":"Family Vision Clinic",
    "wof:placetype":"venue"
},
  "geometry": {"coordinates":[-109.05361600000001,44.518749],"type":"Point"}
}