{
  "type": "Feature",
  "properties": {
    "addr:full":"386 N Adams Ave Buffalo WY 82834",
    "addr:housenumber":"386",
    "addr:postcode":"82834",
    "addr:street":"N Adams Ave Buffalo Wy",
    "iso:country":"US",
    "sg:address":"386 N Adams Ave",
    "sg:city":"Buffalo",
    "sg:classifiers":[
        {
            "category":"Building & Trades",
            "subcategory":"Plumbing",
            "type":"Services"
        }
    ],
    "sg:phone":"+1 307 684 5193",
    "sg:postcode":"82834",
    "sg:province":"WY",
    "sg:tags":[
        "contractor"
    ],
    "wof:name":"Dick Roush Plumbing",
    "wof:placetype":"venue"
},
  "geometry": {"coordinates":[-106.700529,44.352031],"type":"Point"}
}