{
  "type": "Feature",
  "properties": {
    "iso:country":"US",
    "sg:address":"71 Green Creek Rd",
    "sg:city":"Cody",
    "sg:classifiers":[
        {
            "category":"Professional",
            "subcategory":"Art Services",
            "type":"Services"
        }
    ],
    "sg:phone":"+1 307 587 5405",
    "sg:postcode":"82414",
    "sg:province":"WY",
    "sg:tags":[
        "commercial",
        "design"
    ],
    "wof:name":"Halvorsen Studios",
    "wof:placetype":"venue"
},
  "geometry": {"coordinates":[-109.492862,44.452668],"type":"Point"}
}