{
  "type": "Feature",
  "properties": {
    "iso:country":"US",
    "sg:address":"6 Sarah Dr",
    "sg:city":"Riverton",
    "sg:classifiers":[
        {
            "category":"Building & Trades",
            "subcategory":"Construction",
            "type":"Services"
        }
    ],
    "sg:phone":"+1 307 857 1669",
    "sg:postcode":"82501",
    "sg:province":"WY",
    "sg:tags":[
        "pumping",
        "contractor"
    ],
    "wof:name":"M & M Inc",
    "wof:placetype":"venue"
},
  "geometry": {"coordinates":[-108.360826,43.118227],"type":"Point"}
}