{
  "type": "Feature",
  "properties": {
    "iso:country":"US",
    "sg:address":"4250 Raven Haven Rd",
    "sg:city":"Jackson",
    "sg:classifiers":[
        {
            "category":"Travel",
            "subcategory":"Hotels & Motels",
            "type":"Entertainment"
        }
    ],
    "sg:phone":"+1 307 739 1411",
    "sg:postcode":"83001",
    "sg:province":"WY",
    "sg:tags":[
        "breakfast",
        "accommodation",
        "bed"
    ],
    "sg:website":"www.bentwoodinn.com",
    "wof:name":"Bentwood Bed & Breakfast",
    "wof:placetype":"venue"
},
  "geometry": {"coordinates":[-110.847692,43.505174],"type":"Point"}
}