{
  "type": "Feature",
  "properties": {
    "addr:full":"300 E Avalanche Canyon Dr Jackson WY 83001",
    "addr:housenumber":"300",
    "addr:postcode":"83001",
    "addr:street":"E Avalanche Canyon Dr Jackson Wy",
    "iso:country":"US",
    "sg:address":"300 E Avalanche Canyon Dr",
    "sg:city":"Jackson",
    "sg:classifiers":[
        {
            "category":"Professional",
            "type":"Services"
        }
    ],
    "sg:phone":"+1 307 733 2676",
    "sg:postcode":"83001",
    "sg:province":"WY",
    "wof:name":"Rick & Barbara Turner",
    "wof:placetype":"venue"
},
  "geometry": {"coordinates":[-110.76229499999999,43.613859],"type":"Point"}
}