{
  "type": "Feature",
  "properties": {
    "addr:full":"3540 E 2nd St Casper WY 82609",
    "addr:housenumber":"3540",
    "addr:postcode":"82609",
    "addr:street":"E 2Nd St",
    "iso:country":"US",
    "sg:address":"3540 E 2nd St",
    "sg:city":"Casper",
    "sg:classifiers":[
        {
            "category":"Shopping",
            "subcategory":"Stationery & Office Supplies",
            "type":"Retail Goods"
        }
    ],
    "sg:phone":"+1 307 234 4770",
    "sg:postcode":"82609",
    "sg:province":"WY",
    "sg:tags":[
        "product"
    ],
    "wof:name":"OfficeMax",
    "wof:placetype":"venue"
},
  "geometry": {"coordinates":[-106.28322900000001,42.848925],"type":"Point"}
}