{
  "type": "Feature",
  "properties": {
    "iso:country":"US",
    "sg:address":"6746 Coffeen Ave",
    "sg:city":"Sheridan",
    "sg:classifiers":[
        {
            "category":"Building & Trades",
            "subcategory":"Construction",
            "type":"Services"
        }
    ],
    "sg:phone":"+1 307 672 3038",
    "sg:postcode":"82801",
    "sg:province":"WY",
    "sg:tags":[
        "house"
    ],
    "wof:name":"All Seasons Insul & Roofg",
    "wof:placetype":"venue"
},
  "geometry": {"coordinates":[-106.957762,44.724583],"type":"Point"}
}