{
  "type": "Feature",
  "properties": {
    "iso:country":"US",
    "sg:address":"611 Crook Ave",
    "sg:city":"Cheyenne",
    "sg:classifiers":[
        {
            "category":"Professional",
            "subcategory":"Engineering",
            "type":"Services"
        }
    ],
    "sg:phone":"+1 307 635 1474",
    "sg:postcode":"82001",
    "sg:province":"WY",
    "sg:tags":[
        "engineer"
    ],
    "wof:name":"Q C Testing",
    "wof:placetype":"venue"
},
  "geometry": {"coordinates":[-104.788589,41.132122],"type":"Point"}
}