{
  "type": "Feature",
  "properties": {
    "iso:country":"US",
    "sg:address":"34 Cottonwood Dr",
    "sg:city":"Sheridan",
    "sg:classifiers":[
        {
            "category":"Health Services",
            "subcategory":"Hospital",
            "type":"Services"
        }
    ],
    "sg:phone":"+1 307 672 3904",
    "sg:postcode":"82801",
    "sg:province":"WY",
    "sg:tags":[
        "specialty"
    ],
    "wof:name":"Cloud Peak Recovery",
    "wof:placetype":"venue"
},
  "geometry": {"coordinates":[-106.948121,44.729212],"type":"Point"}
}