{
  "type": "Feature",
  "properties": {
    "iso:country":"US",
    "sg:address":"121 E Grand Ave",
    "sg:city":"Laramie",
    "sg:classifiers":[
        {
            "category":"Government",
            "subcategory":"Court House",
            "type":"Public Place"
        }
    ],
    "sg:phone":"+1 307 721 3089",
    "sg:postcode":"82070",
    "sg:province":"WY",
    "sg:tags":[
        "county"
    ],
    "wof:name":"Albany County Drug Court",
    "wof:placetype":"venue"
},
  "geometry": {"coordinates":[-105.595941,41.311239],"type":"Point"}
}