{
  "type": "Feature",
  "properties": {
    "iso:country":"US",
    "sg:address":"125 E Pearl Ave",
    "sg:city":"Jackson",
    "sg:classifiers":[
        {
            "category":"Social Services",
            "type":"Services"
        }
    ],
    "sg:phone":"+1 307 733 5453",
    "sg:postcode":"83001",
    "sg:province":"WY",
    "sg:tags":[
        "probation"
    ],
    "wof:name":"Probation & Parole Ofc",
    "wof:placetype":"venue"
},
  "geometry": {"coordinates":[-110.76034300000001,43.478586],"type":"Point"}
}