{
  "type": "Feature",
  "properties": {
    "addr:full":"125 E Pearl Ave Jackson WY 83001",
    "addr:housenumber":"125",
    "addr:postcode":"83001",
    "addr:street":"E Pearl Ave Jackson Wy",
    "iso:country":"US",
    "sg:address":"125 E Pearl Ave",
    "sg:city":"Jackson",
    "sg:classifiers":[
        {
            "category":"Social Services",
            "type":"Services"
        }
    ],
    "sg:phone":"+1 307 733 5453",
    "sg:postcode":"83001",
    "sg:province":"WY",
    "sg:tags":[
        "probation"
    ],
    "wof:name":"Probation & Parole Ofc",
    "wof:placetype":"venue"
},
  "geometry": {"coordinates":[-110.76034300000001,43.478586],"type":"Point"}
}