{
  "type": "Feature",
  "properties": {
    "addr:full":"3320 E Lincolnway Cheyenne WY 82001",
    "addr:housenumber":"3320",
    "addr:postcode":"82001",
    "addr:street":"E Lincolnway;Wy",
    "iso:country":"US",
    "sg:address":"3320 E Lincolnway",
    "sg:city":"Cheyenne",
    "sg:classifiers":[
        {
            "category":"Autos & Motor Vehicles",
            "subcategory":"Motorcycle Sales",
            "type":"Retail Goods"
        }
    ],
    "sg:phone":"+1 307 638 8307",
    "sg:postcode":"82001",
    "sg:province":"WY",
    "sg:tags":[
        "repair"
    ],
    "sg:website":"www.maverickcycles.com",
    "wof:name":"Maverick Cycles",
    "wof:placetype":"venue"
},
  "geometry": {"coordinates":[-104.775561,41.138484],"type":"Point"}
}