{
  "type": "Feature",
  "properties": {
    "addr:full":"1520 Spring Creek Dr Laramie WY 82070",
    "addr:housenumber":"1520",
    "addr:postcode":"82070",
    "addr:street":"Spring Creek Dr",
    "iso:country":"US",
    "sg:address":"1520 Spring Creek Dr",
    "sg:city":"Laramie",
    "sg:classifiers":[
        {
            "category":"Shopping",
            "subcategory":"Pharmacy",
            "type":"Retail Goods"
        }
    ],
    "sg:phone":"+1 307 742 2136",
    "sg:postcode":"82070",
    "sg:province":"WY",
    "sg:tags":[
        "drug",
        "store"
    ],
    "wof:name":"Rite Aid",
    "wof:placetype":"venue"
},
  "geometry": {"coordinates":[-105.575445,41.302887],"type":"Point"}
}