{
  "type": "Feature",
  "properties": {
    "iso:country":"US",
    "sg:address":"120 S Main St",
    "sg:city":"Thayne",
    "sg:classifiers":[
        {
            "category":"Real Estate",
            "subcategory":"Real Estate Agent",
            "type":"Services"
        }
    ],
    "sg:phone":"+1 307 883 2441",
    "sg:postcode":"83127",
    "sg:province":"WY",
    "wof:name":"Edward L Nelson Realty",
    "wof:placetype":"venue"
},
  "geometry": {"coordinates":[-111.00000799999999,42.913449],"type":"Point"}
}