{
  "type": "Feature",
  "properties": {
    "addr:full":"129 N Hwy 33 Driggs WY 83422",
    "addr:housenumber":"129",
    "addr:postcode":"83422",
    "addr:street":"N Hwy 33 Driggs Wy",
    "iso:country":"US",
    "sg:address":"129 N Hwy 33",
    "sg:city":"Driggs",
    "sg:classifiers":[
        {
            "category":"Retail",
            "subcategory":"Veterinary Services",
            "type":"Services"
        }
    ],
    "sg:phone":"+1 208 354 2212",
    "sg:postcode":"83422",
    "sg:province":"WY",
    "sg:tags":[
        "veterinarian"
    ],
    "wof:name":"Driggs Veterinary Clinic",
    "wof:placetype":"venue"
},
  "geometry": {"coordinates":[-111.11089,43.741254],"type":"Point"}
}