{
  "type": "Feature",
  "properties": {
    "addr:full":"1031 S Gurley Ave Gillette WY 82716",
    "addr:housenumber":"1031",
    "addr:postcode":"82716",
    "addr:street":"S Gurley Ave",
    "iso:country":"US",
    "sg:address":"1031 S Gurley Ave",
    "sg:city":"Gillette",
    "sg:classifiers":[
        {
            "category":"Building & Trades",
            "subcategory":"Construction",
            "type":"Services"
        }
    ],
    "sg:phone":"+1 307 685 3676",
    "sg:postcode":"82716",
    "sg:province":"WY",
    "sg:tags":[
        "boring",
        "drilling",
        "contractor"
    ],
    "wof:name":"Simmons Drilling Corp",
    "wof:placetype":"venue"
},
  "geometry": {"coordinates":[-105.48851500000001,44.285429],"type":"Point"}
}