{
  "type": "Feature",
  "properties": {
    "iso:country":"US",
    "sg:address":"2103 E 12th St",
    "sg:city":"Casper",
    "sg:classifiers":[
        {
            "category":"Shopping",
            "subcategory":"Hobbies, Toys, & Games",
            "type":"Retail Goods"
        }
    ],
    "sg:phone":"+1 307 234 9079",
    "sg:postcode":"82601",
    "sg:province":"WY",
    "wof:name":"Scrapbook Superstore",
    "wof:placetype":"venue"
},
  "geometry": {"coordinates":[-106.29788000000001,42.838879],"type":"Point"}
}