{
  "type": "Feature",
  "properties": {
    "addr:full":"1002 Liberty Ln Gillette WY 82716",
    "addr:housenumber":"1002",
    "addr:postcode":"82716",
    "addr:street":"Liberty Ln",
    "iso:country":"US",
    "sg:address":"1002 Liberty Ln",
    "sg:city":"Gillette",
    "sg:classifiers":[
        {
            "category":"Social Services",
            "subcategory":"Child Care",
            "type":"Services"
        }
    ],
    "sg:phone":"+1 307 686 2825",
    "sg:postcode":"82716",
    "sg:province":"WY",
    "sg:tags":[
        "day"
    ],
    "wof:name":"24 7 Babysitter From Heaven",
    "wof:placetype":"venue"
},
  "geometry": {"coordinates":[-105.47974499999999,44.30817],"type":"Point"}
}