{
  "type": "Feature",
  "properties": {
    "iso:country":"US",
    "sg:address":"3913 Evans Ave",
    "sg:city":"Cheyenne",
    "sg:classifiers":[
        {
            "category":"Building & Trades",
            "subcategory":"Equipment Rental",
            "type":"Services"
        }
    ],
    "sg:phone":"+1 307 634 4417",
    "sg:postcode":"82001",
    "sg:province":"WY",
    "sg:tags":[
        "aircraft",
        "leasing",
        "charter"
    ],
    "sg:website":"www.skyharborair.com",
    "wof:name":"Sky Harbor Air Svc",
    "wof:placetype":"venue"
},
  "geometry": {"coordinates":[-104.818572,41.152207],"type":"Point"}
}