{
  "type": "Feature",
  "properties": {
    "iso:country":"US",
    "sg:address":"6409 Tassel Ave",
    "sg:city":"Gillette",
    "sg:classifiers":[
        {
            "category":"Real Estate",
            "subcategory":"Real Estate Agent",
            "type":"Services"
        }
    ],
    "sg:phone":"+1 307 682 3021",
    "sg:postcode":"82718",
    "sg:province":"WY",
    "sg:tags":[
        "business"
    ],
    "wof:name":"Robert L Zabel & Co",
    "wof:placetype":"venue"
},
  "geometry": {"coordinates":[-105.426294,44.235002],"type":"Point"}
}