{
  "type": "Feature",
  "properties": {
    "iso:country":"US",
    "sg:address":"109 E 17th St",
    "sg:city":"Cheyenne",
    "sg:classifiers":[
        {
            "category":"Real Estate",
            "subcategory":"Real Estate Agent",
            "type":"Services"
        }
    ],
    "sg:phone":"+1 307 638 1700",
    "sg:postcode":"82001",
    "sg:province":"WY",
    "wof:name":"Era Advantage Real Estate",
    "wof:placetype":"venue"
},
  "geometry": {"coordinates":[-104.813647,41.134343],"type":"Point"}
}