{
  "type": "Feature",
  "properties": {
    "iso:country":"US",
    "sg:address":"1225 10th St",
    "sg:city":"Cody",
    "sg:classifiers":[
        {
            "category":"Education",
            "subcategory":"School",
            "type":"Public Place"
        }
    ],
    "sg:phone":"+1 307 587 7025",
    "sg:postcode":"82414",
    "sg:province":"WY",
    "wof:name":"School Officer",
    "wof:placetype":"venue"
},
  "geometry": {"coordinates":[-109.06789499999999,44.524686],"type":"Point"}
}