{
  "type": "Feature",
  "properties": {
    "iso:country":"US",
    "sg:address":"250 Monroe Ave",
    "sg:city":"Green River",
    "sg:classifiers":[
        {
            "category":"Education",
            "subcategory":"School",
            "type":"Public Place"
        }
    ],
    "sg:phone":"+1 307 872 4000",
    "sg:postcode":"82935",
    "sg:province":"WY",
    "wof:name":"Monroe Intermedite School",
    "wof:placetype":"venue"
},
  "geometry": {"coordinates":[-109.46917000000001,41.51076],"type":"Point"}
}