{
  "type": "Feature",
  "properties": {
    "addr:full":"3702 Dell Range Blvd Cheyenne WY 82009",
    "addr:housenumber":"3702",
    "addr:postcode":"82009",
    "addr:street":"Dell Range Blvd",
    "iso:country":"US",
    "sg:address":"3702 Dell Range Blvd",
    "sg:city":"Cheyenne",
    "sg:classifiers":[
        {
            "category":"Food & Beverages",
            "subcategory":"Groceries & Convenience Stores",
            "type":"Retail Goods"
        }
    ],
    "sg:phone":"+1 307 638 0014",
    "sg:postcode":"82009",
    "sg:province":"WY",
    "sg:tags":[
        "supermarket"
    ],
    "wof:name":"King Soopers 079",
    "wof:placetype":"venue"
},
  "geometry": {"coordinates":[-104.763914,41.160138],"type":"Point"}
}