{
  "type": "Feature",
  "properties": {
    "iso:country":"US",
    "sg:address":"429 E Sunset Dr",
    "sg:city":"Riverton",
    "sg:classifiers":[
        {
            "category":"Organizations",
            "subcategory":"Religious Organization",
            "type":"Services"
        }
    ],
    "sg:phone":"+1 307 856 6320",
    "sg:postcode":"82501",
    "sg:province":"WY",
    "sg:tags":[
        "church"
    ],
    "wof:name":"Calvary Baptist Church",
    "wof:placetype":"venue"
},
  "geometry": {"coordinates":[-108.38668,43.03391],"type":"Point"}
}