{
  "type": "Feature",
  "properties": {
    "addr:full":"1720 Jafer Rd Casper WY 82601",
    "addr:housenumber":"1720",
    "addr:postcode":"82601",
    "addr:street":"Jafer Rd",
    "iso:country":"US",
    "sg:address":"1720 Jafer Rd",
    "sg:city":"Casper",
    "sg:classifiers":[
        {
            "category":"Mining & Drilling",
            "type":"Manufacturing & Wholesale Goods"
        }
    ],
    "sg:phone":"+1 307 237 0613",
    "sg:postcode":"82601",
    "sg:province":"WY",
    "sg:tags":[
        "field",
        "oil"
    ],
    "wof:name":"Moxley & Moxley Transportation",
    "wof:placetype":"venue"
},
  "geometry": {"coordinates":[-106.345692,42.89823],"type":"Point"}
}