{
  "type": "Feature",
  "properties": {
    "iso:country":"US",
    "sg:address":"140 N Cache Dr",
    "sg:city":"Jackson",
    "sg:classifiers":[
        {
            "category":"Retail",
            "subcategory":"Photofinishing",
            "type":"Services"
        }
    ],
    "sg:phone":"+1 307 733 0635",
    "sg:postcode":"83001",
    "sg:province":"WY",
    "sg:tags":[
        "photo",
        "finishing"
    ],
    "wof:name":"Sure Shot 1 Hr Photo",
    "wof:placetype":"venue"
},
  "geometry": {"coordinates":[-110.76230200000001,43.481538],"type":"Point"}
}