{
  "type": "Feature",
  "properties": {
    "addr:full":"15 N Fork Rd Fort Washakie WY 82514",
    "addr:housenumber":"15",
    "addr:postcode":"82514",
    "addr:street":"N Fork Rd Fort Washakie Wy",
    "iso:country":"US",
    "sg:address":"15 N Fork Rd",
    "sg:city":"Fort Washakie",
    "sg:classifiers":[
        {
            "category":"Government",
            "subcategory":"Office",
            "type":"Public Place"
        }
    ],
    "sg:phone":"+1 307 856 7870",
    "sg:postcode":"82514",
    "sg:province":"WY",
    "wof:name":"Shoshone Child Protection",
    "wof:placetype":"venue"
},
  "geometry": {"coordinates":[-108.88405,43.002955],"type":"Point"}
}