{
  "type": "Feature",
  "properties": {
    "iso:country":"US",
    "sg:address":"801 W 20th St",
    "sg:city":"Cheyenne",
    "sg:classifiers":[
        {
            "category":"Government",
            "subcategory":"Office",
            "type":"Public Place"
        }
    ],
    "sg:phone":"+1 307 777 7767",
    "sg:postcode":"82001",
    "sg:province":"WY",
    "sg:tags":[
        "administration",
        "general"
    ],
    "wof:name":"Adminstrtion Info Wyoming Dept",
    "wof:placetype":"venue"
},
  "geometry": {"coordinates":[-104.825434,41.133374],"type":"Point"}
}