{
  "type": "Feature",
  "properties": {
    "addr:full":"803 S 3rd St Laramie WY 82070",
    "addr:housenumber":"803",
    "addr:postcode":"82070",
    "addr:street":"S 3Rd St",
    "iso:country":"US",
    "sg:address":"803 S 3rd St",
    "sg:city":"Laramie",
    "sg:classifiers":[
        {
            "category":"Health Services",
            "subcategory":"Health Practitioner",
            "type":"Services"
        }
    ],
    "sg:phone":"+1 307 721 9527",
    "sg:postcode":"82070",
    "sg:province":"WY",
    "wof:name":"Snowy Range Audiology",
    "wof:placetype":"venue"
},
  "geometry": {"coordinates":[-105.594044,41.306278],"type":"Point"}
}