{
  "type": "Feature",
  "properties": {
    "iso:country":"US",
    "sg:address":"1259 Bishop Rd",
    "sg:city":"Rozet",
    "sg:classifiers":[
        {
            "category":"Mining & Drilling",
            "type":"Manufacturing & Wholesale Goods"
        }
    ],
    "sg:phone":"+1 307 682 9578",
    "sg:postcode":"82727",
    "sg:province":"WY",
    "sg:tags":[
        "field"
    ],
    "wof:name":"Timothy Fleck",
    "wof:placetype":"venue"
},
  "geometry": {"coordinates":[-105.199713,44.092534],"type":"Point"}
}