{
  "type": "Feature",
  "properties": {
    "iso:country":"US",
    "sg:address":"530 E Broadway",
    "sg:city":"Jackson",
    "sg:classifiers":[
        {
            "category":"Wholesale",
            "subcategory":"Construction Materials",
            "type":"Manufacturing & Wholesale Goods"
        }
    ],
    "sg:phone":"+1 307 733 0535",
    "sg:postcode":"83001",
    "sg:province":"WY",
    "wof:name":"Pella Products Inc",
    "wof:placetype":"venue"
},
  "geometry": {"coordinates":[-110.75076199999999,43.479693],"type":"Point"}
}