{
  "type": "Feature",
  "properties": {
    "addr:full":"114 S 6th St E Riverton WY 82501",
    "addr:housenumber":"114",
    "addr:postcode":"82501",
    "addr:street":"S 6Th St",
    "iso:country":"US",
    "sg:address":"114 S 6th St E",
    "sg:city":"Riverton",
    "sg:classifiers":[
        {
            "category":"Professional",
            "subcategory":"Accounting & Tax Preparation",
            "type":"Services"
        }
    ],
    "sg:phone":"+1 307 856 7300",
    "sg:postcode":"82501",
    "sg:province":"WY",
    "sg:tags":[
        "accountant"
    ],
    "wof:name":"Albright Becker & Stoddard Inc",
    "wof:placetype":"venue"
},
  "geometry": {"coordinates":[-108.383506,43.024512],"type":"Point"}
}