{
  "type": "Feature",
  "properties": {
    "iso:country":"US",
    "sg:address":"2204 Steadman St",
    "sg:city":"Cody",
    "sg:classifiers":[
        {
            "category":"Recreation",
            "type":"Entertainment"
        }
    ],
    "sg:phone":"+1 307 527 7822",
    "sg:postcode":"82414",
    "sg:province":"WY",
    "sg:tags":[
        "organization",
        "membership"
    ],
    "wof:name":"Cody Skylighters",
    "wof:placetype":"venue"
},
  "geometry": {"coordinates":[-109.094956,44.510713],"type":"Point"}
}