{
  "type": "Feature",
  "properties": {
    "iso:country":"US",
    "sg:address":"6645 Lower Cascade Dr",
    "sg:city":"Jackson",
    "sg:classifiers":[
        {
            "category":"Professional",
            "subcategory":"Advertising",
            "type":"Services"
        }
    ],
    "sg:phone":"+1 307 732 2325",
    "sg:postcode":"83001",
    "sg:province":"WY",
    "sg:tags":[
        "agency"
    ],
    "wof:name":"Metafore Mktg Communications",
    "wof:placetype":"venue"
},
  "geometry": {"coordinates":[-110.777402,43.575166],"type":"Point"}
}