{
  "type": "Feature",
  "properties": {
    "iso:country":"US",
    "sg:address":"515 E Carlson St",
    "sg:city":"Cheyenne",
    "sg:classifiers":[
        {
            "category":"Recreation",
            "type":"Entertainment"
        }
    ],
    "sg:phone":"+1 307 433 1881",
    "sg:postcode":"82009",
    "sg:province":"WY",
    "sg:tags":[
        "instruction",
        "gymnastic"
    ],
    "wof:name":"Wyoming School Of Gymnastics",
    "wof:placetype":"venue"
},
  "geometry": {"coordinates":[-104.818669,41.171163],"type":"Point"}
}