{
  "type": "Feature",
  "properties": {
    "addr:full":"425 S Gillette Ave Gillette WY 82716",
    "addr:housenumber":"425",
    "addr:postcode":"82716",
    "addr:street":"S Gillette Ave",
    "iso:country":"US",
    "sg:address":"425 S Gillette Ave",
    "sg:city":"Gillette",
    "sg:classifiers":[
        {
            "category":"Retail",
            "subcategory":"Portrait Studio",
            "type":"Services"
        }
    ],
    "sg:phone":"+1 307 686 3094",
    "sg:postcode":"82716",
    "sg:province":"WY",
    "sg:tags":[
        "photographer"
    ],
    "sg:website":"www.dunlapphoto.com",
    "wof:name":"Dunlap Photography",
    "wof:placetype":"venue"
},
  "geometry": {"coordinates":[-105.50386,44.290978],"type":"Point"}
}