{
  "type": "Feature",
  "properties": {
    "iso:country":"US",
    "sg:address":"211 E 6th St",
    "sg:city":"Casper",
    "sg:classifiers":[
        {
            "category":"Personal",
            "subcategory":"Beauty Salon",
            "type":"Services"
        }
    ],
    "sg:phone":"+1 307 577 5652",
    "sg:postcode":"82601",
    "sg:province":"WY",
    "wof:name":"Village Hairsmith",
    "wof:placetype":"venue"
},
  "geometry": {"coordinates":[-106.322463,42.844561],"type":"Point"}
}