{
  "type": "Feature",
  "properties": {
    "iso:country":"US",
    "sg:address":"10711 E Polo Plate",
    "sg:city":"Cheyenne",
    "sg:classifiers":[
        {
            "category":"Farming",
            "subcategory":"Fish & Marine Products",
            "type":"Manufacturing & Wholesale Goods"
        }
    ],
    "sg:phone":"+1 307 635 1030",
    "sg:postcode":"82009",
    "sg:province":"WY",
    "sg:tags":[
        "catching"
    ],
    "wof:name":"GP Service Inc",
    "wof:placetype":"venue"
},
  "geometry": {"coordinates":[-104.819458,41.216966],"type":"Point"}
}