{
  "type": "Feature",
  "properties": {
    "addr:full":"425 N Irishman Rd Riverton WY 82501",
    "addr:housenumber":"425",
    "addr:postcode":"82501",
    "addr:street":"N Irishman Rd",
    "iso:country":"US",
    "sg:address":"425 N Irishman Rd",
    "sg:city":"Riverton",
    "sg:classifiers":[
        {
            "category":"Professional",
            "subcategory":"Management & Consulting",
            "type":"Services"
        }
    ],
    "sg:phone":"+1 307 857 3083",
    "sg:postcode":"82501",
    "sg:province":"WY",
    "sg:tags":[
        "consultant"
    ],
    "wof:name":"Wind River Consulting Svc Inc",
    "wof:placetype":"venue"
},
  "geometry": {"coordinates":[-108.530883,43.180559],"type":"Point"}
}