{
  "type": "Feature",
  "properties": {
    "iso:country":"US",
    "sg:address":"3633 US Hwy 191",
    "sg:city":"Farson",
    "sg:classifiers":[
        {
            "category":"Bars & Pubs",
            "type":"Food & Drink"
        }
    ],
    "sg:phone":"+1 307 273 9496",
    "sg:postcode":"82932",
    "sg:province":"WY",
    "sg:tags":[
        "saloon"
    ],
    "wof:name":"Eden Saloon",
    "wof:placetype":"venue"
},
  "geometry": {"coordinates":[-109.438085,42.048526],"type":"Point"}
}