{
  "type": "Feature",
  "properties": {
    "addr:full":"1127 Division St Upton WY 82730",
    "addr:housenumber":"1127",
    "addr:postcode":"82730",
    "addr:street":"Division St Upton Wy",
    "iso:country":"US",
    "sg:address":"1127 Division St",
    "sg:city":"Upton",
    "sg:classifiers":[
        {
            "category":"Autos & Motor Vehicles",
            "subcategory":"Automobile Sales",
            "type":"Retail Goods"
        }
    ],
    "sg:phone":"+1 307 468 2333",
    "sg:postcode":"82730",
    "sg:province":"WY",
    "sg:tags":[
        "car",
        "dealer"
    ],
    "wof:name":"Jones Auto Lube",
    "wof:placetype":"venue"
},
  "geometry": {"coordinates":[-104.618894,44.104165],"type":"Point"}
}