{
  "type": "Feature",
  "properties": {
    "iso:country":"US",
    "sg:address":"225 Sherman St",
    "sg:city":"Rock Springs",
    "sg:classifiers":[
        {
            "category":"Building & Trades",
            "subcategory":"Landscaping Services",
            "type":"Services"
        }
    ],
    "sg:phone":"+1 307 382 8675",
    "sg:postcode":"82901",
    "sg:province":"WY",
    "wof:name":"Lewis Tree Service",
    "wof:placetype":"venue"
},
  "geometry": {"coordinates":[-109.225556,41.586788],"type":"Point"}
}