{
  "type": "Feature",
  "properties": {
    "iso:country":"US",
    "sg:address":"704 Co Rd 5",
    "sg:city":"Deaver",
    "sg:classifiers":[
        {
            "category":"Building & Trades",
            "subcategory":"Electrical",
            "type":"Services"
        }
    ],
    "sg:phone":"+1 307 548 7686",
    "sg:postcode":"82421",
    "sg:province":"WY",
    "sg:tags":[
        "electrical",
        "contractor"
    ],
    "wof:name":"D & M Electric",
    "wof:placetype":"venue"
},
  "geometry": {"coordinates":[-108.51915200000001,44.899398],"type":"Point"}
}