{
  "type": "Feature",
  "properties": {
    "iso:country":"US",
    "sg:address":"101 Bridger Xing",
    "sg:city":"Douglas",
    "sg:classifiers":[
        {
            "category":"Communications",
            "subcategory":"Film & Video Production",
            "type":"Services"
        }
    ],
    "sg:phone":"+1 307 358 5117",
    "sg:postcode":"82633",
    "sg:province":"WY",
    "sg:tags":[
        "motion"
    ],
    "wof:name":"Venjohn Production Services In",
    "wof:placetype":"venue"
},
  "geometry": {"coordinates":[-105.17196,42.648348],"type":"Point"}
}