{
  "type": "Feature",
  "properties": {
    "iso:country":"US",
    "sg:address":"208 S 6th St E",
    "sg:city":"Riverton",
    "sg:classifiers":[
        {
            "category":"Social Services",
            "type":"Services"
        }
    ],
    "sg:phone":"+1 307 856 9630",
    "sg:postcode":"82501",
    "sg:province":"WY",
    "wof:name":"Milk On Mooove",
    "wof:placetype":"venue"
},
  "geometry": {"coordinates":[-108.383493,43.023501],"type":"Point"}
}