{
  "type": "Feature",
  "properties": {
    "iso:country":"US",
    "sg:address":"1657 Snowy Range Rd",
    "sg:city":"Laramie",
    "sg:classifiers":[
        {
            "category":"Autos & Motor Vehicles",
            "subcategory":"Fuel & Gas Station",
            "type":"Retail Goods"
        }
    ],
    "sg:phone":"+1 307 745 5425",
    "sg:postcode":"82070",
    "sg:province":"WY",
    "sg:tags":[
        "station",
        "gasoline",
        "fishing",
        "hunting",
        "supply"
    ],
    "sg:website":"www.flystore.net",
    "wof:name":"West Laramie Fly Store",
    "wof:placetype":"venue"
},
  "geometry": {"coordinates":[-105.61797199999999,41.309063],"type":"Point"}
}