{
  "type": "Feature",
  "properties": {
    "addr:full":"2923 E Lincolnway Cheyenne WY 82001",
    "addr:housenumber":"2923",
    "addr:postcode":"82001",
    "addr:street":"E Lincolnway;Wy",
    "iso:country":"US",
    "sg:address":"2923 E Lincolnway",
    "sg:city":"Cheyenne",
    "sg:classifiers":[
        {
            "category":"Communications",
            "subcategory":"Television Station",
            "type":"Services"
        }
    ],
    "sg:phone":"+1 307 634 7755",
    "sg:postcode":"82001",
    "sg:province":"WY",
    "wof:name":"Kgwn TV",
    "wof:placetype":"venue"
},
  "geometry": {"coordinates":[-104.781272,41.13833],"type":"Point"}
}