{
  "type": "Feature",
  "properties": {
    "addr:full":"111 N Bent St Powell WY 82435",
    "addr:housenumber":"111",
    "addr:postcode":"82435",
    "addr:street":"N Bent St Powell Wy",
    "iso:country":"US",
    "sg:address":"111 N Bent St",
    "sg:city":"Powell",
    "sg:classifiers":[
        {
            "category":"Professional",
            "subcategory":"Printing & Photocopies",
            "type":"Services"
        }
    ],
    "sg:phone":"+1 307 754 9001",
    "sg:postcode":"82435",
    "sg:province":"WY",
    "sg:tags":[
        "photocopying",
        "business",
        "duplicating",
        "communications",
        "telegraph",
        "copying"
    ],
    "wof:name":"Z Bar Diamond Copy Center",
    "wof:placetype":"venue"
},
  "geometry": {"coordinates":[-108.75752300000001,44.754043],"type":"Point"}
}