{
  "type": "Feature",
  "properties": {
    "addr:full":"1532 Willow Dr Cheyenne WY 82001",
    "addr:housenumber":"1532",
    "addr:postcode":"82001",
    "addr:street":"Willow Dr",
    "iso:country":"US",
    "sg:address":"1532 Willow Dr",
    "sg:city":"Cheyenne",
    "sg:classifiers":[
        {
            "category":"Shopping",
            "subcategory":"Used Merchandise",
            "type":"Retail Goods"
        }
    ],
    "sg:phone":"+1 307 635 1185",
    "sg:postcode":"82001",
    "sg:province":"WY",
    "sg:tags":[
        "furniture"
    ],
    "wof:name":"Southside Furniture",
    "wof:placetype":"venue"
},
  "geometry": {"coordinates":[-104.782881,41.141279],"type":"Point"}
}