{
  "type": "Feature",
  "properties": {
    "addr:full":"1221 E Main St Riverton WY 82501",
    "addr:housenumber":"1221",
    "addr:postcode":"82501",
    "addr:street":"E Main St",
    "iso:country":"US",
    "sg:address":"1221 E Main St",
    "sg:city":"Riverton",
    "sg:classifiers":[
        {
            "category":"Health Services",
            "subcategory":"Chiropractor",
            "type":"Services"
        }
    ],
    "sg:phone":"+1 307 856 4945",
    "sg:postcode":"82501",
    "sg:province":"WY",
    "wof:name":"Riverton Chiropractic Clinic",
    "wof:placetype":"venue"
},
  "geometry": {"coordinates":[-108.375429,43.02463],"type":"Point"}
}