{
  "type": "Feature",
  "properties": {
    "addr:full":"1906 Garrett St Cheyenne WY 82001",
    "addr:housenumber":"1906",
    "addr:postcode":"82001",
    "addr:street":"Garrett St",
    "iso:country":"US",
    "sg:address":"1906 Garrett St",
    "sg:city":"Cheyenne",
    "sg:classifiers":[
        {
            "category":"Organizations",
            "subcategory":"Religious Organization",
            "type":"Services"
        }
    ],
    "sg:phone":"+1 307 638 8006",
    "sg:postcode":"82001",
    "sg:province":"WY",
    "wof:name":"Redeemer Lutheran Church",
    "wof:placetype":"venue"
},
  "geometry": {"coordinates":[-104.792721,41.143416],"type":"Point"}
}