{
  "type": "Feature",
  "properties": {
    "iso:country":"US",
    "sg:address":"841 Main St",
    "sg:city":"Dayton",
    "sg:classifiers":[
        {
            "category":"Shopping",
            "subcategory":"Gifts & Souvenirs",
            "type":"Retail Goods"
        }
    ],
    "sg:phone":"+1 307 655 3974",
    "sg:postcode":"82836",
    "sg:province":"WY",
    "sg:tags":[
        "shop"
    ],
    "wof:name":"Aspen Creek Galleria",
    "wof:placetype":"venue"
},
  "geometry": {"coordinates":[-107.26261700000001,44.871337],"type":"Point"}
}