{
  "type": "Feature",
  "properties": {
    "addr:full":"1805 Big Horn Ave Worland WY 82401",
    "addr:housenumber":"1805",
    "addr:postcode":"82401",
    "addr:street":"Big Horn Ave",
    "iso:country":"US",
    "sg:address":"1805 Big Horn Ave",
    "sg:city":"Worland",
    "sg:classifiers":[
        {
            "category":"Banks & Credit Unions",
            "subcategory":"Bank",
            "type":"Services"
        }
    ],
    "sg:phone":"+1 307 347 8315",
    "sg:postcode":"82401",
    "sg:province":"WY",
    "sg:tags":[
        "federal"
    ],
    "wof:name":"Sunlight Federal Credit Union",
    "wof:placetype":"venue"
},
  "geometry": {"coordinates":[-107.944833,44.016903],"type":"Point"}
}