{
  "type": "Feature",
  "properties": {
    "iso:country":"US",
    "sg:address":"8344 Shady Ln",
    "sg:city":"Evansville",
    "sg:classifiers":[
        {
            "category":"Building & Trades",
            "subcategory":"Construction",
            "type":"Services"
        }
    ],
    "sg:phone":"+1 307 235 6456",
    "sg:postcode":"82636",
    "sg:province":"WY",
    "sg:tags":[
        "water",
        "boring",
        "well",
        "drilling",
        "contractor"
    ],
    "wof:name":"Mead Drilling Inc",
    "wof:placetype":"venue"
},
  "geometry": {"coordinates":[-106.19468999999999,42.88507],"type":"Point"}
}