{
  "type": "Feature",
  "properties": {
    "iso:country":"US",
    "sg:address":"341 E Mill Rd",
    "sg:city":"Alpine",
    "sg:classifiers":[
        {
            "category":"Building & Trades",
            "subcategory":"Construction",
            "type":"Services"
        }
    ],
    "sg:phone":"+1 307 654 0494",
    "sg:postcode":"83128",
    "sg:province":"WY",
    "sg:tags":[
        "log",
        "chinking"
    ],
    "wof:name":"Teton Chinking",
    "wof:placetype":"venue"
},
  "geometry": {"coordinates":[-111.00686899999999,43.158599],"type":"Point"}
}