{
  "type": "Feature",
  "properties": {
    "iso:country":"US",
    "sg:address":"376 S Sublette Ave",
    "sg:city":"Pinedale",
    "sg:classifiers":[
        {
            "category":"Health Services",
            "subcategory":"Optometrist",
            "type":"Services"
        }
    ],
    "sg:phone":"+1 307 367 2727",
    "sg:postcode":"82941",
    "sg:province":"WY",
    "wof:name":"Clear Creek Vision Care",
    "wof:placetype":"venue"
},
  "geometry": {"coordinates":[-109.858456,42.863146],"type":"Point"}
}