{
  "type": "Feature",
  "properties": {
    "addr:full":"1701 Stampede Ave Cody WY 82414",
    "addr:housenumber":"1701",
    "addr:postcode":"82414",
    "addr:street":"Stampede Ave",
    "iso:country":"US",
    "sg:address":"1701 Stampede Ave",
    "sg:city":"Cody",
    "sg:classifiers":[
        {
            "category":"Professional",
            "subcategory":"Accounting & Tax Preparation",
            "type":"Services"
        }
    ],
    "sg:phone":"+1 307 587 1141",
    "sg:postcode":"82414",
    "sg:province":"WY",
    "sg:tags":[
        "accountant"
    ],
    "wof:name":"Jim Vanaman Tax & Accounting",
    "wof:placetype":"venue"
},
  "geometry": {"coordinates":[-109.05355900000001,44.518826],"type":"Point"}
}