{
  "type": "Feature",
  "properties": {
    "addr:full":"615 W Elk Ave Jackson WY 83001",
    "addr:housenumber":"615",
    "addr:postcode":"83001",
    "addr:street":"W Elk Ave Jackson Wy",
    "iso:country":"US",
    "sg:address":"615 W Elk Ave",
    "sg:city":"Jackson",
    "sg:classifiers":[
        {
            "category":"Freight",
            "type":"Transportation"
        }
    ],
    "sg:phone":"+1 307 739 8553",
    "sg:postcode":"83001",
    "sg:province":"WY",
    "sg:tags":[
        "mover"
    ],
    "wof:name":"Black Diamond Moving Co",
    "wof:placetype":"venue"
},
  "geometry": {"coordinates":[-110.77591099999999,43.423335],"type":"Point"}
}