{
  "type": "Feature",
  "properties": {
    "addr:full":"2849 E 2nd St Casper WY 82609",
    "addr:housenumber":"2849",
    "addr:postcode":"82609",
    "addr:street":"E 2Nd St",
    "iso:country":"US",
    "sg:address":"2849 E 2nd St",
    "sg:city":"Casper",
    "sg:classifiers":[
        {
            "category":"Real Estate",
            "subcategory":"Real Estate Agent",
            "type":"Services"
        }
    ],
    "sg:phone":"+1 307 577 5707",
    "sg:postcode":"82609",
    "sg:province":"WY",
    "wof:name":"Real Estate Company",
    "wof:placetype":"venue"
},
  "geometry": {"coordinates":[-106.289929,42.848735],"type":"Point"}
}