{
  "type": "Feature",
  "properties": {
    "addr:full":"1904 E 15th St Cheyenne WY 82001",
    "addr:housenumber":"1904",
    "addr:postcode":"82001",
    "addr:street":"E 15Th St",
    "iso:country":"US",
    "sg:address":"1904 E 15th St",
    "sg:city":"Cheyenne",
    "sg:classifiers":[
        {
            "category":"Professional",
            "subcategory":"Research",
            "type":"Services"
        }
    ],
    "sg:phone":"+1 307 634 0752",
    "sg:postcode":"82001",
    "sg:province":"WY",
    "sg:tags":[
        "commercial",
        "physical"
    ],
    "wof:name":"Purcell Consulting",
    "wof:placetype":"venue"
},
  "geometry": {"coordinates":[-104.794023,41.139296],"type":"Point"}
}