{
  "type": "Feature",
  "properties": {
    "iso:country":"US",
    "sg:address":"340 Popo Agie St",
    "sg:city":"Lander",
    "sg:classifiers":[
        {
            "category":"Professional",
            "subcategory":"Management & Consulting",
            "type":"Services"
        }
    ],
    "sg:phone":"+1 307 332 7214",
    "sg:postcode":"82520",
    "sg:province":"WY",
    "sg:tags":[
        "business"
    ],
    "wof:name":"Kanengieter Consulting Group L",
    "wof:placetype":"venue"
},
  "geometry": {"coordinates":[-108.733221,42.830258],"type":"Point"}
}