{
  "type": "Feature",
  "properties": {
    "addr:full":"971 Rd 17 Powell WY 82435",
    "addr:housenumber":"971",
    "addr:postcode":"82435",
    "addr:street":"Rd 17 Powell Wy",
    "iso:country":"US",
    "sg:address":"971 Rd 17",
    "sg:city":"Powell",
    "sg:classifiers":[
        {
            "category":"Freight",
            "type":"Transportation"
        }
    ],
    "sg:phone":"+1 307 754 9002",
    "sg:postcode":"82435",
    "sg:province":"WY",
    "sg:tags":[
        "operator",
        "hauling",
        "trucking"
    ],
    "wof:name":"Rodriquez Truck",
    "wof:placetype":"venue"
},
  "geometry": {"coordinates":[-108.912001,44.744462],"type":"Point"}
}