{
  "type": "Feature",
  "properties": {
    "iso:country":"US",
    "sg:address":"406 Co Rd 154",
    "sg:city":"Carpenter",
    "sg:classifiers":[
        {
            "category":"Shopping",
            "subcategory":"Computers & Home Electronics",
            "type":"Retail Goods"
        }
    ],
    "sg:phone":"+1 307 649 2339",
    "sg:postcode":"82054",
    "sg:province":"WY",
    "wof:name":"Mile HI Search & Recovery",
    "wof:placetype":"venue"
},
  "geometry": {"coordinates":[-104.25514,41.07032],"type":"Point"}
}