{
  "type": "Feature",
  "properties": {
    "iso:country":"US",
    "sg:address":"440 Dewar Dr",
    "sg:city":"Rock Springs",
    "sg:classifiers":[
        {
            "category":"Education",
            "subcategory":"School",
            "type":"Public Place"
        }
    ],
    "sg:phone":"+1 307 362 6524",
    "sg:postcode":"82901",
    "sg:province":"WY",
    "sg:tags":[
        "academic",
        "special"
    ],
    "wof:name":"Roosevelt Project",
    "wof:placetype":"venue"
},
  "geometry": {"coordinates":[-109.226596,41.584632],"type":"Point"}
}