{
  "type": "Feature",
  "properties": {
    "iso:country":"US",
    "sg:address":"716 Jason Rd",
    "sg:city":"Powell",
    "sg:classifiers":[
        {
            "category":"Restaurant",
            "type":"Food & Drink"
        }
    ],
    "sg:phone":"+1 307 754 3837",
    "sg:postcode":"82435",
    "sg:province":"WY",
    "sg:tags":[
        "eating"
    ],
    "wof:name":"Espresso Express/Lunch To Go",
    "wof:placetype":"venue"
},
  "geometry": {"coordinates":[-108.77385,44.779389],"type":"Point"}
}