{
  "type": "Feature",
  "properties": {
    "addr:full":"1646 Bowman Ave Sheridan WY 82801",
    "addr:housenumber":"1646",
    "addr:postcode":"82801",
    "addr:street":"Bowman Ave",
    "iso:country":"US",
    "sg:address":"1646 Bowman Ave",
    "sg:city":"Sheridan",
    "sg:classifiers":[
        {
            "category":"Professional",
            "type":"Services"
        }
    ],
    "sg:phone":"+1 307 672 5535",
    "sg:postcode":"82801",
    "sg:province":"WY",
    "wof:name":"FTL Svc Co",
    "wof:placetype":"venue"
},
  "geometry": {"coordinates":[-106.96713,44.815229],"type":"Point"}
}