{
  "type": "Feature",
  "properties": {
    "iso:country":"US",
    "sg:address":"614 S 1st St",
    "sg:city":"Dubois",
    "sg:classifiers":[
        {
            "category":"Building & Trades",
            "subcategory":"Construction",
            "type":"Services"
        }
    ],
    "sg:phone":"+1 307 455 2731",
    "sg:postcode":"82513",
    "sg:province":"WY",
    "sg:tags":[
        "woodworker"
    ],
    "wof:name":"Deertrack",
    "wof:placetype":"venue"
},
  "geometry": {"coordinates":[-109.630805,43.531974],"type":"Point"}
}