{
  "type": "Feature",
  "properties": {
    "iso:country":"US",
    "sg:address":"919 W Brundage Ln",
    "sg:city":"Sheridan",
    "sg:classifiers":[
        {
            "category":"Manufacturing",
            "subcategory":"Aerospace",
            "type":"Manufacturing & Wholesale Goods"
        }
    ],
    "sg:phone":"+1 307 674 6497",
    "sg:postcode":"82801",
    "sg:province":"WY",
    "sg:tags":[
        "protective",
        "shield",
        "for",
        "mfg",
        "sun",
        "covering",
        "aircraft"
    ],
    "wof:name":"Kennon Protective Coverings",
    "wof:placetype":"venue"
},
  "geometry": {"coordinates":[-106.9683,44.77343],"type":"Point"}
}