{
  "type": "Feature",
  "properties": {
    "addr:full":"3322 E Grand Ave Laramie WY 82070",
    "addr:housenumber":"3322",
    "addr:postcode":"82070",
    "addr:street":"E Grand Ave",
    "iso:country":"US",
    "sg:address":"3322 E Grand Ave",
    "sg:city":"Laramie",
    "sg:classifiers":[
        {
            "category":"Shopping",
            "subcategory":"Discount & Variety Stores",
            "type":"Retail Goods"
        }
    ],
    "sg:phone":"+1 307 745 8527",
    "sg:postcode":"82070",
    "sg:province":"WY",
    "sg:website":"www.dollardiscount.com",
    "wof:name":"Dollar Discount",
    "wof:placetype":"venue"
},
  "geometry": {"coordinates":[-105.554479,41.308489],"type":"Point"}
}