{
  "type": "Feature",
  "properties": {
    "addr:full":"13893 US Hwy 191 Bondurant WY 82922",
    "addr:housenumber":"13893",
    "addr:postcode":"82922",
    "addr:street":"Us Hwy 191 Bondurant Wy",
    "iso:country":"US",
    "sg:address":"13893 US Hwy 191",
    "sg:city":"Bondurant",
    "sg:classifiers":[
        {
            "category":"Manufacturing",
            "subcategory":"Buildings",
            "type":"Manufacturing & Wholesale Goods"
        }
    ],
    "sg:phone":"+1 307 734 2652",
    "sg:postcode":"82922",
    "sg:province":"WY",
    "sg:tags":[
        "home",
        "log",
        "cabin"
    ],
    "wof:name":"Old World Designs Inc",
    "wof:placetype":"venue"
},
  "geometry": {"coordinates":[-110.36684,43.1605],"type":"Point"}
}