{
  "type": "Feature",
  "properties": {
    "iso:country":"US",
    "sg:address":"330 S Walsh Dr",
    "sg:city":"Casper",
    "sg:classifiers":[
        {
            "category":"Shopping",
            "subcategory":"Computers & Home Electronics",
            "type":"Retail Goods"
        }
    ],
    "sg:phone":"+1 307 235 6212",
    "sg:postcode":"82609",
    "sg:province":"WY",
    "sg:tags":[
        "asp",
        "networking",
        "hosting",
        "hardware",
        "var",
        "software"
    ],
    "sg:website":"www.acadea.com",
    "wof:name":"CPU Venture Tech",
    "wof:placetype":"venue"
},
  "geometry": {"coordinates":[-106.27698599999999,42.846806],"type":"Point"}
}