{
  "type": "Feature",
  "properties": {
    "iso:country":"US",
    "sg:address":"242 E Broadway",
    "sg:city":"Jackson",
    "sg:classifiers":[
        {
            "category":"Personal",
            "subcategory":"Beauty Salon",
            "type":"Services"
        }
    ],
    "sg:phone":"+1 307 734 7899",
    "sg:postcode":"83001",
    "sg:province":"WY",
    "wof:name":"Blue Room",
    "wof:placetype":"venue"
},
  "geometry": {"coordinates":[-110.75819199999999,43.47953],"type":"Point"}
}