{
  "type": "Feature",
  "properties": {
    "addr:full":"1604 Maple St Casper WY 82604",
    "addr:housenumber":"1604",
    "addr:postcode":"82604",
    "addr:street":"Maple St",
    "iso:country":"US",
    "sg:address":"1604 Maple St",
    "sg:city":"Casper",
    "sg:classifiers":[
        {
            "category":"Retail",
            "subcategory":"Repair Shop",
            "type":"Services"
        }
    ],
    "sg:phone":"+1 307 266 5743",
    "sg:postcode":"82604",
    "sg:province":"WY",
    "wof:name":"Creative Designs Trade Shop",
    "wof:placetype":"venue"
},
  "geometry": {"coordinates":[-106.34892499999999,42.832906],"type":"Point"}
}