{
  "type": "Feature",
  "properties": {
    "addr:full":"839 5th Ave Belle Fourche WY 57717",
    "addr:housenumber":"839",
    "addr:postcode":"57717",
    "addr:street":"5Th Ave",
    "iso:country":"US",
    "sg:address":"839 5th Ave",
    "sg:city":"Belle Fourche",
    "sg:classifiers":[
        {
            "category":"Government",
            "subcategory":"Office",
            "type":"Public Place"
        }
    ],
    "sg:phone":"+1 605 892 2516",
    "sg:postcode":"57717",
    "sg:province":"WY",
    "wof:name":"Butte County Clerk Of Courts",
    "wof:placetype":"venue"
},
  "geometry": {"coordinates":[-103.853452,44.669316],"type":"Point"}
}