{
  "type": "Feature",
  "properties": {
    "addr:full":"19 McBride Rd Centennial WY 82055",
    "addr:housenumber":"19",
    "addr:postcode":"82055",
    "addr:street":"Mcbride Rd Centennial Wy",
    "iso:country":"US",
    "sg:address":"19 McBride Rd",
    "sg:city":"Centennial",
    "sg:classifiers":[
        {
            "category":"Travel",
            "subcategory":"Hotels & Motels",
            "type":"Entertainment"
        }
    ],
    "sg:phone":"+1 307 755 0696",
    "sg:postcode":"82055",
    "sg:province":"WY",
    "wof:name":"Carr's Middle Mt Guest Cottage",
    "wof:placetype":"venue"
},
  "geometry": {"coordinates":[-106.140822,41.313428],"type":"Point"}
}