{
  "type": "Feature",
  "properties": {
    "iso:country":"US",
    "sg:address":"2001 Capitol Ave",
    "sg:city":"Cheyenne",
    "sg:classifiers":[
        {
            "category":"Insurance",
            "subcategory":"Health Insurance",
            "type":"Services"
        }
    ],
    "sg:phone":"+1 307 777 6714",
    "sg:postcode":"82001",
    "sg:province":"WY",
    "sg:tags":[
        "carrier"
    ],
    "wof:name":"Wyoming Employees Group",
    "wof:placetype":"venue"
},
  "geometry": {"coordinates":[-104.818178,41.137156],"type":"Point"}
}