{
  "type": "Feature",
  "properties": {
    "addr:full":"83 E Ridge Rd Sheridan WY 82801",
    "addr:housenumber":"83",
    "addr:postcode":"82801",
    "addr:street":"E Ridge Rd",
    "iso:country":"US",
    "sg:address":"83 E Ridge Rd",
    "sg:city":"Sheridan",
    "sg:classifiers":[
        {
            "category":"Government",
            "subcategory":"Office",
            "type":"Public Place"
        }
    ],
    "sg:phone":"+1 307 674 8461",
    "sg:postcode":"82801",
    "sg:province":"WY",
    "sg:tags":[
        "city",
        "program"
    ],
    "wof:name":"Sheridan Solid Waste Disposal",
    "wof:placetype":"venue"
},
  "geometry": {"coordinates":[-106.927233,44.798001],"type":"Point"}
}