{
  "type": "Feature",
  "properties": {
    "addr:full":"901 Eisenhower Dr Rock Springs CO 82901",
    "addr:housenumber":"901",
    "addr:postcode":"82901",
    "addr:street":"Eisenhower Dr",
    "iso:country":"US",
    "sg:address":"901 Eisenhower Dr",
    "sg:city":"Rock Springs",
    "sg:classifiers":[
        {
            "category":"Professional",
            "subcategory":"Computer Services",
            "type":"Services"
        }
    ],
    "sg:phone":"+1 307 382 4503",
    "sg:postcode":"82901",
    "sg:province":"CO",
    "sg:tags":[
        "consultant",
        "designer"
    ],
    "wof:name":"Rnd Consulting",
    "wof:placetype":"venue"
},
  "geometry": {"coordinates":[-109.24603999999999,41.597159],"type":"Point"}
}