{
  "type": "Feature",
  "properties": {
    "iso:country":"US",
    "sg:address":"915 Rd 8",
    "sg:city":"Powell",
    "sg:classifiers":[
        {
            "category":"Retail",
            "subcategory":"Auto Repair",
            "type":"Services"
        }
    ],
    "sg:phone":"+1 307 754 9091",
    "sg:postcode":"82435",
    "sg:province":"WY",
    "sg:tags":[
        "repairing",
        "automobile",
        "general"
    ],
    "wof:name":"My Auto Repair",
    "wof:placetype":"venue"
},
  "geometry": {"coordinates":[-108.7396,44.753142],"type":"Point"}
}