{
  "type": "Feature",
  "properties": {
    "addr:full":"834 S Summit Ave Newcastle WY 82701",
    "addr:housenumber":"834",
    "addr:postcode":"82701",
    "addr:street":"S Summit Ave Newcastle Wy",
    "iso:country":"US",
    "sg:address":"834 S Summit Ave",
    "sg:city":"Newcastle",
    "sg:classifiers":[
        {
            "category":"Restaurant",
            "type":"Food & Drink"
        }
    ],
    "sg:phone":"+1 307 746 2176",
    "sg:postcode":"82701",
    "sg:province":"WY",
    "sg:tags":[
        "out"
    ],
    "wof:name":"Howdy Drive In",
    "wof:placetype":"venue"
},
  "geometry": {"coordinates":[-104.19506800000001,43.848327],"type":"Point"}
}