{
  "type": "Feature",
  "properties": {
    "addr:full":"219 S 8th St Thermopolis WY 82443",
    "addr:housenumber":"219",
    "addr:postcode":"82443",
    "addr:street":"S 8Th St Thermopolis Wy",
    "iso:country":"US",
    "sg:address":"219 S 8th St",
    "sg:city":"Thermopolis",
    "sg:classifiers":[
        {
            "category":"Organizations",
            "subcategory":"Community Association",
            "type":"Services"
        }
    ],
    "sg:phone":"+1 307 864 3039",
    "sg:postcode":"82443",
    "sg:province":"WY",
    "wof:name":"Drove 50",
    "wof:placetype":"venue"
},
  "geometry": {"coordinates":[-108.215397,43.644798],"type":"Point"}
}