{
  "type": "Feature",
  "properties": {
    "addr:full":"404 9th St Wheatland WY 82201",
    "addr:housenumber":"404",
    "addr:postcode":"82201",
    "addr:street":"9Th St Wheatland Wy",
    "iso:country":"US",
    "sg:address":"404 9th St",
    "sg:city":"Wheatland",
    "sg:classifiers":[
        {
            "category":"Health Services",
            "subcategory":"Optometrist",
            "type":"Services"
        }
    ],
    "sg:phone":"+1 307 322 9747",
    "sg:postcode":"82201",
    "sg:province":"WY",
    "wof:name":"Split Rock Vision Clinic",
    "wof:placetype":"venue"
},
  "geometry": {"coordinates":[-104.95314500000001,42.052474],"type":"Point"}
}