{
  "type": "Feature",
  "properties": {
    "addr:full":"887 Coleman Cir Casper WY 82601",
    "addr:housenumber":"887",
    "addr:postcode":"82601",
    "addr:street":"Coleman Cir",
    "iso:country":"US",
    "sg:address":"887 Coleman Cir",
    "sg:city":"Casper",
    "sg:classifiers":[
        {
            "category":"Mining & Drilling",
            "type":"Manufacturing & Wholesale Goods"
        }
    ],
    "sg:phone":"+1 307 472 3113",
    "sg:postcode":"82601",
    "sg:province":"WY",
    "sg:tags":[
        "field",
        "oil"
    ],
    "wof:name":"Anadrill Schlumberger",
    "wof:placetype":"venue"
},
  "geometry": {"coordinates":[-106.351342,42.877538],"type":"Point"}
}