{
  "type": "Feature",
  "properties": {
    "addr:full":"2008 Cy Ave Casper WY 82604",
    "addr:housenumber":"2008",
    "addr:postcode":"82604",
    "addr:street":"Cy Ave",
    "iso:country":"US",
    "sg:address":"2008 Cy Ave",
    "sg:city":"Casper",
    "sg:classifiers":[
        {
            "category":"Restaurant",
            "type":"Food & Drink"
        }
    ],
    "sg:phone":"+1 307 234 9464",
    "sg:postcode":"82604",
    "sg:province":"WY",
    "sg:tags":[
        "eating"
    ],
    "wof:name":"Wings N Things",
    "wof:placetype":"venue"
},
  "geometry": {"coordinates":[-106.34152,42.832138],"type":"Point"}
}