{
  "type": "Feature",
  "properties": {
    "iso:country":"US",
    "sg:address":"2535 Primrose Ln",
    "sg:city":"Riverton",
    "sg:classifiers":[
        {
            "category":"Professional",
            "subcategory":"Employment Agencies",
            "type":"Services"
        }
    ],
    "sg:phone":"+1 307 857 3031",
    "sg:postcode":"82501",
    "sg:province":"WY",
    "sg:tags":[
        "company",
        "trucking"
    ],
    "wof:name":"Fairwinds Co",
    "wof:placetype":"venue"
},
  "geometry": {"coordinates":[-108.42325700000001,43.020183],"type":"Point"}
}