{
  "type": "Feature",
  "properties": {
    "iso:country":"US",
    "sg:address":"810 Belinda Dr",
    "sg:city":"Riverton",
    "sg:classifiers":[
        {
            "category":"Shopping",
            "subcategory":"Hobbies, Toys, & Games",
            "type":"Retail Goods"
        }
    ],
    "sg:phone":"+1 307 856 6980",
    "sg:postcode":"82501",
    "sg:province":"WY",
    "sg:tags":[
        "device",
        "operator",
        "amusement"
    ],
    "wof:name":"Goodbuddys Coin O P",
    "wof:placetype":"venue"
},
  "geometry": {"coordinates":[-108.376912,43.032784],"type":"Point"}
}