{
  "type": "Feature",
  "properties": {
    "iso:country":"US",
    "sg:address":"316 E Cleveland St",
    "sg:city":"Sundance",
    "sg:classifiers":[
        {
            "category":"Real Estate",
            "subcategory":"Real Estate Agent",
            "type":"Services"
        }
    ],
    "sg:phone":"+1 307 283 2211",
    "sg:postcode":"82729",
    "sg:province":"WY",
    "wof:name":"Snook & Sons Realty",
    "wof:placetype":"venue"
},
  "geometry": {"coordinates":[-104.377832,44.405087],"type":"Point"}
}