{
  "type": "Feature",
  "properties": {
    "addr:full":"710 W 8th St Gillette WY 82716",
    "addr:housenumber":"710",
    "addr:postcode":"82716",
    "addr:street":"W 8Th St",
    "iso:country":"US",
    "sg:address":"710 W 8th St",
    "sg:city":"Gillette",
    "sg:classifiers":[
        {
            "category":"Social Services",
            "type":"Services"
        }
    ],
    "sg:phone":"+1 307 682 2440",
    "sg:postcode":"82716",
    "sg:province":"WY",
    "sg:tags":[
        "probation"
    ],
    "wof:name":"Probation & Parole Ofc",
    "wof:placetype":"venue"
},
  "geometry": {"coordinates":[-105.512463,44.287641],"type":"Point"}
}