{
  "type": "Feature",
  "properties": {
    "iso:country":"US",
    "sg:address":"1111 N Elma St",
    "sg:city":"Casper",
    "sg:classifiers":[
        {
            "category":"Arts & Performance",
            "subcategory":"Theater",
            "type":"Entertainment"
        }
    ],
    "sg:phone":"+1 307 234 3639",
    "sg:postcode":"82601",
    "sg:province":"WY",
    "sg:tags":[
        "dance",
        "group"
    ],
    "wof:name":"Jamal Kema",
    "wof:placetype":"venue"
},
  "geometry": {"coordinates":[-106.30920500000001,42.861838],"type":"Point"}
}