{
  "type": "Feature",
  "properties": {
    "addr:full":"2167 N Main St Sheridan WY 82801",
    "addr:housenumber":"2167",
    "addr:postcode":"82801",
    "addr:street":"N Main St",
    "iso:country":"US",
    "sg:address":"2167 N Main St",
    "sg:city":"Sheridan",
    "sg:classifiers":[
        {
            "category":"Travel",
            "subcategory":"Hotels & Motels",
            "type":"Entertainment"
        }
    ],
    "sg:phone":"+1 307 672 3459",
    "sg:postcode":"82801",
    "sg:province":"WY",
    "sg:tags":[
        "operation",
        "eating"
    ],
    "wof:name":"Stage Stop Motel",
    "wof:placetype":"venue"
},
  "geometry": {"coordinates":[-106.955675,44.821371],"type":"Point"}
}