{
  "type": "Feature",
  "properties": {
    "iso:country":"US",
    "sg:address":"10 Antelope Dr",
    "sg:city":"Wheatland",
    "sg:classifiers":[
        {
            "category":"Manufacturing",
            "subcategory":"Rubber & Plastics",
            "type":"Manufacturing & Wholesale Goods"
        }
    ],
    "sg:phone":"+1 307 322 3973",
    "sg:postcode":"82201",
    "sg:province":"WY",
    "sg:tags":[
        "product",
        "mfg"
    ],
    "wof:name":"Donco Tool Inc",
    "wof:placetype":"venue"
},
  "geometry": {"coordinates":[-104.94053,42.033539],"type":"Point"}
}