{
  "type": "Feature",
  "properties": {
    "iso:country":"US",
    "sg:address":"1025 Glenarm St",
    "sg:city":"Casper",
    "sg:classifiers":[
        {
            "category":"Professional",
            "subcategory":"Computer Services",
            "type":"Services"
        }
    ],
    "sg:phone":"+1 307 473 3030",
    "sg:postcode":"82601",
    "sg:province":"WY",
    "sg:tags":[
        "website",
        "design"
    ],
    "wof:name":"Commerce Developers Inc",
    "wof:placetype":"venue"
},
  "geometry": {"coordinates":[-106.31609899999999,42.859846],"type":"Point"}
}