{
  "type": "Feature",
  "properties": {
    "iso:country":"US",
    "sg:address":"224 Springview St",
    "sg:city":"Thermopolis",
    "sg:classifiers":[
        {
            "category":"Professional",
            "subcategory":"Lawyer & Legal Services",
            "type":"Services"
        }
    ],
    "sg:phone":"+1 307 864 5474",
    "sg:postcode":"82443",
    "sg:province":"WY",
    "sg:tags":[
        "attorney"
    ],
    "wof:name":"Special Master",
    "wof:placetype":"venue"
},
  "geometry": {"coordinates":[-108.20897600000001,43.647519],"type":"Point"}
}