{
  "type": "Feature",
  "properties": {
    "iso:country":"US",
    "sg:address":"209 S 4th St",
    "sg:city":"Basin",
    "sg:classifiers":[
        {
            "category":"Government",
            "subcategory":"Office",
            "type":"Public Place"
        }
    ],
    "sg:phone":"+1 307 568 3331",
    "sg:postcode":"82410",
    "sg:province":"WY",
    "sg:tags":[
        "city"
    ],
    "sg:website":"www.basinwyo.net",
    "wof:name":"Basin Town Hall",
    "wof:placetype":"venue"
},
  "geometry": {"coordinates":[-108.03885699999999,44.380726],"type":"Point"}
}