{
  "type": "Feature",
  "properties": {
    "iso:country":"US",
    "sg:address":"1532 Wyoming Ave",
    "sg:city":"Cody",
    "sg:classifiers":[
        {
            "category":"Personal",
            "subcategory":"Tanning Parlor",
            "type":"Services"
        }
    ],
    "sg:phone":"+1 307 587 4733",
    "sg:postcode":"82414",
    "sg:province":"WY",
    "sg:tags":[
        "salon"
    ],
    "wof:name":"Tropical Spray Tan",
    "wof:placetype":"venue"
},
  "geometry": {"coordinates":[-109.057686,44.530334],"type":"Point"}
}