{
  "type": "Feature",
  "properties": {
    "iso:country":"US",
    "sg:address":"1215 E Gibbon St",
    "sg:city":"Laramie",
    "sg:classifiers":[
        {
            "category":"Organizations",
            "subcategory":"Religious Organization",
            "type":"Services"
        }
    ],
    "sg:phone":"+1 307 742 8121",
    "sg:postcode":"82072",
    "sg:province":"WY",
    "sg:website":"www.laramie-umc.com",
    "wof:name":"First United Methodist Church",
    "wof:placetype":"venue"
},
  "geometry": {"coordinates":[-105.58087500000001,41.3179],"type":"Point"}
}