{
  "type": "Feature",
  "properties": {
    "addr:full":"749 E 2nd St Powell WY 82435",
    "addr:housenumber":"749",
    "addr:postcode":"82435",
    "addr:street":"E 2Nd St Powell Wy",
    "iso:country":"US",
    "sg:address":"749 E 2nd St",
    "sg:city":"Powell",
    "sg:classifiers":[
        {
            "category":"Personal",
            "subcategory":"Tanning Parlor",
            "type":"Services"
        }
    ],
    "sg:phone":"+1 307 754 4834",
    "sg:postcode":"82435",
    "sg:province":"WY",
    "sg:tags":[
        "salon"
    ],
    "wof:name":"J & S Laundry",
    "wof:placetype":"venue"
},
  "geometry": {"coordinates":[-108.749343,44.754279],"type":"Point"}
}