{
  "type": "Feature",
  "properties": {
    "iso:country":"US",
    "sg:address":"240 N Elk St",
    "sg:city":"Casper",
    "sg:classifiers":[
        {
            "category":"Wholesale",
            "subcategory":"Medical Equipment & Supplies",
            "type":"Manufacturing & Wholesale Goods"
        }
    ],
    "sg:phone":"+1 307 237 7350",
    "sg:postcode":"82601",
    "sg:province":"WY",
    "sg:tags":[
        "physician",
        "surgeon"
    ],
    "wof:name":"Community Home Oxygen Inc",
    "wof:placetype":"venue"
},
  "geometry": {"coordinates":[-106.302595,42.851958],"type":"Point"}
}