{
  "type": "Feature",
  "properties": {
    "addr:full":"2023 State Hwy 50 Gillette WY 82718",
    "addr:housenumber":"2023",
    "addr:postcode":"82718",
    "addr:street":"State Hwy 50",
    "iso:country":"US",
    "sg:address":"2023 State Hwy 50",
    "sg:city":"Gillette",
    "sg:classifiers":[
        {
            "category":"Building & Trades",
            "subcategory":"Electrical",
            "type":"Services"
        }
    ],
    "sg:phone":"+1 307 685 6670",
    "sg:postcode":"82718",
    "sg:province":"WY",
    "sg:tags":[
        "electric",
        "contractor"
    ],
    "wof:name":"Blair Electric Svc Co",
    "wof:placetype":"venue"
},
  "geometry": {"coordinates":[-105.71554500000001,44.084433],"type":"Point"}
}