{
  "type": "Feature",
  "properties": {
    "addr:full":"503 5th St Marbleton WY 83113",
    "addr:housenumber":"503",
    "addr:postcode":"83113",
    "addr:street":"5Th St Marbleton Wy",
    "iso:country":"US",
    "sg:address":"503 5th St",
    "sg:city":"Marbleton",
    "sg:classifiers":[
        {
            "category":"Mining & Drilling",
            "type":"Manufacturing & Wholesale Goods"
        }
    ],
    "sg:phone":"+1 307 276 5358",
    "sg:postcode":"83113",
    "sg:province":"WY",
    "sg:tags":[
        "field",
        "oil"
    ],
    "wof:name":"Wayne's Hot Oil Svc",
    "wof:placetype":"venue"
},
  "geometry": {"coordinates":[-110.103044,42.557389],"type":"Point"}
}