{
  "type": "Feature",
  "properties": {
    "iso:country":"US",
    "sg:address":"419 S Spokane Ave",
    "sg:city":"Newcastle",
    "sg:classifiers":[
        {
            "category":"Retail",
            "subcategory":"Repair Shop",
            "type":"Services"
        }
    ],
    "sg:phone":"+1 307 746 2558",
    "sg:postcode":"82701",
    "sg:province":"WY",
    "sg:tags":[
        "refrigeration"
    ],
    "wof:name":"Rays Refrigeration LLC",
    "wof:placetype":"venue"
},
  "geometry": {"coordinates":[-104.197095,43.853553],"type":"Point"}
}