{
  "type": "Feature",
  "properties": {
    "iso:country":"US",
    "sg:address":"6000 Hannum Rd",
    "sg:city":"Gillette",
    "sg:classifiers":[
        {
            "category":"Retail",
            "subcategory":"Auto Repair",
            "type":"Services"
        }
    ],
    "sg:phone":"+1 307 685 0066",
    "sg:postcode":"82716",
    "sg:province":"WY",
    "sg:tags":[
        "body",
        "automobile",
        "painting"
    ],
    "wof:name":"A-1 Auto Body",
    "wof:placetype":"venue"
},
  "geometry": {"coordinates":[-105.524546,44.338794],"type":"Point"}
}