{
  "type": "Feature",
  "properties": {
    "addr:full":"2986 US Hwy 87 Sheridan WY 82801",
    "addr:housenumber":"2986",
    "addr:postcode":"82801",
    "addr:street":"Us Hwy 87 Sheridan Wy",
    "iso:country":"US",
    "sg:address":"2986 US Hwy 87",
    "sg:city":"Sheridan",
    "sg:classifiers":[
        {
            "category":"Recreation",
            "type":"Entertainment"
        }
    ],
    "sg:phone":"+1 307 672 6383",
    "sg:postcode":"82801",
    "sg:province":"WY",
    "sg:tags":[
        "parks"
    ],
    "wof:name":"Sheridan Commercial Park",
    "wof:placetype":"venue"
},
  "geometry": {"coordinates":[-106.95713600000001,44.711805],"type":"Point"}
}