{
  "type": "Feature",
  "properties": {
    "addr:full":"2124 S Douglas Hwy Gillette WY 82718",
    "addr:housenumber":"2124",
    "addr:postcode":"82718",
    "addr:street":"S Douglas Hwy",
    "iso:country":"US",
    "sg:address":"2124 S Douglas Hwy",
    "sg:city":"Gillette",
    "sg:classifiers":[
        {
            "category":"Banks & Credit Unions",
            "subcategory":"Bank",
            "type":"Services"
        }
    ],
    "sg:phone":"+1 307 686 8080",
    "sg:postcode":"82718",
    "sg:province":"WY",
    "sg:website":"www.securitystatebk.com",
    "wof:name":"Security State Bank",
    "wof:placetype":"venue"
},
  "geometry": {"coordinates":[-105.49411000000001,44.275117],"type":"Point"}
}