{
  "type": "Feature",
  "properties": {
    "iso:country":"US",
    "sg:address":"2106 Stundon Ave",
    "sg:city":"Cheyenne",
    "sg:classifiers":[
        {
            "category":"Building & Trades",
            "subcategory":"Construction",
            "type":"Services"
        }
    ],
    "sg:phone":"+1 307 635 8446",
    "sg:postcode":"82007",
    "sg:province":"WY",
    "sg:tags":[
        "contractor"
    ],
    "wof:name":"Phillip J Lupo Jr",
    "wof:placetype":"venue"
},
  "geometry": {"coordinates":[-104.796813,41.097123],"type":"Point"}
}