{
  "type": "Feature",
  "properties": {
    "addr:full":"6101 Yellowstone Rd Cheyenne WY 82009",
    "addr:housenumber":"6101",
    "addr:postcode":"82009",
    "addr:street":"Yellowstone Rd",
    "iso:country":"US",
    "sg:address":"6101 Yellowstone Rd",
    "sg:city":"Cheyenne",
    "sg:classifiers":[
        {
            "category":"Government",
            "subcategory":"Office",
            "type":"Public Place"
        }
    ],
    "sg:phone":"+1 307 777 7531",
    "sg:postcode":"82009",
    "sg:province":"WY",
    "sg:tags":[
        "state",
        "resource"
    ],
    "wof:name":"Medicaid Office",
    "wof:placetype":"venue"
},
  "geometry": {"coordinates":[-104.82857799999999,41.177344],"type":"Point"}
}