{
  "type": "Feature",
  "properties": {
    "iso:country":"US",
    "sg:address":"2401 S Greeley Hwy",
    "sg:city":"Cheyenne",
    "sg:classifiers":[
        {
            "category":"Home & Garden",
            "subcategory":"Mobile Homes",
            "type":"Retail Goods"
        }
    ],
    "sg:phone":"+1 307 632 2797",
    "sg:postcode":"82007",
    "sg:province":"WY",
    "wof:name":"Golden Villa Homes Inc",
    "wof:placetype":"venue"
},
  "geometry": {"coordinates":[-104.800338,41.095537],"type":"Point"}
}