{
  "type": "Feature",
  "properties": {
    "addr:full":"1215 S Beverly St Casper WY 82609",
    "addr:housenumber":"1215",
    "addr:postcode":"82609",
    "addr:street":"S Beverly St",
    "iso:country":"US",
    "sg:address":"1215 S Beverly St",
    "sg:city":"Casper",
    "sg:classifiers":[
        {
            "category":"Restaurant",
            "type":"Food & Drink"
        }
    ],
    "sg:menulink":"http://www.allmenus.com/wy/casper/235561-taco-time/menu/",
    "sg:phone":"+1 307 237 9891",
    "sg:postcode":"82609",
    "sg:province":"WY",
    "sg:tags":[
        "american",
        "mexican",
        "tex-mex"
    ],
    "wof:name":"Taco Time",
    "wof:placetype":"venue"
},
  "geometry": {"coordinates":[-106.29786900000001,42.838746],"type":"Point"}
}