{
  "type": "Feature",
  "properties": {
    "iso:country":"US",
    "sg:address":"1070 W Main St",
    "sg:city":"Newcastle",
    "sg:classifiers":[
        {
            "category":"Building & Trades",
            "subcategory":"Equipment Rental",
            "type":"Services"
        }
    ],
    "sg:phone":"+1 307 746 2656",
    "sg:postcode":"82701",
    "sg:province":"WY",
    "sg:tags":[
        "leasing"
    ],
    "wof:name":"Aulick Leasing Corp",
    "wof:placetype":"venue"
},
  "geometry": {"coordinates":[-104.218673,43.851129],"type":"Point"}
}