{
  "type": "Feature",
  "properties": {
    "iso:country":"US",
    "sg:address":"363 S Riverbend Dr",
    "sg:city":"Douglas",
    "sg:classifiers":[
        {
            "category":"Home & Garden",
            "subcategory":"Building Materials",
            "type":"Retail Goods"
        },
        {
            "category":"Retail",
            "subcategory":"Auto Repair",
            "type":"Services"
        }
    ],
    "sg:phone":"+1 307 358 0012",
    "sg:postcode":"82633",
    "sg:province":"WY",
    "sg:tags":[
        "glass",
        "window",
        "automobile",
        "plate"
    ],
    "wof:name":"Decker Auto Glass",
    "wof:placetype":"venue"
},
  "geometry": {"coordinates":[-105.406368,42.755535],"type":"Point"}
}