{
  "type": "Feature",
  "properties": {
    "iso:country":"US",
    "sg:address":"821 Elm Ct",
    "sg:city":"Gillette",
    "sg:classifiers":[
        {
            "category":"Building & Trades",
            "subcategory":"Construction",
            "type":"Services"
        }
    ],
    "sg:phone":"+1 307 686 0178",
    "sg:postcode":"82716",
    "sg:province":"WY",
    "sg:tags":[
        "house"
    ],
    "wof:name":"Back In Action Builders LLC",
    "wof:placetype":"venue"
},
  "geometry": {"coordinates":[-105.523287,44.302705],"type":"Point"}
}