{
  "type": "Feature",
  "properties": {
    "iso:country":"US",
    "sg:address":"441 Landmark Dr",
    "sg:city":"Casper",
    "sg:classifiers":[
        {
            "category":"Wholesale",
            "subcategory":"Stationery",
            "type":"Manufacturing & Wholesale Goods"
        }
    ],
    "sg:phone":"+1 307 233 7021",
    "sg:postcode":"82609",
    "sg:province":"WY",
    "sg:tags":[
        "supply",
        "furniture"
    ],
    "wof:name":"Boise Cascade",
    "wof:placetype":"venue"
},
  "geometry": {"coordinates":[-106.260745,42.845977],"type":"Point"}
}