{
  "type": "Feature",
  "properties": {
    "addr:full":"413 S Sonora Ave Newcastle WY 82701",
    "addr:housenumber":"413",
    "addr:postcode":"82701",
    "addr:street":"S Sonora Ave Newcastle Wy",
    "iso:country":"US",
    "sg:address":"413 S Sonora Ave",
    "sg:city":"Newcastle",
    "sg:classifiers":[
        {
            "category":"Arts & Performance",
            "subcategory":"Theater",
            "type":"Entertainment"
        }
    ],
    "sg:phone":"+1 307 746 2245",
    "sg:postcode":"82701",
    "sg:province":"WY",
    "sg:tags":[
        "group"
    ],
    "wof:name":"Tubb Town Muzzleloaders",
    "wof:placetype":"venue"
},
  "geometry": {"coordinates":[-104.197951,43.852666],"type":"Point"}
}