{
  "type": "Feature",
  "properties": {
    "addr:full":"795 Bull Mountain Rd Laramie WY 82070",
    "addr:housenumber":"795",
    "addr:postcode":"82070",
    "addr:street":"Bull Mountain Rd",
    "iso:country":"US",
    "sg:address":"795 Bull Mountain Rd",
    "sg:city":"Laramie",
    "sg:classifiers":[
        {
            "category":"Travel",
            "subcategory":"Campground",
            "type":"Entertainment"
        }
    ],
    "sg:phone":"+1 307 745 4507",
    "sg:postcode":"82070",
    "sg:province":"WY",
    "sg:tags":[
        "camp"
    ],
    "wof:name":"Bull Mountain Ranch",
    "wof:placetype":"venue"
},
  "geometry": {"coordinates":[-105.852057,41.004461],"type":"Point"}
}