{
  "type": "Feature",
  "properties": {
    "iso:country":"US",
    "sg:address":"1457 Sweetwater Rd",
    "sg:city":"Douglas",
    "sg:classifiers":[
        {
            "category":"Real Estate",
            "subcategory":"Real Estate Operator",
            "type":"Services"
        }
    ],
    "sg:phone":"+1 307 358 5927",
    "sg:postcode":"82633",
    "sg:province":"WY",
    "sg:tags":[
        "apartment"
    ],
    "wof:name":"Westgate Limited",
    "wof:placetype":"venue"
},
  "geometry": {"coordinates":[-105.406375,42.765164],"type":"Point"}
}