{
  "type": "Feature",
  "properties": {
    "addr:full":"125 S Greeley Hwy Cheyenne WY 82007",
    "addr:housenumber":"125",
    "addr:postcode":"82007",
    "addr:street":"S Greeley Hwy;Wy",
    "iso:country":"US",
    "sg:address":"125 S Greeley Hwy",
    "sg:city":"Cheyenne",
    "sg:classifiers":[
        {
            "category":"Restaurant",
            "type":"Food & Drink"
        }
    ],
    "sg:menulink":"http://www.allmenus.com/wy/cheyenne/191848-sonic/menu/",
    "sg:phone":"+1 307 432 0053",
    "sg:postcode":"82007",
    "sg:province":"WY",
    "sg:tags":[
        "burger",
        "american"
    ],
    "wof:name":"Sonic",
    "wof:placetype":"venue"
},
  "geometry": {"coordinates":[-104.803077,41.116122],"type":"Point"}
}