{
  "type": "Feature",
  "properties": {
    "iso:country":"US",
    "sg:address":"1002 Elk St",
    "sg:city":"Kemmerer",
    "sg:classifiers":[
        {
            "category":"Education",
            "subcategory":"School",
            "type":"Public Place"
        }
    ],
    "sg:phone":"+1 307 877 5819",
    "sg:postcode":"83101",
    "sg:province":"WY",
    "wof:name":"Kemmerer Alternative School",
    "wof:placetype":"venue"
},
  "geometry": {"coordinates":[-110.545044,41.788164],"type":"Point"}
}