{
  "type": "Feature",
  "properties": {
    "iso:country":"US",
    "sg:address":"1819 Carey Ave",
    "sg:city":"Cheyenne",
    "sg:classifiers":[
        {
            "category":"Real Estate",
            "subcategory":"Real Estate Agent",
            "type":"Services"
        }
    ],
    "sg:phone":"+1 307 635 2888",
    "sg:postcode":"82001",
    "sg:province":"WY",
    "sg:website":"www.bestprop.com",
    "wof:name":"Best Properties Inc",
    "wof:placetype":"venue"
},
  "geometry": {"coordinates":[-104.817984,41.134851],"type":"Point"}
}