{
  "type": "Feature",
  "properties": {
    "addr:full":"111 W 2nd St Casper WY 82601",
    "addr:housenumber":"111",
    "addr:postcode":"82601",
    "addr:street":"W 2Nd St",
    "iso:country":"US",
    "sg:address":"111 W 2nd St",
    "sg:city":"Casper",
    "sg:classifiers":[
        {
            "category":"Professional",
            "subcategory":"Accounting & Tax Preparation",
            "type":"Services"
        }
    ],
    "sg:phone":"+1 307 234 1122",
    "sg:postcode":"82601",
    "sg:province":"WY",
    "sg:tags":[
        "accountant"
    ],
    "wof:name":"Paul Homar CPA",
    "wof:placetype":"venue"
},
  "geometry": {"coordinates":[-106.32648,42.848608],"type":"Point"}
}