{
  "type": "Feature",
  "properties": {
    "iso:country":"US",
    "sg:address":"1901 Kennedy Ave",
    "sg:city":"Rock Springs",
    "sg:classifiers":[
        {
            "category":"Home & Garden",
            "subcategory":"Building Materials",
            "type":"Retail Goods"
        }
    ],
    "sg:phone":"+1 307 362 4194",
    "sg:postcode":"82901",
    "sg:province":"WY",
    "wof:name":"Burstad Over Head Doors",
    "wof:placetype":"venue"
},
  "geometry": {"coordinates":[-109.24965,41.596],"type":"Point"}
}