{
  "type": "Feature",
  "properties": {
    "addr:full":"6101 Yellowstone Rd Cheyenne WY 82009",
    "addr:housenumber":"6101",
    "addr:postcode":"82009",
    "addr:street":"Yellowstone Rd",
    "iso:country":"US",
    "sg:address":"6101 Yellowstone Rd",
    "sg:city":"Cheyenne",
    "sg:classifiers":[
        {
            "category":"Real Estate",
            "subcategory":"Real Estate Agent",
            "type":"Services"
        },
        {
            "category":"Insurance",
            "subcategory":"Insurance Agent",
            "type":"Services"
        }
    ],
    "sg:phone":"+1 307 632 5778",
    "sg:postcode":"82009",
    "sg:province":"WY",
    "wof:name":"Wyoming Financial Properties",
    "wof:placetype":"venue"
},
  "geometry": {"coordinates":[-104.82857799999999,41.177344],"type":"Point"}
}