{
  "type": "Feature",
  "properties": {
    "iso:country":"US",
    "sg:address":"36 Piper Rd",
    "sg:city":"Sheridan",
    "sg:classifiers":[
        {
            "category":"Organizations",
            "subcategory":"Professional Association",
            "type":"Services"
        }
    ],
    "sg:phone":"+1 307 672 0932",
    "sg:postcode":"82801",
    "sg:province":"WY",
    "wof:name":"Wyoming Assn Career Tech",
    "wof:placetype":"venue"
},
  "geometry": {"coordinates":[-106.993464,44.746901],"type":"Point"}
}