{
  "type": "Feature",
  "properties": {
    "iso:country":"US",
    "sg:address":"1 W Main St",
    "sg:city":"Newcastle",
    "sg:classifiers":[
        {
            "category":"Government",
            "subcategory":"Office",
            "type":"Public Place"
        }
    ],
    "sg:phone":"+1 307 746 4633",
    "sg:postcode":"82701",
    "sg:province":"WY",
    "sg:tags":[
        "county",
        "taxation"
    ],
    "wof:name":"County Assessor",
    "wof:placetype":"venue"
},
  "geometry": {"coordinates":[-104.202027,43.85535],"type":"Point"}
}