{
  "type": "Feature",
  "properties": {
    "iso:country":"US",
    "sg:address":"1650 Sesame St",
    "sg:city":"Worland",
    "sg:classifiers":[
        {
            "category":"Shopping",
            "subcategory":"Clothing, Apparel, & Fashions",
            "type":"Retail Goods"
        }
    ],
    "sg:phone":"+1 307 347 2100",
    "sg:postcode":"82401",
    "sg:province":"WY",
    "sg:tags":[
        "western"
    ],
    "wof:name":"Tombstone Outfitters",
    "wof:placetype":"venue"
},
  "geometry": {"coordinates":[-108.003623,43.952011],"type":"Point"}
}