{
  "type": "Feature",
  "properties": {
    "addr:full":"400 1st Ave N Greybull WY 82426",
    "addr:housenumber":"400",
    "addr:postcode":"82426",
    "addr:street":"1St Ave N Greybull Wy",
    "iso:country":"US",
    "sg:address":"400 1st Ave N",
    "sg:city":"Greybull",
    "sg:classifiers":[
        {
            "category":"Organizations",
            "subcategory":"Religious Organization",
            "type":"Services"
        }
    ],
    "sg:phone":"+1 307 765 2640",
    "sg:postcode":"82426",
    "sg:province":"WY",
    "sg:tags":[
        "church"
    ],
    "wof:name":"First Baptist Church",
    "wof:placetype":"venue"
},
  "geometry": {"coordinates":[-108.053917,44.489917],"type":"Point"}
}