{
  "type": "Feature",
  "properties": {
    "iso:country":"US",
    "sg:address":"816 E 7th St",
    "sg:city":"Gillette",
    "sg:classifiers":[
        {
            "category":"Education",
            "subcategory":"School",
            "type":"Public Place"
        }
    ],
    "sg:phone":"+1 307 672 3786",
    "sg:postcode":"82716",
    "sg:province":"WY",
    "wof:name":"Gillette & Wright Elemntry Scl",
    "wof:placetype":"venue"
},
  "geometry": {"coordinates":[-105.49361,44.288254],"type":"Point"}
}