{
  "type": "Feature",
  "properties": {
    "iso:country":"US",
    "sg:address":"803 N Main St",
    "sg:city":"Sheridan",
    "sg:classifiers":[
        {
            "category":"Food & Beverages",
            "subcategory":"Groceries & Convenience Stores",
            "type":"Retail Goods"
        }
    ],
    "sg:phone":"+1 307 674 8262",
    "sg:postcode":"82801",
    "sg:province":"WY",
    "sg:tags":[
        "independent"
    ],
    "wof:name":"Binos Grocery & Meats",
    "wof:placetype":"venue"
},
  "geometry": {"coordinates":[-106.955555,44.806828],"type":"Point"}
}