{
  "type": "Feature",
  "properties": {
    "addr:full":"1371 Sheridan Ave Cody WY 82414",
    "addr:housenumber":"1371",
    "addr:postcode":"82414",
    "addr:street":"Sheridan Ave",
    "iso:country":"US",
    "sg:address":"1371 Sheridan Ave",
    "sg:city":"Cody",
    "sg:classifiers":[
        {
            "category":"Home & Garden",
            "subcategory":"Furniture",
            "type":"Retail Goods"
        }
    ],
    "sg:phone":"+1 307 587 4246",
    "sg:postcode":"82414",
    "sg:province":"WY",
    "wof:name":"Timbercreek Interiors",
    "wof:placetype":"venue"
},
  "geometry": {"coordinates":[-109.060875,44.52613],"type":"Point"}
}