{
  "type": "Feature",
  "properties": {
    "addr:full":"1123 Big Horn Ave Worland WY 82401",
    "addr:housenumber":"1123",
    "addr:postcode":"82401",
    "addr:street":"Big Horn Ave",
    "iso:country":"US",
    "sg:address":"1123 Big Horn Ave",
    "sg:city":"Worland",
    "sg:classifiers":[
        {
            "category":"Real Estate",
            "subcategory":"Real Estate Agent",
            "type":"Services"
        }
    ],
    "sg:phone":"+1 307 347 9192",
    "sg:postcode":"82401",
    "sg:province":"WY",
    "wof:name":"Marshall Realty Inc",
    "wof:placetype":"venue"
},
  "geometry": {"coordinates":[-107.954143,44.016904],"type":"Point"}
}