{
  "type": "Feature",
  "properties": {
    "addr:full":"825 Saratoga Dr Green River WY 82935",
    "addr:housenumber":"825",
    "addr:postcode":"82935",
    "addr:street":"Saratoga Dr Green",
    "iso:country":"US",
    "sg:address":"825 Saratoga Dr",
    "sg:city":"Green River",
    "sg:classifiers":[
        {
            "category":"Professional",
            "type":"Services"
        }
    ],
    "sg:phone":"+1 307 875 7352",
    "sg:postcode":"82935",
    "sg:province":"WY",
    "wof:name":"Remember When",
    "wof:placetype":"venue"
},
  "geometry": {"coordinates":[-109.45918899999999,41.504555],"type":"Point"}
}