{
  "type": "Feature",
  "properties": {
    "iso:country":"US",
    "sg:address":"453 W Main St",
    "sg:city":"Lander",
    "sg:classifiers":[
        {
            "category":"Manufacturing",
            "subcategory":"Printing",
            "type":"Manufacturing & Wholesale Goods"
        }
    ],
    "sg:phone":"+1 307 332 3111",
    "sg:postcode":"82520",
    "sg:province":"WY",
    "sg:tags":[
        "publisher"
    ],
    "wof:name":"WCS Corp",
    "wof:placetype":"venue"
},
  "geometry": {"coordinates":[-108.744946,42.839673],"type":"Point"}
}