{
  "type": "Feature",
  "properties": {
    "addr:full":"77 Gardenia St Casper WY 82604",
    "addr:housenumber":"77",
    "addr:postcode":"82604",
    "addr:street":"Gardenia St",
    "iso:country":"US",
    "sg:address":"77 Gardenia St",
    "sg:city":"Casper",
    "sg:classifiers":[
        {
            "category":"Organizations",
            "subcategory":"Non-profit Organization",
            "type":"Services"
        }
    ],
    "sg:phone":"+1 307 234 0572",
    "sg:postcode":"82604",
    "sg:province":"WY",
    "sg:tags":[
        "human"
    ],
    "wof:name":"Maurice Griffith Manor",
    "wof:placetype":"venue"
},
  "geometry": {"coordinates":[-106.400634,42.822273],"type":"Point"}
}