{
  "type": "Feature",
  "properties": {
    "iso:country":"US",
    "sg:address":"613 S Federal Blvd",
    "sg:city":"Riverton",
    "sg:classifiers":[
        {
            "category":"Retail",
            "subcategory":"Auto Repair",
            "type":"Services"
        }
    ],
    "sg:phone":"+1 307 856 9744",
    "sg:postcode":"82501",
    "sg:province":"WY",
    "sg:tags":[
        "repairing",
        "automobile"
    ],
    "wof:name":"Riverton Tire & Oil Inc",
    "wof:placetype":"venue"
},
  "geometry": {"coordinates":[-108.380487,43.019345],"type":"Point"}
}