{
  "type": "Feature",
  "properties": {
    "addr:full":"1608 E 12th St Cheyenne WY 82001",
    "addr:housenumber":"1608",
    "addr:postcode":"82001",
    "addr:street":"E 12Th St",
    "iso:country":"US",
    "sg:address":"1608 E 12th St",
    "sg:city":"Cheyenne",
    "sg:classifiers":[
        {
            "category":"Personal",
            "subcategory":"Beauty Salon",
            "type":"Services"
        }
    ],
    "sg:phone":"+1 307 634 0763",
    "sg:postcode":"82001",
    "sg:province":"WY",
    "sg:tags":[
        "merchandise"
    ],
    "wof:name":"Styling Salon The",
    "wof:placetype":"venue"
},
  "geometry": {"coordinates":[-104.794025,41.1363],"type":"Point"}
}