{
  "type": "Feature",
  "properties": {
    "addr:full":"1700 W Lincolnway Cheyenne WY 82001",
    "addr:housenumber":"1700",
    "addr:postcode":"82001",
    "addr:street":"W Lincolnway;Wy",
    "iso:country":"US",
    "sg:address":"1700 W Lincolnway",
    "sg:city":"Cheyenne",
    "sg:classifiers":[
        {
            "category":"Sports & Exercise",
            "subcategory":"Gym",
            "type":"Entertainment"
        }
    ],
    "sg:phone":"+1 307 638 9278",
    "sg:postcode":"82001",
    "sg:province":"WY",
    "sg:tags":[
        "club",
        "health",
        "studio",
        "gymnasium"
    ],
    "wof:name":"Millennium Fitness Spa",
    "wof:placetype":"venue"
},
  "geometry": {"coordinates":[-104.834941,41.124798],"type":"Point"}
}