{
  "type": "Feature",
  "properties": {
    "iso:country":"US",
    "sg:address":"2124 E 9th St",
    "sg:city":"Cheyenne",
    "sg:classifiers":[
        {
            "category":"Retail",
            "subcategory":"Auto Repair",
            "type":"Services"
        }
    ],
    "sg:phone":"+1 307 638 4997",
    "sg:postcode":"82001",
    "sg:province":"WY",
    "sg:tags":[
        "transmission"
    ],
    "wof:name":"Cheyenne Transmission",
    "wof:placetype":"venue"
},
  "geometry": {"coordinates":[-104.790468,41.133893],"type":"Point"}
}