{
  "type": "Feature",
  "properties": {
    "iso:country":"US",
    "sg:address":"5113 Ridge Rd",
    "sg:city":"Cheyenne",
    "sg:classifiers":[
        {
            "category":"Taxi",
            "type":"Transportation"
        }
    ],
    "sg:phone":"+1 307 632 8294",
    "sg:postcode":"82009",
    "sg:province":"WY",
    "sg:tags":[
        "taxicab"
    ],
    "wof:name":"Capitol City Cab",
    "wof:placetype":"venue"
},
  "geometry": {"coordinates":[-104.768323,41.165182],"type":"Point"}
}