{
  "type": "Feature",
  "properties": {
    "iso:country":"US",
    "sg:address":"1146 W 20th St",
    "sg:city":"Casper",
    "sg:classifiers":[
        {
            "category":"Freight",
            "type":"Transportation"
        }
    ],
    "sg:phone":"+1 307 237 3127",
    "sg:postcode":"82604",
    "sg:province":"WY",
    "sg:tags":[
        "operator",
        "trucking"
    ],
    "wof:name":"Whitys Car Hauling",
    "wof:placetype":"venue"
},
  "geometry": {"coordinates":[-106.33946,42.830962],"type":"Point"}
}