{
  "type": "Feature",
  "properties": {
    "addr:full":"35 N Scott St Sheridan WY 82801",
    "addr:housenumber":"35",
    "addr:postcode":"82801",
    "addr:street":"N Scott St",
    "iso:country":"US",
    "sg:address":"35 N Scott St",
    "sg:city":"Sheridan",
    "sg:classifiers":[
        {
            "category":"Building & Trades",
            "subcategory":"Construction",
            "type":"Services"
        }
    ],
    "sg:phone":"+1 307 672 2128",
    "sg:postcode":"82801",
    "sg:province":"WY",
    "sg:tags":[
        "house",
        "general",
        "contractor"
    ],
    "wof:name":"J'Dan Builders",
    "wof:placetype":"venue"
},
  "geometry": {"coordinates":[-106.953221,44.797813],"type":"Point"}
}