{
  "type": "Feature",
  "properties": {
    "iso:country":"US",
    "sg:address":"703 E Laramie St",
    "sg:city":"Gillette",
    "sg:classifiers":[
        {
            "category":"Professional",
            "subcategory":"Management & Consulting",
            "type":"Services"
        }
    ],
    "sg:phone":"+1 307 686 1245",
    "sg:postcode":"82716",
    "sg:province":"WY",
    "sg:tags":[
        "sp",
        "mfg"
    ],
    "wof:name":"Kathy Cermak",
    "wof:placetype":"venue"
},
  "geometry": {"coordinates":[-105.495901,44.295809],"type":"Point"}
}