{
  "type": "Feature",
  "properties": {
    "iso:country":"US",
    "sg:address":"107 N Gillette Ave",
    "sg:city":"Gillette",
    "sg:classifiers":[
        {
            "category":"Railroad",
            "type":"Transportation"
        }
    ],
    "sg:phone":"+1 307 689 2633",
    "sg:postcode":"82716",
    "sg:province":"WY",
    "sg:tags":[
        "line",
        "haul"
    ],
    "wof:name":"Burlington Northern",
    "wof:placetype":"venue"
},
  "geometry": {"coordinates":[-105.50409000000001,44.295696],"type":"Point"}
}