{
  "type": "Feature",
  "properties": {
    "iso:country":"US",
    "sg:address":"239 E 1st St",
    "sg:city":"Casper",
    "sg:classifiers":[
        {
            "category":"Restaurant",
            "type":"Food & Drink"
        }
    ],
    "sg:phone":"+1 307 237 7999",
    "sg:postcode":"82601",
    "sg:province":"WY",
    "sg:tags":[
        "eating"
    ],
    "wof:name":"Mountain View Sub Shp-Downtown",
    "wof:placetype":"venue"
},
  "geometry": {"coordinates":[-106.32359599999999,42.850015],"type":"Point"}
}