{
  "type": "Feature",
  "properties": {
    "addr:full":"23 N Tyler Ave Pinedale WY 82941",
    "addr:housenumber":"23",
    "addr:postcode":"82941",
    "addr:street":"N Tyler Ave",
    "iso:country":"US",
    "sg:address":"23 N Tyler Ave",
    "sg:city":"Pinedale",
    "sg:classifiers":[
        {
            "category":"Organizations",
            "subcategory":"Community Association",
            "type":"Services"
        }
    ],
    "sg:phone":"+1 307 367 2604",
    "sg:postcode":"82941",
    "sg:province":"WY",
    "wof:name":"Masonic Hall",
    "wof:placetype":"venue"
},
  "geometry": {"coordinates":[-109.861374,42.866899],"type":"Point"}
}