{
  "type": "Feature",
  "properties": {
    "addr:full":"210 S Fillmore St Laramie WY 82070",
    "addr:housenumber":"210",
    "addr:postcode":"82070",
    "addr:street":"S Fillmore St",
    "iso:country":"US",
    "sg:address":"210 S Fillmore St",
    "sg:city":"Laramie",
    "sg:classifiers":[
        {
            "category":"Manufacturing",
            "subcategory":"Lumber",
            "type":"Manufacturing & Wholesale Goods"
        }
    ],
    "sg:phone":"+1 307 742 0244",
    "sg:postcode":"82070",
    "sg:province":"WY",
    "sg:tags":[
        "forestry"
    ],
    "wof:name":"Aaron Lund",
    "wof:placetype":"venue"
},
  "geometry": {"coordinates":[-105.618803,41.311728],"type":"Point"}
}