{
  "type": "Feature",
  "properties": {
    "addr:full":"1620 Elk St Rock Springs WY 82901",
    "addr:housenumber":"1620",
    "addr:postcode":"82901",
    "addr:street":"Elk St Rock Springs Wy",
    "iso:country":"US",
    "sg:address":"1620 Elk St",
    "sg:city":"Rock Springs",
    "sg:classifiers":[
        {
            "category":"Restaurant",
            "type":"Food & Drink"
        }
    ],
    "sg:menulink":"http://www.allmenus.com/wy/rock-springs-north/166987-burger-king/menu/",
    "sg:phone":"+1 307 382 4285",
    "sg:postcode":"82901",
    "sg:province":"WY",
    "sg:tags":[
        "american"
    ],
    "wof:name":"Burger King",
    "wof:placetype":"venue"
},
  "geometry": {"coordinates":[-109.229761,41.608896],"type":"Point"}
}