{
  "type": "Feature",
  "properties": {
    "addr:full":"4101 Evans Ave Cheyenne WY 82001",
    "addr:housenumber":"4101",
    "addr:postcode":"82001",
    "addr:street":"Evans Ave",
    "iso:country":"US",
    "sg:address":"4101 Evans Ave",
    "sg:city":"Cheyenne",
    "sg:classifiers":[
        {
            "category":"Airport",
            "type":"Transportation"
        }
    ],
    "sg:phone":"+1 307 778 5704",
    "sg:postcode":"82001",
    "sg:province":"WY",
    "wof:name":"Transaero",
    "wof:placetype":"venue"
},
  "geometry": {"coordinates":[-104.81869,41.152294],"type":"Point"}
}