{
  "type": "Feature",
  "properties": {
    "iso:country":"US",
    "sg:address":"808 E Custer St",
    "sg:city":"Laramie",
    "sg:classifiers":[
        {
            "category":"Building & Trades",
            "subcategory":"Plumbing",
            "type":"Services"
        }
    ],
    "sg:phone":"+1 307 721 2104",
    "sg:postcode":"82070",
    "sg:province":"WY",
    "sg:tags":[
        "plumbing",
        "contractor"
    ],
    "wof:name":"Eagle Plumbing & Heating Inc",
    "wof:placetype":"venue"
},
  "geometry": {"coordinates":[-105.587166,41.308642],"type":"Point"}
}