{
  "type": "Feature",
  "properties": {
    "addr:full":"50 E Ski Hill Rd Driggs WY 83422",
    "addr:housenumber":"50",
    "addr:postcode":"83422",
    "addr:street":"E Ski Hill Rd Driggs Wy",
    "iso:country":"US",
    "sg:address":"50 E Ski Hill Rd",
    "sg:city":"Driggs",
    "sg:classifiers":[
        {
            "category":"Social Services",
            "subcategory":"Child Care",
            "type":"Services"
        }
    ],
    "sg:phone":"+1 208 354 2580",
    "sg:postcode":"83422",
    "sg:province":"WY",
    "sg:tags":[
        "day"
    ],
    "wof:name":"Little Peoples Learning Place",
    "wof:placetype":"venue"
},
  "geometry": {"coordinates":[-111.069159,43.738842],"type":"Point"}
}