{
  "type": "Feature",
  "properties": {
    "iso:country":"US",
    "sg:address":"556 Yellowstone Ave",
    "sg:city":"Cody",
    "sg:classifiers":[
        {
            "category":"Home & Garden",
            "subcategory":"Household Appliances",
            "type":"Retail Goods"
        }
    ],
    "sg:phone":"+1 307 587 4986",
    "sg:postcode":"82414",
    "sg:province":"WY",
    "wof:name":"Discount Appliance & Furniture",
    "wof:placetype":"venue"
},
  "geometry": {"coordinates":[-109.08396,44.51692],"type":"Point"}
}