{
  "type": "Feature",
  "properties": {
    "iso:country":"US",
    "sg:address":"24695 US Hwy 85",
    "sg:city":"Newcastle",
    "sg:classifiers":[
        {
            "category":"Food & Beverages",
            "subcategory":"Groceries & Convenience Stores",
            "type":"Retail Goods"
        }
    ],
    "sg:phone":"+1 307 746 4776",
    "sg:postcode":"82715",
    "sg:province":"WY",
    "wof:name":"Four Corners General Store",
    "wof:placetype":"venue"
},
  "geometry": {"coordinates":[-104.131449,44.095804],"type":"Point"}
}