{
  "type": "Feature",
  "properties": {
    "addr:full":"1107 N Durbin St Casper WY 82601",
    "addr:housenumber":"1107",
    "addr:postcode":"82601",
    "addr:street":"N Durbin St",
    "iso:country":"US",
    "sg:address":"1107 N Durbin St",
    "sg:city":"Casper",
    "sg:classifiers":[
        {
            "category":"Food & Beverages",
            "subcategory":"Liquor & Beverages",
            "type":"Retail Goods"
        }
    ],
    "sg:phone":"+1 307 235 5655",
    "sg:postcode":"82601",
    "sg:province":"WY",
    "sg:tags":[
        "alcoholic"
    ],
    "wof:name":"Oil City Liquors",
    "wof:placetype":"venue"
},
  "geometry": {"coordinates":[-106.321995,42.862229],"type":"Point"}
}