{
  "type": "Feature",
  "properties": {
    "addr:full":"407 S Gillette Ave Gillette WY 82716",
    "addr:housenumber":"407",
    "addr:postcode":"82716",
    "addr:street":"S Gillette Ave",
    "iso:country":"US",
    "sg:address":"407 S Gillette Ave",
    "sg:city":"Gillette",
    "sg:classifiers":[
        {
            "category":"Personal",
            "subcategory":"Beauty Salon",
            "type":"Services"
        }
    ],
    "sg:phone":"+1 307 687 0028",
    "sg:postcode":"82716",
    "sg:province":"WY",
    "wof:name":"Sandra's Precision Hair Care",
    "wof:placetype":"venue"
},
  "geometry": {"coordinates":[-105.50386399999999,44.29116],"type":"Point"}
}