{
  "type": "Feature",
  "properties": {
    "addr:full":"2155 Cy Ave Casper WY 82604",
    "addr:housenumber":"2155",
    "addr:postcode":"82604",
    "addr:street":"Cy Ave",
    "iso:country":"US",
    "sg:address":"2155 Cy Ave",
    "sg:city":"Casper",
    "sg:classifiers":[
        {
            "category":"Retail",
            "subcategory":"Auto Repair",
            "type":"Services"
        }
    ],
    "sg:phone":"+1 307 237 1185",
    "sg:postcode":"82604",
    "sg:province":"WY",
    "sg:tags":[
        "muffler",
        "exhaust",
        "system"
    ],
    "wof:name":"Meineke Car Care Ctr",
    "wof:placetype":"venue"
},
  "geometry": {"coordinates":[-106.343199,42.831596],"type":"Point"}
}