{
  "type": "Feature",
  "properties": {
    "addr:full":"409 W Birch St Glenrock WY 82637",
    "addr:housenumber":"409",
    "addr:postcode":"82637",
    "addr:street":"W Birch St Glenrock Wy",
    "iso:country":"US",
    "sg:address":"409 W Birch St",
    "sg:city":"Glenrock",
    "sg:classifiers":[
        {
            "category":"Shopping",
            "subcategory":"Gifts & Souvenirs",
            "type":"Retail Goods"
        }
    ],
    "sg:phone":"+1 307 436 8291",
    "sg:postcode":"82637",
    "sg:province":"WY",
    "sg:tags":[
        "shop"
    ],
    "wof:name":"Glenrock Gift & Book Emporium",
    "wof:placetype":"venue"
},
  "geometry": {"coordinates":[-105.87335400000001,42.861413],"type":"Point"}
}