{
  "type": "Feature",
  "properties": {
    "addr:full":"475 State Hwy 50 Gillette WY 82718",
    "addr:housenumber":"475",
    "addr:postcode":"82718",
    "addr:street":"State Hwy 50",
    "iso:country":"US",
    "sg:address":"475 State Hwy 50",
    "sg:city":"Gillette",
    "sg:classifiers":[
        {
            "category":"Freight",
            "type":"Transportation"
        }
    ],
    "sg:phone":"+1 307 687 3160",
    "sg:postcode":"82718",
    "sg:province":"WY",
    "sg:tags":[
        "delivery",
        "parcel",
        "package"
    ],
    "wof:name":"UPS",
    "wof:placetype":"venue"
},
  "geometry": {"coordinates":[-105.53238899999999,44.289925],"type":"Point"}
}