{
  "type": "Feature",
  "properties": {
    "iso:country":"US",
    "sg:address":"1740 Dell Range Blvd",
    "sg:city":"Cheyenne",
    "sg:classifiers":[
        {
            "category":"Wholesale",
            "subcategory":"Books, Periodicals, & Newspapers",
            "type":"Manufacturing & Wholesale Goods"
        }
    ],
    "sg:phone":"+1 307 635 0118",
    "sg:postcode":"82009",
    "sg:province":"WY",
    "wof:name":"Investment Group Service Ltd",
    "wof:placetype":"venue"
},
  "geometry": {"coordinates":[-104.80336,41.160369],"type":"Point"}
}