{
  "type": "Feature",
  "properties": {
    "iso:country":"US",
    "sg:address":"1066 McDonald Rd",
    "sg:city":"Cheyenne",
    "sg:classifiers":[
        {
            "category":"Professional",
            "type":"Services"
        }
    ],
    "sg:phone":"+1 307 632 7655",
    "sg:postcode":"82009",
    "sg:province":"WY",
    "wof:name":"Daryl Poulin Western Artist",
    "wof:placetype":"venue"
},
  "geometry": {"coordinates":[-105.06796900000001,41.153024],"type":"Point"}
}