{
  "type": "Feature",
  "properties": {
    "addr:full":"920 Main St Evanston UT 82930",
    "addr:housenumber":"920",
    "addr:postcode":"82930",
    "addr:street":"Main St",
    "iso:country":"US",
    "sg:address":"920 Main St",
    "sg:city":"Evanston",
    "sg:classifiers":[
        {
            "category":"Communications",
            "type":"Services"
        }
    ],
    "sg:phone":"+1 307 789 6808",
    "sg:postcode":"82930",
    "sg:province":"UT",
    "wof:name":"Visionary Communications",
    "wof:placetype":"venue"
},
  "geometry": {"coordinates":[-110.965693,41.267689],"type":"Point"}
}