{
  "type": "Feature",
  "properties": {
    "iso:country":"US",
    "sg:address":"4770 Linden Way",
    "sg:city":"Cheyenne",
    "sg:classifiers":[
        {
            "category":"Retail",
            "subcategory":"Repair Shop",
            "type":"Services"
        }
    ],
    "sg:phone":"+1 307 634 2402",
    "sg:postcode":"82009",
    "sg:province":"WY",
    "wof:name":"Moomacs Mounts",
    "wof:placetype":"venue"
},
  "geometry": {"coordinates":[-104.77974500000001,41.165679],"type":"Point"}
}