{
  "type": "Feature",
  "properties": {
    "iso:country":"US",
    "sg:address":"255 N Jean St",
    "sg:city":"Jackson",
    "sg:classifiers":[
        {
            "category":"Education",
            "subcategory":"School",
            "type":"Public Place"
        }
    ],
    "sg:phone":"+1 307 733 2704",
    "sg:postcode":"83001",
    "sg:province":"WY",
    "sg:website":"www.tcsd.org",
    "wof:name":"Teton County School Dist No 01",
    "wof:placetype":"venue"
},
  "geometry": {"coordinates":[-110.757195,43.482294],"type":"Point"}
}