{
  "type": "Feature",
  "properties": {
    "addr:full":"14 Sunrise Ln Gillette WY 82716",
    "addr:housenumber":"14",
    "addr:postcode":"82716",
    "addr:street":"Sunrise Ln",
    "iso:country":"US",
    "sg:address":"14 Sunrise Ln",
    "sg:city":"Gillette",
    "sg:classifiers":[
        {
            "category":"Organizations",
            "subcategory":"Community Association",
            "type":"Services"
        }
    ],
    "sg:phone":"+1 307 682 9252",
    "sg:postcode":"82716",
    "sg:province":"WY",
    "wof:name":"Lions of Wyoming",
    "wof:placetype":"venue"
},
  "geometry": {"coordinates":[-105.49866299999999,44.283059],"type":"Point"}
}