{
  "type": "Feature",
  "properties": {
    "addr:full":"314 US Hwy 20 Manderson WY 82432",
    "addr:housenumber":"314",
    "addr:postcode":"82432",
    "addr:street":"Us Hwy 20 Manderson Wy",
    "iso:country":"US",
    "sg:address":"314 US Hwy 20",
    "sg:city":"Manderson",
    "sg:classifiers":[
        {
            "category":"Utilities",
            "subcategory":"Telephone",
            "type":"Services"
        }
    ],
    "sg:phone":"+1 307 568 9990",
    "sg:postcode":"82432",
    "sg:province":"WY",
    "sg:tags":[
        "company"
    ],
    "wof:name":"Mountain West Telecommunicatns",
    "wof:placetype":"venue"
},
  "geometry": {"coordinates":[-107.96876,44.266109],"type":"Point"}
}