{
  "type": "Feature",
  "properties": {
    "addr:full":"8601 Ptarmigan Ave Gillette WY 82718",
    "addr:housenumber":"8601",
    "addr:postcode":"82718",
    "addr:street":"Ptarmigan Ave",
    "iso:country":"US",
    "sg:address":"8601 Ptarmigan Ave",
    "sg:city":"Gillette",
    "sg:classifiers":[
        {
            "category":"Building & Trades",
            "subcategory":"Equipment Rental",
            "type":"Services"
        }
    ],
    "sg:phone":"+1 307 686 6529",
    "sg:postcode":"82718",
    "sg:province":"WY",
    "wof:name":"Km Energy Services",
    "wof:placetype":"venue"
},
  "geometry": {"coordinates":[-105.45283000000001,44.21462],"type":"Point"}
}