{
  "type": "Feature",
  "properties": {
    "iso:country":"US",
    "sg:address":"1410 Gregory Ln",
    "sg:city":"Jackson",
    "sg:classifiers":[
        {
            "category":"Professional",
            "subcategory":"Advertising",
            "type":"Services"
        }
    ],
    "sg:phone":"+1 307 733 9349",
    "sg:postcode":"83001",
    "sg:province":"WY",
    "sg:tags":[
        "mail"
    ],
    "wof:name":"FBN Mailings",
    "wof:placetype":"venue"
},
  "geometry": {"coordinates":[-110.797651,43.460097],"type":"Point"}
}