{
  "type": "Feature",
  "properties": {
    "addr:full":"27 Pine Ln Sheridan WY 82801",
    "addr:housenumber":"27",
    "addr:postcode":"82801",
    "addr:street":"Pine Ln",
    "iso:country":"US",
    "sg:address":"27 Pine Ln",
    "sg:city":"Sheridan",
    "sg:classifiers":[
        {
            "category":"Travel",
            "subcategory":"Travel Agent",
            "type":"Entertainment"
        }
    ],
    "sg:phone":"+1 307 673 5728",
    "sg:postcode":"82801",
    "sg:province":"WY",
    "sg:tags":[
        "agency",
        "bureau"
    ],
    "wof:name":"Wild West Vacations & Travel",
    "wof:placetype":"venue"
},
  "geometry": {"coordinates":[-106.991016,44.743518],"type":"Point"}
}