{
  "type": "Feature",
  "properties": {
    "addr:full":"1245 Apache Ave Green River WY 82935",
    "addr:housenumber":"1245",
    "addr:postcode":"82935",
    "addr:street":"Apache Ave Green",
    "iso:country":"US",
    "sg:address":"1245 Apache Ave",
    "sg:city":"Green River",
    "sg:classifiers":[
        {
            "category":"Professional",
            "subcategory":"Lawyer & Legal Services",
            "type":"Services"
        }
    ],
    "sg:phone":"+1 307 875 2696",
    "sg:postcode":"82935",
    "sg:province":"WY",
    "wof:name":"Melissa A Botham",
    "wof:placetype":"venue"
},
  "geometry": {"coordinates":[-109.470405,41.504669],"type":"Point"}
}