{
  "type": "Feature",
  "properties": {
    "addr:full":"1128 King Ct Cheyenne WY 82007",
    "addr:housenumber":"1128",
    "addr:postcode":"82007",
    "addr:street":"King Ct",
    "iso:country":"US",
    "sg:address":"1128 King Ct",
    "sg:city":"Cheyenne",
    "sg:classifiers":[
        {
            "category":"Real Estate",
            "subcategory":"Real Estate Agent",
            "type":"Services"
        }
    ],
    "sg:phone":"+1 307 634 5494",
    "sg:postcode":"82007",
    "sg:province":"WY",
    "wof:name":"Mona Coler",
    "wof:placetype":"venue"
},
  "geometry": {"coordinates":[-104.82611300000001,41.111717],"type":"Point"}
}