{
  "type": "Feature",
  "properties": {
    "iso:country":"US",
    "sg:address":"1873 State Hwy 24",
    "sg:city":"Hulett",
    "sg:classifiers":[
        {
            "category":"Travel",
            "subcategory":"Hotels & Motels",
            "type":"Entertainment"
        }
    ],
    "sg:phone":"+1 307 467 5885",
    "sg:postcode":"82720",
    "sg:province":"WY",
    "sg:tags":[
        "operation"
    ],
    "wof:name":"Rimrock Lodge",
    "wof:placetype":"venue"
},
  "geometry": {"coordinates":[-104.599163,44.686762],"type":"Point"}
}