{
  "type": "Feature",
  "properties": {
    "addr:full":"2526 Seymour Ave Cheyenne WY 82001",
    "addr:housenumber":"2526",
    "addr:postcode":"82001",
    "addr:street":"Seymour Ave",
    "iso:country":"US",
    "sg:address":"2526 Seymour Ave",
    "sg:city":"Cheyenne",
    "sg:classifiers":[
        {
            "category":"Health Services",
            "subcategory":"Health Practitioner",
            "type":"Services"
        }
    ],
    "sg:phone":"+1 307 634 9653",
    "sg:postcode":"82001",
    "sg:province":"WY",
    "wof:name":"Peak Walnut Center",
    "wof:placetype":"venue"
},
  "geometry": {"coordinates":[-104.813148,41.14424],"type":"Point"}
}