{
  "type": "Feature",
  "properties": {
    "iso:country":"US",
    "sg:address":"534 15th St",
    "sg:city":"Cody",
    "sg:classifiers":[
        {
            "category":"Home & Garden",
            "subcategory":"Building Materials",
            "type":"Retail Goods"
        }
    ],
    "sg:phone":"+1 307 527 4361",
    "sg:postcode":"82414",
    "sg:province":"WY",
    "wof:name":"Bighorn Window Tinting",
    "wof:placetype":"venue"
},
  "geometry": {"coordinates":[-109.05818499999999,44.531752],"type":"Point"}
}