{
  "type": "Feature",
  "properties": {
    "addr:full":"130 S Ash St Casper WY 82601",
    "addr:housenumber":"130",
    "addr:postcode":"82601",
    "addr:street":"S Ash St",
    "iso:country":"US",
    "sg:address":"130 S Ash St",
    "sg:city":"Casper",
    "sg:classifiers":[
        {
            "category":"Health Services",
            "subcategory":"Clinic",
            "type":"Services"
        }
    ],
    "sg:phone":"+1 307 234 6684",
    "sg:postcode":"82601",
    "sg:province":"WY",
    "sg:tags":[
        "home"
    ],
    "wof:name":"North Platte Home Health Care",
    "wof:placetype":"venue"
},
  "geometry": {"coordinates":[-106.328675,42.849433],"type":"Point"}
}