{
  "type": "Feature",
  "properties": {
    "iso:country":"US",
    "sg:address":"107 N 4th St",
    "sg:city":"Worland",
    "sg:classifiers":[
        {
            "category":"Government",
            "subcategory":"Office",
            "type":"Public Place"
        }
    ],
    "sg:phone":"+1 307 864 4030",
    "sg:postcode":"82401",
    "sg:province":"WY",
    "sg:tags":[
        "village"
    ],
    "wof:name":"Kirby Town Office",
    "wof:placetype":"venue"
},
  "geometry": {"coordinates":[-107.96383299999999,44.017816],"type":"Point"}
}