{
  "type": "Feature",
  "properties": {
    "addr:full":"3633 Bradley Ave Cheyenne WY 82001",
    "addr:housenumber":"3633",
    "addr:postcode":"82001",
    "addr:street":"Bradley Ave",
    "iso:country":"US",
    "sg:address":"3633 Bradley Ave",
    "sg:city":"Cheyenne",
    "sg:classifiers":[
        {
            "category":"Retail",
            "subcategory":"Repair Shop",
            "type":"Services"
        }
    ],
    "sg:phone":"+1 307 635 2086",
    "sg:postcode":"82001",
    "sg:province":"WY",
    "wof:name":"Boston Electronics",
    "wof:placetype":"venue"
},
  "geometry": {"coordinates":[-104.808162,41.150292],"type":"Point"}
}