{
  "type": "Feature",
  "properties": {
    "iso:country":"US",
    "sg:address":"501 Parsley Blvd",
    "sg:city":"Cheyenne",
    "sg:classifiers":[
        {
            "category":"Organizations",
            "subcategory":"Membership Organization",
            "type":"Services"
        }
    ],
    "sg:phone":"+1 307 632 6655",
    "sg:postcode":"82007",
    "sg:province":"WY",
    "sg:tags":[
        "veterinary"
    ],
    "wof:name":"Cheyenne Animal Control",
    "wof:placetype":"venue"
},
  "geometry": {"coordinates":[-104.82830199999999,41.123519],"type":"Point"}
}