{
  "type": "Feature",
  "properties": {
    "iso:country":"US",
    "sg:address":"5151 Newland Ave",
    "sg:city":"Cheyenne",
    "sg:classifiers":[
        {
            "category":"Building & Trades",
            "subcategory":"Landscaping Services",
            "type":"Services"
        }
    ],
    "sg:phone":"+1 307 635 1522",
    "sg:postcode":"82009",
    "sg:province":"WY",
    "wof:name":"H2o Irrigation Systems",
    "wof:placetype":"venue"
},
  "geometry": {"coordinates":[-104.760358,41.166246],"type":"Point"}
}