{
  "type": "Feature",
  "properties": {
    "iso:country":"US",
    "sg:address":"940 E 3rd St",
    "sg:city":"Casper",
    "sg:classifiers":[
        {
            "category":"Health Services",
            "subcategory":"Doctor",
            "type":"Services"
        }
    ],
    "sg:phone":"+1 307 577 0480",
    "sg:postcode":"82601",
    "sg:province":"WY",
    "sg:tags":[
        "medical"
    ],
    "wof:name":"Michael J Quinn MD",
    "wof:placetype":"venue"
},
  "geometry": {"coordinates":[-106.313686,42.847782],"type":"Point"}
}