{
  "type": "Feature",
  "properties": {
    "iso:country":"US",
    "sg:address":"1324 N 6th St",
    "sg:city":"Greybull",
    "sg:classifiers":[
        {
            "category":"Travel",
            "subcategory":"Hotels & Motels",
            "type":"Entertainment"
        }
    ],
    "sg:phone":"+1 307 765 2105",
    "sg:postcode":"82426",
    "sg:province":"WY",
    "sg:tags":[
        "operation",
        "business"
    ],
    "wof:name":"Buget Host",
    "wof:placetype":"venue"
},
  "geometry": {"coordinates":[-108.055588,44.503337],"type":"Point"}
}