{
  "type": "Feature",
  "properties": {
    "iso:country":"US",
    "sg:address":"14 Fox Creek Rd",
    "sg:city":"Laramie",
    "sg:classifiers":[
        {
            "category":"Building & Trades",
            "subcategory":"Construction",
            "type":"Services"
        }
    ],
    "sg:phone":"+1 307 742 5629",
    "sg:postcode":"82070",
    "sg:province":"WY",
    "sg:tags":[
        "excavation",
        "contractor"
    ],
    "wof:name":"Timberline Excavating",
    "wof:placetype":"venue"
},
  "geometry": {"coordinates":[-106.086654,41.195068],"type":"Point"}
}