{
  "type": "Feature",
  "properties": {
    "iso:country":"US",
    "sg:address":"1945 S Jefferson St",
    "sg:city":"Casper",
    "sg:classifiers":[
        {
            "category":"Building & Trades",
            "subcategory":"Plumbing",
            "type":"Services"
        }
    ],
    "sg:phone":"+1 307 234 6368",
    "sg:postcode":"82601",
    "sg:province":"WY",
    "sg:tags":[
        "contractor"
    ],
    "wof:name":"F Doyal Plumbing & Heating",
    "wof:placetype":"venue"
},
  "geometry": {"coordinates":[-106.31340899999999,42.829803],"type":"Point"}
}