{
  "type": "Feature",
  "properties": {
    "addr:full":"2020 Carey Ave Cheyenne WY 82001",
    "addr:housenumber":"2020",
    "addr:postcode":"82001",
    "addr:street":"Carey Ave",
    "iso:country":"US",
    "sg:address":"2020 Carey Ave",
    "sg:city":"Cheyenne",
    "sg:classifiers":[
        {
            "category":"Professional",
            "type":"Services"
        }
    ],
    "sg:phone":"+1 307 634 6264",
    "sg:postcode":"82001",
    "sg:province":"WY",
    "sg:tags":[
        "establishment"
    ],
    "wof:name":"Wercs Comm Tribcsr",
    "wof:placetype":"venue"
},
  "geometry": {"coordinates":[-104.819239,41.136538],"type":"Point"}
}