{
  "type": "Feature",
  "properties": {
    "iso:country":"US",
    "sg:address":"2800 Central Ave",
    "sg:city":"Cheyenne",
    "sg:classifiers":[
        {
            "category":"Education",
            "subcategory":"Library",
            "type":"Public Place"
        },
        {
            "category":"Organizations",
            "subcategory":"Professional Association",
            "type":"Services"
        }
    ],
    "sg:phone":"+1 307 635 1032",
    "sg:postcode":"82001",
    "sg:province":"WY",
    "sg:tags":[
        "executive"
    ],
    "wof:name":"Laramie County Library System",
    "wof:placetype":"venue"
},
  "geometry": {"coordinates":[-104.82166599999999,41.144663],"type":"Point"}
}