{
  "type": "Feature",
  "properties": {
    "addr:full":"3500 Co Rd 28 Greybull WY 82426",
    "addr:housenumber":"3500;28",
    "addr:postcode":"82426",
    "addr:street":"Co Rd;Greybull Wy",
    "iso:country":"US",
    "sg:address":"3500 Co Rd 28",
    "sg:city":"Greybull",
    "sg:classifiers":[
        {
            "category":"Government",
            "subcategory":"Office",
            "type":"Public Place"
        }
    ],
    "sg:phone":"+1 307 765 2290",
    "sg:postcode":"82426",
    "sg:province":"WY",
    "sg:tags":[
        "village"
    ],
    "wof:name":"Greybull Town Shop",
    "wof:placetype":"venue"
},
  "geometry": {"coordinates":[-108.02708,44.487771],"type":"Point"}
}