{
  "type": "Feature",
  "properties": {
    "addr:full":"6022 State Hwy 89 N Evanston UT 82930",
    "addr:housenumber":"6022",
    "addr:postcode":"82930",
    "addr:street":"State Hwy 89 N",
    "iso:country":"US",
    "sg:address":"6022 State Hwy 89 N",
    "sg:city":"Evanston",
    "sg:classifiers":[
        {
            "category":"Utilities",
            "subcategory":"Refuse",
            "type":"Services"
        }
    ],
    "sg:phone":"+1 307 789 9202",
    "sg:postcode":"82930",
    "sg:province":"UT",
    "sg:tags":[
        "sanitation"
    ],
    "wof:name":"Rocket Sanitation",
    "wof:placetype":"venue"
},
  "geometry": {"coordinates":[-111.00267599999999,41.350444],"type":"Point"}
}