{
  "type": "Feature",
  "properties": {
    "iso:country":"US",
    "sg:address":"1603 Capitol Ave",
    "sg:city":"Cheyenne",
    "sg:classifiers":[
        {
            "category":"Organizations",
            "subcategory":"Professional Association",
            "type":"Services"
        }
    ],
    "sg:phone":"+1 307 635 1124",
    "sg:postcode":"82001",
    "sg:province":"WY",
    "wof:name":"Sierra Club Wyoming",
    "wof:placetype":"venue"
},
  "geometry": {"coordinates":[-104.81577299999999,41.133635],"type":"Point"}
}