{
  "type": "Feature",
  "properties": {
    "addr:full":"1119 W 20th St Cheyenne WY 82001",
    "addr:housenumber":"1119",
    "addr:postcode":"82001",
    "addr:street":"W 20Th St",
    "iso:country":"US",
    "sg:address":"1119 W 20th St",
    "sg:city":"Cheyenne",
    "sg:classifiers":[
        {
            "category":"Wholesale",
            "subcategory":"Machinery & Supplies",
            "type":"Manufacturing & Wholesale Goods"
        }
    ],
    "sg:phone":"+1 307 632 5569",
    "sg:postcode":"82001",
    "sg:province":"WY",
    "sg:tags":[
        "equipment",
        "industrial",
        "electrical",
        "bearing"
    ],
    "wof:name":"Applied Industrial Tech Inc",
    "wof:placetype":"venue"
},
  "geometry": {"coordinates":[-104.828622,41.132146],"type":"Point"}
}