{
  "type": "Feature",
  "properties": {
    "addr:full":"406 Broadway St Rock Springs WY 82901",
    "addr:housenumber":"406",
    "addr:postcode":"82901",
    "addr:street":"Broadway St Rock Springs Wy",
    "iso:country":"US",
    "sg:address":"406 Broadway St",
    "sg:city":"Rock Springs",
    "sg:classifiers":[
        {
            "category":"Shopping",
            "subcategory":"Used Merchandise",
            "type":"Retail Goods"
        }
    ],
    "sg:phone":"+1 307 362 7786",
    "sg:postcode":"82901",
    "sg:province":"WY",
    "sg:tags":[
        "clothing"
    ],
    "wof:name":"Coal Miners Daughter",
    "wof:placetype":"venue"
},
  "geometry": {"coordinates":[-109.219504,41.586115],"type":"Point"}
}