{
  "type": "Feature",
  "properties": {
    "iso:country":"US",
    "sg:address":"4316 W Highway St",
    "sg:city":"Casper",
    "sg:classifiers":[
        {
            "category":"Building & Trades",
            "subcategory":"Landscaping Services",
            "type":"Services"
        }
    ],
    "sg:phone":"+1 307 234 3874",
    "sg:postcode":"82604",
    "sg:province":"WY",
    "sg:tags":[
        "landscape",
        "contractor"
    ],
    "wof:name":"J & G Landscaping",
    "wof:placetype":"venue"
},
  "geometry": {"coordinates":[-106.38047400000001,42.850335],"type":"Point"}
}