{
  "type": "Feature",
  "properties": {
    "addr:full":"145 S Durbin St Casper WY 82601",
    "addr:housenumber":"145",
    "addr:postcode":"82601",
    "addr:street":"S Durbin St",
    "iso:country":"US",
    "sg:address":"145 S Durbin St",
    "sg:city":"Casper",
    "sg:classifiers":[
        {
            "category":"Government",
            "subcategory":"Office",
            "type":"Public Place"
        }
    ],
    "sg:phone":"+1 307 472 5591",
    "sg:postcode":"82601",
    "sg:province":"WY",
    "wof:name":"Amacoreuse Agreement Joint",
    "wof:placetype":"venue"
},
  "geometry": {"coordinates":[-106.32225800000001,42.849336],"type":"Point"}
}