{
  "type": "Feature",
  "properties": {
    "iso:country":"US",
    "sg:address":"77 Hitching Post Dr",
    "sg:city":"Cody",
    "sg:classifiers":[
        {
            "category":"Retail",
            "subcategory":"Auto Repair",
            "type":"Services"
        }
    ],
    "sg:phone":"+1 307 587 8575",
    "sg:postcode":"82414",
    "sg:province":"WY",
    "sg:tags":[
        "repairing",
        "automobile"
    ],
    "wof:name":"Roadrunner Mobile Tune",
    "wof:placetype":"venue"
},
  "geometry": {"coordinates":[-109.011501,44.56092],"type":"Point"}
}