{
  "type": "Feature",
  "properties": {
    "addr:full":"160 N Millward St Jackson WY 83001",
    "addr:housenumber":"160",
    "addr:postcode":"83001",
    "addr:street":"N Millward St Jackson Wy",
    "iso:country":"US",
    "sg:address":"160 N Millward St",
    "sg:city":"Jackson",
    "sg:classifiers":[
        {
            "category":"Restaurant",
            "type":"Food & Drink"
        }
    ],
    "sg:phone":"+1 307 733 3912",
    "sg:postcode":"83001",
    "sg:province":"WY",
    "sg:website":"www.bluelionrestaurant.com",
    "wof:name":"Blue Lion",
    "wof:placetype":"venue"
},
  "geometry": {"coordinates":[-110.765074,43.480319],"type":"Point"}
}