{
  "type": "Feature",
  "properties": {
    "iso:country":"US",
    "sg:address":"140 N Ferris St",
    "sg:city":"Powell",
    "sg:classifiers":[
        {
            "category":"Education",
            "subcategory":"School",
            "type":"Public Place"
        }
    ],
    "sg:phone":"+1 307 754 0901",
    "sg:postcode":"82435",
    "sg:province":"WY",
    "wof:name":"Shoshone Learning Ctr",
    "wof:placetype":"venue"
},
  "geometry": {"coordinates":[-108.75172499999999,44.75374],"type":"Point"}
}