{
  "type": "Feature",
  "properties": {
    "iso:country":"US",
    "sg:address":"3416 White Mountain Blvd",
    "sg:city":"Rock Springs",
    "sg:classifiers":[
        {
            "category":"Social Services",
            "subcategory":"Adult Care",
            "type":"Services"
        }
    ],
    "sg:phone":"+1 307 352 0136",
    "sg:postcode":"82901",
    "sg:province":"WY",
    "sg:tags":[
        "home",
        "group"
    ],
    "wof:name":"Supervised Living",
    "wof:placetype":"venue"
},
  "geometry": {"coordinates":[-109.25789,41.586958],"type":"Point"}
}