{
  "type": "Feature",
  "properties": {
    "iso:country":"US",
    "sg:address":"602 W 13th St",
    "sg:city":"Casper",
    "sg:classifiers":[
        {
            "category":"Real Estate",
            "subcategory":"Real Estate Operator",
            "type":"Services"
        }
    ],
    "sg:phone":"+1 307 237 9292",
    "sg:postcode":"82601",
    "sg:province":"WY",
    "sg:tags":[
        "building",
        "apartment"
    ],
    "wof:name":"Granada Corp",
    "wof:placetype":"venue"
},
  "geometry": {"coordinates":[-106.333044,42.837625],"type":"Point"}
}