{
  "type": "Feature",
  "properties": {
    "addr:full":"1170 Country Club Rd Gillette WY 82717",
    "addr:housenumber":"1170",
    "addr:postcode":"82717",
    "addr:street":"Country Club Rd",
    "iso:country":"US",
    "sg:address":"1170 Country Club Rd",
    "sg:city":"Gillette",
    "sg:classifiers":[
        {
            "category":"Organizations",
            "subcategory":"Religious Organization",
            "type":"Services"
        }
    ],
    "sg:phone":"+1 307 682 2543",
    "sg:postcode":"82717",
    "sg:province":"WY",
    "sg:tags":[
        "school"
    ],
    "wof:name":"Central Baptist Church",
    "wof:placetype":"venue"
},
  "geometry": {"coordinates":[-105.48394999999999,44.275339],"type":"Point"}
}