{
  "type": "Feature",
  "properties": {
    "addr:full":"33 Allegiance Cir Evanston WY 82930",
    "addr:housenumber":"33",
    "addr:postcode":"82930",
    "addr:street":"Allegiance Cir",
    "iso:country":"US",
    "sg:address":"33 Allegiance Cir",
    "sg:city":"Evanston",
    "sg:classifiers":[
        {
            "category":"Government",
            "subcategory":"Office",
            "type":"Public Place"
        }
    ],
    "sg:phone":"+1 307 789 9805",
    "sg:postcode":"82930",
    "sg:province":"WY",
    "sg:tags":[
        "city",
        "planning",
        "dev"
    ],
    "wof:name":"Evanston Planning & Zoning",
    "wof:placetype":"venue"
},
  "geometry": {"coordinates":[-110.992018,41.261795],"type":"Point"}
}