{
  "type": "Feature",
  "properties": {
    "addr:full":"2510 E 15th St Casper WY 82609",
    "addr:housenumber":"2510",
    "addr:postcode":"82609",
    "addr:street":"E 15Th St",
    "iso:country":"US",
    "sg:address":"2510 E 15th St",
    "sg:city":"Casper",
    "sg:classifiers":[
        {
            "category":"Insurance",
            "subcategory":"Insurance Agent",
            "type":"Services"
        }
    ],
    "sg:phone":"+1 307 266 2116",
    "sg:postcode":"82609",
    "sg:province":"WY",
    "wof:name":"Allstate",
    "wof:placetype":"venue"
},
  "geometry": {"coordinates":[-106.294746,42.835403],"type":"Point"}
}