{
  "type": "Feature",
  "properties": {
    "iso:country":"US",
    "sg:address":"2106 E Holliday Dr",
    "sg:city":"Laramie",
    "sg:classifiers":[
        {
            "category":"Building & Trades",
            "subcategory":"Construction",
            "type":"Services"
        }
    ],
    "sg:phone":"+1 307 742 7687",
    "sg:postcode":"82070",
    "sg:province":"WY",
    "sg:tags":[
        "a",
        "house",
        "carpentry",
        "contractor"
    ],
    "wof:name":"David Paulekas",
    "wof:placetype":"venue"
},
  "geometry": {"coordinates":[-105.566632,41.302714],"type":"Point"}
}