{
  "type": "Feature",
  "properties": {
    "iso:country":"US",
    "sg:address":"714 Fullerton Ave",
    "sg:city":"Buffalo",
    "sg:classifiers":[
        {
            "category":"Building & Trades",
            "subcategory":"Cleaning & Sanitation",
            "type":"Services"
        }
    ],
    "sg:phone":"+1 307 684 2882",
    "sg:postcode":"82834",
    "sg:province":"WY",
    "sg:tags":[
        "maintenance"
    ],
    "wof:name":"Bobs Cleaning Service",
    "wof:placetype":"venue"
},
  "geometry": {"coordinates":[-106.70696599999999,44.336208],"type":"Point"}
}