{
  "type": "Feature",
  "properties": {
    "addr:full":"2109 Main St Torrington WY 82240",
    "addr:housenumber":"2109",
    "addr:postcode":"82240",
    "addr:street":"Main St",
    "iso:country":"US",
    "sg:address":"2109 Main St",
    "sg:city":"Torrington",
    "sg:classifiers":[
        {
            "category":"Personal",
            "subcategory":"Beauty Salon",
            "type":"Services"
        }
    ],
    "sg:phone":"+1 307 532 7890",
    "sg:postcode":"82240",
    "sg:province":"WY",
    "sg:tags":[
        "shop"
    ],
    "wof:name":"North Main Studio",
    "wof:placetype":"venue"
},
  "geometry": {"coordinates":[-104.18431,42.065912],"type":"Point"}
}