{
  "type": "Feature",
  "properties": {
    "addr:full":"2025 Main St Torrington WY 82240",
    "addr:housenumber":"2025",
    "addr:postcode":"82240",
    "addr:street":"Main St",
    "iso:country":"US",
    "sg:address":"2025 Main St",
    "sg:city":"Torrington",
    "sg:classifiers":[
        {
            "category":"Manufacturing",
            "subcategory":"Printing",
            "type":"Manufacturing & Wholesale Goods"
        }
    ],
    "sg:phone":"+1 307 532 2184",
    "sg:postcode":"82240",
    "sg:province":"WY",
    "sg:tags":[
        "newspaper"
    ],
    "sg:website":"www.torringtontelegram.com",
    "wof:name":"Torrington Telegram",
    "wof:placetype":"venue"
},
  "geometry": {"coordinates":[-104.184307,42.064771],"type":"Point"}
}