{
  "type": "Feature",
  "properties": {
    "addr:full":"27 Mayoworth Rd Kaycee WY 82639",
    "addr:housenumber":"27",
    "addr:postcode":"82639",
    "addr:street":"Mayoworth Rd Kaycee Wy",
    "iso:country":"US",
    "sg:address":"27 Mayoworth Rd",
    "sg:city":"Kaycee",
    "sg:classifiers":[
        {
            "category":"Autos & Motor Vehicles",
            "subcategory":"Fuel & Gas Station",
            "type":"Retail Goods"
        }
    ],
    "sg:phone":"+1 307 738 2213",
    "sg:postcode":"82639",
    "sg:province":"WY",
    "sg:tags":[
        "station",
        "gasoline"
    ],
    "wof:name":"Kaycee Sinclair",
    "wof:placetype":"venue"
},
  "geometry": {"coordinates":[-106.643967,43.716804],"type":"Point"}
}