{
  "type": "Feature",
  "properties": {
    "iso:country":"US",
    "sg:address":"2222 Rollins Ave",
    "sg:city":"Cheyenne",
    "sg:classifiers":[
        {
            "category":"Professional",
            "subcategory":"Management & Consulting",
            "type":"Services"
        }
    ],
    "sg:phone":"+1 307 635 7166",
    "sg:postcode":"82001",
    "sg:province":"WY",
    "sg:tags":[
        "specialist",
        "education"
    ],
    "wof:name":"Tina Linde",
    "wof:placetype":"venue"
},
  "geometry": {"coordinates":[-104.80246099999999,41.144953],"type":"Point"}
}