{
  "type": "Feature",
  "properties": {
    "iso:country":"US",
    "sg:address":"106 N 3rd St E",
    "sg:city":"Riverton",
    "sg:classifiers":[
        {
            "category":"Home & Garden",
            "subcategory":"Furniture",
            "type":"Retail Goods"
        }
    ],
    "sg:phone":"+1 307 856 7336",
    "sg:postcode":"82501",
    "sg:province":"WY",
    "wof:name":"Country Cottage",
    "wof:placetype":"venue"
},
  "geometry": {"coordinates":[-108.38784200000001,43.025655],"type":"Point"}
}