{
  "type": "Feature",
  "properties": {
    "addr:full":"200 W 24th St Cheyenne WY 82001",
    "addr:housenumber":"200",
    "addr:postcode":"82001",
    "addr:street":"W 24Th St",
    "iso:country":"US",
    "sg:address":"200 W 24th St",
    "sg:city":"Cheyenne",
    "sg:classifiers":[
        {
            "category":"Government",
            "subcategory":"Office",
            "type":"Public Place"
        }
    ],
    "sg:phone":"+1 307 777 7408",
    "sg:postcode":"82001",
    "sg:province":"WY",
    "sg:tags":[
        "state",
        "taxation"
    ],
    "wof:name":"State Treasurer",
    "wof:placetype":"venue"
},
  "geometry": {"coordinates":[-104.82101900000001,41.139406],"type":"Point"}
}