{
  "type": "Feature",
  "properties": {
    "addr:full":"263 N 3rd St Laramie WY 82072",
    "addr:housenumber":"263",
    "addr:postcode":"82072",
    "addr:street":"N 3Rd St",
    "iso:country":"US",
    "sg:address":"263 N 3rd St",
    "sg:city":"Laramie",
    "sg:classifiers":[
        {
            "category":"Real Estate",
            "subcategory":"Real Estate Agent",
            "type":"Services"
        }
    ],
    "sg:phone":"+1 307 742 2151",
    "sg:postcode":"82072",
    "sg:province":"WY",
    "wof:name":"O'Dell Enterprises",
    "wof:placetype":"venue"
},
  "geometry": {"coordinates":[-105.593192,41.314186],"type":"Point"}
}