{
  "type": "Feature",
  "properties": {
    "iso:country":"US",
    "sg:address":"2525 Co Rd 124-A",
    "sg:city":"Cheyenne",
    "sg:classifiers":[
        {
            "category":"Health Services",
            "subcategory":"Doctor",
            "type":"Services"
        }
    ],
    "sg:phone":"+1 307 632 1172",
    "sg:postcode":"82009",
    "sg:province":"WY",
    "sg:tags":[
        "physician",
        "surgeon"
    ],
    "wof:name":"Emergency Medical Physicians",
    "wof:placetype":"venue"
},
  "geometry": {"coordinates":[-104.82717700000001,41.353217],"type":"Point"}
}