{
  "type": "Feature",
  "properties": {
    "iso:country":"US",
    "sg:address":"997 Fort St",
    "sg:city":"Buffalo",
    "sg:classifiers":[
        {
            "category":"Travel",
            "subcategory":"Hotels & Motels",
            "type":"Entertainment"
        }
    ],
    "sg:phone":"+1 307 684 2957",
    "sg:postcode":"82834",
    "sg:province":"WY",
    "wof:name":"Canyon Motel",
    "wof:placetype":"venue"
},
  "geometry": {"coordinates":[-106.718388,44.347254],"type":"Point"}
}