{
  "type": "Feature",
  "properties": {
    "iso:country":"US",
    "sg:address":"250 Scott Ln",
    "sg:city":"Jackson",
    "sg:classifiers":[
        {
            "category":"Professional",
            "subcategory":"Computer Services",
            "type":"Services"
        }
    ],
    "sg:phone":"+1 307 733 5565",
    "sg:postcode":"83001",
    "sg:province":"WY",
    "sg:tags":[
        "internet"
    ],
    "wof:name":"21st Century Goods",
    "wof:placetype":"venue"
},
  "geometry": {"coordinates":[-110.782426,43.472135],"type":"Point"}
}