{
  "type": "Feature",
  "properties": {
    "iso:country":"US",
    "sg:address":"106 Fort St",
    "sg:city":"Buffalo",
    "sg:classifiers":[
        {
            "category":"Banks & Credit Unions",
            "subcategory":"Financial Services",
            "type":"Services"
        }
    ],
    "sg:phone":"+1 307 684 5591",
    "sg:postcode":"82834",
    "sg:province":"WY",
    "sg:tags":[
        "company",
        "holding"
    ],
    "wof:name":"Crazy Woman Creek Bancorp Inc",
    "wof:placetype":"venue"
},
  "geometry": {"coordinates":[-106.700185,44.348271],"type":"Point"}
}