{
  "type": "Feature",
  "properties": {
    "iso:country":"US",
    "sg:address":"711 S Railway Ave",
    "sg:city":"Worland",
    "sg:classifiers":[
        {
            "category":"Autos & Motor Vehicles",
            "subcategory":"Auto Supplies",
            "type":"Retail Goods"
        }
    ],
    "sg:phone":"+1 307 347 3281",
    "sg:postcode":"82401",
    "sg:province":"WY",
    "sg:tags":[
        "automobile",
        "parts"
    ],
    "wof:name":"Western Auto",
    "wof:placetype":"venue"
},
  "geometry": {"coordinates":[-107.966362,44.010656],"type":"Point"}
}