{
  "type": "Feature",
  "properties": {
    "iso:country":"US",
    "sg:address":"352 Dalcour Dr",
    "sg:city":"Cheyenne",
    "sg:classifiers":[
        {
            "category":"Personal",
            "type":"Services"
        }
    ],
    "sg:phone":"+1 307 778 7173",
    "sg:postcode":"82009",
    "sg:province":"WY",
    "sg:tags":[
        "therapist",
        "massage"
    ],
    "wof:name":"Lis Therapeutic Massage",
    "wof:placetype":"venue"
},
  "geometry": {"coordinates":[-104.823589,41.177947],"type":"Point"}
}