{
  "type": "Feature",
  "properties": {
    "iso:country":"US",
    "sg:address":"19 W 5th Ave",
    "sg:city":"Afton",
    "sg:classifiers":[
        {
            "category":"Shopping",
            "subcategory":"Clothing, Apparel, & Fashions",
            "type":"Retail Goods"
        }
    ],
    "sg:phone":"+1 307 885 0066",
    "sg:postcode":"83110",
    "sg:province":"WY",
    "sg:tags":[
        "baby",
        "accessory"
    ],
    "wof:name":"Little Things Baby Boutique",
    "wof:placetype":"venue"
},
  "geometry": {"coordinates":[-110.936031,42.723403],"type":"Point"}
}