{
  "type": "Feature",
  "properties": {
    "iso:country":"US",
    "sg:address":"348 N Main St",
    "sg:city":"Sheridan",
    "sg:classifiers":[
        {
            "category":"Manufacturing",
            "subcategory":"Signs",
            "type":"Manufacturing & Wholesale Goods"
        }
    ],
    "sg:phone":"+1 307 672 8778",
    "sg:postcode":"82801",
    "sg:province":"WY",
    "sg:tags":[
        "specialty",
        "mfg"
    ],
    "wof:name":"ABC Signs & Specialities",
    "wof:placetype":"venue"
},
  "geometry": {"coordinates":[-106.95583000000001,44.801225],"type":"Point"}
}