{
  "type": "Feature",
  "properties": {
    "iso:country":"US",
    "sg:address":"836 N Glenn Rd",
    "sg:city":"Casper",
    "sg:classifiers":[
        {
            "category":"Wholesale",
            "subcategory":"Electrical",
            "type":"Manufacturing & Wholesale Goods"
        }
    ],
    "sg:phone":"+1 307 237 4719",
    "sg:postcode":"82601",
    "sg:province":"WY",
    "sg:tags":[
        "equipment",
        "electric",
        "supply"
    ],
    "wof:name":"Western States Electric Supply",
    "wof:placetype":"venue"
},
  "geometry": {"coordinates":[-106.33831600000001,42.858671],"type":"Point"}
}