{
  "type": "Feature",
  "properties": {
    "iso:country":"US",
    "sg:address":"309 S 4th St",
    "sg:city":"Laramie",
    "sg:classifiers":[
        {
            "category":"Government",
            "subcategory":"Police Station",
            "type":"Public Place"
        }
    ],
    "sg:phone":"+1 307 721 5322",
    "sg:postcode":"82070",
    "sg:province":"WY",
    "sg:tags":[
        "sheriff"
    ],
    "wof:name":"Albany County Sheriff Dept",
    "wof:placetype":"venue"
},
  "geometry": {"coordinates":[-105.59223299999999,41.310852],"type":"Point"}
}