{
  "type": "Feature",
  "properties": {
    "iso:country":"US",
    "sg:address":"437 S Spruce St",
    "sg:city":"Casper",
    "sg:classifiers":[
        {
            "category":"Social Services",
            "subcategory":"Job Training",
            "type":"Services"
        }
    ],
    "sg:phone":"+1 307 577 3091",
    "sg:postcode":"82601",
    "sg:province":"WY",
    "wof:name":"Rocky Mountain Re-Entry Svc",
    "wof:placetype":"venue"
},
  "geometry": {"coordinates":[-106.33183699999999,42.845644],"type":"Point"}
}