{
  "type": "Feature",
  "properties": {
    "iso:country":"US",
    "sg:address":"413 W Fairview Rd",
    "sg:city":"Wheatland",
    "sg:phone":"+1 307 322 3803",
    "sg:postcode":"82201",
    "sg:province":"WY",
    "sg:tags":[
        "farm",
        "corn",
        "beet"
    ],
    "wof:name":"Farming",
    "wof:placetype":"venue"
},
  "geometry": {"coordinates":[-105.027767,42.089218],"type":"Point"}
}