{
  "type": "Feature",
  "properties": {
    "iso:country":"US",
    "sg:address":"1307 Crook Ave",
    "sg:city":"Cheyenne",
    "sg:classifiers":[
        {
            "category":"Health Services",
            "subcategory":"Doctor",
            "type":"Services"
        }
    ],
    "sg:phone":"+1 307 778 2015",
    "sg:postcode":"82001",
    "sg:province":"WY",
    "sg:tags":[
        "clinic"
    ],
    "wof:name":"Allergy & Asthma Clinic Of Wy",
    "wof:placetype":"venue"
},
  "geometry": {"coordinates":[-104.78868199999999,41.138369],"type":"Point"}
}