{
  "type": "Feature",
  "properties": {
    "iso:country":"US",
    "sg:address":"2909 E 11th St",
    "sg:city":"Casper",
    "sg:classifiers":[
        {
            "category":"Building & Trades",
            "subcategory":"Construction",
            "type":"Services"
        }
    ],
    "sg:phone":"+1 307 235 1704",
    "sg:postcode":"82609",
    "sg:province":"WY",
    "sg:tags":[
        "hanging",
        "contractor"
    ],
    "wof:name":"Hamre Painting",
    "wof:placetype":"venue"
},
  "geometry": {"coordinates":[-106.288721,42.839759],"type":"Point"}
}