{
  "type": "Feature",
  "properties": {
    "iso:country":"US",
    "sg:address":"4801 Central Ave",
    "sg:city":"Cheyenne",
    "sg:classifiers":[
        {
            "category":"Restaurant",
            "type":"Food & Drink"
        }
    ],
    "sg:phone":"+1 307 632 2065",
    "sg:postcode":"82009",
    "sg:province":"WY",
    "sg:tags":[
        "eating"
    ],
    "wof:name":"Double Eagle Diner",
    "wof:placetype":"venue"
},
  "geometry": {"coordinates":[-104.831096,41.162062],"type":"Point"}
}