{
  "type": "Feature",
  "properties": {
    "addr:full":"4001 Pinehurst Ct Riverton WY 82501",
    "addr:housenumber":"4001",
    "addr:postcode":"82501",
    "addr:street":"Pinehurst Ct",
    "iso:country":"US",
    "sg:address":"4001 Pinehurst Ct",
    "sg:city":"Riverton",
    "sg:classifiers":[
        {
            "category":"Real Estate",
            "subcategory":"Real Estate Agent",
            "type":"Services"
        }
    ],
    "sg:phone":"+1 307 856 4071",
    "sg:postcode":"82501",
    "sg:province":"WY",
    "wof:name":"21st Century Comm",
    "wof:placetype":"venue"
},
  "geometry": {"coordinates":[-108.444959,43.025435],"type":"Point"}
}