{
  "type": "Feature",
  "properties": {
    "iso:country":"US",
    "sg:address":"818 S Federal Blvd",
    "sg:city":"Riverton",
    "sg:classifiers":[
        {
            "category":"Government",
            "subcategory":"Police Station",
            "type":"Public Place"
        }
    ],
    "sg:phone":"+1 307 856 7200",
    "sg:postcode":"82501",
    "sg:province":"WY",
    "sg:tags":[
        "sheriff"
    ],
    "wof:name":"County Sheriff",
    "wof:placetype":"venue"
},
  "geometry": {"coordinates":[-108.38064900000001,43.017714],"type":"Point"}
}