{
  "type": "Feature",
  "properties": {
    "addr:full":"10 Aztec Rd Cody WY 82414",
    "addr:housenumber":"10",
    "addr:postcode":"82414",
    "addr:street":"Aztec Rd",
    "iso:country":"US",
    "sg:address":"10 Aztec Rd",
    "sg:city":"Cody",
    "sg:classifiers":[
        {
            "category":"Retail",
            "subcategory":"Repair Shop",
            "type":"Services"
        }
    ],
    "sg:phone":"+1 307 527 7887",
    "sg:postcode":"82414",
    "sg:province":"WY",
    "sg:tags":[
        "equipment",
        "establishment"
    ],
    "wof:name":"Free Flight Taxidermy",
    "wof:placetype":"venue"
},
  "geometry": {"coordinates":[-109.119775,44.474897],"type":"Point"}
}