{
  "type": "Feature",
  "properties": {
    "iso:country":"US",
    "sg:address":"216 E Ivinson Ave",
    "sg:city":"Laramie",
    "sg:classifiers":[
        {
            "category":"Insurance",
            "subcategory":"Insurance Agent",
            "type":"Services"
        }
    ],
    "sg:phone":"+1 307 742 2244",
    "sg:postcode":"82070",
    "sg:province":"WY",
    "sg:website":"www.primerica.com",
    "wof:name":"Primerica Financial Svc",
    "wof:placetype":"venue"
},
  "geometry": {"coordinates":[-105.59464800000001,41.311971],"type":"Point"}
}