{
  "type": "Feature",
  "properties": {
    "iso:country":"US",
    "sg:address":"409 E Lakeway Rd",
    "sg:city":"Gillette",
    "sg:classifiers":[
        {
            "category":"Bars & Pubs",
            "type":"Food & Drink"
        }
    ],
    "sg:phone":"+1 307 682 8100",
    "sg:postcode":"82718",
    "sg:province":"WY",
    "wof:name":"Lakeside Liquor & Lounge",
    "wof:placetype":"venue"
},
  "geometry": {"coordinates":[-105.49925500000001,44.269138],"type":"Point"}
}