{
  "type": "Feature",
  "properties": {
    "iso:country":"US",
    "sg:address":"1969 S Sheridan Ave",
    "sg:city":"Sheridan",
    "sg:classifiers":[
        {
            "category":"Government",
            "subcategory":"Office",
            "type":"Public Place"
        }
    ],
    "sg:phone":"+1 307 674 2600",
    "sg:postcode":"82801",
    "sg:province":"WY",
    "wof:name":"Tongue District Ranger",
    "wof:placetype":"venue"
},
  "geometry": {"coordinates":[-106.947796,44.775794],"type":"Point"}
}