{
  "type": "Feature",
  "properties": {
    "iso:country":"US",
    "sg:address":"232 E Grinnell St",
    "sg:city":"Sheridan",
    "sg:classifiers":[
        {
            "category":"Wholesale",
            "subcategory":"Metals & Minerals",
            "type":"Manufacturing & Wholesale Goods"
        }
    ],
    "sg:phone":"+1 307 674 4401",
    "sg:postcode":"82801",
    "sg:province":"WY",
    "sg:tags":[
        "pipe"
    ],
    "wof:name":"Sheridan Winnelson Co",
    "wof:placetype":"venue"
},
  "geometry": {"coordinates":[-106.95285199999999,44.799475],"type":"Point"}
}