{
  "type": "Feature",
  "properties": {
    "iso:country":"US",
    "sg:address":"510 Two Valley Rd",
    "sg:city":"Shoshoni",
    "sg:classifiers":[
        {
            "category":"Farming",
            "subcategory":"Farm & Veterinary Services",
            "type":"Manufacturing & Wholesale Goods"
        }
    ],
    "sg:phone":"+1 307 856 0539",
    "sg:postcode":"82649",
    "sg:province":"WY",
    "wof:name":"Bar Med Inc",
    "wof:placetype":"venue"
},
  "geometry": {"coordinates":[-108.361425,43.172212],"type":"Point"}
}