{
  "type": "Feature",
  "properties": {
    "iso:country":"US",
    "sg:address":"673 S Carlin St",
    "sg:city":"Sheridan",
    "sg:classifiers":[
        {
            "category":"Building & Trades",
            "subcategory":"Construction",
            "type":"Services"
        }
    ],
    "sg:phone":"+1 307 672 0595",
    "sg:postcode":"82801",
    "sg:province":"WY",
    "sg:tags":[
        "contractor",
        "co",
        "hanging"
    ],
    "wof:name":"Big Horn Drywall & Paint",
    "wof:placetype":"venue"
},
  "geometry": {"coordinates":[-106.94516299999999,44.790904],"type":"Point"}
}