{
  "type": "Feature",
  "properties": {
    "iso:country":"US",
    "sg:address":"75 S Glenwood St",
    "sg:city":"Jackson",
    "sg:classifiers":[
        {
            "category":"Restaurant",
            "type":"Food & Drink"
        }
    ],
    "sg:phone":"+1 307 734 5407",
    "sg:postcode":"83001",
    "sg:province":"WY",
    "wof:name":"Taqueria Sanchez",
    "wof:placetype":"venue"
},
  "geometry": {"coordinates":[-110.763792,43.47875],"type":"Point"}
}