{
  "type": "Feature",
  "properties": {
    "addr:full":"793 Bunny Dr Worland WY 82401",
    "addr:housenumber":"793",
    "addr:postcode":"82401",
    "addr:street":"Bunny Dr",
    "iso:country":"US",
    "sg:address":"793 Bunny Dr",
    "sg:city":"Worland",
    "sg:classifiers":[
        {
            "category":"Building & Trades",
            "subcategory":"Plumbing",
            "type":"Services"
        }
    ],
    "sg:phone":"+1 307 568 2509",
    "sg:postcode":"82401",
    "sg:province":"WY",
    "sg:tags":[
        "contractor"
    ],
    "wof:name":"Riverbend Enterprises Inc",
    "wof:placetype":"venue"
},
  "geometry": {"coordinates":[-107.95988800000001,44.066187],"type":"Point"}
}