{
  "type": "Feature",
  "properties": {
    "iso:country":"US",
    "sg:address":"1413 5th Ave",
    "sg:city":"Belle Fourche",
    "sg:classifiers":[
        {
            "category":"Autos & Motor Vehicles",
            "subcategory":"Auto Supplies",
            "type":"Retail Goods"
        }
    ],
    "sg:phone":"+1 605 892 2658",
    "sg:postcode":"57717",
    "sg:province":"WY",
    "sg:tags":[
        "automobile",
        "parts"
    ],
    "sg:website":"www.sturdevants.com",
    "wof:name":"Sturdevant's Pronto Auto Parts",
    "wof:placetype":"venue"
},
  "geometry": {"coordinates":[-103.85432900000001,44.662479],"type":"Point"}
}