{
  "type": "Feature",
  "properties": {
    "iso:country":"US",
    "sg:address":"6750 W Zero Rd",
    "sg:city":"Casper",
    "sg:classifiers":[
        {
            "category":"Wholesale",
            "subcategory":"Machinery & Supplies",
            "type":"Manufacturing & Wholesale Goods"
        }
    ],
    "sg:phone":"+1 307 265 4610",
    "sg:postcode":"82604",
    "sg:province":"WY",
    "sg:tags":[
        "sandblasting"
    ],
    "wof:name":"Abrasive Sales",
    "wof:placetype":"venue"
},
  "geometry": {"coordinates":[-106.42938599999999,42.863174],"type":"Point"}
}