{
  "type": "Feature",
  "properties": {
    "iso:country":"US",
    "sg:address":"940 S Center St",
    "sg:city":"Casper",
    "sg:classifiers":[
        {
            "category":"Professional",
            "subcategory":"Research",
            "type":"Services"
        }
    ],
    "sg:phone":"+1 307 577 7442",
    "sg:postcode":"82601",
    "sg:province":"WY",
    "sg:tags":[
        "archaeologist"
    ],
    "wof:name":"North Platte Archaeological",
    "wof:placetype":"venue"
},
  "geometry": {"coordinates":[-106.325228,42.840995],"type":"Point"}
}