{
  "type": "Feature",
  "properties": {
    "iso:country":"US",
    "sg:address":"1140 N 8th St",
    "sg:city":"Greybull",
    "sg:classifiers":[
        {
            "category":"Shopping",
            "subcategory":"Bicycles & Sporting Goods",
            "type":"Retail Goods"
        }
    ],
    "sg:phone":"+1 307 765 9315",
    "sg:postcode":"82426",
    "sg:province":"WY",
    "wof:name":"Martins Sporting Goods",
    "wof:placetype":"venue"
},
  "geometry": {"coordinates":[-108.0582,44.500921],"type":"Point"}
}