{
  "type": "Feature",
  "properties": {
    "iso:country":"US",
    "sg:address":"121 W Carlson St",
    "sg:city":"Cheyenne",
    "sg:classifiers":[
        {
            "category":"Health Services",
            "subcategory":"Doctor",
            "type":"Services"
        }
    ],
    "sg:phone":"+1 307 635 1197",
    "sg:postcode":"82009",
    "sg:province":"WY",
    "sg:tags":[
        "dentist"
    ],
    "wof:name":"Westgate Dental Clinic",
    "wof:placetype":"venue"
},
  "geometry": {"coordinates":[-104.830152,41.171218],"type":"Point"}
}