{
  "type": "Feature",
  "properties": {
    "addr:full":"1949 Sugarland Dr Sheridan WY 82801",
    "addr:housenumber":"1949",
    "addr:postcode":"82801",
    "addr:street":"Sugarland Dr",
    "iso:country":"US",
    "sg:address":"1949 Sugarland Dr",
    "sg:city":"Sheridan",
    "sg:classifiers":[
        {
            "category":"Farming",
            "subcategory":"Livestock Farm",
            "type":"Manufacturing & Wholesale Goods"
        }
    ],
    "sg:phone":"+1 307 672 5663",
    "sg:postcode":"82801",
    "sg:province":"WY",
    "sg:tags":[
        "ranch"
    ],
    "sg:website":"www.poloranch.com",
    "wof:name":"Polo Ranch",
    "wof:placetype":"venue"
},
  "geometry": {"coordinates":[-106.93949000000001,44.777426],"type":"Point"}
}