{
  "type": "Feature",
  "properties": {
    "iso:country":"US",
    "sg:address":"731 E 5th St",
    "sg:city":"Casper",
    "sg:classifiers":[
        {
            "category":"Mining & Drilling",
            "type":"Manufacturing & Wholesale Goods"
        }
    ],
    "sg:phone":"+1 307 265 3488",
    "sg:postcode":"82601",
    "sg:province":"WY",
    "sg:tags":[
        "well"
    ],
    "wof:name":"Trenchless Engineering LLC",
    "wof:placetype":"venue"
},
  "geometry": {"coordinates":[-106.316408,42.845599],"type":"Point"}
}