{
  "type": "Feature",
  "properties": {
    "iso:country":"US",
    "sg:address":"340 W B St",
    "sg:city":"Casper",
    "sg:classifiers":[
        {
            "category":"Professional",
            "type":"Services"
        }
    ],
    "sg:phone":"+1 307 577 9538",
    "sg:postcode":"82601",
    "sg:province":"WY",
    "wof:name":"Blackstone and Associates",
    "wof:placetype":"venue"
},
  "geometry": {"coordinates":[-106.32926399999999,42.852026],"type":"Point"}
}