{
  "type": "Feature",
  "properties": {
    "addr:full":"300 W Main St Lander WY 82520",
    "addr:housenumber":"300",
    "addr:postcode":"wy 82520",
    "addr:street":"W Main St",
    "iso:country":"US",
    "sg:address":"300 W Main St",
    "sg:city":"Lander",
    "sg:classifiers":[
        {
            "category":"Shopping",
            "subcategory":"Books",
            "type":"Retail Goods"
        }
    ],
    "sg:phone":"+1 307 332 7661",
    "sg:postcode":"82520",
    "sg:province":"WY",
    "sg:tags":[
        "dealer"
    ],
    "sg:website":"www.mainstreetbooks.com",
    "wof:name":"Main Street Books",
    "wof:placetype":"venue"
},
  "geometry": {"coordinates":[-108.74481400000001,42.838976],"type":"Point"}
}