{
  "type": "Feature",
  "properties": {
    "iso:country":"US",
    "sg:address":"207 E Fremont St",
    "sg:city":"Laramie",
    "sg:classifiers":[
        {
            "category":"Wholesale",
            "subcategory":"Auto Parts",
            "type":"Manufacturing & Wholesale Goods"
        }
    ],
    "sg:phone":"+1 307 745 8926",
    "sg:postcode":"82072",
    "sg:province":"WY",
    "wof:name":"Carquest Auto Parts",
    "wof:placetype":"venue"
},
  "geometry": {"coordinates":[-105.594554,41.314007],"type":"Point"}
}