{
  "type": "Feature",
  "properties": {
    "iso:country":"US",
    "sg:address":"214 E Ord St",
    "sg:city":"Laramie",
    "sg:classifiers":[
        {
            "category":"Food & Beverages",
            "subcategory":"Specialty",
            "type":"Retail Goods"
        }
    ],
    "sg:phone":"+1 307 742 0404",
    "sg:postcode":"82070",
    "sg:province":"WY",
    "sg:tags":[
        "herb",
        "product",
        "health",
        "diet",
        "mfg"
    ],
    "wof:name":"Herb House The",
    "wof:placetype":"venue"
},
  "geometry": {"coordinates":[-105.595502,41.304427],"type":"Point"}
}