{
  "type": "Feature",
  "properties": {
    "iso:country":"US",
    "sg:address":"1401 9th St",
    "sg:city":"Wheatland",
    "sg:classifiers":[
        {
            "category":"Organizations",
            "subcategory":"Labor Organization",
            "type":"Services"
        }
    ],
    "sg:phone":"+1 307 322 5534",
    "sg:postcode":"82201",
    "sg:province":"WY",
    "wof:name":"IBEW",
    "wof:placetype":"venue"
},
  "geometry": {"coordinates":[-104.95329,42.06128],"type":"Point"}
}