{
  "type": "Feature",
  "properties": {
    "addr:full":"2220 Cedar Ln Cody WY 82414",
    "addr:housenumber":"2220",
    "addr:postcode":"82414",
    "addr:street":"Cedar Ln",
    "iso:country":"US",
    "sg:address":"2220 Cedar Ln",
    "sg:city":"Cody",
    "sg:classifiers":[
        {
            "category":"Real Estate",
            "subcategory":"Real Estate Agent",
            "type":"Services"
        }
    ],
    "sg:phone":"+1 307 587 2625",
    "sg:postcode":"82414",
    "sg:province":"WY",
    "wof:name":"Springari Real Estate",
    "wof:placetype":"venue"
},
  "geometry": {"coordinates":[-109.061921,44.51446],"type":"Point"}
}