{
  "type": "Feature",
  "properties": {
    "iso:country":"US",
    "sg:address":"7131 Sharrock Rd",
    "sg:city":"Casper",
    "sg:classifiers":[
        {
            "category":"Wholesale",
            "subcategory":"Electrical",
            "type":"Manufacturing & Wholesale Goods"
        }
    ],
    "sg:phone":"+1 307 266 3424",
    "sg:postcode":"82604",
    "sg:province":"WY",
    "sg:tags":[
        "control"
    ],
    "wof:name":"Cowboy Electric Inc",
    "wof:placetype":"venue"
},
  "geometry": {"coordinates":[-106.433423,42.804292],"type":"Point"}
}