{
  "type": "Feature",
  "properties": {
    "addr:full":"727 Laramie St Douglas WY 82633",
    "addr:housenumber":"727",
    "addr:postcode":"82633",
    "addr:street":"Laramie St Douglas Wy",
    "iso:country":"US",
    "sg:address":"727 Laramie St",
    "sg:city":"Douglas",
    "sg:classifiers":[
        {
            "category":"Organizations",
            "subcategory":"Religious Organization",
            "type":"Services"
        }
    ],
    "sg:phone":"+1 307 358 6472",
    "sg:postcode":"82633",
    "sg:province":"WY",
    "sg:tags":[
        "church"
    ],
    "wof:name":"Jehovah's Witnesses",
    "wof:placetype":"venue"
},
  "geometry": {"coordinates":[-105.37858,42.744554],"type":"Point"}
}