{
  "type": "Feature",
  "properties": {
    "addr:full":"301 E 16th St Cheyenne WY 82001",
    "addr:housenumber":"301",
    "addr:postcode":"82001",
    "addr:street":"E 16Th St",
    "iso:country":"US",
    "sg:address":"301 E 16th St",
    "sg:city":"Cheyenne",
    "sg:classifiers":[
        {
            "category":"Bars & Pubs",
            "type":"Food & Drink"
        }
    ],
    "sg:phone":"+1 307 634 4141",
    "sg:postcode":"82001",
    "sg:province":"WY",
    "sg:tags":[
        "drinking",
        "beverage",
        "alcoholic"
    ],
    "wof:name":"Green Door Drive-In Liquors",
    "wof:placetype":"venue"
},
  "geometry": {"coordinates":[-104.81081,41.134434],"type":"Point"}
}