{
  "type": "Feature",
  "properties": {
    "iso:country":"US",
    "sg:address":"114 US Hwy 14",
    "sg:city":"Gillette",
    "sg:classifiers":[
        {
            "category":"Bars & Pubs",
            "type":"Food & Drink"
        }
    ],
    "sg:phone":"+1 307 682 7545",
    "sg:postcode":"82716",
    "sg:province":"WY",
    "sg:tags":[
        "drinking"
    ],
    "wof:name":"Fireside Bar & Lounge",
    "wof:placetype":"venue"
},
  "geometry": {"coordinates":[-105.503855,44.293115],"type":"Point"}
}