{
  "type": "Feature",
  "properties": {
    "addr:full":"5351 S Winland Dr Gillette WY 82718",
    "addr:housenumber":"5351",
    "addr:postcode":"82718",
    "addr:street":"S Winland Dr",
    "iso:country":"US",
    "sg:address":"5351 S Winland Dr",
    "sg:city":"Gillette",
    "sg:classifiers":[
        {
            "category":"Retail",
            "subcategory":"Repair Shop",
            "type":"Services"
        }
    ],
    "sg:phone":"+1 307 682 5724",
    "sg:postcode":"82718",
    "sg:province":"WY",
    "sg:tags":[
        "crane"
    ],
    "wof:name":"Rocky Mountain Hoist Svc",
    "wof:placetype":"venue"
},
  "geometry": {"coordinates":[-105.476269,44.244115],"type":"Point"}
}