{
  "type": "Feature",
  "properties": {
    "iso:country":"US",
    "sg:address":"340 W Dow St",
    "sg:city":"Sheridan",
    "sg:classifiers":[
        {
            "category":"Health Services",
            "subcategory":"Doctor",
            "type":"Services"
        }
    ],
    "sg:phone":"+1 307 674 7469",
    "sg:postcode":"82801",
    "sg:province":"WY",
    "sg:tags":[
        "physician",
        "surgeon"
    ],
    "wof:name":"Sheridan Orthopaedic Assoc",
    "wof:placetype":"venue"
},
  "geometry": {"coordinates":[-106.959767,44.802452],"type":"Point"}
}