{
  "type": "Feature",
  "properties": {
    "addr:full":"55 Woodland Park Rd Sheridan WY 82801",
    "addr:housenumber":"55",
    "addr:postcode":"82801",
    "addr:street":"Woodland Park Rd",
    "iso:country":"US",
    "sg:address":"55 Woodland Park Rd",
    "sg:city":"Sheridan",
    "sg:classifiers":[
        {
            "category":"Building & Trades",
            "subcategory":"Construction",
            "type":"Services"
        }
    ],
    "sg:phone":"+1 307 752 4749",
    "sg:postcode":"82801",
    "sg:province":"WY",
    "sg:tags":[
        "contractor"
    ],
    "wof:name":"Competition Drywall LLC",
    "wof:placetype":"venue"
},
  "geometry": {"coordinates":[-106.95762999999999,44.74791],"type":"Point"}
}