{
  "type": "Feature",
  "properties": {
    "addr:full":"701 E 1st St Cheyenne WY 82007",
    "addr:housenumber":"701",
    "addr:postcode":"82007",
    "addr:street":"E 1St St",
    "iso:country":"US",
    "sg:address":"701 E 1st St",
    "sg:city":"Cheyenne",
    "sg:classifiers":[
        {
            "category":"Retail",
            "subcategory":"Auto Repair",
            "type":"Services"
        }
    ],
    "sg:phone":"+1 307 635 4221",
    "sg:postcode":"82007",
    "sg:province":"WY",
    "sg:tags":[
        "truck"
    ],
    "wof:name":"Lariat International Trucks",
    "wof:placetype":"venue"
},
  "geometry": {"coordinates":[-104.797659,41.122766],"type":"Point"}
}