{
  "type": "Feature",
  "properties": {
    "iso:country":"US",
    "sg:address":"1297 Ln 12",
    "sg:city":"Lovell",
    "sg:classifiers":[
        {
            "category":"Social Services",
            "type":"Services"
        }
    ],
    "sg:phone":"+1 307 772 5967",
    "sg:postcode":"82431",
    "sg:province":"WY",
    "sg:tags":[
        "to",
        "support",
        "family",
        "military"
    ],
    "wof:name":"Wyoming Family Support",
    "wof:placetype":"venue"
},
  "geometry": {"coordinates":[-108.36308,44.825837],"type":"Point"}
}