{
  "type": "Feature",
  "properties": {
    "iso:country":"US",
    "sg:address":"204 Goes in Lodge Rd",
    "sg:city":"Riverton",
    "sg:classifiers":[
        {
            "category":"Wholesale",
            "subcategory":"Meat",
            "type":"Manufacturing & Wholesale Goods"
        }
    ],
    "sg:phone":"+1 307 856 1210",
    "sg:postcode":"82501",
    "sg:province":"WY",
    "sg:tags":[
        "plant",
        "packing"
    ],
    "wof:name":"A-Z Processing",
    "wof:placetype":"venue"
},
  "geometry": {"coordinates":[-108.401455,43.001447],"type":"Point"}
}