{
  "type": "Feature",
  "properties": {
    "iso:country":"US",
    "sg:address":"1005 D St",
    "sg:city":"Rock Springs",
    "sg:classifiers":[
        {
            "category":"Professional",
            "type":"Services"
        }
    ],
    "sg:phone":"+1 307 382 8882",
    "sg:postcode":"82901",
    "sg:province":"WY",
    "sg:tags":[
        "establishment"
    ],
    "wof:name":"Questar Pipeline Co",
    "wof:placetype":"venue"
},
  "geometry": {"coordinates":[-109.210857,41.581666],"type":"Point"}
}