{
  "type": "Feature",
  "properties": {
    "addr:full":"815 Brandner Cir Green River WY 82935",
    "addr:housenumber":"815",
    "addr:postcode":"82935",
    "addr:street":"Brandner Cir Green River Wy",
    "iso:country":"US",
    "sg:address":"815 Brandner Cir",
    "sg:city":"Green River",
    "sg:classifiers":[
        {
            "category":"Building & Trades",
            "subcategory":"Construction",
            "type":"Services"
        }
    ],
    "sg:phone":"+1 307 875 7582",
    "sg:postcode":"82935",
    "sg:province":"WY",
    "sg:tags":[
        "dry wall",
        "contractor"
    ],
    "wof:name":"Intermountain Drywall Inc",
    "wof:placetype":"venue"
},
  "geometry": {"coordinates":[-109.48131600000001,41.519018],"type":"Point"}
}