{
  "type": "Feature",
  "properties": {
    "iso:country":"US",
    "sg:address":"73 Uinta Dr",
    "sg:city":"Green River",
    "sg:classifiers":[
        {
            "category":"Autos & Motor Vehicles",
            "subcategory":"Auto Supplies",
            "type":"Retail Goods"
        }
    ],
    "sg:phone":"+1 307 875 5253",
    "sg:postcode":"82935",
    "sg:province":"WY",
    "sg:tags":[
        "tire"
    ],
    "wof:name":"Zumbrennen Tire Svc Inc",
    "wof:placetype":"venue"
},
  "geometry": {"coordinates":[-109.465154,41.519742],"type":"Point"}
}