{
  "type": "Feature",
  "properties": {
    "iso:country":"US",
    "sg:address":"429 Broadway St",
    "sg:city":"Thermopolis",
    "sg:classifiers":[
        {
            "category":"Insurance",
            "subcategory":"Insurance Agent",
            "type":"Services"
        }
    ],
    "sg:phone":"+1 307 864 3878",
    "sg:postcode":"82443",
    "sg:province":"WY",
    "wof:name":"Farm Bureau Insurance",
    "wof:placetype":"venue"
},
  "geometry": {"coordinates":[-108.209765,43.645919],"type":"Point"}
}