{
  "type": "Feature",
  "properties": {
    "addr:full":"340 Spruce St Medicine Bow WY 82329",
    "addr:housenumber":"340",
    "addr:postcode":"82329",
    "addr:street":"Spruce St Medicine Bow Wy",
    "iso:country":"US",
    "sg:address":"340 Spruce St",
    "sg:city":"Medicine Bow",
    "sg:classifiers":[
        {
            "category":"Education",
            "subcategory":"School",
            "type":"Public Place"
        }
    ],
    "sg:phone":"+1 307 379 2345",
    "sg:postcode":"82329",
    "sg:province":"WY",
    "wof:name":"Medicine Bow School",
    "wof:placetype":"venue"
},
  "geometry": {"coordinates":[-106.201864,41.900297],"type":"Point"}
}