{
  "type": "Feature",
  "properties": {
    "iso:country":"US",
    "sg:address":"3345 Stirrup St",
    "sg:city":"Newcastle",
    "sg:classifiers":[
        {
            "category":"Organizations",
            "subcategory":"Religious Organization",
            "type":"Services"
        }
    ],
    "sg:phone":"+1 307 746 4932",
    "sg:postcode":"82701",
    "sg:province":"WY",
    "wof:name":"Faith Bahai",
    "wof:placetype":"venue"
},
  "geometry": {"coordinates":[-104.248791,43.844796],"type":"Point"}
}