{
  "type": "Feature",
  "properties": {
    "addr:full":"2515 Foothill Blvd Rock Springs WY 82901",
    "addr:housenumber":"2515",
    "addr:postcode":"82901",
    "addr:street":"Foothill Blvd;Springs Wy",
    "iso:country":"US",
    "sg:address":"2515 Foothill Blvd",
    "sg:city":"Rock Springs",
    "sg:classifiers":[
        {
            "category":"Utilities",
            "subcategory":"Natural Gas",
            "type":"Services"
        }
    ],
    "sg:phone":"+1 307 352 6009",
    "sg:postcode":"82901",
    "sg:province":"WY",
    "sg:tags":[
        "pipeline",
        "transportation"
    ],
    "wof:name":"Overland Trail Transm Co LP",
    "wof:placetype":"venue"
},
  "geometry": {"coordinates":[-109.25950899999999,41.581662],"type":"Point"}
}