{
  "type": "Feature",
  "properties": {
    "addr:full":"536 S Center St Casper WY 82601",
    "addr:housenumber":"536",
    "addr:postcode":"82601",
    "addr:street":"S Center St",
    "iso:country":"US",
    "sg:address":"536 S Center St",
    "sg:city":"Casper",
    "sg:classifiers":[
        {
            "category":"Professional",
            "subcategory":"Lawyer & Legal Services",
            "type":"Services"
        }
    ],
    "sg:phone":"+1 307 265 2003",
    "sg:postcode":"82601",
    "sg:province":"WY",
    "sg:tags":[
        "attorney"
    ],
    "wof:name":"Sean Benham",
    "wof:placetype":"venue"
},
  "geometry": {"coordinates":[-106.325255,42.844996],"type":"Point"}
}