{
  "type": "Feature",
  "properties": {
    "addr:full":"565 Ln 9 Powell WY 82435",
    "addr:housenumber":"9",
    "addr:postcode":"82435",
    "addr:street":"565 Ln;Powell Wy",
    "iso:country":"US",
    "sg:address":"565 Ln 9",
    "sg:city":"Powell",
    "sg:classifiers":[
        {
            "category":"Building & Trades",
            "subcategory":"Construction",
            "type":"Services"
        }
    ],
    "sg:phone":"+1 307 754 3910",
    "sg:postcode":"82435",
    "sg:province":"WY",
    "sg:tags":[
        "pipe",
        "line",
        "contractor"
    ],
    "wof:name":"Brandon Construction Inc",
    "wof:placetype":"venue"
},
  "geometry": {"coordinates":[-108.694912,44.753736],"type":"Point"}
}