{
  "type": "Feature",
  "properties": {
    "iso:country":"US",
    "sg:address":"320 Monroe Ave",
    "sg:city":"Green River",
    "sg:classifiers":[
        {
            "category":"Education",
            "subcategory":"School",
            "type":"Public Place"
        }
    ],
    "sg:phone":"+1 307 872 5570",
    "sg:postcode":"82935",
    "sg:province":"WY",
    "wof:name":"Roosevelt Elementary School",
    "wof:placetype":"venue"
},
  "geometry": {"coordinates":[-109.465829,41.510748],"type":"Point"}
}