{
  "type": "Feature",
  "properties": {
    "iso:country":"US",
    "sg:address":"446 N Lowell St",
    "sg:city":"Casper",
    "sg:classifiers":[
        {
            "category":"Real Estate",
            "subcategory":"Real Estate Operator",
            "type":"Services"
        }
    ],
    "sg:phone":"+1 307 234 7059",
    "sg:postcode":"82601",
    "sg:province":"WY",
    "sg:tags":[
        "building",
        "apartment"
    ],
    "wof:name":"Alibi Apts",
    "wof:placetype":"venue"
},
  "geometry": {"coordinates":[-106.300955,42.855175],"type":"Point"}
}