{
  "type": "Feature",
  "properties": {
    "addr:full":"30 Sacajawea Ave Lander WY 82520",
    "addr:housenumber":"30",
    "addr:postcode":"wy 82520",
    "addr:street":"Sacajawea Ave",
    "iso:country":"US",
    "sg:address":"30 Sacajawea Ave",
    "sg:city":"Lander",
    "sg:classifiers":[
        {
            "category":"Building & Trades",
            "subcategory":"Construction",
            "type":"Services"
        }
    ],
    "sg:phone":"+1 307 332 7229",
    "sg:postcode":"82520",
    "sg:province":"WY",
    "sg:tags":[
        "general",
        "contractor"
    ],
    "wof:name":"D E Foss Co Inc",
    "wof:placetype":"venue"
},
  "geometry": {"coordinates":[-108.800528,42.810627],"type":"Point"}
}