{
  "type": "Feature",
  "properties": {
    "iso:country":"US",
    "sg:address":"3430 E Riding Club Rd",
    "sg:city":"Cheyenne",
    "sg:classifiers":[
        {
            "category":"Building & Trades",
            "subcategory":"Construction",
            "type":"Services"
        }
    ],
    "sg:phone":"+1 307 634 4661",
    "sg:postcode":"82009",
    "sg:province":"WY",
    "sg:tags":[
        "floor",
        "laying",
        "contractor"
    ],
    "wof:name":"Flooring Installers",
    "wof:placetype":"venue"
},
  "geometry": {"coordinates":[-104.77055,41.203681],"type":"Point"}
}