{
  "type": "Feature",
  "properties": {
    "iso:country":"US",
    "sg:address":"114 N 2nd St",
    "sg:city":"Douglas",
    "sg:classifiers":[
        {
            "category":"Education",
            "subcategory":"Dance Studio",
            "type":"Public Place"
        }
    ],
    "sg:phone":"+1 307 358 5225",
    "sg:postcode":"82633",
    "sg:province":"WY",
    "sg:tags":[
        "instruction",
        "dancing"
    ],
    "wof:name":"Shatto School of Dance",
    "wof:placetype":"venue"
},
  "geometry": {"coordinates":[-105.385485,42.760831],"type":"Point"}
}