{
  "type": "Feature",
  "properties": {
    "iso:country":"US",
    "sg:address":"1707 W Hill Rd",
    "sg:city":"Laramie",
    "sg:classifiers":[
        {
            "category":"Building & Trades",
            "subcategory":"Plumbing",
            "type":"Services"
        }
    ],
    "sg:phone":"+1 307 745 7413",
    "sg:postcode":"82072",
    "sg:province":"WY",
    "sg:tags":[
        "contractor"
    ],
    "wof:name":"C K Service Plumbing & Heating",
    "wof:placetype":"venue"
},
  "geometry": {"coordinates":[-105.574241,41.327577],"type":"Point"}
}