{
  "type": "Feature",
  "properties": {
    "iso:country":"US",
    "sg:address":"625 Big Horn Ave",
    "sg:city":"Worland",
    "sg:classifiers":[
        {
            "category":"Bars & Pubs",
            "type":"Food & Drink"
        }
    ],
    "sg:phone":"+1 307 347 4541",
    "sg:postcode":"82401",
    "sg:province":"WY",
    "sg:tags":[
        "drinking"
    ],
    "wof:name":"Little Chicago",
    "wof:placetype":"venue"
},
  "geometry": {"coordinates":[-107.960972,44.016747],"type":"Point"}
}