{
  "type": "Feature",
  "properties": {
    "iso:country":"US",
    "sg:address":"6175 Heck of A Hill Rd",
    "sg:city":"Wilson",
    "sg:classifiers":[
        {
            "category":"Travel",
            "subcategory":"Hotels & Motels",
            "type":"Entertainment"
        }
    ],
    "sg:phone":"+1 307 733 3233",
    "sg:postcode":"83014",
    "sg:province":"WY",
    "wof:name":"Teton Treehouse B & B",
    "wof:placetype":"venue"
},
  "geometry": {"coordinates":[-110.883295,43.492038],"type":"Point"}
}