{
  "type": "Feature",
  "properties": {
    "iso:country":"US",
    "sg:address":"418 Pine St",
    "sg:city":"Pine Bluffs",
    "sg:classifiers":[
        {
            "category":"Organizations",
            "subcategory":"Religious Organization",
            "type":"Services"
        }
    ],
    "sg:phone":"+1 307 245 3534",
    "sg:postcode":"82082",
    "sg:province":"WY",
    "sg:tags":[
        "church"
    ],
    "wof:name":"Pine Bluffs Baptist Church",
    "wof:placetype":"venue"
},
  "geometry": {"coordinates":[-104.065405,41.179884],"type":"Point"}
}