{
  "type": "Feature",
  "properties": {
    "iso:country":"US",
    "sg:address":"250 Stockade Ct",
    "sg:city":"Powell",
    "sg:classifiers":[
        {
            "category":"Education",
            "subcategory":"School",
            "type":"Public Place"
        }
    ],
    "sg:phone":"+1 307 754 2047",
    "sg:postcode":"82435",
    "sg:province":"WY",
    "wof:name":"Powell Schools Foundation",
    "wof:placetype":"venue"
},
  "geometry": {"coordinates":[-108.77427900000001,44.75508],"type":"Point"}
}