{
  "type": "Feature",
  "properties": {
    "iso:country":"US",
    "sg:address":"6101 Yellowstone Rd",
    "sg:city":"Cheyenne",
    "sg:classifiers":[
        {
            "category":"Social Services",
            "type":"Services"
        }
    ],
    "sg:phone":"+1 307 638 8904",
    "sg:postcode":"82009",
    "sg:province":"WY",
    "sg:tags":[
        "organization",
        "welfare"
    ],
    "sg:website":"www.laramiecounitedway.org",
    "wof:name":"United Way",
    "wof:placetype":"venue"
},
  "geometry": {"coordinates":[-104.82857799999999,41.177344],"type":"Point"}
}