{
  "type": "Feature",
  "properties": {
    "iso:country":"US",
    "sg:address":"11017 Hwy 789",
    "sg:city":"Riverton",
    "sg:classifiers":[
        {
            "category":"Mining & Drilling",
            "type":"Manufacturing & Wholesale Goods"
        }
    ],
    "sg:phone":"+1 307 876 9421",
    "sg:postcode":"82501",
    "sg:province":"WY",
    "sg:tags":[
        "field",
        "oil"
    ],
    "wof:name":"Double D Enterprises",
    "wof:placetype":"venue"
},
  "geometry": {"coordinates":[-108.37709099999999,43.010003],"type":"Point"}
}