{
  "type": "Feature",
  "properties": {
    "addr:full":"81 Juniper Dr Lander WY 82520",
    "addr:housenumber":"81",
    "addr:postcode":"wy 82520",
    "addr:street":"Juniper Dr",
    "iso:country":"US",
    "sg:address":"81 Juniper Dr",
    "sg:city":"Lander",
    "sg:classifiers":[
        {
            "category":"Building & Trades",
            "subcategory":"Construction",
            "type":"Services"
        }
    ],
    "sg:phone":"+1 307 332 4607",
    "sg:postcode":"82520",
    "sg:province":"WY",
    "sg:tags":[
        "house"
    ],
    "wof:name":"Jacle Inc",
    "wof:placetype":"venue"
},
  "geometry": {"coordinates":[-108.81998400000001,42.822808],"type":"Point"}
}