{
  "type": "Feature",
  "properties": {
    "addr:full":"1317 Stonegate Dr Sheridan WY 82801",
    "addr:housenumber":"1317",
    "addr:postcode":"82801",
    "addr:street":"Stonegate Dr",
    "iso:country":"US",
    "sg:address":"1317 Stonegate Dr",
    "sg:city":"Sheridan",
    "sg:classifiers":[
        {
            "category":"Farming",
            "subcategory":"Livestock Farm",
            "type":"Manufacturing & Wholesale Goods"
        }
    ],
    "sg:phone":"+1 307 672 3695",
    "sg:postcode":"82801",
    "sg:province":"WY",
    "sg:tags":[
        "beef",
        "feedlot",
        "cattle"
    ],
    "wof:name":"Kane Land & Livestock Inc",
    "wof:placetype":"venue"
},
  "geometry": {"coordinates":[-106.974949,44.799326],"type":"Point"}
}