{
  "type": "Feature",
  "properties": {
    "addr:full":"4996 State Hwy 374 Green River WY 82935",
    "addr:housenumber":"4996",
    "addr:postcode":"82935",
    "addr:street":"State Hwy 374 Green River Wy",
    "iso:country":"US",
    "sg:address":"4996 State Hwy 374",
    "sg:city":"Green River",
    "sg:classifiers":[
        {
            "category":"Building & Trades",
            "subcategory":"Construction",
            "type":"Services"
        }
    ],
    "sg:phone":"+1 307 875 6555",
    "sg:postcode":"82935",
    "sg:province":"WY",
    "sg:tags":[
        "painter"
    ],
    "wof:name":"Mandros Painting Inc",
    "wof:placetype":"venue"
},
  "geometry": {"coordinates":[-109.52152,41.555942],"type":"Point"}
}