{
  "type": "Feature",
  "properties": {
    "iso:country":"US",
    "sg:address":"3504 US Hwy 16",
    "sg:city":"Gillette",
    "sg:classifiers":[
        {
            "category":"Autos & Motor Vehicles",
            "subcategory":"Fuel & Gas Station",
            "type":"Retail Goods"
        }
    ],
    "sg:phone":"+1 307 682 3238",
    "sg:postcode":"82716",
    "sg:province":"WY",
    "sg:tags":[
        "station",
        "gasoline"
    ],
    "wof:name":"Miles Towing and Recovery Inc",
    "wof:placetype":"venue"
},
  "geometry": {"coordinates":[-105.529393,44.329513],"type":"Point"}
}