{
  "type": "Feature",
  "properties": {
    "addr:full":"517 Broadway St Thermopolis WY 82443",
    "addr:housenumber":"517",
    "addr:postcode":"82443",
    "addr:street":"Broadway St Thermopolis Wy",
    "iso:country":"US",
    "sg:address":"517 Broadway St",
    "sg:city":"Thermopolis",
    "sg:classifiers":[
        {
            "category":"Professional",
            "type":"Services"
        }
    ],
    "sg:phone":"+1 307 864 4308",
    "sg:postcode":"82443",
    "sg:province":"WY",
    "sg:tags":[
        "establishment"
    ],
    "wof:name":"Cheetahadvance Technology",
    "wof:placetype":"venue"
},
  "geometry": {"coordinates":[-108.211693,43.645945],"type":"Point"}
}