{
  "type": "Feature",
  "properties": {
    "iso:country":"US",
    "sg:address":"519 Spy Glass Cir",
    "sg:city":"Riverton",
    "sg:classifiers":[
        {
            "category":"Banks & Credit Unions",
            "subcategory":"Investment Brokerage",
            "type":"Services"
        }
    ],
    "sg:phone":"+1 307 856 3576",
    "sg:postcode":"82501",
    "sg:province":"WY",
    "sg:tags":[
        "advisory"
    ],
    "wof:name":"McBratney Investments",
    "wof:placetype":"venue"
},
  "geometry": {"coordinates":[-108.444987,43.02177],"type":"Point"}
}