{
  "type": "Feature",
  "properties": {
    "iso:country":"US",
    "sg:address":"544 Park St",
    "sg:city":"Thermopolis",
    "sg:classifiers":[
        {
            "category":"Personal",
            "subcategory":"Beauty Salon",
            "type":"Services"
        }
    ],
    "sg:phone":"+1 307 864 3619",
    "sg:postcode":"82443",
    "sg:province":"WY",
    "sg:tags":[
        "shop"
    ],
    "wof:name":"Country Hairitage Salon",
    "wof:placetype":"venue"
},
  "geometry": {"coordinates":[-108.21075,43.650645],"type":"Point"}
}