{
  "type": "Feature",
  "properties": {
    "iso:country":"US",
    "sg:address":"410 E Grand Ave",
    "sg:city":"Laramie",
    "sg:classifiers":[
        {
            "category":"Building & Trades",
            "subcategory":"Construction",
            "type":"Services"
        }
    ],
    "sg:phone":"+1 307 742 5821",
    "sg:postcode":"82070",
    "sg:province":"WY",
    "sg:tags":[
        "well",
        "drilling"
    ],
    "wof:name":"National Water Surveying",
    "wof:placetype":"venue"
},
  "geometry": {"coordinates":[-105.59220500000001,41.31085],"type":"Point"}
}