{
  "type": "Feature",
  "properties": {
    "iso:country":"US",
    "sg:address":"1700 W 1st St",
    "sg:city":"Casper",
    "sg:classifiers":[
        {
            "category":"Wholesale",
            "subcategory":"Office Equipment",
            "type":"Manufacturing & Wholesale Goods"
        }
    ],
    "sg:phone":"+1 307 577 5656",
    "sg:postcode":"82604",
    "sg:province":"WY",
    "sg:tags":[
        "machine",
        "duplicating",
        "copying"
    ],
    "wof:name":"Express Business Systems",
    "wof:placetype":"venue"
},
  "geometry": {"coordinates":[-106.355228,42.845296],"type":"Point"}
}