{
  "type": "Feature",
  "properties": {
    "iso:country":"US",
    "sg:address":"235 N 19th St",
    "sg:city":"Worland",
    "sg:classifiers":[
        {
            "category":"Shopping",
            "subcategory":"Bicycles & Sporting Goods",
            "type":"Retail Goods"
        }
    ],
    "sg:phone":"+1 307 347 8894",
    "sg:postcode":"82401",
    "sg:province":"WY",
    "wof:name":"Red Oak Manufacturing",
    "wof:placetype":"venue"
},
  "geometry": {"coordinates":[-107.943434,44.018837],"type":"Point"}
}