{
  "type": "Feature",
  "properties": {
    "addr:full":"1501 Big Horn Ave Worland WY 82401",
    "addr:housenumber":"1501",
    "addr:postcode":"82401",
    "addr:street":"Big Horn Ave",
    "iso:country":"US",
    "sg:address":"1501 Big Horn Ave",
    "sg:city":"Worland",
    "sg:classifiers":[
        {
            "category":"Food & Beverages",
            "subcategory":"Groceries & Convenience Stores",
            "type":"Retail Goods"
        },
        {
            "category":"Autos & Motor Vehicles",
            "subcategory":"Fuel & Gas Station",
            "type":"Retail Goods"
        }
    ],
    "sg:phone":"+1 307 347 6135",
    "sg:postcode":"82401",
    "sg:province":"WY",
    "sg:tags":[
        "gasoline"
    ],
    "wof:name":"Maverik Country Stores 166",
    "wof:placetype":"venue"
},
  "geometry": {"coordinates":[-107.948397,44.01683],"type":"Point"}
}