{
  "type": "Feature",
  "properties": {
    "addr:full":"85 State Hwy 10 Jelm WY 82063",
    "addr:housenumber":"85",
    "addr:postcode":"82063",
    "addr:street":"State Hwy 10 Jelm Wy",
    "iso:country":"US",
    "sg:address":"85 State Hwy 10",
    "sg:city":"Jelm",
    "sg:classifiers":[
        {
            "category":"Retail",
            "subcategory":"Repair Shop",
            "type":"Services"
        }
    ],
    "sg:phone":"+1 307 755 0151",
    "sg:postcode":"82063",
    "sg:province":"WY",
    "wof:name":"Epi Service Co",
    "wof:placetype":"venue"
},
  "geometry": {"coordinates":[-106.01009000000001,41.103074],"type":"Point"}
}