{
  "type": "Feature",
  "properties": {
    "addr:full":"932 Kroe Ln Sheridan WY 82801",
    "addr:housenumber":"932",
    "addr:postcode":"82801",
    "addr:street":"Kroe Ln",
    "iso:country":"US",
    "sg:address":"932 Kroe Ln",
    "sg:city":"Sheridan",
    "sg:classifiers":[
        {
            "category":"Manufacturing",
            "subcategory":"Wood Products",
            "type":"Manufacturing & Wholesale Goods"
        },
        {
            "category":"Manufacturing",
            "subcategory":"Lumber",
            "type":"Manufacturing & Wholesale Goods"
        }
    ],
    "sg:phone":"+1 307 672 9797",
    "sg:postcode":"82801",
    "sg:province":"WY",
    "sg:tags":[
        "shaving",
        "pellet",
        "compressed",
        "mfg"
    ],
    "wof:name":"C N Z Wood Pellet Mfg",
    "wof:placetype":"venue"
},
  "geometry": {"coordinates":[-106.944289,44.799088],"type":"Point"}
}