{
  "type": "Feature",
  "properties": {
    "iso:country":"US",
    "sg:address":"166 Morgan Cir",
    "sg:city":"Evanston",
    "sg:classifiers":[
        {
            "category":"Professional",
            "subcategory":"Accounting & Tax Preparation",
            "type":"Services"
        }
    ],
    "sg:phone":"+1 307 789 8642",
    "sg:postcode":"82930",
    "sg:province":"WY",
    "sg:tags":[
        "return"
    ],
    "wof:name":"Wendys Tax Service",
    "wof:placetype":"venue"
},
  "geometry": {"coordinates":[-110.97218100000001,41.249784],"type":"Point"}
}