{
  "type": "Feature",
  "properties": {
    "iso:country":"US",
    "sg:address":"130 Boxelder Trl",
    "sg:city":"Glenrock",
    "sg:classifiers":[
        {
            "category":"Real Estate",
            "subcategory":"Real Estate Operator",
            "type":"Services"
        }
    ],
    "sg:phone":"+1 307 436 8401",
    "sg:postcode":"82637",
    "sg:province":"WY",
    "sg:tags":[
        "building",
        "apartment"
    ],
    "wof:name":"Trails Apartments",
    "wof:placetype":"venue"
},
  "geometry": {"coordinates":[-105.84752,42.8592],"type":"Point"}
}