{
  "type": "Feature",
  "properties": {
    "iso:country":"US",
    "sg:address":"34 Allegiance Cir",
    "sg:city":"Evanston",
    "sg:classifiers":[
        {
            "category":"Wholesale",
            "subcategory":"Machinery & Supplies",
            "type":"Manufacturing & Wholesale Goods"
        }
    ],
    "sg:phone":"+1 307 789 6235",
    "sg:postcode":"82930",
    "sg:province":"WY",
    "sg:tags":[
        "equipment",
        "industrial"
    ],
    "sg:website":"www.morcon-ind.com",
    "wof:name":"Morcon Industrial Specialty",
    "wof:placetype":"venue"
},
  "geometry": {"coordinates":[-110.991845,41.261745],"type":"Point"}
}