{
  "type": "Feature",
  "properties": {
    "addr:full":"2502 Mountain View Dr Cody WY 82414",
    "addr:housenumber":"2502",
    "addr:postcode":"82414",
    "addr:street":"Mountain View Dr",
    "iso:country":"US",
    "sg:address":"2502 Mountain View Dr",
    "sg:city":"Cody",
    "sg:classifiers":[
        {
            "category":"Shopping",
            "subcategory":"Used Merchandise",
            "type":"Retail Goods"
        }
    ],
    "sg:phone":"+1 307 527 7383",
    "sg:postcode":"82414",
    "sg:province":"WY",
    "wof:name":"Mountain View Antiques",
    "wof:placetype":"venue"
},
  "geometry": {"coordinates":[-109.044798,44.51508],"type":"Point"}
}