{
  "type": "Feature",
  "properties": {
    "iso:country":"US",
    "sg:address":"1101 W Lincolnway",
    "sg:city":"Cheyenne",
    "sg:classifiers":[
        {
            "category":"Food & Beverages",
            "subcategory":"Liquor & Beverages",
            "type":"Retail Goods"
        }
    ],
    "sg:phone":"+1 307 778 7678",
    "sg:postcode":"82001",
    "sg:province":"WY",
    "wof:name":"Eagle's Nest",
    "wof:placetype":"venue"
},
  "geometry": {"coordinates":[-104.826245,41.128659],"type":"Point"}
}