{
  "type": "Feature",
  "properties": {
    "addr:full":"325 Silver Springs Rd Lusk WY 82225",
    "addr:housenumber":"325",
    "addr:postcode":"82225",
    "addr:street":"Silver Springs Rd Lusk Wy",
    "iso:country":"US",
    "sg:address":"325 Silver Springs Rd",
    "sg:city":"Lusk",
    "sg:classifiers":[
        {
            "category":"Farming",
            "subcategory":"Farm & Veterinary Services",
            "type":"Manufacturing & Wholesale Goods"
        }
    ],
    "sg:phone":"+1 307 334 3432",
    "sg:postcode":"82225",
    "sg:province":"WY",
    "sg:tags":[
        "sheep",
        "shearing"
    ],
    "wof:name":"5r Ranch",
    "wof:placetype":"venue"
},
  "geometry": {"coordinates":[-104.49918,42.686303],"type":"Point"}
}