{
  "type": "Feature",
  "properties": {
    "iso:country":"US",
    "sg:address":"86 Peno Rd",
    "sg:city":"Sheridan",
    "sg:classifiers":[
        {
            "category":"Building & Trades",
            "subcategory":"Construction",
            "type":"Services"
        }
    ],
    "sg:phone":"+1 307 674 4737",
    "sg:postcode":"82801",
    "sg:province":"WY",
    "sg:tags":[
        "tile",
        "dealer"
    ],
    "wof:name":"Tile Accents Inc",
    "wof:placetype":"venue"
},
  "geometry": {"coordinates":[-106.903218,44.779914],"type":"Point"}
}