{
  "type": "Feature",
  "properties": {
    "iso:country":"US",
    "sg:address":"516 A St",
    "sg:city":"Rock Springs",
    "sg:classifiers":[
        {
            "category":"Building & Trades",
            "subcategory":"Construction",
            "type":"Services"
        }
    ],
    "sg:phone":"+1 307 362 3385",
    "sg:postcode":"82901",
    "sg:province":"WY",
    "sg:tags":[
        "excavating",
        "contractor"
    ],
    "wof:name":"Ama Hot Shot & Trenching",
    "wof:placetype":"venue"
},
  "geometry": {"coordinates":[-109.21884,41.581837],"type":"Point"}
}