{
  "type": "Feature",
  "properties": {
    "iso:country":"US",
    "sg:address":"5001 Chalk Bluff Rd",
    "sg:city":"Cheyenne",
    "sg:classifiers":[
        {
            "category":"Farming",
            "subcategory":"Farm",
            "type":"Manufacturing & Wholesale Goods"
        }
    ],
    "sg:phone":"+1 307 772 0383",
    "sg:postcode":"82007",
    "sg:province":"WY",
    "sg:tags":[
        "crop",
        "general"
    ],
    "wof:name":"Four R Bison Ranch",
    "wof:placetype":"venue"
},
  "geometry": {"coordinates":[-104.735602,41.044037],"type":"Point"}
}