{
  "type": "Feature",
  "properties": {
    "addr:full":"2007 S Mitchell St Casper WY 82601",
    "addr:housenumber":"2007",
    "addr:postcode":"82601",
    "addr:street":"S Mitchell St",
    "iso:country":"US",
    "sg:address":"2007 S Mitchell St",
    "sg:city":"Casper",
    "sg:classifiers":[
        {
            "category":"Building & Trades",
            "subcategory":"Plumbing",
            "type":"Services"
        }
    ],
    "sg:phone":"+1 307 234 8585",
    "sg:postcode":"82601",
    "sg:province":"WY",
    "sg:tags":[
        "contractor"
    ],
    "wof:name":"Park Sprinkler Systems",
    "wof:placetype":"venue"
},
  "geometry": {"coordinates":[-106.314656,42.828147],"type":"Point"}
}