{
  "type": "Feature",
  "properties": {
    "iso:country":"US",
    "sg:address":"112 S Gillette Ave",
    "sg:city":"Gillette",
    "sg:classifiers":[
        {
            "category":"Manufacturing",
            "subcategory":"Printing",
            "type":"Manufacturing & Wholesale Goods"
        }
    ],
    "sg:phone":"+1 307 682 1711",
    "sg:postcode":"82716",
    "sg:province":"WY",
    "sg:tags":[
        "lithographic",
        "commercial"
    ],
    "wof:name":"Zip Printing",
    "wof:placetype":"venue"
},
  "geometry": {"coordinates":[-105.504085,44.29398],"type":"Point"}
}