{
  "type": "Feature",
  "properties": {
    "addr:full":"1441 E M St Torrington WY 82240",
    "addr:housenumber":"1441",
    "addr:postcode":"82240",
    "addr:street":"E M St",
    "iso:country":"US",
    "sg:address":"1441 E M St",
    "sg:city":"Torrington",
    "sg:classifiers":[
        {
            "category":"Government",
            "subcategory":"Office",
            "type":"Public Place"
        }
    ],
    "sg:phone":"+1 307 532 4880",
    "sg:postcode":"82240",
    "sg:province":"WY",
    "sg:tags":[
        "farm",
        "agency"
    ],
    "wof:name":"Farm Service Agency",
    "wof:placetype":"venue"
},
  "geometry": {"coordinates":[-104.168114,42.057522],"type":"Point"}
}