{
  "type": "Feature",
  "properties": {
    "iso:country":"US",
    "sg:address":"144 Western Hills Blvd",
    "sg:city":"Cheyenne",
    "sg:classifiers":[
        {
            "category":"Arts & Performance",
            "subcategory":"Theater",
            "type":"Entertainment"
        }
    ],
    "sg:phone":"+1 307 635 8411",
    "sg:postcode":"82009",
    "sg:province":"WY",
    "sg:tags":[
        "live",
        "music"
    ],
    "wof:name":"Sound Connection",
    "wof:placetype":"venue"
},
  "geometry": {"coordinates":[-104.829712,41.174963],"type":"Point"}
}