{
  "type": "Feature",
  "properties": {
    "iso:country":"US",
    "sg:address":"5608 S Winland Dr",
    "sg:city":"Gillette",
    "sg:classifiers":[
        {
            "category":"Mining & Drilling",
            "type":"Manufacturing & Wholesale Goods"
        }
    ],
    "sg:phone":"+1 307 685 3030",
    "sg:postcode":"82718",
    "sg:province":"WY",
    "sg:tags":[
        "field",
        "oil"
    ],
    "wof:name":"T J's Anchor Svc",
    "wof:placetype":"venue"
},
  "geometry": {"coordinates":[-105.477752,44.245222],"type":"Point"}
}