{
  "type": "Feature",
  "properties": {
    "iso:country":"US",
    "sg:address":"109 W 14th St",
    "sg:city":"Powell",
    "sg:classifiers":[
        {
            "category":"Social Services",
            "type":"Services"
        }
    ],
    "sg:phone":"+1 307 754 0362",
    "sg:postcode":"82435",
    "sg:province":"WY",
    "wof:name":"Basin Authority",
    "wof:placetype":"venue"
},
  "geometry": {"coordinates":[-109.055921,44.537777],"type":"Point"}
}