{
  "type": "Feature",
  "properties": {
    "iso:country":"US",
    "sg:address":"113 S Cedar St",
    "sg:city":"Laramie",
    "sg:classifiers":[
        {
            "category":"Restaurant",
            "type":"Food & Drink"
        }
    ],
    "sg:phone":"+1 307 742 3908",
    "sg:postcode":"82072",
    "sg:province":"WY",
    "sg:tags":[
        "eating"
    ],
    "wof:name":"Tweet Treats",
    "wof:placetype":"venue"
},
  "geometry": {"coordinates":[-105.600633,41.313252],"type":"Point"}
}