{
  "type": "Feature",
  "properties": {
    "iso:country":"US",
    "sg:address":"230 Scrutchfield Ln",
    "sg:city":"Sheridan",
    "sg:classifiers":[
        {
            "category":"Freight",
            "type":"Transportation"
        }
    ],
    "sg:phone":"+1 307 674 4676",
    "sg:postcode":"82801",
    "sg:province":"WY",
    "sg:tags":[
        "commercial",
        "storage"
    ],
    "wof:name":"Crown Storage Inc",
    "wof:placetype":"venue"
},
  "geometry": {"coordinates":[-106.93368599999999,44.799408],"type":"Point"}
}