{
  "type": "Feature",
  "properties": {
    "iso:country":"US",
    "sg:address":"22 Wilson Ln",
    "sg:city":"Sheridan",
    "sg:classifiers":[
        {
            "category":"Professional",
            "subcategory":"Research",
            "type":"Services"
        }
    ],
    "sg:phone":"+1 307 672 3937",
    "sg:postcode":"82801",
    "sg:province":"WY",
    "sg:tags":[
        "environmental",
        "ecological"
    ],
    "wof:name":"Y Environmental",
    "wof:placetype":"venue"
},
  "geometry": {"coordinates":[-106.91862399999999,44.77249],"type":"Point"}
}