{
  "type": "Feature",
  "properties": {
    "iso:country":"US",
    "sg:address":"6416 Mountain Mist Ct",
    "sg:city":"Laramie",
    "sg:classifiers":[
        {
            "category":"Wholesale",
            "subcategory":"Machinery & Supplies",
            "type":"Manufacturing & Wholesale Goods"
        }
    ],
    "sg:phone":"+1 307 745 8358",
    "sg:postcode":"82070",
    "sg:province":"WY",
    "sg:tags":[
        "equipment"
    ],
    "wof:name":"Colling Inc",
    "wof:placetype":"venue"
},
  "geometry": {"coordinates":[-105.51625799999999,41.294495],"type":"Point"}
}