{
  "type": "Feature",
  "properties": {
    "addr:full":"312 N 8th St W Riverton WY 82501",
    "addr:housenumber":"312",
    "addr:postcode":"82501",
    "addr:street":"N 8Th St W",
    "iso:country":"US",
    "sg:address":"312 N 8th St W",
    "sg:city":"Riverton",
    "sg:classifiers":[
        {
            "category":"Health Services",
            "subcategory":"Doctor",
            "type":"Services"
        }
    ],
    "sg:phone":"+1 307 856 9789",
    "sg:postcode":"82501",
    "sg:province":"WY",
    "wof:name":"Harold A Macon DDS",
    "wof:placetype":"venue"
},
  "geometry": {"coordinates":[-108.40047300000001,43.027509],"type":"Point"}
}