{
  "type": "Feature",
  "properties": {
    "iso:country":"US",
    "sg:address":"616 Crook Ave",
    "sg:city":"Cheyenne",
    "sg:classifiers":[
        {
            "category":"Home & Garden",
            "subcategory":"Building Materials",
            "type":"Retail Goods"
        }
    ],
    "sg:phone":"+1 307 634 2011",
    "sg:postcode":"82001",
    "sg:province":"WY",
    "sg:tags":[
        "glass",
        "window",
        "plate"
    ],
    "wof:name":"Artistic Auto Glass",
    "wof:placetype":"venue"
},
  "geometry": {"coordinates":[-104.788737,41.132095],"type":"Point"}
}