{
  "type": "Feature",
  "properties": {
    "iso:country":"US",
    "sg:address":"3 Gros Ventre Dr",
    "sg:city":"Bondurant",
    "sg:classifiers":[
        {
            "category":"Building & Trades",
            "subcategory":"Construction",
            "type":"Services"
        }
    ],
    "sg:phone":"+1 307 859 8836",
    "sg:postcode":"82922",
    "sg:province":"WY",
    "sg:tags":[
        "water",
        "well",
        "drilling"
    ],
    "wof:name":"Pinedale Pump Svc",
    "wof:placetype":"venue"
},
  "geometry": {"coordinates":[-110.27351899999999,43.119609],"type":"Point"}
}