{
  "type": "Feature",
  "properties": {
    "iso:country":"US",
    "sg:address":"601 SE Wyoming Blvd",
    "sg:city":"Casper",
    "sg:classifiers":[
        {
            "category":"Restaurant",
            "type":"Food & Drink"
        }
    ],
    "sg:phone":"+1 307 235 8587",
    "sg:postcode":"82601",
    "sg:province":"WY",
    "sg:tags":[
        "concession"
    ],
    "wof:name":"Hdos Enterprises",
    "wof:placetype":"venue"
},
  "geometry": {"coordinates":[-106.26674,42.844139],"type":"Point"}
}