{
  "type": "Feature",
  "properties": {
    "addr:full":"1197 Vista Dr Thayne WY 83127",
    "addr:housenumber":"1197",
    "addr:postcode":"83127",
    "addr:street":"Vista Dr Thayne Wy",
    "iso:country":"US",
    "sg:address":"1197 Vista Dr",
    "sg:city":"Thayne",
    "sg:classifiers":[
        {
            "category":"Building & Trades",
            "subcategory":"Construction",
            "type":"Services"
        }
    ],
    "sg:phone":"+1 307 733 6486",
    "sg:postcode":"83127",
    "sg:province":"WY",
    "sg:tags":[
        "painter"
    ],
    "wof:name":"Pratt Painting & Paper Hanging",
    "wof:placetype":"venue"
},
  "geometry": {"coordinates":[-110.94914,42.97575],"type":"Point"}
}