{
  "type": "Feature",
  "properties": {
    "iso:country":"US",
    "sg:address":"1096 W River Rd",
    "sg:city":"Worland",
    "sg:classifiers":[
        {
            "category":"Mining & Drilling",
            "type":"Manufacturing & Wholesale Goods"
        }
    ],
    "sg:phone":"+1 307 347 2431",
    "sg:postcode":"82401",
    "sg:province":"WY",
    "sg:tags":[
        "field",
        "oil"
    ],
    "wof:name":"DAB Oilfield Svc Inc",
    "wof:placetype":"venue"
},
  "geometry": {"coordinates":[-107.975211,44.015034],"type":"Point"}
}