{
  "type": "Feature",
  "properties": {
    "iso:country":"US",
    "sg:address":"255 N Wolcott St",
    "sg:city":"Casper",
    "sg:classifiers":[
        {
            "category":"Retail",
            "subcategory":"Repair Shop",
            "type":"Services"
        }
    ],
    "sg:phone":"+1 307 234 3553",
    "sg:postcode":"82601",
    "sg:province":"WY",
    "sg:tags":[
        "water",
        "equipment",
        "softening"
    ],
    "wof:name":"Culligan Of Casper",
    "wof:placetype":"venue"
},
  "geometry": {"coordinates":[-106.32366500000001,42.851461],"type":"Point"}
}