{
  "type": "Feature",
  "properties": {
    "iso:country":"US",
    "sg:address":"724 Golden Hill St",
    "sg:city":"Cheyenne",
    "sg:classifiers":[
        {
            "category":"Professional",
            "subcategory":"Engineering",
            "type":"Services"
        }
    ],
    "sg:phone":"+1 307 635 4278",
    "sg:postcode":"82009",
    "sg:province":"WY",
    "sg:tags":[
        "firm"
    ],
    "wof:name":"Douglas Engineering",
    "wof:placetype":"venue"
},
  "geometry": {"coordinates":[-104.842134,41.18101],"type":"Point"}
}