{
  "type": "Feature",
  "properties": {
    "iso:country":"US",
    "sg:address":"1211 Gold Rd",
    "sg:city":"Gillette",
    "sg:classifiers":[
        {
            "category":"Building & Trades",
            "subcategory":"Construction",
            "type":"Services"
        }
    ],
    "sg:phone":"+1 307 686 2686",
    "sg:postcode":"82716",
    "sg:province":"WY",
    "wof:name":"Cinch Construction Inc",
    "wof:placetype":"venue"
},
  "geometry": {"coordinates":[-105.51961900000001,44.32764],"type":"Point"}
}