{
  "type": "Feature",
  "properties": {
    "addr:full":"1 S Main St Sheridan WY 82801",
    "addr:housenumber":"1",
    "addr:postcode":"82801",
    "addr:street":"S Main St",
    "iso:country":"US",
    "sg:address":"1 S Main St",
    "sg:city":"Sheridan",
    "sg:classifiers":[
        {
            "category":"Shopping",
            "subcategory":"Pharmacy",
            "type":"Retail Goods"
        }
    ],
    "sg:phone":"+1 307 672 2426",
    "sg:postcode":"82801",
    "sg:province":"WY",
    "wof:name":"Hospital Pharmacy United Drugs",
    "wof:placetype":"venue"
},
  "geometry": {"coordinates":[-106.9558,44.79723],"type":"Point"}
}