{
  "type": "Feature",
  "properties": {
    "iso:country":"US",
    "sg:address":"217 E Garfield St",
    "sg:city":"Laramie",
    "sg:classifiers":[
        {
            "category":"Manufacturing",
            "subcategory":"Jewelry",
            "type":"Manufacturing & Wholesale Goods"
        }
    ],
    "sg:phone":"+1 307 745 1580",
    "sg:postcode":"82070",
    "sg:province":"WY",
    "sg:tags":[
        "ware",
        "mfg"
    ],
    "wof:name":"Buffalo Silver",
    "wof:placetype":"venue"
},
  "geometry": {"coordinates":[-105.59486800000001,41.310228],"type":"Point"}
}