{
  "type": "Feature",
  "properties": {
    "iso:country":"US",
    "sg:address":"819 Washakie Ave",
    "sg:city":"Worland",
    "sg:classifiers":[
        {
            "category":"Farming",
            "subcategory":"Livestock Farm",
            "type":"Manufacturing & Wholesale Goods"
        }
    ],
    "sg:phone":"+1 307 347 3758",
    "sg:postcode":"82401",
    "sg:province":"WY",
    "sg:tags":[
        "animal",
        "general"
    ],
    "wof:name":"Hampton Sheep Company",
    "wof:placetype":"venue"
},
  "geometry": {"coordinates":[-107.95843600000001,44.007964],"type":"Point"}
}