{
  "type": "Feature",
  "properties": {
    "addr:full":"280 S Main St Hudson WY 82515",
    "addr:housenumber":"280",
    "addr:postcode":"82515",
    "addr:street":"S Main St",
    "iso:country":"US",
    "sg:address":"280 S Main St",
    "sg:city":"Hudson",
    "sg:classifiers":[
        {
            "category":"Government",
            "subcategory":"Post Office",
            "type":"Public Place"
        }
    ],
    "sg:phone":"+1 307 332 5596",
    "sg:postcode":"82515",
    "sg:province":"WY",
    "wof:name":"US Post Office",
    "wof:placetype":"venue"
},
  "geometry": {"coordinates":[-108.58366700000001,42.903976],"type":"Point"}
}