{
  "type": "Feature",
  "properties": {
    "iso:country":"US",
    "sg:address":"504 S Veterans St",
    "sg:city":"Saratoga",
    "sg:classifiers":[
        {
            "category":"Restaurant",
            "type":"Food & Drink"
        }
    ],
    "sg:phone":"+1 307 326 5046",
    "sg:postcode":"82331",
    "sg:province":"WY",
    "sg:tags":[
        "eating"
    ],
    "wof:name":"Corral Restaurant",
    "wof:placetype":"venue"
},
  "geometry": {"coordinates":[-106.804344,41.449012],"type":"Point"}
}