{
  "type": "Feature",
  "properties": {
    "iso:country":"US",
    "sg:address":"217 Dell Range Blvd",
    "sg:city":"Cheyenne",
    "sg:classifiers":[
        {
            "category":"Government",
            "subcategory":"Office",
            "type":"Public Place"
        },
        {
            "category":"Education",
            "subcategory":"School",
            "type":"Public Place"
        }
    ],
    "sg:phone":"+1 307 638 2173",
    "sg:postcode":"82009",
    "sg:province":"WY",
    "sg:tags":[
        "military"
    ],
    "wof:name":"Star Base Academy",
    "wof:placetype":"venue"
},
  "geometry": {"coordinates":[-104.82390100000001,41.164006],"type":"Point"}
}