{
  "type": "Feature",
  "properties": {
    "iso:country":"US",
    "sg:address":"1212 E Park Ave",
    "sg:city":"Laramie",
    "sg:classifiers":[
        {
            "category":"Professional",
            "subcategory":"Management & Consulting",
            "type":"Services"
        }
    ],
    "sg:phone":"+1 307 745 3000",
    "sg:postcode":"82070",
    "sg:province":"WY",
    "sg:tags":[
        "security"
    ],
    "wof:name":"American Express",
    "wof:placetype":"venue"
},
  "geometry": {"coordinates":[-105.58224800000001,41.30551],"type":"Point"}
}