{
  "type": "Feature",
  "properties": {
    "iso:country":"US",
    "sg:address":"1575 State Hwy 150 S",
    "sg:city":"Evanston",
    "sg:classifiers":[
        {
            "category":"Building & Trades",
            "subcategory":"Construction",
            "type":"Services"
        }
    ],
    "sg:phone":"+1 307 783 7500",
    "sg:postcode":"82930",
    "sg:province":"WY",
    "sg:tags":[
        "crude",
        "pipeline",
        "petroleum"
    ],
    "wof:name":"Rocky Mtn Pipeline Systems",
    "wof:placetype":"venue"
},
  "geometry": {"coordinates":[-110.941152,41.251745],"type":"Point"}
}