{
  "type": "Feature",
  "properties": {
    "addr:full":"608 E Pershing Ave Riverton WY 82501",
    "addr:housenumber":"608",
    "addr:postcode":"82501",
    "addr:street":"E Pershing Ave",
    "iso:country":"US",
    "sg:address":"608 E Pershing Ave",
    "sg:city":"Riverton",
    "sg:classifiers":[
        {
            "category":"Manufacturing",
            "subcategory":"Printing",
            "type":"Manufacturing & Wholesale Goods"
        }
    ],
    "sg:phone":"+1 307 857 6114",
    "sg:postcode":"82501",
    "sg:province":"WY",
    "sg:tags":[
        "newspaper"
    ],
    "sg:website":"www.wyomingadvertiser.com",
    "wof:name":"Advertiser",
    "wof:placetype":"venue"
},
  "geometry": {"coordinates":[-108.383236,43.030477],"type":"Point"}
}