{
  "type": "Feature",
  "properties": {
    "iso:country":"US",
    "sg:address":"200 E Railroad Ave",
    "sg:city":"Green River",
    "sg:classifiers":[
        {
            "category":"Railroad",
            "type":"Transportation"
        }
    ],
    "sg:phone":"+1 307 875 6051",
    "sg:postcode":"82935",
    "sg:province":"WY",
    "sg:tags":[
        "operator",
        "line"
    ],
    "wof:name":"Union Pacific Railroad Company",
    "wof:placetype":"venue"
},
  "geometry": {"coordinates":[-109.46608999999999,41.5271],"type":"Point"}
}