{
  "type": "Feature",
  "properties": {
    "iso:country":"US",
    "sg:address":"1550 E Antelope Rd",
    "sg:city":"Douglas",
    "sg:classifiers":[
        {
            "category":"Building & Trades",
            "subcategory":"Construction",
            "type":"Services"
        }
    ],
    "sg:phone":"+1 307 358 3628",
    "sg:postcode":"82633",
    "sg:province":"WY",
    "sg:tags":[
        "concrete",
        "contractor"
    ],
    "wof:name":"Seim Concrete",
    "wof:placetype":"venue"
},
  "geometry": {"coordinates":[-105.100825,42.743264],"type":"Point"}
}