{
  "type": "Feature",
  "properties": {
    "iso:country":"US",
    "sg:address":"120 Lincoln St",
    "sg:city":"Thayne",
    "sg:classifiers":[
        {
            "category":"Manufacturing",
            "subcategory":"Building Materials",
            "type":"Manufacturing & Wholesale Goods"
        }
    ],
    "sg:phone":"+1 307 883 2957",
    "sg:postcode":"83110",
    "sg:province":"WY",
    "sg:tags":[
        "mfg",
        "wood",
        "kitchen",
        "cabinet"
    ],
    "wof:name":"Woodworks Unlimited",
    "wof:placetype":"venue"
},
  "geometry": {"coordinates":[-110.936143,42.72873],"type":"Point"}
}