{
  "type": "Feature",
  "properties": {
    "iso:country":"US",
    "sg:address":"306 Grace Ave",
    "sg:city":"Worland",
    "sg:phone":"+1 307 347 4622",
    "sg:postcode":"82401",
    "sg:province":"WY",
    "sg:tags":[
        "distributor",
        "oil",
        "marketer"
    ],
    "wof:name":"Exxon Distributor",
    "wof:placetype":"venue"
},
  "geometry": {"coordinates":[-107.964157,44.01366],"type":"Point"}
}