{
  "type": "Feature",
  "properties": {
    "addr:full":"1081 Bade Rd Cheyenne WY 82009",
    "addr:housenumber":"1081",
    "addr:postcode":"82009",
    "addr:street":"Bade Rd",
    "iso:country":"US",
    "sg:address":"1081 Bade Rd",
    "sg:city":"Cheyenne",
    "sg:classifiers":[
        {
            "category":"Retail",
            "subcategory":"Auto Repair",
            "type":"Services"
        }
    ],
    "sg:phone":"+1 307 634 8840",
    "sg:postcode":"82009",
    "sg:province":"WY",
    "sg:tags":[
        "body"
    ],
    "wof:name":"Little Body Shop",
    "wof:placetype":"venue"
},
  "geometry": {"coordinates":[-105.005082,41.157533],"type":"Point"}
}