{
  "type": "Feature",
  "properties": {
    "iso:country":"US",
    "sg:address":"915 S Federal Blvd",
    "sg:city":"Riverton",
    "sg:classifiers":[
        {
            "category":"Wholesale",
            "subcategory":"Farm Supplies",
            "type":"Manufacturing & Wholesale Goods"
        }
    ],
    "sg:phone":"+1 307 857 7008",
    "sg:postcode":"82501",
    "sg:province":"WY",
    "sg:tags":[
        "feed"
    ],
    "wof:name":"Murphy's Feed & More",
    "wof:placetype":"venue"
},
  "geometry": {"coordinates":[-108.380505,43.016949],"type":"Point"}
}