{
  "type": "Feature",
  "properties": {
    "iso:country":"US",
    "sg:address":"801 N Center St",
    "sg:city":"Casper",
    "sg:classifiers":[
        {
            "category":"Home & Garden",
            "subcategory":"Building Materials",
            "type":"Retail Goods"
        }
    ],
    "sg:phone":"+1 307 234 4032",
    "sg:postcode":"82601",
    "sg:province":"WY",
    "sg:tags":[
        "glass",
        "window",
        "plate"
    ],
    "wof:name":"Wyoming Glass Inc",
    "wof:placetype":"venue"
},
  "geometry": {"coordinates":[-106.32519000000001,42.85772],"type":"Point"}
}