{
  "type": "Feature",
  "properties": {
    "iso:country":"US",
    "sg:address":"28 Murphy Gulch Rd",
    "sg:city":"Banner",
    "sg:classifiers":[
        {
            "category":"Professional",
            "subcategory":"Business Services",
            "type":"Services"
        }
    ],
    "sg:phone":"+1 307 674 6252",
    "sg:postcode":"82832",
    "sg:province":"WY",
    "sg:tags":[
        "water",
        "treatment"
    ],
    "wof:name":"A T & S Water Conditioning",
    "wof:placetype":"venue"
},
  "geometry": {"coordinates":[-106.81809,44.643959],"type":"Point"}
}