{
  "type": "Feature",
  "properties": {
    "addr:full":"115 N 5th St E Riverton WY 82501",
    "addr:housenumber":"115",
    "addr:postcode":"82501",
    "addr:street":"N 5Th St",
    "iso:country":"US",
    "sg:address":"115 N 5th St E",
    "sg:city":"Riverton",
    "sg:classifiers":[
        {
            "category":"Wholesale",
            "subcategory":"Medical Equipment & Supplies",
            "type":"Manufacturing & Wholesale Goods"
        }
    ],
    "sg:phone":"+1 307 856 9415",
    "sg:postcode":"82501",
    "sg:province":"WY",
    "sg:tags":[
        "merchandise"
    ],
    "wof:name":"Community Home Oxygen",
    "wof:placetype":"venue"
},
  "geometry": {"coordinates":[-108.384777,43.025566],"type":"Point"}
}