{
  "type": "Feature",
  "properties": {
    "iso:country":"US",
    "sg:address":"16 5th Ave",
    "sg:city":"Belle Fourche",
    "sg:classifiers":[
        {
            "category":"Autos & Motor Vehicles",
            "subcategory":"Fuel & Gas Station",
            "type":"Retail Goods"
        }
    ],
    "sg:phone":"+1 605 892 2270",
    "sg:postcode":"57717",
    "sg:province":"WY",
    "sg:tags":[
        "gasoline",
        "station",
        "truck",
        "stops",
        "plaza"
    ],
    "wof:name":"Jumpin Jacks",
    "wof:placetype":"venue"
},
  "geometry": {"coordinates":[-103.853645,44.679423],"type":"Point"}
}