{
  "type": "Feature",
  "properties": {
    "addr:full":"510 N Lennox St Casper WY 82601",
    "addr:housenumber":"510",
    "addr:postcode":"82601",
    "addr:street":"N Lennox St",
    "iso:country":"US",
    "sg:address":"510 N Lennox St",
    "sg:city":"Casper",
    "sg:classifiers":[
        {
            "category":"Retail",
            "subcategory":"Auto Repair",
            "type":"Services"
        }
    ],
    "sg:phone":"+1 307 234 1365",
    "sg:postcode":"82601",
    "sg:province":"WY",
    "sg:tags":[
        "body",
        "automobile",
        "painting"
    ],
    "wof:name":"Central Paint & Body Inc",
    "wof:placetype":"venue"
},
  "geometry": {"coordinates":[-106.299723,42.854757],"type":"Point"}
}