{
  "type": "Feature",
  "properties": {
    "iso:country":"US",
    "sg:address":"240 Chamberlain Rd",
    "sg:city":"Mills",
    "sg:classifiers":[
        {
            "category":"Mining & Drilling",
            "type":"Manufacturing & Wholesale Goods"
        }
    ],
    "sg:phone":"+1 307 577 5600",
    "sg:postcode":"82604",
    "sg:province":"WY",
    "sg:tags":[
        "field",
        "oil"
    ],
    "sg:website":"www.crown-energy.com",
    "wof:name":"Crown Energy Technologies",
    "wof:placetype":"venue"
},
  "geometry": {"coordinates":[-106.38066499999999,42.843214],"type":"Point"}
}