{
  "type": "Feature",
  "properties": {
    "addr:full":"411 California St Shoshoni WY 82649",
    "addr:housenumber":"411",
    "addr:postcode":"82649",
    "addr:street":"California St Shoshoni Wy",
    "iso:country":"US",
    "sg:address":"411 California St",
    "sg:city":"Shoshoni",
    "sg:classifiers":[
        {
            "category":"Recreation",
            "type":"Entertainment"
        }
    ],
    "sg:phone":"+1 307 876 2721",
    "sg:postcode":"82649",
    "sg:province":"WY",
    "sg:tags":[
        "club",
        "membership"
    ],
    "wof:name":"Shoshoni Boys & Girls Club",
    "wof:placetype":"venue"
},
  "geometry": {"coordinates":[-108.112741,43.238578],"type":"Point"}
}