{
  "type": "Feature",
  "properties": {
    "iso:country":"US",
    "sg:address":"100 N Center St",
    "sg:city":"Casper",
    "sg:classifiers":[
        {
            "category":"Utilities",
            "type":"Services"
        }
    ],
    "sg:phone":"+1 307 268 9917",
    "sg:postcode":"82601",
    "sg:province":"WY",
    "sg:tags":[
        "electric"
    ],
    "wof:name":"Northwestern Corporation",
    "wof:placetype":"venue"
},
  "geometry": {"coordinates":[-106.32516,42.85142],"type":"Point"}
}