{
  "type": "Feature",
  "properties": {
    "addr:full":"816 Klondyke St Kemmerer WY 83101",
    "addr:housenumber":"816",
    "addr:postcode":"83101",
    "addr:street":"Klondyke St Kemmerer Wy",
    "iso:country":"US",
    "sg:address":"816 Klondyke St",
    "sg:city":"Kemmerer",
    "sg:classifiers":[
        {
            "category":"Health Services",
            "subcategory":"Optometrist",
            "type":"Services"
        }
    ],
    "sg:phone":"+1 307 877 9250",
    "sg:postcode":"83101",
    "sg:province":"WY",
    "wof:name":"Robert D Schaffarzick OD",
    "wof:placetype":"venue"
},
  "geometry": {"coordinates":[-110.537159,41.793241],"type":"Point"}
}