{
  "type": "Feature",
  "properties": {
    "iso:country":"US",
    "sg:address":"307 E 20th St",
    "sg:city":"Cheyenne",
    "sg:classifiers":[
        {
            "category":"Shopping",
            "type":"Retail Goods"
        }
    ],
    "sg:phone":"+1 307 634 4100",
    "sg:postcode":"82001",
    "sg:province":"WY",
    "sg:tags":[
        "merchandise"
    ],
    "wof:name":"Hearing Center Inc",
    "wof:placetype":"venue"
},
  "geometry": {"coordinates":[-104.813112,41.137861],"type":"Point"}
}