{
  "type": "Feature",
  "properties": {
    "addr:full":"705 9th St Wheatland WY 82201",
    "addr:housenumber":"705",
    "addr:postcode":"82201",
    "addr:street":"9Th St Wheatland Wy",
    "iso:country":"US",
    "sg:address":"705 9th St",
    "sg:city":"Wheatland",
    "sg:classifiers":[
        {
            "category":"Shopping",
            "subcategory":"Department Store",
            "type":"Retail Goods"
        }
    ],
    "sg:phone":"+1 307 322 1905",
    "sg:postcode":"82201",
    "sg:province":"WY",
    "sg:tags":[
        "shop"
    ],
    "wof:name":"Dollar Discount",
    "wof:placetype":"venue"
},
  "geometry": {"coordinates":[-104.953335,42.055261],"type":"Point"}
}