{
  "type": "Feature",
  "properties": {
    "iso:country":"US",
    "sg:address":"1131 11th St",
    "sg:city":"Cody",
    "sg:classifiers":[
        {
            "category":"Government",
            "subcategory":"Office",
            "type":"Public Place"
        }
    ],
    "sg:phone":"+1 307 754 8710",
    "sg:postcode":"82414",
    "sg:province":"WY",
    "sg:tags":[
        "village"
    ],
    "wof:name":"Powell Administration & Civil",
    "wof:placetype":"venue"
},
  "geometry": {"coordinates":[-109.065979,44.525713],"type":"Point"}
}