{
  "type": "Feature",
  "properties": {
    "addr:full":"3105 E 2nd St Gillette WY 82718",
    "addr:housenumber":"3105",
    "addr:postcode":"82718",
    "addr:street":"E 2Nd St",
    "iso:country":"US",
    "sg:address":"3105 E 2nd St",
    "sg:city":"Gillette",
    "sg:classifiers":[
        {
            "category":"Mining & Drilling",
            "type":"Manufacturing & Wholesale Goods"
        }
    ],
    "sg:phone":"+1 307 685 4210",
    "sg:postcode":"82718",
    "sg:province":"WY",
    "sg:tags":[
        "field",
        "oil"
    ],
    "sg:website":"www.conquestoil.com",
    "wof:name":"Conquest Energy Svc",
    "wof:placetype":"venue"
},
  "geometry": {"coordinates":[-105.455714,44.292675],"type":"Point"}
}