{
  "type": "Feature",
  "properties": {
    "iso:country":"US",
    "sg:address":"441 N Kenwood St",
    "sg:city":"Casper",
    "sg:classifiers":[
        {
            "category":"Wholesale",
            "subcategory":"Electrical",
            "type":"Manufacturing & Wholesale Goods"
        }
    ],
    "sg:phone":"+1 307 234 1821",
    "sg:postcode":"82601",
    "sg:province":"WY",
    "sg:tags":[
        "equipment",
        "electronic",
        "supply"
    ],
    "wof:name":"Hathaway Electronics Supply",
    "wof:placetype":"venue"
},
  "geometry": {"coordinates":[-106.30325000000001,42.855025],"type":"Point"}
}