{
  "type": "Feature",
  "properties": {
    "addr:full":"100 E 4th St Gillette WY 82716",
    "addr:housenumber":"100",
    "addr:postcode":"82716",
    "addr:street":"E 4Th St",
    "iso:country":"US",
    "sg:address":"100 E 4th St",
    "sg:city":"Gillette",
    "sg:classifiers":[
        {
            "category":"Banks & Credit Unions",
            "subcategory":"Investment Brokerage",
            "type":"Services"
        }
    ],
    "sg:phone":"+1 307 682 6840",
    "sg:postcode":"82716",
    "sg:province":"WY",
    "sg:tags":[
        "security"
    ],
    "wof:name":"D A Davidson & Co",
    "wof:placetype":"venue"
},
  "geometry": {"coordinates":[-105.50394,44.291219],"type":"Point"}
}