{
  "type": "Feature",
  "properties": {
    "iso:country":"US",
    "sg:address":"310 US Hwy 189",
    "sg:city":"Kemmerer",
    "sg:classifiers":[
        {
            "category":"Travel",
            "subcategory":"Campground",
            "type":"Entertainment"
        }
    ],
    "sg:phone":"+1 307 877 6634",
    "sg:postcode":"83101",
    "sg:province":"WY",
    "sg:tags":[
        "recreational",
        "parks",
        "vehicle"
    ],
    "wof:name":"Foothills Residential Cmnty",
    "wof:placetype":"venue"
},
  "geometry": {"coordinates":[-110.535376,41.805594],"type":"Point"}
}