{
  "type": "Feature",
  "properties": {
    "addr:full":"138 Fremont Lake Rd Pinedale WY 82941",
    "addr:housenumber":"138",
    "addr:postcode":"82941",
    "addr:street":"Fremont Lake Rd",
    "iso:country":"US",
    "sg:address":"138 Fremont Lake Rd",
    "sg:city":"Pinedale",
    "sg:classifiers":[
        {
            "category":"Retail",
            "subcategory":"Animal Services",
            "type":"Services"
        }
    ],
    "sg:phone":"+1 307 367 2687",
    "sg:postcode":"82941",
    "sg:province":"WY",
    "sg:tags":[
        "training",
        "dog"
    ],
    "wof:name":"Jaune Roche Kennels",
    "wof:placetype":"venue"
},
  "geometry": {"coordinates":[-109.84231,42.882529],"type":"Point"}
}