{
  "type": "Feature",
  "properties": {
    "addr:city":"Cheyenne",
    "addr:full":"710 S Lions Park Drive Cheyenne, Wy 82001",
    "addr:house_number":"710",
    "addr:housenumber":"710",
    "addr:phone":"+1 307-637-6458",
    "addr:postcode":"82001",
    "addr:road":"S Lions Park Drive",
    "addr:state":"WY",
    "addr:street":"S Lions Park Dr",
    "iso:country":"US",
    "sg:address":"710 S Lions Park Dr",
    "sg:city":"Cheyenne",
    "sg:classifiers":[
        {
            "category":"Government",
            "subcategory":"Office",
            "type":"Public Place"
        }
    ],
    "sg:phone":"+1 307 637 6458",
    "sg:postcode":"82001",
    "sg:province":"WY",
    "sg:tags":[
        "village"
    ],
    "sg:website":"www.botanic.org",
    "wof:airports":[
        102531225
    ],
    "wof:name":"Cheyenne Botanic Gardens",
    "wof:placetype":"venue"
},
  "geometry": {"coordinates":[-104.82598,41.15409],"type":"Point"}
}