{
  "type": "Feature",
  "properties": {
    "iso:country":"US",
    "sg:address":"710 S Lions Park Dr",
    "sg:city":"Cheyenne",
    "sg:classifiers":[
        {
            "category":"Government",
            "subcategory":"Office",
            "type":"Public Place"
        }
    ],
    "sg:phone":"+1 307 637 6458",
    "sg:postcode":"82001",
    "sg:province":"WY",
    "sg:tags":[
        "village"
    ],
    "sg:website":"www.botanic.org",
    "wof:name":"Cheyenne Botanic Gardens",
    "wof:placetype":"venue"
},
  "geometry": {"coordinates":[-104.82884,41.154539],"type":"Point"}
}