{
  "type": "Feature",
  "properties": {
    "addr:full":"1066 Hwy 237 Grover WY 83110",
    "addr:housenumber":"1066",
    "addr:postcode":"83110",
    "addr:street":"Hwy 237 Grover Wy",
    "iso:country":"US",
    "sg:address":"1066 Hwy 237",
    "sg:city":"Grover",
    "sg:classifiers":[
        {
            "category":"Building & Trades",
            "subcategory":"Plumbing",
            "type":"Services"
        }
    ],
    "sg:phone":"+1 307 886 3918",
    "sg:postcode":"83110",
    "sg:province":"WY",
    "sg:tags":[
        "mechanical",
        "contractor"
    ],
    "wof:name":"On-Line Mechanical Inc",
    "wof:placetype":"venue"
},
  "geometry": {"coordinates":[-110.94838,42.793949],"type":"Point"}
}