{
  "type": "Feature",
  "properties": {
    "iso:country":"US",
    "sg:address":"208 E Fairview Rd",
    "sg:city":"Wheatland",
    "sg:classifiers":[
        {
            "category":"Professional",
            "type":"Services"
        }
    ],
    "sg:phone":"+1 307 322 5364",
    "sg:postcode":"82201",
    "sg:province":"WY",
    "sg:tags":[
        "establishment"
    ],
    "wof:name":"Wheatland Backgrounders",
    "wof:placetype":"venue"
},
  "geometry": {"coordinates":[-104.910923,42.089378],"type":"Point"}
}