{
  "type": "Feature",
  "properties": {
    "iso:country":"US",
    "sg:address":"4396 Orchard Bench Rd",
    "sg:city":"Basin",
    "sg:classifiers":[
        {
            "category":"Retail",
            "subcategory":"Animal Services",
            "type":"Services"
        }
    ],
    "sg:phone":"+1 307 568 3882",
    "sg:postcode":"82410",
    "sg:province":"WY",
    "wof:name":"Avalon Boarding Kennels",
    "wof:placetype":"venue"
},
  "geometry": {"coordinates":[-108.03399400000001,44.357078],"type":"Point"}
}