{
  "type": "Feature",
  "properties": {
    "iso:country":"US",
    "sg:address":"4424 Skylane Ave",
    "sg:city":"Riverton",
    "sg:classifiers":[
        {
            "category":"Mining & Drilling",
            "type":"Manufacturing & Wholesale Goods"
        }
    ],
    "sg:phone":"+1 307 856 1577",
    "sg:postcode":"82501",
    "sg:province":"WY",
    "sg:tags":[
        "oil",
        "well"
    ],
    "wof:name":"Eli D Bebout Office",
    "wof:placetype":"venue"
},
  "geometry": {"coordinates":[-108.452398,43.054861],"type":"Point"}
}