{
  "type": "Feature",
  "properties": {
    "iso:country":"US",
    "sg:address":"1300 S Creamery Ln",
    "sg:city":"Jackson",
    "sg:classifiers":[
        {
            "category":"Farming",
            "subcategory":"Livestock Farm",
            "type":"Manufacturing & Wholesale Goods"
        }
    ],
    "sg:phone":"+1 307 734 3839",
    "sg:postcode":"83001",
    "sg:province":"WY",
    "sg:tags":[
        "ranch"
    ],
    "wof:name":"E Bar S Ranch",
    "wof:placetype":"venue"
},
  "geometry": {"coordinates":[-110.82561099999999,43.460454],"type":"Point"}
}