{
  "type": "Feature",
  "properties": {
    "addr:full":"2202 Public St Cody WY 82414",
    "addr:housenumber":"2202",
    "addr:postcode":"82414",
    "addr:street":"Public St",
    "iso:country":"US",
    "sg:address":"2202 Public St",
    "sg:city":"Cody",
    "sg:classifiers":[
        {
            "category":"Manufacturing",
            "subcategory":"Furniture",
            "type":"Manufacturing & Wholesale Goods"
        }
    ],
    "sg:phone":"+1 307 587 6543",
    "sg:postcode":"82414",
    "sg:province":"WY",
    "sg:tags":[
        "upholstered",
        "wood"
    ],
    "wof:name":"Arcadia Woodworks",
    "wof:placetype":"venue"
},
  "geometry": {"coordinates":[-109.048948,44.532456],"type":"Point"}
}