{
  "type": "Feature",
  "properties": {
    "iso:country":"US",
    "sg:address":"2936 Ridgecrest Dr",
    "sg:city":"Casper",
    "sg:classifiers":[
        {
            "category":"Social Services",
            "subcategory":"Child Care",
            "type":"Services"
        }
    ],
    "sg:phone":"+1 307 266 5907",
    "sg:postcode":"82604",
    "sg:province":"WY",
    "wof:name":"Comfy Cozy Child Care",
    "wof:placetype":"venue"
},
  "geometry": {"coordinates":[-106.351086,42.82172],"type":"Point"}
}