{
  "type": "Feature",
  "properties": {
    "iso:country":"US",
    "sg:address":"1350 US Hwy 89",
    "sg:city":"Jackson",
    "sg:classifiers":[
        {
            "category":"Autos & Motor Vehicles",
            "subcategory":"Auto Supplies",
            "type":"Retail Goods"
        }
    ],
    "sg:phone":"+1 307 733 2694",
    "sg:postcode":"83001",
    "sg:province":"WY",
    "sg:tags":[
        "automobile",
        "parts"
    ],
    "wof:name":"Motor Mart",
    "wof:placetype":"venue"
},
  "geometry": {"coordinates":[-110.79323100000001,43.460952],"type":"Point"}
}