{
  "type": "Feature",
  "properties": {
    "iso:country":"US",
    "sg:address":"406 W 17th St",
    "sg:city":"Cheyenne",
    "sg:classifiers":[
        {
            "category":"Wholesale",
            "subcategory":"Auto Parts",
            "type":"Manufacturing & Wholesale Goods"
        }
    ],
    "sg:phone":"+1 307 638 3348",
    "sg:postcode":"82001",
    "sg:province":"WY",
    "sg:tags":[
        "body",
        "automobile",
        "shop"
    ],
    "wof:name":"Sidles Co Automotive Parts",
    "wof:placetype":"venue"
},
  "geometry": {"coordinates":[-104.81918899999999,41.132463],"type":"Point"}
}