{
  "type": "Feature",
  "properties": {
    "iso:country":"US",
    "sg:address":"2200 W 45th St",
    "sg:city":"Casper",
    "sg:classifiers":[
        {
            "category":"Retail",
            "subcategory":"Repair Shop",
            "type":"Services"
        }
    ],
    "sg:phone":"+1 307 266 1258",
    "sg:postcode":"82604",
    "sg:province":"WY",
    "sg:tags":[
        "vinyl"
    ],
    "wof:name":"A & S Enterprises",
    "wof:placetype":"venue"
},
  "geometry": {"coordinates":[-106.35151999999999,42.80678],"type":"Point"}
}