{
  "type": "Feature",
  "properties": {
    "iso:country":"US",
    "sg:address":"309 E 2nd St",
    "sg:city":"Gillette",
    "sg:classifiers":[
        {
            "category":"Wholesale",
            "subcategory":"Auto Parts",
            "type":"Manufacturing & Wholesale Goods"
        }
    ],
    "sg:phone":"+1 307 685 8049",
    "sg:postcode":"82716",
    "sg:province":"WY",
    "sg:tags":[
        "body",
        "automobile",
        "shop"
    ],
    "wof:name":"Record Supply/Napa Auto Parts",
    "wof:placetype":"venue"
},
  "geometry": {"coordinates":[-105.500995,44.293295],"type":"Point"}
}