{
  "type": "Feature",
  "properties": {
    "addr:full":"180 Uinta Dr Green River WY 82935",
    "addr:housenumber":"180",
    "addr:postcode":"82935",
    "addr:street":"Uinta Dr Green",
    "iso:country":"US",
    "sg:address":"180 Uinta Dr",
    "sg:city":"Green River",
    "sg:classifiers":[
        {
            "category":"Insurance",
            "subcategory":"Insurance Agent",
            "type":"Services"
        }
    ],
    "sg:phone":"+1 307 875 3471",
    "sg:postcode":"82935",
    "sg:province":"WY",
    "wof:name":"Farmers Insurance Group",
    "wof:placetype":"venue"
},
  "geometry": {"coordinates":[-109.46780800000001,41.518137],"type":"Point"}
}