{
  "type": "Feature",
  "properties": {
    "addr:full":"3203 W College Dr Cheyenne WY 82007",
    "addr:housenumber":"3203",
    "addr:postcode":"82007",
    "addr:street":"W College Dr",
    "iso:country":"US",
    "sg:address":"3203 W College Dr",
    "sg:city":"Cheyenne",
    "sg:classifiers":[
        {
            "category":"Manufacturing",
            "subcategory":"Chemicals & Compounds",
            "type":"Manufacturing & Wholesale Goods"
        }
    ],
    "sg:phone":"+1 307 635 9112",
    "sg:postcode":"82007",
    "sg:province":"WY",
    "sg:tags":[
        "preparation",
        "mfg"
    ],
    "wof:name":"Fire King Fireworks",
    "wof:placetype":"venue"
},
  "geometry": {"coordinates":[-104.845798,41.09908],"type":"Point"}
}