{
  "type": "Feature",
  "properties": {
    "addr:full":"820 8th Ave Belle Fourche WY 57717",
    "addr:housenumber":"820",
    "addr:postcode":"57717",
    "addr:street":"8Th Ave",
    "iso:country":"US",
    "sg:address":"820 8th Ave",
    "sg:city":"Belle Fourche",
    "sg:classifiers":[
        {
            "category":"Manufacturing",
            "subcategory":"Textiles",
            "type":"Manufacturing & Wholesale Goods"
        }
    ],
    "sg:phone":"+1 605 892 6311",
    "sg:postcode":"57717",
    "sg:province":"WY",
    "wof:name":"Center Of The Nation Wool Inc",
    "wof:placetype":"venue"
},
  "geometry": {"coordinates":[-103.849311,44.669651],"type":"Point"}
}