{
  "type": "Feature",
  "properties": {
    "iso:country":"US",
    "sg:address":"229 E Main St",
    "sg:city":"Riverton",
    "sg:classifiers":[
        {
            "category":"Bars & Pubs",
            "type":"Food & Drink"
        }
    ],
    "sg:phone":"+1 307 856 1439",
    "sg:postcode":"82501",
    "sg:province":"WY",
    "wof:name":"Landing Lounge",
    "wof:placetype":"venue"
},
  "geometry": {"coordinates":[-108.38886100000001,43.024562],"type":"Point"}
}