{
  "type": "Feature",
  "properties": {
    "iso:country":"US",
    "sg:address":"8700 Meander Way",
    "sg:city":"Jackson",
    "sg:classifiers":[
        {
            "category":"Building & Trades",
            "subcategory":"Electrical",
            "type":"Services"
        }
    ],
    "sg:phone":"+1 307 733 4605",
    "sg:postcode":"83001",
    "sg:province":"WY",
    "sg:tags":[
        "electric",
        "contractor"
    ],
    "wof:name":"I '2r Electric Inc",
    "wof:placetype":"venue"
},
  "geometry": {"coordinates":[-110.718592,43.354749],"type":"Point"}
}