{
  "type": "Feature",
  "properties": {
    "iso:country":"US",
    "sg:address":"944 N Custer St",
    "sg:city":"Sheridan",
    "sg:classifiers":[
        {
            "category":"Wholesale",
            "subcategory":"Electrical",
            "type":"Manufacturing & Wholesale Goods"
        }
    ],
    "sg:phone":"+1 307 673 1299",
    "sg:postcode":"82801",
    "sg:province":"WY",
    "sg:tags":[
        "control",
        "security",
        "system"
    ],
    "wof:name":"Scott Security Source",
    "wof:placetype":"venue"
},
  "geometry": {"coordinates":[-106.95028499999999,44.807383],"type":"Point"}
}