{
  "type": "Feature",
  "properties": {
    "addr:full":"908 Apricot St Gillette WY 82716",
    "addr:housenumber":"908",
    "addr:postcode":"82716",
    "addr:street":"Apricot St",
    "iso:country":"US",
    "sg:address":"908 Apricot St",
    "sg:city":"Gillette",
    "sg:classifiers":[
        {
            "category":"Government",
            "subcategory":"Office",
            "type":"Public Place"
        }
    ],
    "sg:phone":"+1 307 687 7157",
    "sg:postcode":"82716",
    "sg:province":"WY",
    "sg:tags":[
        "state"
    ],
    "wof:name":"Game & Fish Dept Game Warden",
    "wof:placetype":"venue"
},
  "geometry": {"coordinates":[-105.52013599999999,44.305098],"type":"Point"}
}