{
  "type": "Feature",
  "properties": {
    "iso:country":"US",
    "sg:address":"311 Progress Cir",
    "sg:city":"Cheyenne",
    "sg:classifiers":[
        {
            "category":"Communications",
            "subcategory":"News Services",
            "type":"Services"
        }
    ],
    "sg:phone":"+1 307 632 5888",
    "sg:postcode":"82007",
    "sg:province":"WY",
    "wof:name":"Denver Newspaper Agency",
    "wof:placetype":"venue"
},
  "geometry": {"coordinates":[-104.74023800000001,41.12877],"type":"Point"}
}