{
  "type": "Feature",
  "properties": {
    "iso:country":"US",
    "sg:address":"1121 McMicken St",
    "sg:city":"Rawlins",
    "sg:classifiers":[
        {
            "category":"Retail",
            "subcategory":"Auto Repair",
            "type":"Services"
        }
    ],
    "sg:phone":"+1 307 324 6352",
    "sg:postcode":"82301",
    "sg:province":"WY",
    "sg:tags":[
        "repairing",
        "automobile"
    ],
    "wof:name":"Kar Kraft Inc",
    "wof:placetype":"venue"
},
  "geometry": {"coordinates":[-107.22235999999999,41.797082],"type":"Point"}
}