{
  "type": "Feature",
  "properties": {
    "addr:full":"2344 E 2nd St Casper WY 82609",
    "addr:housenumber":"2344",
    "addr:postcode":"82609",
    "addr:street":"E 2Nd St",
    "iso:country":"US",
    "sg:address":"2344 E 2nd St",
    "sg:city":"Casper",
    "sg:classifiers":[
        {
            "category":"Organizations",
            "subcategory":"Religious Organization",
            "type":"Services"
        }
    ],
    "sg:phone":"+1 307 235 8187",
    "sg:postcode":"82609",
    "sg:province":"WY",
    "sg:tags":[
        "church"
    ],
    "sg:website":"www.casperchurchofchrist.com",
    "wof:name":"Church Of Christ",
    "wof:placetype":"venue"
},
  "geometry": {"coordinates":[-106.29447500000001,42.848829],"type":"Point"}
}