{
  "type": "Feature",
  "properties": {
    "addr:full":"120 Clark St Thermopolis WY 82443",
    "addr:housenumber":"120",
    "addr:postcode":"82443",
    "addr:street":"Clark St Thermopolis Wy",
    "iso:country":"US",
    "sg:address":"120 Clark St",
    "sg:city":"Thermopolis",
    "sg:classifiers":[
        {
            "category":"Organizations",
            "subcategory":"Religious Organization",
            "type":"Services"
        }
    ],
    "sg:phone":"+1 307 864 2478",
    "sg:postcode":"82443",
    "sg:province":"WY",
    "wof:name":"Thermopolis Seventh Day Advent",
    "wof:placetype":"venue"
},
  "geometry": {"coordinates":[-108.20358299999999,43.642668],"type":"Point"}
}