{
  "type": "Feature",
  "properties": {
    "iso:country":"US",
    "sg:address":"5008 Ridge Rd",
    "sg:city":"Cheyenne",
    "sg:classifiers":[
        {
            "category":"Professional",
            "subcategory":"Art Services",
            "type":"Services"
        }
    ],
    "sg:phone":"+1 307 638 7414",
    "sg:postcode":"82009",
    "sg:province":"WY",
    "sg:tags":[
        "graphic",
        "designer"
    ],
    "wof:name":"A1 Super Signs",
    "wof:placetype":"venue"
},
  "geometry": {"coordinates":[-104.768224,41.164598],"type":"Point"}
}