{
  "type": "Feature",
  "properties": {
    "iso:country":"US",
    "sg:address":"200 N David St",
    "sg:city":"Casper",
    "sg:classifiers":[
        {
            "category":"Government",
            "subcategory":"Office",
            "type":"Public Place"
        }
    ],
    "sg:phone":"+1 307 235 8224",
    "sg:postcode":"82601",
    "sg:province":"WY",
    "sg:tags":[
        "city"
    ],
    "wof:name":"Casper City Manager",
    "wof:placetype":"venue"
},
  "geometry": {"coordinates":[-106.326544,42.851024],"type":"Point"}
}