{
  "type": "Feature",
  "properties": {
    "iso:country":"US",
    "sg:address":"327 S Kenwood St",
    "sg:city":"Casper",
    "sg:classifiers":[
        {
            "category":"Shopping",
            "subcategory":"Florist",
            "type":"Retail Goods"
        }
    ],
    "sg:phone":"+1 307 234 7553",
    "sg:postcode":"82601",
    "sg:province":"WY",
    "wof:name":"Plant Peddlers",
    "wof:placetype":"venue"
},
  "geometry": {"coordinates":[-106.303867,42.846601],"type":"Point"}
}