{
  "type": "Feature",
  "properties": {
    "addr:full":"804 Coffeen Ave Sheridan WY 82801",
    "addr:housenumber":"804",
    "addr:postcode":"82801",
    "addr:street":"Coffeen Ave",
    "iso:country":"US",
    "sg:address":"804 Coffeen Ave",
    "sg:city":"Sheridan",
    "sg:classifiers":[
        {
            "category":"Banks & Credit Unions",
            "subcategory":"Bank",
            "type":"Services"
        }
    ],
    "sg:phone":"+1 307 672 3451",
    "sg:postcode":"82801",
    "sg:province":"WY",
    "sg:tags":[
        "term",
        "short",
        "consumer",
        "loan",
        "financing"
    ],
    "wof:name":"Citi Financial",
    "wof:placetype":"venue"
},
  "geometry": {"coordinates":[-106.946523,44.788891],"type":"Point"}
}