{
  "type": "Feature",
  "properties": {
    "addr:full":"109 W 14th St Powell WY 82435",
    "addr:housenumber":"109",
    "addr:postcode":"82435",
    "addr:street":"W 14Th St Powell Wy",
    "iso:country":"US",
    "sg:address":"109 W 14th St",
    "sg:city":"Powell",
    "sg:classifiers":[
        {
            "category":"Social Services",
            "type":"Services"
        }
    ],
    "sg:phone":"+1 307 754 2245",
    "sg:postcode":"82435",
    "sg:province":"WY",
    "sg:tags":[
        "government"
    ],
    "wof:name":"Family Service Dept",
    "wof:placetype":"venue"
},
  "geometry": {"coordinates":[-109.055921,44.537777],"type":"Point"}
}