{
  "type": "Feature",
  "properties": {
    "addr:full":"1924 Sheridan Ave Cody WY 82414",
    "addr:housenumber":"1924",
    "addr:postcode":"82414",
    "addr:street":"Sheridan Ave",
    "iso:country":"US",
    "sg:address":"1924 Sheridan Ave",
    "sg:city":"Cody",
    "sg:classifiers":[
        {
            "category":"Home & Garden",
            "subcategory":"Building Materials",
            "type":"Retail Goods"
        }
    ],
    "sg:phone":"+1 307 527 6120",
    "sg:postcode":"82414",
    "sg:province":"WY",
    "sg:tags":[
        "paint"
    ],
    "wof:name":"Big Horn Paint",
    "wof:placetype":"venue"
},
  "geometry": {"coordinates":[-109.05116200000001,44.525995],"type":"Point"}
}