{
  "type": "Feature",
  "properties": {
    "iso:country":"US",
    "sg:address":"56 Sunshine Dr",
    "sg:city":"Lander",
    "sg:classifiers":[
        {
            "category":"Shopping",
            "subcategory":"Crafts & Fabrics",
            "type":"Retail Goods"
        }
    ],
    "sg:phone":"+1 307 332 2285",
    "sg:postcode":"82520",
    "sg:province":"WY",
    "sg:tags":[
        "shop"
    ],
    "wof:name":"Sew & So",
    "wof:placetype":"venue"
},
  "geometry": {"coordinates":[-108.638907,42.863902],"type":"Point"}
}