{
  "type": "Feature",
  "properties": {
    "iso:country":"US",
    "sg:address":"409 11th Ave N",
    "sg:city":"Greybull",
    "sg:classifiers":[
        {
            "category":"Real Estate",
            "subcategory":"Real Estate Agent",
            "type":"Services"
        }
    ],
    "sg:phone":"+1 307 765 9521",
    "sg:postcode":"82426",
    "sg:province":"WY",
    "wof:name":"Wright Appraisals",
    "wof:placetype":"venue"
},
  "geometry": {"coordinates":[-108.05311500000001,44.500269],"type":"Point"}
}