{
  "type": "Feature",
  "properties": {
    "iso:country":"US",
    "sg:address":"308 W 21st St",
    "sg:city":"Cheyenne",
    "sg:classifiers":[
        {
            "category":"Government",
            "subcategory":"Office",
            "type":"Public Place"
        }
    ],
    "sg:phone":"+1 307 772 2790",
    "sg:postcode":"82001",
    "sg:province":"WY",
    "sg:tags":[
        "case",
        "monitor",
        "bankruptcy"
    ],
    "wof:name":"Trustees Executive Offs For US",
    "wof:placetype":"venue"
},
  "geometry": {"coordinates":[-104.82037,41.136423],"type":"Point"}
}