{
  "type": "Feature",
  "properties": {
    "iso:country":"US",
    "sg:address":"355 Washington St",
    "sg:city":"Afton",
    "sg:classifiers":[
        {
            "category":"Restaurant",
            "type":"Food & Drink"
        }
    ],
    "sg:phone":"+1 307 885 9893",
    "sg:postcode":"83110",
    "sg:province":"WY",
    "sg:tags":[
        "eating"
    ],
    "wof:name":"Valleon Cafe",
    "wof:placetype":"venue"
},
  "geometry": {"coordinates":[-110.93337099999999,42.726274],"type":"Point"}
}