{
  "type": "Feature",
  "properties": {
    "iso:country":"US",
    "sg:address":"555 County Rd",
    "sg:city":"Evanston",
    "sg:classifiers":[
        {
            "category":"Government",
            "subcategory":"Office",
            "type":"Public Place"
        }
    ],
    "sg:phone":"+1 307 789 3363",
    "sg:postcode":"82930",
    "sg:province":"WY",
    "sg:tags":[
        "state",
        "program"
    ],
    "wof:name":"Transportation Dept",
    "wof:placetype":"venue"
},
  "geometry": {"coordinates":[-110.962611,41.280814],"type":"Point"}
}