{
  "type": "Feature",
  "properties": {
    "iso:country":"US",
    "sg:address":"2613 Sheridan Ave",
    "sg:city":"Cody",
    "sg:classifiers":[
        {
            "category":"Education",
            "subcategory":"Dance Studio",
            "type":"Public Place"
        },
        {
            "category":"Education",
            "subcategory":"Special Training",
            "type":"Public Place"
        }
    ],
    "sg:phone":"+1 307 527 9973",
    "sg:postcode":"82414",
    "sg:province":"WY",
    "sg:tags":[
        "instruction",
        "dancing"
    ],
    "sg:website":"www.rmsainc.com",
    "wof:name":"Rocky Mountain School-The Arts",
    "wof:placetype":"venue"
},
  "geometry": {"coordinates":[-109.039185,44.526201],"type":"Point"}
}