{
  "type": "Feature",
  "properties": {
    "iso:country":"US",
    "sg:address":"220 N Wolcott St",
    "sg:city":"Casper",
    "sg:classifiers":[
        {
            "category":"Food & Beverages",
            "subcategory":"Specialty",
            "type":"Retail Goods"
        }
    ],
    "sg:phone":"+1 307 577 6444",
    "sg:postcode":"82601",
    "sg:province":"WY",
    "sg:tags":[
        "herb"
    ],
    "sg:website":"www.herbalremedies.com",
    "wof:name":"Herbal Remedies",
    "wof:placetype":"venue"
},
  "geometry": {"coordinates":[-106.323815,42.851819],"type":"Point"}
}