{
  "type": "Feature",
  "properties": {
    "addr:full":"120 N Greeley Hwy Cheyenne WY 82007",
    "addr:housenumber":"120",
    "addr:postcode":"82007",
    "addr:street":"N Greeley Hwy;Wy",
    "iso:country":"US",
    "sg:address":"120 N Greeley Hwy",
    "sg:city":"Cheyenne",
    "sg:classifiers":[
        {
            "category":"Restaurant",
            "type":"Food & Drink"
        }
    ],
    "sg:menulink":"http://www.allmenus.com/wy/cheyenne/135341-subway/menu/",
    "sg:phone":"+1 307 778 8199",
    "sg:postcode":"82007",
    "sg:province":"WY",
    "sg:tags":[
        "american",
        "sandwich"
    ],
    "wof:name":"Subway",
    "wof:placetype":"venue"
},
  "geometry": {"coordinates":[-104.80566399999999,41.119984],"type":"Point"}
}