{
  "type": "Feature",
  "properties": {
    "addr:full":"4020 Grizzly Casper WY 82604",
    "addr:housenumber":"4020",
    "addr:postcode":"82604",
    "addr:street":"Grizzly",
    "iso:country":"US",
    "sg:address":"4020 Grizzly",
    "sg:city":"Casper",
    "sg:classifiers":[
        {
            "category":"Mining & Drilling",
            "type":"Manufacturing & Wholesale Goods"
        }
    ],
    "sg:phone":"+1 307 237 7262",
    "sg:postcode":"82604",
    "sg:province":"WY",
    "sg:tags":[
        "field"
    ],
    "wof:name":"Frac Tanks By Bryson Inc",
    "wof:placetype":"venue"
},
  "geometry": {"coordinates":[-106.37428199999999,42.809113],"type":"Point"}
}