{
  "type": "Feature",
  "properties": {
    "addr:full":"200 Greybull Ave Greybull WY 82426",
    "addr:housenumber":"200",
    "addr:postcode":"82426",
    "addr:street":"Greybull Ave Greybull Wy",
    "iso:country":"US",
    "sg:address":"200 Greybull Ave",
    "sg:city":"Greybull",
    "sg:classifiers":[
        {
            "category":"Restaurant",
            "type":"Food & Drink"
        }
    ],
    "sg:menulink":"http://www.allmenus.com/wy/big-horn-central/236549-lisas-western-cuisine/menu/",
    "sg:phone":"+1 307 765 4765",
    "sg:postcode":"82426",
    "sg:province":"WY",
    "sg:tags":[
        "american"
    ],
    "wof:name":"Lisa's Western Cuisine",
    "wof:placetype":"venue"
},
  "geometry": {"coordinates":[-108.056879,44.488991],"type":"Point"}
}