{
  "type": "Feature",
  "properties": {
    "addr:full":"1606 Ratcliff Dr Gillette WY 82717",
    "addr:housenumber":"1606",
    "addr:postcode":"82717",
    "addr:street":"Ratcliff Dr",
    "iso:country":"US",
    "sg:address":"1606 Ratcliff Dr",
    "sg:city":"Gillette",
    "sg:classifiers":[
        {
            "category":"Retail",
            "subcategory":"Auto Repair",
            "type":"Services"
        }
    ],
    "sg:phone":"+1 307 682 6361",
    "sg:postcode":"82717",
    "sg:province":"WY",
    "sg:tags":[
        "repairing",
        "automobile"
    ],
    "wof:name":"ACT Ion Automotive Repair",
    "wof:placetype":"venue"
},
  "geometry": {"coordinates":[-105.52710999999999,44.320356],"type":"Point"}
}