{
  "type": "Feature",
  "properties": {
    "iso:country":"US",
    "sg:address":"420 2nd St",
    "sg:city":"Mills",
    "sg:classifiers":[
        {
            "category":"Education",
            "subcategory":"School",
            "type":"Public Place"
        }
    ],
    "sg:phone":"+1 307 577 4558",
    "sg:postcode":"82644",
    "sg:province":"WY",
    "wof:name":"Mills Elementary School",
    "wof:placetype":"venue"
},
  "geometry": {"coordinates":[-106.36681,42.841298],"type":"Point"}
}