{
  "type": "Feature",
  "properties": {
    "iso:country":"US",
    "sg:address":"4 Cysco Ct",
    "sg:city":"Gillette",
    "sg:classifiers":[
        {
            "category":"Manufacturing",
            "subcategory":"Tools & Machinery",
            "type":"Manufacturing & Wholesale Goods"
        }
    ],
    "sg:phone":"+1 307 682 2063",
    "sg:postcode":"82718",
    "sg:province":"WY",
    "sg:tags":[
        "equipment",
        "industrial",
        "supply"
    ],
    "sg:website":"www.nisprocess.com",
    "wof:name":"Northland Industrial Specs",
    "wof:placetype":"venue"
},
  "geometry": {"coordinates":[-105.443011,44.201115],"type":"Point"}
}