{
  "type": "Feature",
  "properties": {
    "iso:country":"US",
    "sg:address":"110 W Main St",
    "sg:city":"Newcastle",
    "sg:classifiers":[
        {
            "category":"Real Estate",
            "subcategory":"Real Estate Services",
            "type":"Services"
        }
    ],
    "sg:phone":"+1 307 746 2001",
    "sg:postcode":"82701",
    "sg:province":"WY",
    "sg:tags":[
        "abstract",
        "title"
    ],
    "wof:name":"Weston County Title",
    "wof:placetype":"venue"
},
  "geometry": {"coordinates":[-104.203208,43.855172],"type":"Point"}
}