{
  "type": "Feature",
  "properties": {
    "iso:country":"US",
    "sg:address":"1911 Sage Ln",
    "sg:city":"Worland",
    "sg:classifiers":[
        {
            "category":"Building & Trades",
            "subcategory":"Construction",
            "type":"Services"
        }
    ],
    "sg:phone":"+1 307 347 8505",
    "sg:postcode":"82401",
    "sg:province":"WY",
    "sg:tags":[
        "excavation",
        "excavating",
        "contractor"
    ],
    "wof:name":"Nickelson Backhoe Service",
    "wof:placetype":"venue"
},
  "geometry": {"coordinates":[-107.94299700000001,44.007523],"type":"Point"}
}