{
  "type": "Feature",
  "properties": {
    "addr:full":"1837 Madora Ave Douglas WY 82633",
    "addr:housenumber":"1837",
    "addr:postcode":"82633",
    "addr:street":"Madora Ave Douglas Wy",
    "iso:country":"US",
    "sg:address":"1837 Madora Ave",
    "sg:city":"Douglas",
    "sg:classifiers":[
        {
            "category":"Communications",
            "subcategory":"Radio Station",
            "type":"Services"
        }
    ],
    "sg:phone":"+1 307 358 6177",
    "sg:postcode":"82633",
    "sg:province":"WY",
    "sg:tags":[
        "company",
        "broadcasting"
    ],
    "wof:name":"KYOD",
    "wof:placetype":"venue"
},
  "geometry": {"coordinates":[-105.36593999999999,42.746488],"type":"Point"}
}