{
  "type": "Feature",
  "properties": {
    "iso:country":"US",
    "sg:address":"715 E Roosevelt Ave",
    "sg:city":"Riverton",
    "sg:classifiers":[
        {
            "category":"Government",
            "subcategory":"Office",
            "type":"Public Place"
        }
    ],
    "sg:phone":"+1 307 856 0747",
    "sg:postcode":"82501",
    "sg:province":"WY",
    "wof:name":"Engineer Board Of Control",
    "wof:placetype":"venue"
},
  "geometry": {"coordinates":[-108.380741,43.029744],"type":"Point"}
}