{
  "type": "Feature",
  "properties": {
    "addr:full":"1125 S Jackson St Casper WY 82601",
    "addr:housenumber":"1125",
    "addr:postcode":"82601",
    "addr:street":"S Jackson St",
    "iso:country":"US",
    "sg:address":"1125 S Jackson St",
    "sg:city":"Casper",
    "sg:classifiers":[
        {
            "category":"Shopping",
            "type":"Retail Goods"
        }
    ],
    "sg:phone":"+1 307 473 5666",
    "sg:postcode":"82601",
    "sg:province":"WY",
    "sg:tags":[
        "hearing",
        "equipment",
        "supply",
        "impaired"
    ],
    "wof:name":"Hearing Aid Ctr",
    "wof:placetype":"venue"
},
  "geometry": {"coordinates":[-106.311072,42.840334],"type":"Point"}
}