{
  "type": "Feature",
  "properties": {
    "iso:country":"US",
    "sg:address":"2250 Etchepare Cir",
    "sg:city":"Cheyenne",
    "sg:classifiers":[
        {
            "category":"Autos & Motor Vehicles",
            "subcategory":"Fuel & Gas Station",
            "type":"Retail Goods"
        }
    ],
    "sg:phone":"+1 307 635 2918",
    "sg:postcode":"82007",
    "sg:province":"WY",
    "sg:tags":[
        "plaza",
        "truck",
        "stops"
    ],
    "wof:name":"Flying J Travel Plaza",
    "wof:placetype":"venue"
},
  "geometry": {"coordinates":[-104.85269,41.099926],"type":"Point"}
}