{
  "type": "Feature",
  "properties": {
    "iso:country":"US",
    "sg:address":"52 Rd 2Ec",
    "sg:city":"Cody",
    "sg:classifiers":[
        {
            "category":"Farming",
            "subcategory":"Farm",
            "type":"Manufacturing & Wholesale Goods"
        }
    ],
    "sg:phone":"+1 307 587 3503",
    "sg:postcode":"82414",
    "sg:province":"WY",
    "sg:tags":[
        "crop",
        "general"
    ],
    "wof:name":"Reed Joe & Kathy",
    "wof:placetype":"venue"
},
  "geometry": {"coordinates":[-108.978797,44.562424],"type":"Point"}
}