{
  "type": "Feature",
  "properties": {
    "iso:country":"US",
    "sg:address":"1514 State Hwy 230",
    "sg:city":"Laramie",
    "sg:classifiers":[
        {
            "category":"Professional",
            "subcategory":"Business Services",
            "type":"Services"
        }
    ],
    "sg:phone":"+1 307 721 6307",
    "sg:postcode":"82070",
    "sg:province":"WY",
    "wof:name":"George Grimm",
    "wof:placetype":"venue"
},
  "geometry": {"coordinates":[-105.819733,41.19003],"type":"Point"}
}