{
  "type": "Feature",
  "properties": {
    "iso:country":"US",
    "sg:address":"1948 Howe Rd",
    "sg:city":"Laramie",
    "sg:classifiers":[
        {
            "category":"Professional",
            "subcategory":"Research",
            "type":"Services"
        }
    ],
    "sg:phone":"+1 307 745 3652",
    "sg:postcode":"82070",
    "sg:province":"WY",
    "sg:tags":[
        "commercial",
        "physical"
    ],
    "wof:name":"Wyobigen Inc",
    "wof:placetype":"venue"
},
  "geometry": {"coordinates":[-105.56852499999999,41.26301],"type":"Point"}
}