{
  "type": "Feature",
  "properties": {
    "iso:country":"US",
    "sg:address":"818 Country Club Rd",
    "sg:city":"Gillette",
    "sg:classifiers":[
        {
            "category":"Home & Garden",
            "subcategory":"Building Materials",
            "type":"Retail Goods"
        }
    ],
    "sg:phone":"+1 307 685 3024",
    "sg:postcode":"82717",
    "sg:province":"WY",
    "sg:tags":[
        "paint"
    ],
    "wof:name":"Sherwin-Williams Paints",
    "wof:placetype":"venue"
},
  "geometry": {"coordinates":[-105.493678,44.274959],"type":"Point"}
}