{
  "type": "Feature",
  "properties": {
    "addr:full":"120 Rule Rd Recluse WY 82716",
    "addr:housenumber":"120",
    "addr:postcode":"82716",
    "addr:street":"Rule Rd Recluse Wy",
    "iso:country":"US",
    "sg:address":"120 Rule Rd",
    "sg:city":"Recluse",
    "sg:classifiers":[
        {
            "category":"Professional",
            "subcategory":"Management & Consulting",
            "type":"Services"
        }
    ],
    "sg:phone":"+1 307 686 2404",
    "sg:postcode":"82716",
    "sg:province":"WY",
    "sg:tags":[
        "business"
    ],
    "wof:name":"Rogers Consulting LLC",
    "wof:placetype":"venue"
},
  "geometry": {"coordinates":[-105.731647,44.698353],"type":"Point"}
}