{
  "type": "Feature",
  "properties": {
    "addr:full":"1150 W Coyote Ave Bar Nunn WY 82601",
    "addr:housenumber":"1150",
    "addr:postcode":"82601",
    "addr:street":"W Coyote Ave;Nunn Wy",
    "iso:country":"US",
    "sg:address":"1150 W Coyote Ave",
    "sg:city":"Bar Nunn",
    "sg:classifiers":[
        {
            "category":"Home & Garden",
            "subcategory":"Building Materials",
            "type":"Retail Goods"
        }
    ],
    "sg:phone":"+1 307 234 7416",
    "sg:postcode":"82601",
    "sg:province":"WY",
    "sg:tags":[
        "truss"
    ],
    "wof:name":"Trusses Inc",
    "wof:placetype":"venue"
},
  "geometry": {"coordinates":[-106.338686,42.916799],"type":"Point"}
}