{
  "type": "Feature",
  "properties": {
    "iso:country":"US",
    "sg:address":"812 E 4th St",
    "sg:city":"Gillette",
    "sg:classifiers":[
        {
            "category":"Health Services",
            "subcategory":"Chiropractor",
            "type":"Services"
        }
    ],
    "sg:phone":"+1 307 686 2327",
    "sg:postcode":"82716",
    "sg:province":"WY",
    "wof:name":"Gillette Chiropractic Center",
    "wof:placetype":"venue"
},
  "geometry": {"coordinates":[-105.49365899999999,44.291218],"type":"Point"}
}