{
  "type": "Feature",
  "properties": {
    "iso:country":"US",
    "sg:address":"500 S Gillette Ave",
    "sg:city":"Gillette",
    "sg:classifiers":[
        {
            "category":"Building & Trades",
            "subcategory":"Construction",
            "type":"Services"
        }
    ],
    "sg:phone":"+1 307 685 8061",
    "sg:postcode":"82716",
    "sg:province":"WY",
    "sg:tags":[
        "grading",
        "contractor"
    ],
    "wof:name":"Campbell County Public Works",
    "wof:placetype":"venue"
},
  "geometry": {"coordinates":[-105.50391999999999,44.29023],"type":"Point"}
}