{
  "type": "Feature",
  "properties": {
    "iso:country":"US",
    "sg:address":"425 S Maple St",
    "sg:city":"Lusk",
    "sg:classifiers":[
        {
            "category":"Education",
            "subcategory":"School",
            "type":"Public Place"
        }
    ],
    "sg:phone":"+1 307 334 2224",
    "sg:postcode":"82225",
    "sg:province":"WY",
    "wof:name":"Lusk Grade School",
    "wof:placetype":"venue"
},
  "geometry": {"coordinates":[-104.44789400000001,42.761042],"type":"Point"}
}