{
  "type": "Feature",
  "properties": {
    "addr:full":"114 Uphill Rd Dubois WY 82513",
    "addr:housenumber":"114",
    "addr:postcode":"82513",
    "addr:street":"Uphill Rd Dubois Wy",
    "iso:country":"US",
    "sg:address":"114 Uphill Rd",
    "sg:city":"Dubois",
    "sg:classifiers":[
        {
            "category":"Health Services",
            "subcategory":"Clinic",
            "type":"Services"
        },
        {
            "category":"Social Services",
            "type":"Services"
        }
    ],
    "sg:phone":"+1 307 455 4090",
    "sg:postcode":"82513",
    "sg:province":"WY",
    "sg:tags":[
        "instruction",
        "care"
    ],
    "wof:name":"Limberpine Associates Inc",
    "wof:placetype":"venue"
},
  "geometry": {"coordinates":[-109.765625,43.575367],"type":"Point"}
}