{
  "type": "Feature",
  "properties": {
    "iso:country":"US",
    "sg:address":"2113 Main St",
    "sg:city":"Torrington",
    "sg:classifiers":[
        {
            "category":"Coffee & Tea",
            "type":"Food & Drink"
        },
        {
            "category":"Bakery",
            "type":"Food & Drink"
        },
        {
            "category":"Donuts",
            "type":"Food & Drink"
        }
    ],
    "sg:menulink":"http://www.allmenus.com/wy/torrington/231010-daylight-donuts/menu/",
    "sg:phone":"+1 307 532 4840",
    "sg:postcode":"82240",
    "sg:province":"WY",
    "sg:tags":[
        "american",
        "pastry"
    ],
    "wof:name":"Daylight Donuts",
    "wof:placetype":"venue"
},
  "geometry": {"coordinates":[-104.184375,42.065156],"type":"Point"}
}