{
  "type": "Feature",
  "properties": {
    "iso:country":"US",
    "sg:address":"33 Rd 3Ng",
    "sg:city":"Meeteetse",
    "sg:classifiers":[
        {
            "category":"Farming",
            "subcategory":"Livestock Farm",
            "type":"Manufacturing & Wholesale Goods"
        }
    ],
    "sg:phone":"+1 307 868 2443",
    "sg:postcode":"82433",
    "sg:province":"WY",
    "sg:tags":[
        "ranch",
        "beef",
        "feedlot",
        "cattle"
    ],
    "wof:name":"Sleeper Ranch",
    "wof:placetype":"venue"
},
  "geometry": {"coordinates":[-108.789294,44.262526],"type":"Point"}
}