{
  "type": "Feature",
  "properties": {
    "iso:country":"US",
    "sg:address":"828 Mountain Vw",
    "sg:city":"Lander",
    "sg:classifiers":[
        {
            "category":"Health Services",
            "subcategory":"Clinic",
            "type":"Services"
        }
    ],
    "sg:phone":"+1 307 332 2150",
    "sg:postcode":"82520",
    "sg:province":"WY",
    "wof:name":"Community Entry Services",
    "wof:placetype":"venue"
},
  "geometry": {"coordinates":[-108.74720600000001,42.82529],"type":"Point"}
}