{
  "type": "Feature",
  "properties": {
    "addr:full":"308 US Hwy 189 Kemmerer WY 83101",
    "addr:housenumber":"308",
    "addr:postcode":"83101",
    "addr:street":"Us Hwy 189 Kemmerer Wy",
    "iso:country":"US",
    "sg:address":"308 US Hwy 189",
    "sg:city":"Kemmerer",
    "sg:classifiers":[
        {
            "category":"Government",
            "subcategory":"Office",
            "type":"Public Place"
        }
    ],
    "sg:phone":"+1 307 877 4415",
    "sg:postcode":"83101",
    "sg:province":"WY",
    "sg:tags":[
        "federal",
        "program"
    ],
    "wof:name":"US Agricultural Dept",
    "wof:placetype":"venue"
},
  "geometry": {"coordinates":[-110.53538,41.805569],"type":"Point"}
}