{
  "type": "Feature",
  "properties": {
    "addr:full":"71 25th St Wheatland WY 82201",
    "addr:housenumber":"71",
    "addr:postcode":"82201",
    "addr:street":"25Th St Wheatland Wy",
    "iso:country":"US",
    "sg:address":"71 25th St",
    "sg:city":"Wheatland",
    "sg:classifiers":[
        {
            "category":"Freight",
            "type":"Transportation"
        },
        {
            "category":"Wholesale",
            "subcategory":"Farm Supplies",
            "type":"Manufacturing & Wholesale Goods"
        }
    ],
    "sg:phone":"+1 307 322 4565",
    "sg:postcode":"82201",
    "sg:province":"WY",
    "sg:tags":[
        "operator",
        "local",
        "trucking"
    ],
    "wof:name":"Flying S Transportation",
    "wof:placetype":"venue"
},
  "geometry": {"coordinates":[-104.97621100000001,42.046372],"type":"Point"}
}