{
  "type": "Feature",
  "properties": {
    "iso:country":"US",
    "sg:address":"6946 Big Horn Ave",
    "sg:city":"Sheridan",
    "sg:phone":"+1 307 673 4795",
    "sg:postcode":"82801",
    "sg:province":"WY",
    "sg:tags":[
        "farm",
        "grain",
        "cash"
    ],
    "wof:name":"Max Flax Inc",
    "wof:placetype":"venue"
},
  "geometry": {"coordinates":[-106.96268499999999,44.721865],"type":"Point"}
}