{
  "type": "Feature",
  "properties": {
    "iso:country":"US",
    "sg:address":"852 Pine St",
    "sg:city":"Wheatland",
    "sg:classifiers":[
        {
            "category":"Building & Trades",
            "subcategory":"Construction",
            "type":"Services"
        }
    ],
    "sg:phone":"+1 307 322 3832",
    "sg:postcode":"82201",
    "sg:province":"WY",
    "sg:tags":[
        "excavation",
        "contractor"
    ],
    "wof:name":"Willcuts Backhoe Service",
    "wof:placetype":"venue"
},
  "geometry": {"coordinates":[-104.952494,42.057185],"type":"Point"}
}