{
  "type": "Feature",
  "properties": {
    "addr:full":"1305 State Hwy 239 Freedom WY 83120",
    "addr:housenumber":"1305",
    "addr:postcode":"83120",
    "addr:street":"State Hwy 239 Freedom Wy",
    "iso:country":"US",
    "sg:address":"1305 State Hwy 239",
    "sg:city":"Freedom",
    "sg:classifiers":[
        {
            "category":"Personal",
            "subcategory":"Beauty Salon",
            "type":"Services"
        }
    ],
    "sg:phone":"+1 307 883 2649",
    "sg:postcode":"83120",
    "sg:province":"WY",
    "wof:name":"Hair Boutique",
    "wof:placetype":"venue"
},
  "geometry": {"coordinates":[-111.026777,42.982447],"type":"Point"}
}