{
  "type": "Feature",
  "properties": {
    "addr:full":"1850 N 3rd St Laramie WY 82072",
    "addr:housenumber":"1850",
    "addr:postcode":"82072",
    "addr:street":"N 3Rd St",
    "iso:country":"US",
    "sg:address":"1850 N 3rd St",
    "sg:city":"Laramie",
    "sg:classifiers":[
        {
            "category":"Retail",
            "subcategory":"Auto Repair",
            "type":"Services"
        }
    ],
    "sg:phone":"+1 307 742 0264",
    "sg:postcode":"82072",
    "sg:province":"WY",
    "sg:tags":[
        "automotive"
    ],
    "wof:name":"Aaarms Inc",
    "wof:placetype":"venue"
},
  "geometry": {"coordinates":[-105.59179399999999,41.328757],"type":"Point"}
}