{
  "type": "Feature",
  "properties": {
    "iso:country":"US",
    "sg:address":"157 State Hwy 24",
    "sg:city":"Devils Tower",
    "sg:classifiers":[
        {
            "category":"Recreation",
            "type":"Entertainment"
        }
    ],
    "sg:phone":"+1 307 756 9470",
    "sg:postcode":"82714",
    "sg:province":"WY",
    "sg:tags":[
        "guide"
    ],
    "wof:name":"Above Ouray Ice & Devil Tower",
    "wof:placetype":"venue"
},
  "geometry": {"coordinates":[-104.680717,44.534161],"type":"Point"}
}