{
  "type": "Feature",
  "properties": {
    "iso:country":"US",
    "sg:address":"1754 Custer Ave",
    "sg:city":"Casper",
    "sg:classifiers":[
        {
            "category":"Manufacturing",
            "subcategory":"Petroleum Products",
            "type":"Manufacturing & Wholesale Goods"
        }
    ],
    "sg:phone":"+1 307 234 2350",
    "sg:postcode":"82604",
    "sg:province":"WY",
    "sg:tags":[
        "refiner"
    ],
    "wof:name":"Valve Tech & Services Inc",
    "wof:placetype":"venue"
},
  "geometry": {"coordinates":[-106.356345,42.833687],"type":"Point"}
}