{
  "type": "Feature",
  "properties": {
    "iso:country":"US",
    "sg:address":"615 Hamilton St",
    "sg:city":"Douglas",
    "sg:classifiers":[
        {
            "category":"Education",
            "subcategory":"School",
            "type":"Public Place"
        }
    ],
    "sg:phone":"+1 307 358 2942",
    "sg:postcode":"82633",
    "sg:province":"WY",
    "sg:website":"www.ccsd1.k12.wy.us",
    "wof:name":"Converse County Sch Dist #1",
    "wof:placetype":"venue"
},
  "geometry": {"coordinates":[-105.379355,42.751149],"type":"Point"}
}