{
  "type": "Feature",
  "properties": {
    "iso:country":"US",
    "sg:address":"860 College View Dr",
    "sg:city":"Riverton",
    "sg:classifiers":[
        {
            "category":"Manufacturing",
            "subcategory":"Tools & Machinery",
            "type":"Manufacturing & Wholesale Goods"
        }
    ],
    "sg:phone":"+1 307 856 4821",
    "sg:postcode":"82501",
    "sg:province":"WY",
    "sg:tags":[
        "equipment",
        "peripheral",
        "computer",
        "calculating",
        "mfg"
    ],
    "wof:name":"D H Print",
    "wof:placetype":"venue"
},
  "geometry": {"coordinates":[-108.42034200000001,43.030537],"type":"Point"}
}