{
  "type": "Feature",
  "properties": {
    "addr:full":"521 E 1st St Cheyenne WY 82007",
    "addr:housenumber":"521",
    "addr:postcode":"82007",
    "addr:street":"E 1St St",
    "iso:country":"US",
    "sg:address":"521 E 1st St",
    "sg:city":"Cheyenne",
    "sg:classifiers":[
        {
            "category":"Retail",
            "subcategory":"Auto Repair",
            "type":"Services"
        }
    ],
    "sg:phone":"+1 307 634 7999",
    "sg:postcode":"82007",
    "sg:province":"WY",
    "sg:tags":[
        "wrecker"
    ],
    "wof:name":"D & S Towing & Recovery",
    "wof:placetype":"venue"
},
  "geometry": {"coordinates":[-104.800096,41.121784],"type":"Point"}
}