{
  "type": "Feature",
  "properties": {
    "addr:full":"5305 Liberty St Cheyenne WY 82001",
    "addr:housenumber":"5305",
    "addr:postcode":"82001",
    "addr:street":"Liberty St",
    "iso:country":"US",
    "sg:address":"5305 Liberty St",
    "sg:city":"Cheyenne",
    "sg:classifiers":[
        {
            "category":"Social Services",
            "subcategory":"Child Care",
            "type":"Services"
        }
    ],
    "sg:phone":"+1 307 778 9874",
    "sg:postcode":"82001",
    "sg:province":"WY",
    "wof:name":"Discovery World Inc",
    "wof:placetype":"venue"
},
  "geometry": {"coordinates":[-104.744033,41.157403],"type":"Point"}
}