{
  "type": "Feature",
  "properties": {
    "addr:full":"104 S Wolcott St Casper WY 82601",
    "addr:housenumber":"104",
    "addr:postcode":"82601",
    "addr:street":"S Wolcott St",
    "iso:country":"US",
    "sg:address":"104 S Wolcott St",
    "sg:city":"Casper",
    "sg:classifiers":[
        {
            "category":"Mining & Drilling",
            "type":"Manufacturing & Wholesale Goods"
        }
    ],
    "sg:phone":"+1 307 265 4812",
    "sg:postcode":"82601",
    "sg:province":"WY",
    "sg:tags":[
        "development",
        "gas",
        "oil",
        "exploration"
    ],
    "wof:name":"Laramide LLC",
    "wof:placetype":"venue"
},
  "geometry": {"coordinates":[-106.323835,42.848776],"type":"Point"}
}