{
  "type": "Feature",
  "properties": {
    "addr:full":"847 N Main St Sheridan WY 82801",
    "addr:housenumber":"847",
    "addr:postcode":"82801",
    "addr:street":"N Main St",
    "iso:country":"US",
    "sg:address":"847 N Main St",
    "sg:city":"Sheridan",
    "sg:classifiers":[
        {
            "category":"Retail",
            "subcategory":"Auto Repair",
            "type":"Services"
        }
    ],
    "sg:phone":"+1 307 672 5700",
    "sg:postcode":"82801",
    "sg:province":"WY",
    "sg:tags":[
        "exhaust"
    ],
    "wof:name":"Custom Muffler & Accessories",
    "wof:placetype":"venue"
},
  "geometry": {"coordinates":[-106.955562,44.806365],"type":"Point"}
}