{
  "type": "Feature",
  "properties": {
    "iso:country":"US",
    "sg:address":"57 Antelope Gap Rd",
    "sg:city":"Wheatland",
    "sg:classifiers":[
        {
            "category":"Government",
            "subcategory":"Office",
            "type":"Public Place"
        }
    ],
    "sg:phone":"+1 307 322 3667",
    "sg:postcode":"82201",
    "sg:province":"WY",
    "wof:name":"Platte County Co-Op Extension",
    "wof:placetype":"venue"
},
  "geometry": {"coordinates":[-104.94422,42.05301],"type":"Point"}
}