{
  "type": "Feature",
  "properties": {
    "addr:full":"704 W Buffalo St Rawlins WY 82301",
    "addr:housenumber":"704",
    "addr:postcode":"82301",
    "addr:street":"W Buffalo St",
    "iso:country":"US",
    "sg:address":"704 W Buffalo St",
    "sg:city":"Rawlins",
    "sg:classifiers":[
        {
            "category":"Shopping",
            "subcategory":"Gifts & Souvenirs",
            "type":"Retail Goods"
        }
    ],
    "sg:phone":"+1 307 324 9383",
    "sg:postcode":"82301",
    "sg:province":"WY",
    "sg:tags":[
        "apparel",
        "wedding",
        "flower",
        "novelty",
        "accessory"
    ],
    "wof:name":"Downes Etc",
    "wof:placetype":"venue"
},
  "geometry": {"coordinates":[-107.242875,41.787947],"type":"Point"}
}