{
  "type": "Feature",
  "properties": {
    "iso:country":"US",
    "sg:address":"1902 Thomes Ave",
    "sg:city":"Cheyenne",
    "sg:classifiers":[
        {
            "category":"Real Estate",
            "subcategory":"Real Estate Agent",
            "type":"Services"
        }
    ],
    "sg:phone":"+1 307 634 5282",
    "sg:postcode":"82001",
    "sg:province":"WY",
    "wof:name":"Shamrock Realty",
    "wof:placetype":"venue"
},
  "geometry": {"coordinates":[-104.82101,41.134991],"type":"Point"}
}