{
  "type": "Feature",
  "properties": {
    "iso:country":"US",
    "sg:address":"1220 W Fresno Dr",
    "sg:city":"Jackson",
    "sg:classifiers":[
        {
            "category":"Home & Garden",
            "subcategory":"Building Materials",
            "type":"Retail Goods"
        }
    ],
    "sg:phone":"+1 307 733 0860",
    "sg:postcode":"83001",
    "sg:province":"WY",
    "sg:tags":[
        "door"
    ],
    "wof:name":"Gould's Garage Doors",
    "wof:placetype":"venue"
},
  "geometry": {"coordinates":[-110.786974,43.433302],"type":"Point"}
}