{
  "type": "Feature",
  "properties": {
    "addr:full":"514 Northridge Dr Riverton WY 82501",
    "addr:housenumber":"514",
    "addr:postcode":"82501",
    "addr:street":"Northridge Dr",
    "iso:country":"US",
    "sg:address":"514 Northridge Dr",
    "sg:city":"Riverton",
    "sg:classifiers":[
        {
            "category":"Professional",
            "subcategory":"Business Services",
            "type":"Services"
        },
        {
            "category":"Building & Trades",
            "subcategory":"Construction",
            "type":"Services"
        }
    ],
    "sg:phone":"+1 307 857 3832",
    "sg:postcode":"82501",
    "sg:province":"WY",
    "sg:tags":[
        "contractor"
    ],
    "wof:name":"Chris' Contracting",
    "wof:placetype":"venue"
},
  "geometry": {"coordinates":[-108.385244,43.035711],"type":"Point"}
}