{
  "type": "Feature",
  "properties": {
    "addr:full":"130 S Brooks St Sheridan WY 82801",
    "addr:housenumber":"130",
    "addr:postcode":"82801",
    "addr:street":"S Brooks St",
    "iso:country":"US",
    "sg:address":"130 S Brooks St",
    "sg:city":"Sheridan",
    "sg:classifiers":[
        {
            "category":"Insurance",
            "subcategory":"Insurance Agent",
            "type":"Services"
        }
    ],
    "sg:phone":"+1 307 672 2323",
    "sg:postcode":"82801",
    "sg:province":"WY",
    "wof:name":"Farmers Insurance Group",
    "wof:placetype":"venue"
},
  "geometry": {"coordinates":[-106.957257,44.796098],"type":"Point"}
}