{
  "type": "Feature",
  "properties": {
    "addr:full":"731 C St Rock Springs WY 82901",
    "addr:housenumber":"731",
    "addr:postcode":"82901",
    "addr:street":"C St Rock Springs Wy",
    "iso:country":"US",
    "sg:address":"731 C St",
    "sg:city":"Rock Springs",
    "sg:classifiers":[
        {
            "category":"Government",
            "subcategory":"Court House",
            "type":"Public Place"
        }
    ],
    "sg:phone":"+1 307 352 6817",
    "sg:postcode":"82901",
    "sg:province":"WY",
    "sg:tags":[
        "county"
    ],
    "wof:name":"County Court",
    "wof:placetype":"venue"
},
  "geometry": {"coordinates":[-109.215585,41.580506],"type":"Point"}
}