{
  "type": "Feature",
  "properties": {
    "iso:country":"US",
    "sg:address":"526 S Regency Dr",
    "sg:city":"Laramie",
    "sg:classifiers":[
        {
            "category":"Professional",
            "subcategory":"Lawyer & Legal Services",
            "type":"Services"
        }
    ],
    "sg:phone":"+1 307 745 8440",
    "sg:postcode":"82070",
    "sg:province":"WY",
    "wof:name":"Petroski Mary Attorney At Law",
    "wof:placetype":"venue"
},
  "geometry": {"coordinates":[-105.54668100000001,41.306131],"type":"Point"}
}