{
  "type": "Feature",
  "properties": {
    "addr:full":"57 Dutch Ed Ln Lander WY 82520",
    "addr:housenumber":"57",
    "addr:postcode":"wy 82520",
    "addr:street":"Dutch Ed Ln",
    "iso:country":"US",
    "sg:address":"57 Dutch Ed Ln",
    "sg:city":"Lander",
    "sg:classifiers":[
        {
            "category":"Building & Trades",
            "subcategory":"Construction",
            "type":"Services"
        }
    ],
    "sg:phone":"+1 307 332 2093",
    "sg:postcode":"82520",
    "sg:province":"WY",
    "sg:tags":[
        "excavating",
        "contractor"
    ],
    "wof:name":"Sinks Canyon Inc",
    "wof:placetype":"venue"
},
  "geometry": {"coordinates":[-108.71545999999999,42.857499],"type":"Point"}
}