{
  "type": "Feature",
  "properties": {
    "addr:full":"371 Main St Lander WY 82520",
    "addr:housenumber":"371",
    "addr:postcode":"wy 82520",
    "addr:street":"Main St",
    "iso:country":"US",
    "sg:address":"371 Main St",
    "sg:city":"Lander",
    "sg:classifiers":[
        {
            "category":"Shopping",
            "type":"Retail Goods"
        }
    ],
    "sg:phone":"+1 307 335 7015",
    "sg:postcode":"82520",
    "sg:province":"WY",
    "sg:tags":[
        "merchandise"
    ],
    "wof:name":"McRaes Downtown",
    "wof:placetype":"venue"
},
  "geometry": {"coordinates":[-108.732654,42.833349],"type":"Point"}
}