{
  "type": "Feature",
  "properties": {
    "addr:full":"370 S Bypass Rd Buffalo WY 82834",
    "addr:housenumber":"370",
    "addr:postcode":"82834",
    "addr:street":"S Bypass Rd Buffalo Wy",
    "iso:country":"US",
    "sg:address":"370 S Bypass Rd",
    "sg:city":"Buffalo",
    "sg:classifiers":[
        {
            "category":"Home & Garden",
            "subcategory":"Building Materials",
            "type":"Retail Goods"
        }
    ],
    "sg:phone":"+1 307 684 2231",
    "sg:postcode":"82834",
    "sg:province":"WY",
    "sg:tags":[
        "lumber"
    ],
    "wof:name":"Buckingham Lumber Co",
    "wof:placetype":"venue"
},
  "geometry": {"coordinates":[-106.689911,44.353528],"type":"Point"}
}