{
  "type": "Feature",
  "properties": {
    "addr:full":"1639 Dell Range Blvd Cheyenne WY 82009",
    "addr:housenumber":"1639",
    "addr:postcode":"82009",
    "addr:street":"Dell Range Blvd",
    "iso:country":"US",
    "sg:address":"1639 Dell Range Blvd",
    "sg:city":"Cheyenne",
    "sg:classifiers":[
        {
            "category":"Shopping",
            "type":"Retail Goods"
        }
    ],
    "sg:phone":"+1 307 634 7318",
    "sg:postcode":"82009",
    "sg:province":"WY",
    "sg:tags":[
        "related",
        "sauna",
        "equipment",
        "spa",
        "tub",
        "jetted"
    ],
    "wof:name":"Global Wholesale Distributors",
    "wof:placetype":"venue"
},
  "geometry": {"coordinates":[-104.801429,41.160213],"type":"Point"}
}