{
  "type": "Feature",
  "properties": {
    "iso:country":"US",
    "sg:address":"10421 State Hwy 789",
    "sg:city":"Riverton",
    "sg:classifiers":[
        {
            "category":"Building & Trades",
            "subcategory":"Construction",
            "type":"Services"
        }
    ],
    "sg:phone":"+1 307 857 2944",
    "sg:postcode":"82501",
    "sg:province":"WY",
    "sg:tags":[
        "excavation",
        "contractor"
    ],
    "wof:name":"Welhouse Construction",
    "wof:placetype":"venue"
},
  "geometry": {"coordinates":[-108.378945,43.004838],"type":"Point"}
}