{
  "type": "Feature",
  "properties": {
    "addr:full":"2633 E D St Torrington WY 82240",
    "addr:housenumber":"2633",
    "addr:postcode":"82240",
    "addr:street":"E D St",
    "iso:country":"US",
    "sg:address":"2633 E D St",
    "sg:city":"Torrington",
    "sg:classifiers":[
        {
            "category":"Retail",
            "subcategory":"Laundry & Dry Cleaning",
            "type":"Services"
        }
    ],
    "sg:phone":"+1 307 532 7433",
    "sg:postcode":"82240",
    "sg:province":"WY",
    "sg:tags":[
        "cleaners",
        "restoration",
        "rug",
        "carpet"
    ],
    "wof:name":"Steve's Carpet Care Plus",
    "wof:placetype":"venue"
},
  "geometry": {"coordinates":[-104.179041,42.070938],"type":"Point"}
}