{
  "type": "Feature",
  "properties": {
    "iso:country":"US",
    "sg:address":"112 E Arapahoe St",
    "sg:city":"Thermopolis",
    "sg:classifiers":[
        {
            "category":"Health Services",
            "subcategory":"Doctor",
            "type":"Services"
        }
    ],
    "sg:phone":"+1 307 864 2141",
    "sg:postcode":"82443",
    "sg:province":"WY",
    "sg:tags":[
        "physician",
        "surgeon"
    ],
    "wof:name":"Vernon W Miller MD",
    "wof:placetype":"venue"
},
  "geometry": {"coordinates":[-108.19838,43.647503],"type":"Point"}
}