{
  "type": "Feature",
  "properties": {
    "addr:full":"4515 E Lincolnway Cheyenne WY 82001",
    "addr:housenumber":"4515",
    "addr:postcode":"82001",
    "addr:street":"E Lincolnway;Wy",
    "iso:country":"US",
    "sg:address":"4515 E Lincolnway",
    "sg:city":"Cheyenne",
    "sg:classifiers":[
        {
            "category":"Banks & Credit Unions",
            "subcategory":"Bank",
            "type":"Services"
        }
    ],
    "sg:phone":"+1 307 638 1801",
    "sg:postcode":"82001",
    "sg:province":"WY",
    "sg:tags":[
        "loan",
        "real estate"
    ],
    "wof:name":"American Home Mortgage",
    "wof:placetype":"venue"
},
  "geometry": {"coordinates":[-104.756157,41.14513],"type":"Point"}
}