{
  "type": "Feature",
  "properties": {
    "addr:full":"377 Hightower Rd Wheatland WY 82201",
    "addr:housenumber":"377",
    "addr:postcode":"82201",
    "addr:street":"Hightower Rd Wheatland Wy",
    "iso:country":"US",
    "sg:address":"377 Hightower Rd",
    "sg:city":"Wheatland",
    "sg:classifiers":[
        {
            "category":"Farming",
            "subcategory":"Livestock Farm",
            "type":"Manufacturing & Wholesale Goods"
        }
    ],
    "sg:phone":"+1 307 322 3812",
    "sg:postcode":"82201",
    "sg:province":"WY",
    "sg:tags":[
        "ranch",
        "cattle"
    ],
    "wof:name":"True Ranches",
    "wof:placetype":"venue"
},
  "geometry": {"coordinates":[-105.02123,42.06025],"type":"Point"}
}