{
  "type": "Feature",
  "properties": {
    "iso:country":"US",
    "sg:address":"1998 Oilfield Center Rd",
    "sg:city":"Casper",
    "sg:classifiers":[
        {
            "category":"Autos & Motor Vehicles",
            "subcategory":"Automobile Sales",
            "type":"Retail Goods"
        }
    ],
    "sg:phone":"+1 307 234 4118",
    "sg:postcode":"82604",
    "sg:province":"WY",
    "sg:tags":[
        "car",
        "dealer"
    ],
    "wof:name":"Klode Auto",
    "wof:placetype":"venue"
},
  "geometry": {"coordinates":[-106.42722000000001,42.873619],"type":"Point"}
}