{
  "type": "Feature",
  "properties": {
    "iso:country":"US",
    "sg:address":"2425 Sky View Ln",
    "sg:city":"Laramie",
    "sg:classifiers":[
        {
            "category":"Health Services",
            "subcategory":"Clinic",
            "type":"Services"
        }
    ],
    "sg:phone":"+1 307 742 5675",
    "sg:postcode":"82070",
    "sg:province":"WY",
    "wof:name":"Healthy Mothers Healthy B",
    "wof:placetype":"venue"
},
  "geometry": {"coordinates":[-105.522424,41.294421],"type":"Point"}
}