{
  "type": "Feature",
  "properties": {
    "addr:full":"5940 S Cedar St Casper WY 82601",
    "addr:housenumber":"5940",
    "addr:postcode":"82601",
    "addr:street":"S Cedar St",
    "iso:country":"US",
    "sg:address":"5940 S Cedar St",
    "sg:city":"Casper",
    "sg:classifiers":[
        {
            "category":"Shopping",
            "type":"Retail Goods"
        }
    ],
    "sg:phone":"+1 307 234 2453",
    "sg:postcode":"82601",
    "sg:province":"WY",
    "sg:tags":[
        "merchandise"
    ],
    "wof:name":"Creative Arts",
    "wof:placetype":"venue"
},
  "geometry": {"coordinates":[-106.34289699999999,42.79593],"type":"Point"}
}