{
  "type": "Feature",
  "properties": {
    "addr:full":"800 E 20th St Cheyenne WY 82001",
    "addr:housenumber":"800",
    "addr:postcode":"82001",
    "addr:street":"E 20Th St",
    "iso:country":"US",
    "sg:address":"800 E 20th St",
    "sg:city":"Cheyenne",
    "sg:classifiers":[
        {
            "category":"Professional",
            "subcategory":"Accounting & Tax Preparation",
            "type":"Services"
        }
    ],
    "sg:phone":"+1 307 635 3703",
    "sg:postcode":"82001",
    "sg:province":"WY",
    "sg:tags":[
        "billing"
    ],
    "wof:name":"Center For Medical Billing",
    "wof:placetype":"venue"
},
  "geometry": {"coordinates":[-104.807502,41.140024],"type":"Point"}
}