{
  "type": "Feature",
  "properties": {
    "iso:country":"US",
    "sg:address":"1214 W Collins Dr",
    "sg:city":"Casper",
    "sg:classifiers":[
        {
            "category":"Professional",
            "subcategory":"Business Services",
            "type":"Services"
        },
        {
            "category":"Home & Garden",
            "subcategory":"Home Furnishings",
            "type":"Retail Goods"
        }
    ],
    "sg:phone":"+1 307 234 2210",
    "sg:postcode":"82604",
    "sg:province":"WY",
    "sg:tags":[
        "consultant",
        "window",
        "design",
        "decorator",
        "interior",
        "curtain",
        "drapery"
    ],
    "wof:name":"Window & Wall Gallery Inc",
    "wof:placetype":"venue"
},
  "geometry": {"coordinates":[-106.34005399999999,42.840513],"type":"Point"}
}