{
  "type": "Feature",
  "properties": {
    "iso:country":"US",
    "sg:address":"2417 E 15th St",
    "sg:city":"Casper",
    "sg:classifiers":[
        {
            "category":"Social Services",
            "type":"Services"
        }
    ],
    "sg:phone":"+1 307 234 3638",
    "sg:postcode":"82609",
    "sg:province":"WY",
    "sg:tags":[
        "counselor",
        "marriage",
        "family"
    ],
    "wof:name":"Kerry Derrick",
    "wof:placetype":"venue"
},
  "geometry": {"coordinates":[-106.29427699999999,42.835262],"type":"Point"}
}