{
  "type": "Feature",
  "properties": {
    "iso:country":"US",
    "sg:address":"1739 S Chestnut St",
    "sg:city":"Casper",
    "sg:classifiers":[
        {
            "category":"Professional",
            "subcategory":"Engineering",
            "type":"Services"
        }
    ],
    "sg:phone":"+1 307 266 1482",
    "sg:postcode":"82601",
    "sg:province":"WY",
    "sg:tags":[
        "engineer"
    ],
    "wof:name":"John W Ake PE",
    "wof:placetype":"venue"
},
  "geometry": {"coordinates":[-106.334456,42.831926],"type":"Point"}
}