{
  "type": "Feature",
  "properties": {
    "iso:country":"US",
    "sg:address":"1108 Main St",
    "sg:city":"Torrington",
    "sg:classifiers":[
        {
            "category":"Autos & Motor Vehicles",
            "subcategory":"Auto Supplies",
            "type":"Retail Goods"
        }
    ],
    "sg:phone":"+1 307 532 4141",
    "sg:postcode":"82240",
    "sg:province":"WY",
    "sg:tags":[
        "tire"
    ],
    "wof:name":"Olson Tire Co",
    "wof:placetype":"venue"
},
  "geometry": {"coordinates":[-104.18443000000001,42.058204],"type":"Point"}
}