{
  "type": "Feature",
  "properties": {
    "iso:country":"US",
    "sg:address":"1935 N Loop Ave",
    "sg:city":"Casper",
    "sg:classifiers":[
        {
            "category":"Freight",
            "type":"Transportation"
        }
    ],
    "sg:phone":"+1 307 472 0882",
    "sg:postcode":"82601",
    "sg:province":"WY",
    "sg:tags":[
        "operator",
        "local",
        "trucking"
    ],
    "wof:name":"Air Ride Trucking LLC",
    "wof:placetype":"venue"
},
  "geometry": {"coordinates":[-106.347774,42.873415],"type":"Point"}
}