{
  "type": "Feature",
  "properties": {
    "iso:country":"US",
    "sg:address":"1025 Ln 2",
    "sg:city":"Worland",
    "sg:classifiers":[
        {
            "category":"Mining & Drilling",
            "type":"Manufacturing & Wholesale Goods"
        }
    ],
    "sg:phone":"+1 307 347 6156",
    "sg:postcode":"82401",
    "sg:province":"WY",
    "wof:name":"Black Hills Bentonite Co",
    "wof:placetype":"venue"
},
  "geometry": {"coordinates":[-107.923659,44.153766],"type":"Point"}
}