{
  "type": "Feature",
  "properties": {
    "iso:country":"US",
    "sg:address":"3903 Snyder Ave",
    "sg:city":"Cheyenne",
    "sg:classifiers":[
        {
            "category":"Professional",
            "subcategory":"Computer Services",
            "type":"Services"
        }
    ],
    "sg:phone":"+1 307 772 0446",
    "sg:postcode":"82001",
    "sg:province":"WY",
    "sg:tags":[
        "related"
    ],
    "wof:name":"Johnlushnet Inc",
    "wof:placetype":"venue"
},
  "geometry": {"coordinates":[-104.831222,41.153226],"type":"Point"}
}