{
  "type": "Feature",
  "properties": {
    "addr:full":"203 N Main St Burns WY 82053",
    "addr:housenumber":"203",
    "addr:postcode":"82053",
    "addr:street":"N Main St Burns Wy",
    "iso:country":"US",
    "sg:address":"203 N Main St",
    "sg:city":"Burns",
    "sg:classifiers":[
        {
            "category":"Insurance",
            "subcategory":"Insurance Agent",
            "type":"Services"
        }
    ],
    "sg:phone":"+1 307 547 3571",
    "sg:postcode":"82053",
    "sg:province":"WY",
    "sg:website":"www.afsonline.net",
    "wof:name":"Burns Insurance",
    "wof:placetype":"venue"
},
  "geometry": {"coordinates":[-104.358853,41.192896],"type":"Point"}
}