{
  "type": "Feature",
  "properties": {
    "addr:full":"432 W Pine St Pinedale WY 82941",
    "addr:housenumber":"432",
    "addr:postcode":"82941",
    "addr:street":"W Pine St",
    "iso:country":"US",
    "sg:address":"432 W Pine St",
    "sg:city":"Pinedale",
    "sg:classifiers":[
        {
            "category":"Real Estate",
            "subcategory":"Real Estate Agent",
            "type":"Services"
        }
    ],
    "sg:phone":"+1 307 367 7653",
    "sg:postcode":"82941",
    "sg:province":"WY",
    "wof:name":"Hatch Real Estate",
    "wof:placetype":"venue"
},
  "geometry": {"coordinates":[-109.86562000000001,42.866512],"type":"Point"}
}