{
  "type": "Feature",
  "properties": {
    "iso:country":"US",
    "sg:address":"280 E Broadway",
    "sg:city":"Jackson",
    "sg:classifiers":[
        {
            "category":"Shopping",
            "subcategory":"Computers & Home Electronics",
            "type":"Retail Goods"
        }
    ],
    "sg:phone":"+1 307 733 1454",
    "sg:postcode":"83001",
    "sg:province":"WY",
    "sg:tags":[
        "software"
    ],
    "wof:name":"Gateway Information Resources",
    "wof:placetype":"venue"
},
  "geometry": {"coordinates":[-110.75758999999999,43.479535],"type":"Point"}
}