{
  "type": "Feature",
  "properties": {
    "addr:full":"445 Brubaker Ln Laramie WY 82070",
    "addr:housenumber":"445",
    "addr:postcode":"82070",
    "addr:street":"Brubaker Ln",
    "iso:country":"US",
    "sg:address":"445 Brubaker Ln",
    "sg:city":"Laramie",
    "sg:classifiers":[
        {
            "category":"Farming",
            "subcategory":"Livestock Farm",
            "type":"Manufacturing & Wholesale Goods"
        }
    ],
    "sg:phone":"+1 307 742 7421",
    "sg:postcode":"82070",
    "sg:province":"WY",
    "sg:tags":[
        "animal",
        "general"
    ],
    "wof:name":"Spiegelberg Ranch",
    "wof:placetype":"venue"
},
  "geometry": {"coordinates":[-105.76744600000001,41.150634],"type":"Point"}
}