{
  "type": "Feature",
  "properties": {
    "addr:full":"1909 Park Dr Douglas WY 82633",
    "addr:housenumber":"1909",
    "addr:postcode":"82633",
    "addr:street":"Park Dr Douglas Wy",
    "iso:country":"US",
    "sg:address":"1909 Park Dr",
    "sg:city":"Douglas",
    "sg:classifiers":[
        {
            "category":"Manufacturing",
            "subcategory":"Metals",
            "type":"Manufacturing & Wholesale Goods"
        }
    ],
    "sg:phone":"+1 307 358 6594",
    "sg:postcode":"82633",
    "sg:province":"WY",
    "sg:tags":[
        "abrasive",
        "product",
        "fabricated",
        "mfg"
    ],
    "wof:name":"Mitxelena Bronze",
    "wof:placetype":"venue"
},
  "geometry": {"coordinates":[-105.361048,42.745576],"type":"Point"}
}