{
  "type": "Feature",
  "properties": {
    "iso:country":"US",
    "sg:address":"321 Ln 40",
    "sg:city":"Burlington",
    "sg:classifiers":[
        {
            "category":"Farming",
            "subcategory":"Farm",
            "type":"Manufacturing & Wholesale Goods"
        }
    ],
    "sg:phone":"+1 307 762 3425",
    "sg:postcode":"82411",
    "sg:province":"WY",
    "wof:name":"L A Farms",
    "wof:placetype":"venue"
},
  "geometry": {"coordinates":[-108.52873599999999,44.417622],"type":"Point"}
}