{
  "type": "Feature",
  "properties": {
    "iso:country":"US",
    "sg:address":"302 Main St",
    "sg:city":"Lander",
    "sg:classifiers":[
        {
            "category":"Personal",
            "type":"Services"
        }
    ],
    "sg:phone":"+1 307 332 6961",
    "sg:postcode":"82520",
    "sg:province":"WY",
    "sg:tags":[
        "shop",
        "beauty"
    ],
    "wof:name":"Mane Attraction",
    "wof:placetype":"venue"
},
  "geometry": {"coordinates":[-108.731983,42.833304],"type":"Point"}
}