{
  "type": "Feature",
  "properties": {
    "iso:country":"US",
    "sg:address":"723 7th Ave",
    "sg:city":"Belle Fourche",
    "sg:classifiers":[
        {
            "category":"Building & Trades",
            "subcategory":"Plumbing",
            "type":"Services"
        }
    ],
    "sg:phone":"+1 605 723 3606",
    "sg:postcode":"57717",
    "sg:province":"WY",
    "sg:tags":[
        "contractor"
    ],
    "wof:name":"Air Doctor",
    "wof:placetype":"venue"
},
  "geometry": {"coordinates":[-103.850658,44.671206],"type":"Point"}
}