{
  "type": "Feature",
  "properties": {
    "iso:country":"US",
    "sg:address":"1027 S Bonnie Brae St",
    "sg:city":"Casper",
    "sg:classifiers":[
        {
            "category":"Professional",
            "subcategory":"Management & Consulting",
            "type":"Services"
        }
    ],
    "sg:phone":"+1 307 266 5618",
    "sg:postcode":"82601",
    "sg:province":"WY",
    "sg:tags":[
        "business"
    ],
    "wof:name":"Etmc",
    "wof:placetype":"venue"
},
  "geometry": {"coordinates":[-106.316427,42.83963],"type":"Point"}
}