{
  "type": "Feature",
  "properties": {
    "iso:country":"US",
    "sg:address":"1522 Depot Dr",
    "sg:city":"Cody",
    "sg:classifiers":[
        {
            "category":"Retail",
            "subcategory":"Repair Shop",
            "type":"Services"
        }
    ],
    "sg:phone":"+1 307 587 2469",
    "sg:postcode":"82414",
    "sg:province":"WY",
    "sg:tags":[
        "welding"
    ],
    "wof:name":"Dave's Welding",
    "wof:placetype":"venue"
},
  "geometry": {"coordinates":[-109.05638500000001,44.532389],"type":"Point"}
}