{
  "type": "Feature",
  "properties": {
    "addr:full":"103 E Monroe Ave Riverton WY 82501",
    "addr:housenumber":"103",
    "addr:postcode":"82501",
    "addr:street":"E Monroe Ave",
    "iso:country":"US",
    "sg:address":"103 E Monroe Ave",
    "sg:city":"Riverton",
    "sg:classifiers":[
        {
            "category":"Building & Trades",
            "subcategory":"Construction",
            "type":"Services"
        }
    ],
    "sg:phone":"+1 307 856 6481",
    "sg:postcode":"82501",
    "sg:province":"WY",
    "sg:tags":[
        "well",
        "drilling"
    ],
    "wof:name":"Barnhart Drilling Co",
    "wof:placetype":"venue"
},
  "geometry": {"coordinates":[-108.390562,43.019326],"type":"Point"}
}