{
  "type": "Feature",
  "properties": {
    "iso:country":"US",
    "sg:address":"805 E Richards St",
    "sg:city":"Douglas",
    "sg:classifiers":[
        {
            "category":"Shopping",
            "subcategory":"Florist",
            "type":"Retail Goods"
        }
    ],
    "sg:phone":"+1 307 358 9251",
    "sg:postcode":"82633",
    "sg:province":"WY",
    "wof:name":"A Fresh Attitude Floral",
    "wof:placetype":"venue"
},
  "geometry": {"coordinates":[-105.377415,42.748395],"type":"Point"}
}