{
  "type": "Feature",
  "properties": {
    "iso:country":"US",
    "sg:address":"10 Lost Wells Butte Dr",
    "sg:city":"Riverton",
    "sg:classifiers":[
        {
            "category":"Government",
            "subcategory":"Fire Station",
            "type":"Public Place"
        }
    ],
    "sg:phone":"+1 307 856 0730",
    "sg:postcode":"82501",
    "sg:province":"WY",
    "sg:tags":[
        "protection",
        "business"
    ],
    "wof:name":"Premont County Fire District",
    "wof:placetype":"venue"
},
  "geometry": {"coordinates":[-108.469408,43.117457],"type":"Point"}
}