{
  "type": "Feature",
  "properties": {
    "addr:full":"865 E 4th St Powell WY 82435",
    "addr:housenumber":"865",
    "addr:postcode":"82435",
    "addr:street":"E 4Th St Powell Wy",
    "iso:country":"US",
    "sg:address":"865 E 4th St",
    "sg:city":"Powell",
    "sg:classifiers":[
        {
            "category":"Home & Garden",
            "subcategory":"Building Materials",
            "type":"Retail Goods"
        }
    ],
    "sg:phone":"+1 307 754 2601",
    "sg:postcode":"82435",
    "sg:province":"WY",
    "sg:tags":[
        "door"
    ],
    "wof:name":"Curly's Overhead Doors",
    "wof:placetype":"venue"
},
  "geometry": {"coordinates":[-108.747214,44.756907],"type":"Point"}
}