{
  "type": "Feature",
  "properties": {
    "iso:country":"US",
    "sg:address":"130 S Brooks St",
    "sg:city":"Sheridan",
    "sg:classifiers":[
        {
            "category":"Manufacturing",
            "subcategory":"Buildings",
            "type":"Manufacturing & Wholesale Goods"
        }
    ],
    "sg:phone":"+1 307 672 6241",
    "sg:postcode":"82801",
    "sg:province":"WY",
    "sg:tags":[
        "home",
        "log",
        "cabin"
    ],
    "wof:name":"Banner Log Home Co",
    "wof:placetype":"venue"
},
  "geometry": {"coordinates":[-106.957257,44.796098],"type":"Point"}
}