{
  "type": "Feature",
  "properties": {
    "addr:full":"2156 US Hwy 310 Lovell WY 82431",
    "addr:housenumber":"2156",
    "addr:postcode":"82431",
    "addr:street":"Us Hwy 310 Lovell Wy",
    "iso:country":"US",
    "sg:address":"2156 US Hwy 310",
    "sg:city":"Lovell",
    "sg:classifiers":[
        {
            "category":"Manufacturing",
            "subcategory":"Chemicals & Compounds",
            "type":"Manufacturing & Wholesale Goods"
        },
        {
            "category":"Shopping",
            "subcategory":"Clothing, Apparel, & Fashions",
            "type":"Retail Goods"
        }
    ],
    "sg:phone":"+1 307 548 2348",
    "sg:postcode":"82431",
    "sg:province":"WY",
    "sg:tags":[
        "preparation",
        "mfg",
        "supply",
        "uniform"
    ],
    "wof:name":"Freedom Supply Company",
    "wof:placetype":"venue"
},
  "geometry": {"coordinates":[-108.37331399999999,44.831868],"type":"Point"}
}