{
  "type": "Feature",
  "properties": {
    "iso:country":"US",
    "sg:address":"101 N 4th St",
    "sg:city":"Douglas",
    "sg:classifiers":[
        {
            "category":"Government",
            "subcategory":"Police Station",
            "type":"Public Place"
        }
    ],
    "sg:phone":"+1 307 358 3311",
    "sg:postcode":"82633",
    "sg:province":"WY",
    "sg:tags":[
        "department"
    ],
    "wof:name":"Douglas Police Dept",
    "wof:placetype":"venue"
},
  "geometry": {"coordinates":[-105.38269,42.76087],"type":"Point"}
}