{
  "type": "Feature",
  "properties": {
    "addr:full":"1068 Rd 14 Powell WY 82435",
    "addr:housenumber":"1068",
    "addr:postcode":"82435",
    "addr:street":"Rd 14 Powell Wy",
    "iso:country":"US",
    "sg:address":"1068 Rd 14",
    "sg:city":"Powell",
    "sg:classifiers":[
        {
            "category":"Retail",
            "subcategory":"Repair Shop",
            "type":"Services"
        }
    ],
    "sg:phone":"+1 307 754 2890",
    "sg:postcode":"82435",
    "sg:province":"WY",
    "sg:tags":[
        "welding"
    ],
    "wof:name":"High Performance Welding",
    "wof:placetype":"venue"
},
  "geometry": {"coordinates":[-108.85568499999999,44.731723],"type":"Point"}
}