{
  "type": "Feature",
  "properties": {
    "iso:country":"US",
    "sg:address":"3284 State Hwy 34",
    "sg:city":"Wheatland",
    "sg:classifiers":[
        {
            "category":"Education",
            "subcategory":"School",
            "type":"Public Place"
        }
    ],
    "sg:phone":"+1 307 322 8139",
    "sg:postcode":"82201",
    "sg:province":"WY",
    "wof:name":"Siblee School",
    "wof:placetype":"venue"
},
  "geometry": {"coordinates":[-105.235665,41.827982],"type":"Point"}
}