{
  "type": "Feature",
  "properties": {
    "addr:full":"1315 State Hwy 116 Sundance WY 82729",
    "addr:housenumber":"1315",
    "addr:postcode":"82729",
    "addr:street":"State Hwy 116 Sundance Wy",
    "iso:country":"US",
    "sg:address":"1315 State Hwy 116",
    "sg:city":"Sundance",
    "sg:classifiers":[
        {
            "category":"Farming",
            "subcategory":"Livestock Farm",
            "type":"Manufacturing & Wholesale Goods"
        }
    ],
    "sg:phone":"+1 307 283 2352",
    "sg:postcode":"82729",
    "sg:province":"WY",
    "sg:tags":[
        "beef",
        "feedlot",
        "cattle"
    ],
    "wof:name":"Spring Creek Livestock",
    "wof:placetype":"venue"
},
  "geometry": {"coordinates":[-104.45133199999999,44.227614],"type":"Point"}
}