{
  "type": "Feature",
  "properties": {
    "iso:country":"US",
    "sg:address":"8 Stalnaker St",
    "sg:city":"Dubois",
    "sg:classifiers":[
        {
            "category":"Building & Trades",
            "subcategory":"Electrical",
            "type":"Services"
        }
    ],
    "sg:phone":"+1 307 455 3773",
    "sg:postcode":"82513",
    "sg:province":"WY",
    "sg:tags":[
        "electric",
        "contractor"
    ],
    "wof:name":"Pinnacle Electric",
    "wof:placetype":"venue"
},
  "geometry": {"coordinates":[-109.64469,43.535719],"type":"Point"}
}