{
  "type": "Feature",
  "properties": {
    "iso:country":"US",
    "sg:address":"816 Coburn Ave",
    "sg:city":"Worland",
    "sg:classifiers":[
        {
            "category":"Professional",
            "subcategory":"Lawyer & Legal Services",
            "type":"Services"
        }
    ],
    "sg:phone":"+1 307 347 6375",
    "sg:postcode":"82401",
    "sg:province":"WY",
    "sg:tags":[
        "attorney"
    ],
    "wof:name":"Rush Law Office",
    "wof:placetype":"venue"
},
  "geometry": {"coordinates":[-107.95830100000001,44.015704],"type":"Point"}
}