{
  "type": "Feature",
  "properties": {
    "iso:country":"US",
    "sg:address":"290 W Kelly Ave",
    "sg:city":"Jackson",
    "sg:classifiers":[
        {
            "category":"Social Services",
            "type":"Services"
        }
    ],
    "sg:phone":"+1 307 734 5352",
    "sg:postcode":"83001",
    "sg:province":"WY",
    "sg:tags":[
        "counselor",
        "marriage",
        "family"
    ],
    "wof:name":"Erica Burns",
    "wof:placetype":"venue"
},
  "geometry": {"coordinates":[-110.765557,43.47542],"type":"Point"}
}