{
  "type": "Feature",
  "properties": {
    "addr:full":"1108 14th St Cody WY 82414",
    "addr:housenumber":"1108",
    "addr:postcode":"82414",
    "addr:street":"14Th St",
    "iso:country":"US",
    "sg:address":"1108 14th St",
    "sg:city":"Cody",
    "sg:classifiers":[
        {
            "category":"Professional",
            "subcategory":"Business Services",
            "type":"Services"
        }
    ],
    "sg:phone":"+1 307 527 6980",
    "sg:postcode":"82414",
    "sg:province":"WY",
    "sg:tags":[
        "mail",
        "direct",
        "advertising"
    ],
    "wof:name":"UPS Stores The",
    "wof:placetype":"venue"
},
  "geometry": {"coordinates":[-109.060086,44.525957],"type":"Point"}
}