{
  "type": "Feature",
  "properties": {
    "iso:country":"US",
    "sg:address":"106 N Bent St",
    "sg:city":"Powell",
    "sg:classifiers":[
        {
            "category":"Utilities",
            "subcategory":"Mobile Phone",
            "type":"Services"
        }
    ],
    "sg:phone":"+1 307 754 9449",
    "sg:postcode":"82435",
    "sg:province":"WY",
    "sg:tags":[
        "telephone",
        "cellular"
    ],
    "wof:name":"Home Town Electronics",
    "wof:placetype":"venue"
},
  "geometry": {"coordinates":[-108.75767399999999,44.754096],"type":"Point"}
}