{
  "type": "Feature",
  "properties": {
    "iso:country":"US",
    "sg:address":"820 W Main St",
    "sg:city":"Riverton",
    "sg:classifiers":[
        {
            "category":"Recreation",
            "type":"Entertainment"
        }
    ],
    "sg:phone":"+1 307 857 4200",
    "sg:postcode":"82501",
    "sg:province":"WY",
    "sg:tags":[
        "amusement"
    ],
    "wof:name":"R & R Motor Sports",
    "wof:placetype":"venue"
},
  "geometry": {"coordinates":[-108.401236,43.024675],"type":"Point"}
}