{
  "type": "Feature",
  "properties": {
    "iso:country":"US",
    "sg:address":"12120 Poison Spider Rd",
    "sg:city":"Casper",
    "sg:classifiers":[
        {
            "category":"Professional",
            "subcategory":"Management & Consulting",
            "type":"Services"
        }
    ],
    "sg:phone":"+1 307 265 9296",
    "sg:postcode":"82644",
    "sg:province":"WY",
    "wof:name":"Mule Drilling",
    "wof:placetype":"venue"
},
  "geometry": {"coordinates":[-106.522442,42.852294],"type":"Point"}
}