{
  "type": "Feature",
  "properties": {
    "iso:country":"US",
    "sg:address":"800 E Lincoln St",
    "sg:city":"Gillette",
    "sg:classifiers":[
        {
            "category":"Professional",
            "subcategory":"Advertising",
            "type":"Services"
        },
        {
            "category":"Wholesale",
            "subcategory":"Non-durable Goods",
            "type":"Manufacturing & Wholesale Goods"
        }
    ],
    "sg:phone":"+1 307 686 1120",
    "sg:postcode":"82716",
    "sg:province":"WY",
    "sg:tags":[
        "distribution"
    ],
    "wof:name":"Bundy Distributing LLC",
    "wof:placetype":"venue"
},
  "geometry": {"coordinates":[-105.49526299999999,44.294677],"type":"Point"}
}