{
  "type": "Feature",
  "properties": {
    "iso:country":"US",
    "sg:address":"1729 Dell Range Blvd",
    "sg:city":"Cheyenne",
    "sg:classifiers":[
        {
            "category":"Restaurant",
            "type":"Food & Drink"
        }
    ],
    "sg:menulink":"http://www.allmenus.com/wy/cheyenne/214081-taco-bell/menu/",
    "sg:phone":"+1 307 778 8594",
    "sg:postcode":"82009",
    "sg:province":"WY",
    "sg:tags":[
        "mexican"
    ],
    "wof:name":"Taco Bell",
    "wof:placetype":"venue"
},
  "geometry": {"coordinates":[-104.800721,41.160242],"type":"Point"}
}