{
  "type": "Feature",
  "properties": {
    "iso:country":"US",
    "sg:address":"373 Lakeview Dr",
    "sg:city":"Mills",
    "sg:classifiers":[
        {
            "category":"Building & Trades",
            "subcategory":"Plumbing",
            "type":"Services"
        }
    ],
    "sg:phone":"+1 307 577 1912",
    "sg:postcode":"82604",
    "sg:province":"WY",
    "sg:tags":[
        "heating",
        "contractor"
    ],
    "wof:name":"Act Heating & Cooling",
    "wof:placetype":"venue"
},
  "geometry": {"coordinates":[-106.38656,42.853239],"type":"Point"}
}