{
  "type": "Feature",
  "properties": {
    "addr:full":"239 Pape Rd Daniel WY 83115",
    "addr:housenumber":"239",
    "addr:postcode":"83115",
    "addr:street":"Pape Rd Daniel Wy",
    "iso:country":"US",
    "sg:address":"239 Pape Rd",
    "sg:city":"Daniel",
    "sg:classifiers":[
        {
            "category":"Government",
            "subcategory":"Office",
            "type":"Public Place"
        }
    ],
    "sg:phone":"+1 307 859 8252",
    "sg:postcode":"83115",
    "sg:province":"WY",
    "sg:tags":[
        "state"
    ],
    "wof:name":"Fish Hatchery",
    "wof:placetype":"venue"
},
  "geometry": {"coordinates":[-110.12721000000001,42.929279],"type":"Point"}
}