{
  "type": "Feature",
  "properties": {
    "iso:country":"US",
    "sg:address":"721 Swanton Ave",
    "sg:city":"Casper",
    "sg:classifiers":[
        {
            "category":"Mining & Drilling",
            "type":"Manufacturing & Wholesale Goods"
        }
    ],
    "sg:phone":"+1 307 234 6587",
    "sg:postcode":"82609",
    "sg:province":"WY",
    "wof:name":"Pratt Sodium LLC",
    "wof:placetype":"venue"
},
  "geometry": {"coordinates":[-106.28252000000001,42.844919],"type":"Point"}
}