{
  "type": "Feature",
  "properties": {
    "iso:country":"US",
    "sg:address":"1640 Martin Ln",
    "sg:city":"Jackson",
    "sg:classifiers":[
        {
            "category":"Manufacturing",
            "subcategory":"Printing",
            "type":"Manufacturing & Wholesale Goods"
        }
    ],
    "sg:phone":"+1 307 733 4448",
    "sg:postcode":"83001",
    "sg:province":"WY",
    "sg:tags":[
        "screen"
    ],
    "wof:name":"Tormack Custom Screen Ptg Inc",
    "wof:placetype":"venue"
},
  "geometry": {"coordinates":[-110.796537,43.461732],"type":"Point"}
}