{
  "type": "Feature",
  "properties": {
    "iso:country":"US",
    "sg:address":"166 E 200 S",
    "sg:city":"Driggs",
    "sg:classifiers":[
        {
            "category":"Education",
            "subcategory":"Special Training",
            "type":"Public Place"
        }
    ],
    "sg:phone":"+1 208 354 8443",
    "sg:postcode":"83422",
    "sg:province":"WY",
    "sg:tags":[
        "school",
        "interest"
    ],
    "wof:name":"National Outdoor Leadership",
    "wof:placetype":"venue"
},
  "geometry": {"coordinates":[-111.06720900000001,43.693897],"type":"Point"}
}