{
  "type": "Feature",
  "properties": {
    "iso:country":"US",
    "sg:address":"1099 Rd 19",
    "sg:city":"Powell",
    "sg:classifiers":[
        {
            "category":"Freight",
            "type":"Transportation"
        }
    ],
    "sg:phone":"+1 307 754 2653",
    "sg:postcode":"82435",
    "sg:province":"WY",
    "sg:tags":[
        "operator",
        "local",
        "trucking"
    ],
    "wof:name":"CD Trucking",
    "wof:placetype":"venue"
},
  "geometry": {"coordinates":[-108.95665,44.72597],"type":"Point"}
}