{
  "type": "Feature",
  "properties": {
    "iso:country":"US",
    "sg:address":"2107 E 12th St",
    "sg:city":"Casper",
    "sg:classifiers":[
        {
            "category":"Shopping",
            "subcategory":"Used Merchandise",
            "type":"Retail Goods"
        }
    ],
    "sg:phone":"+1 307 232 8375",
    "sg:postcode":"82601",
    "sg:province":"WY",
    "wof:name":"Babys Trading Post",
    "wof:placetype":"venue"
},
  "geometry": {"coordinates":[-106.29791299999999,42.838802],"type":"Point"}
}