{
  "type": "Feature",
  "properties": {
    "addr:full":"1716 Kroe Ln Sheridan WY 82801",
    "addr:housenumber":"1716",
    "addr:postcode":"82801",
    "addr:street":"Kroe Ln",
    "iso:country":"US",
    "sg:address":"1716 Kroe Ln",
    "sg:city":"Sheridan",
    "sg:classifiers":[
        {
            "category":"Communications",
            "subcategory":"Radio Station",
            "type":"Services"
        }
    ],
    "sg:phone":"+1 307 674 4443",
    "sg:postcode":"82801",
    "sg:province":"WY",
    "sg:tags":[
        "company",
        "broadcasting"
    ],
    "wof:name":"Public Pulse-Swap Shop",
    "wof:placetype":"venue"
},
  "geometry": {"coordinates":[-106.929638,44.799039],"type":"Point"}
}