{
  "type": "Feature",
  "properties": {
    "addr:full":"624 Wright Blvd Wright WY 82718",
    "addr:housenumber":"624",
    "addr:postcode":"82718",
    "addr:street":"Wright Blvd Wright Wy",
    "iso:country":"US",
    "sg:address":"624 Wright Blvd",
    "sg:city":"Wright",
    "sg:classifiers":[
        {
            "category":"Organizations",
            "subcategory":"Religious Organization",
            "type":"Services"
        }
    ],
    "sg:phone":"+1 307 464 0809",
    "sg:postcode":"82718",
    "sg:province":"WY",
    "sg:tags":[
        "church"
    ],
    "wof:name":"Blessed Sacrament Catholic Chr",
    "wof:placetype":"venue"
},
  "geometry": {"coordinates":[-105.480401,43.75025],"type":"Point"}
}