{
  "type": "Feature",
  "properties": {
    "iso:country":"US",
    "sg:address":"2122 W Spruce St",
    "sg:city":"Rawlins",
    "sg:classifiers":[
        {
            "category":"Travel",
            "subcategory":"Hotels & Motels",
            "type":"Entertainment"
        }
    ],
    "sg:phone":"+1 307 324 2737",
    "sg:postcode":"82301",
    "sg:province":"WY",
    "wof:name":"Best Western Inn",
    "wof:placetype":"venue"
},
  "geometry": {"coordinates":[-107.26005499999999,41.785788],"type":"Point"}
}