{
  "type": "Feature",
  "properties": {
    "iso:country":"US",
    "sg:address":"804 N Poplar St",
    "sg:city":"Casper",
    "sg:classifiers":[
        {
            "category":"Retail",
            "subcategory":"Auto Rental",
            "type":"Services"
        }
    ],
    "sg:phone":"+1 307 265 5667",
    "sg:postcode":"82601",
    "sg:province":"WY",
    "sg:tags":[
        "passenger",
        "car"
    ],
    "wof:name":"Around Town Rent-A-Car",
    "wof:placetype":"venue"
},
  "geometry": {"coordinates":[-106.332729,42.859535],"type":"Point"}
}