{
  "type": "Feature",
  "properties": {
    "iso:country":"US",
    "sg:address":"7632 W 6 W N Rd",
    "sg:city":"Casper",
    "sg:classifiers":[
        {
            "category":"Building & Trades",
            "subcategory":"Construction",
            "type":"Services"
        }
    ],
    "sg:phone":"+1 307 472 7272",
    "sg:postcode":"82604",
    "sg:province":"WY",
    "sg:tags":[
        "material",
        "nonresidential"
    ],
    "wof:name":"Construction Systems Inc",
    "wof:placetype":"venue"
},
  "geometry": {"coordinates":[-106.44802,42.877724],"type":"Point"}
}