{
  "type": "Feature",
  "properties": {
    "iso:country":"US",
    "sg:address":"6106 Yellowstone Rd",
    "sg:city":"Cheyenne",
    "sg:classifiers":[
        {
            "category":"Real Estate",
            "subcategory":"Real Estate Agent",
            "type":"Services"
        }
    ],
    "sg:phone":"+1 307 634 2222",
    "sg:postcode":"82009",
    "sg:province":"WY",
    "sg:website":"www.cheyennehomes.com",
    "wof:name":"Number One Properties Real Est",
    "wof:placetype":"venue"
},
  "geometry": {"coordinates":[-104.828653,41.177267],"type":"Point"}
}