{
  "type": "Feature",
  "properties": {
    "addr:full":"88258 US Hwy 89 Afton WY 83110",
    "addr:housenumber":"88258",
    "addr:postcode":"83110",
    "addr:street":"Us Hwy 89 Afton Wy",
    "iso:country":"US",
    "sg:address":"88258 US Hwy 89",
    "sg:city":"Afton",
    "sg:classifiers":[
        {
            "category":"Professional",
            "type":"Services"
        }
    ],
    "sg:phone":"+1 307 886 3536",
    "sg:postcode":"83110",
    "sg:province":"WY",
    "wof:name":"North Canal Irrigation Co",
    "wof:placetype":"venue"
},
  "geometry": {"coordinates":[-110.93338,42.772819],"type":"Point"}
}