{
  "type": "Feature",
  "properties": {
    "addr:full":"912 W Main St Riverton WY 82501",
    "addr:housenumber":"912",
    "addr:postcode":"82501",
    "addr:street":"W Main St",
    "iso:country":"US",
    "sg:address":"912 W Main St",
    "sg:city":"Riverton",
    "sg:classifiers":[
        {
            "category":"Retail",
            "subcategory":"Auto Repair",
            "type":"Services"
        }
    ],
    "sg:phone":"+1 307 856 1412",
    "sg:postcode":"82501",
    "sg:province":"WY",
    "sg:tags":[
        "automotive",
        "station",
        "gasoline",
        "general"
    ],
    "wof:name":"Bobs Hilltop Sinclair",
    "wof:placetype":"venue"
},
  "geometry": {"coordinates":[-108.40319599999999,43.024664],"type":"Point"}
}