{
  "type": "Feature",
  "properties": {
    "addr:full":"1561 Sussex Rd Kaycee WY 82639",
    "addr:housenumber":"1561",
    "addr:postcode":"82639",
    "addr:street":"Sussex Rd Kaycee Wy",
    "iso:country":"US",
    "sg:address":"1561 Sussex Rd",
    "sg:city":"Kaycee",
    "sg:classifiers":[
        {
            "category":"Farming",
            "subcategory":"Livestock Farm",
            "type":"Manufacturing & Wholesale Goods"
        }
    ],
    "sg:phone":"+1 307 738 2259",
    "sg:postcode":"82639",
    "sg:province":"WY",
    "sg:tags":[
        "animal",
        "general"
    ],
    "wof:name":"Four Mile Ranch Inc",
    "wof:placetype":"venue"
},
  "geometry": {"coordinates":[-106.33992000000001,43.712066],"type":"Point"}
}