{
  "type": "Feature",
  "properties": {
    "addr:full":"461 Lower Prairie Dog Rd Sheridan WY 82801",
    "addr:housenumber":"461",
    "addr:postcode":"82801",
    "addr:street":"Lower Prairie Dog Rd",
    "iso:country":"US",
    "sg:address":"461 Lower Prairie Dog Rd",
    "sg:city":"Sheridan",
    "sg:phone":"+1 307 750 2434",
    "sg:postcode":"82801",
    "sg:province":"WY",
    "sg:tags":[
        "farm",
        "field",
        "crop"
    ],
    "wof:name":"Alvin Peterson",
    "wof:placetype":"venue"
},
  "geometry": {"coordinates":[-106.86027799999999,44.895346],"type":"Point"}
}