{
  "type": "Feature",
  "properties": {
    "iso:country":"US",
    "sg:address":"201 S 4th St",
    "sg:city":"Basin",
    "sg:classifiers":[
        {
            "category":"Insurance",
            "subcategory":"Insurance Agent",
            "type":"Services"
        }
    ],
    "sg:phone":"+1 307 568 3345",
    "sg:postcode":"82410",
    "sg:province":"WY",
    "wof:name":"Security Insurance",
    "wof:placetype":"venue"
},
  "geometry": {"coordinates":[-108.03885699999999,44.380754],"type":"Point"}
}