{
  "type": "Feature",
  "properties": {
    "iso:country":"US",
    "sg:address":"16 Rd 2Ab",
    "sg:city":"Cody",
    "sg:classifiers":[
        {
            "category":"Home & Garden",
            "subcategory":"Building Materials",
            "type":"Retail Goods"
        }
    ],
    "sg:phone":"+1 307 587 5334",
    "sg:postcode":"82414",
    "sg:province":"WY",
    "sg:tags":[
        "mixed",
        "concrete"
    ],
    "wof:name":"Rainbow Rock Co",
    "wof:placetype":"venue"
},
  "geometry": {"coordinates":[-109.038194,44.551347],"type":"Point"}
}