{
  "type": "Feature",
  "properties": {
    "iso:country":"US",
    "sg:address":"260 Greasewood St",
    "sg:city":"Green River",
    "sg:classifiers":[
        {
            "category":"Recreation",
            "type":"Entertainment"
        }
    ],
    "sg:phone":"+1 307 875 7981",
    "sg:postcode":"82935",
    "sg:province":"WY",
    "sg:tags":[
        "bingo",
        "game"
    ],
    "wof:name":"Lucky Bucks Bingo",
    "wof:placetype":"venue"
},
  "geometry": {"coordinates":[-109.474867,41.521544],"type":"Point"}
}