{
  "type": "Feature",
  "properties": {
    "iso:country":"US",
    "sg:address":"2003 S Poplar St",
    "sg:city":"Casper",
    "sg:classifiers":[
        {
            "category":"Government",
            "subcategory":"Office",
            "type":"Public Place"
        }
    ],
    "sg:phone":"+1 307 266 6612",
    "sg:postcode":"82601",
    "sg:province":"WY",
    "wof:name":"Game Warden",
    "wof:placetype":"venue"
},
  "geometry": {"coordinates":[-106.336916,42.82862],"type":"Point"}
}