{
  "type": "Feature",
  "properties": {
    "addr:full":"999 Elk St Rock Springs WY 82901",
    "addr:housenumber":"999",
    "addr:postcode":"82901",
    "addr:street":"Elk St Rock Springs Wy",
    "iso:country":"US",
    "sg:address":"999 Elk St",
    "sg:city":"Rock Springs",
    "sg:classifiers":[
        {
            "category":"Wholesale",
            "subcategory":"Electrical",
            "type":"Manufacturing & Wholesale Goods"
        }
    ],
    "sg:phone":"+1 307 382 9150",
    "sg:postcode":"82901",
    "sg:province":"WY",
    "sg:tags":[
        "equipment",
        "electric",
        "supply"
    ],
    "wof:name":"Winlectric",
    "wof:placetype":"venue"
},
  "geometry": {"coordinates":[-109.227035,41.594466],"type":"Point"}
}