{
  "type": "Feature",
  "properties": {
    "iso:country":"US",
    "sg:address":"168 Tepee St",
    "sg:city":"Thermopolis",
    "sg:classifiers":[
        {
            "category":"Recreation",
            "type":"Entertainment"
        }
    ],
    "sg:phone":"+1 307 864 3765",
    "sg:postcode":"82443",
    "sg:province":"WY",
    "sg:tags":[
        "parks"
    ],
    "wof:name":"Hot Springs State Park Bath Hs",
    "wof:placetype":"venue"
},
  "geometry": {"coordinates":[-108.198184,43.652113],"type":"Point"}
}