{
  "type": "Feature",
  "properties": {
    "addr:full":"121 Adams Ln Cody WY 82414",
    "addr:housenumber":"121",
    "addr:postcode":"82414",
    "addr:street":"Adams Ln",
    "iso:country":"US",
    "sg:address":"121 Adams Ln",
    "sg:city":"Cody",
    "sg:phone":"+1 307 587 3833",
    "sg:postcode":"82414",
    "sg:province":"WY",
    "sg:tags":[
        "farm",
        "field",
        "crop"
    ],
    "wof:name":"Vern Decker",
    "wof:placetype":"venue"
},
  "geometry": {"coordinates":[-109.01375400000001,44.546717],"type":"Point"}
}