{
  "type": "Feature",
  "properties": {
    "iso:country":"US",
    "sg:address":"525 E Grand Ave",
    "sg:city":"Laramie",
    "sg:classifiers":[
        {
            "category":"Government",
            "subcategory":"Office",
            "type":"Public Place"
        }
    ],
    "sg:phone":"+1 307 721 2568",
    "sg:postcode":"82070",
    "sg:province":"WY",
    "sg:tags":[
        "county",
        "planner"
    ],
    "wof:name":"Albany County Planner",
    "wof:placetype":"venue"
},
  "geometry": {"coordinates":[-105.590648,41.310911],"type":"Point"}
}