{
  "type": "Feature",
  "properties": {
    "iso:country":"US",
    "sg:address":"203 S Main St",
    "sg:city":"Sheridan",
    "sg:classifiers":[
        {
            "category":"Insurance",
            "subcategory":"Insurance Agent",
            "type":"Services"
        }
    ],
    "sg:phone":"+1 307 674 6973",
    "sg:postcode":"82801",
    "sg:province":"WY",
    "wof:name":"Laurie A Ross CLU",
    "wof:placetype":"venue"
},
  "geometry": {"coordinates":[-106.955806,44.795439],"type":"Point"}
}