{
  "type": "Feature",
  "properties": {
    "iso:country":"US",
    "sg:address":"436 2nd St",
    "sg:city":"Ten Sleep",
    "sg:classifiers":[
        {
            "category":"Museum",
            "type":"Entertainment"
        }
    ],
    "sg:phone":"+1 307 366 2759",
    "sg:postcode":"82442",
    "sg:province":"WY",
    "wof:name":"Ten Sleep Museum",
    "wof:placetype":"venue"
},
  "geometry": {"coordinates":[-107.444638,44.034198],"type":"Point"}
}