{
  "type": "Feature",
  "properties": {
    "iso:country":"US",
    "sg:address":"120 S Main St",
    "sg:city":"Thayne",
    "sg:classifiers":[
        {
            "category":"Personal",
            "subcategory":"Tanning Parlor",
            "type":"Services"
        }
    ],
    "sg:phone":"+1 307 883 2826",
    "sg:postcode":"83127",
    "sg:province":"WY",
    "sg:tags":[
        "salon"
    ],
    "wof:name":"Tan A Rama",
    "wof:placetype":"venue"
},
  "geometry": {"coordinates":[-111.00000799999999,42.913449],"type":"Point"}
}