{
  "type": "Feature",
  "properties": {
    "addr:full":"107 State Hwy 150 S Evanston WY 82930",
    "addr:housenumber":"107",
    "addr:postcode":"82930",
    "addr:street":"State Hwy 150 S Evanston Wy",
    "iso:country":"US",
    "sg:address":"107 State Hwy 150 S",
    "sg:city":"Evanston",
    "sg:classifiers":[
        {
            "category":"Health Services",
            "subcategory":"Doctor",
            "type":"Services"
        }
    ],
    "sg:phone":"+1 307 789 5210",
    "sg:postcode":"82930",
    "sg:province":"WY",
    "sg:tags":[
        "dentist"
    ],
    "wof:name":"Burt & Morgan",
    "wof:placetype":"venue"
},
  "geometry": {"coordinates":[-110.954139,41.262262],"type":"Point"}
}