{
  "type": "Feature",
  "properties": {
    "addr:full":"1205 Dunn Ave Cheyenne WY 82001",
    "addr:housenumber":"1205",
    "addr:postcode":"82001",
    "addr:street":"Dunn Ave",
    "iso:country":"US",
    "sg:address":"1205 Dunn Ave",
    "sg:city":"Cheyenne",
    "sg:classifiers":[
        {
            "category":"Autos & Motor Vehicles",
            "subcategory":"Motorcycle Sales",
            "type":"Retail Goods"
        }
    ],
    "sg:phone":"+1 307 632 3171",
    "sg:postcode":"82001",
    "sg:province":"WY",
    "sg:tags":[
        "scooter"
    ],
    "wof:name":"Cheyenne Sport Ctr",
    "wof:placetype":"venue"
},
  "geometry": {"coordinates":[-104.797445,41.135307],"type":"Point"}
}