{
  "type": "Feature",
  "properties": {
    "iso:country":"US",
    "sg:address":"823 S Center St",
    "sg:city":"Casper",
    "sg:classifiers":[
        {
            "category":"Insurance",
            "subcategory":"Insurance Agent",
            "type":"Services"
        }
    ],
    "sg:phone":"+1 307 235 4565",
    "sg:postcode":"82601",
    "sg:province":"WY",
    "wof:name":"Stan Lore",
    "wof:placetype":"venue"
},
  "geometry": {"coordinates":[-106.325087,42.841827],"type":"Point"}
}