{
  "type": "Feature",
  "properties": {
    "iso:country":"US",
    "sg:address":"735 W 19th St",
    "sg:city":"Casper",
    "sg:classifiers":[
        {
            "category":"Farming",
            "subcategory":"Livestock Farm",
            "type":"Manufacturing & Wholesale Goods"
        }
    ],
    "sg:phone":"+1 307 265 4142",
    "sg:postcode":"82601",
    "sg:province":"WY",
    "sg:tags":[
        "animal",
        "general"
    ],
    "wof:name":"Lyle Livestock",
    "wof:placetype":"venue"
},
  "geometry": {"coordinates":[-106.333483,42.831471],"type":"Point"}
}