{
  "type": "Feature",
  "properties": {
    "iso:country":"US",
    "sg:address":"1048 Gasser Rd",
    "sg:city":"Riverton",
    "sg:classifiers":[
        {
            "category":"Professional",
            "subcategory":"Management & Consulting",
            "type":"Services"
        }
    ],
    "sg:phone":"+1 307 857 3169",
    "sg:postcode":"82501",
    "sg:province":"WY",
    "sg:tags":[
        "business"
    ],
    "wof:name":"Whispering Wire Inc",
    "wof:placetype":"venue"
},
  "geometry": {"coordinates":[-108.406386,43.037548],"type":"Point"}
}