{
  "type": "Feature",
  "properties": {
    "iso:country":"US",
    "sg:address":"316 E Cedar St",
    "sg:city":"Rawlins",
    "sg:classifiers":[
        {
            "category":"Insurance",
            "subcategory":"Insurance Agent",
            "type":"Services"
        }
    ],
    "sg:phone":"+1 307 324 4755",
    "sg:postcode":"82301",
    "sg:province":"WY",
    "wof:name":"Dabb Insurance",
    "wof:placetype":"venue"
},
  "geometry": {"coordinates":[-107.231746,41.789422],"type":"Point"}
}