{
  "type": "Feature",
  "properties": {
    "iso:country":"US",
    "sg:address":"911 N Broomtail Trl",
    "sg:city":"Evansville",
    "sg:classifiers":[
        {
            "category":"Building & Trades",
            "subcategory":"Plumbing",
            "type":"Services"
        }
    ],
    "sg:phone":"+1 307 259 1141",
    "sg:postcode":"82636",
    "sg:province":"WY",
    "sg:tags":[
        "conditioning",
        "air",
        "system",
        "contractor"
    ],
    "wof:name":"Jim's Heating & Cooling",
    "wof:placetype":"venue"
},
  "geometry": {"coordinates":[-106.23224,42.860204],"type":"Point"}
}