{
  "type": "Feature",
  "properties": {
    "iso:country":"US",
    "sg:address":"1700 Yellowstone Ave",
    "sg:city":"Worland",
    "sg:classifiers":[
        {
            "category":"Social Services",
            "subcategory":"Child Care",
            "type":"Services"
        }
    ],
    "sg:phone":"+1 307 347 3643",
    "sg:postcode":"82401",
    "sg:province":"WY",
    "sg:tags":[
        "day"
    ],
    "wof:name":"Apple Academy",
    "wof:placetype":"venue"
},
  "geometry": {"coordinates":[-107.945578,44.022365],"type":"Point"}
}