{
  "type": "Feature",
  "properties": {
    "addr:full":"502 Main St Lander WY 82520",
    "addr:housenumber":"502",
    "addr:postcode":"wy 82520",
    "addr:street":"Main St",
    "iso:country":"US",
    "sg:address":"502 Main St",
    "sg:city":"Lander",
    "sg:classifiers":[
        {
            "category":"Shopping",
            "type":"Retail Goods"
        }
    ],
    "sg:phone":"+1 307 332 2991",
    "sg:postcode":"82520",
    "sg:province":"WY",
    "sg:tags":[
        "merchandise"
    ],
    "wof:name":"Indian Territory Inc",
    "wof:placetype":"venue"
},
  "geometry": {"coordinates":[-108.73716899999999,42.834479],"type":"Point"}
}