{
  "type": "Feature",
  "properties": {
    "addr:full":"381 N Main St Buffalo WY 82834",
    "addr:housenumber":"381",
    "addr:postcode":"82834",
    "addr:street":"N Main St",
    "iso:country":"US",
    "sg:address":"381 N Main St",
    "sg:city":"Buffalo",
    "sg:classifiers":[
        {
            "category":"Real Estate",
            "subcategory":"Real Estate Agent",
            "type":"Services"
        }
    ],
    "sg:phone":"+1 307 684 7013",
    "sg:postcode":"82834",
    "sg:province":"WY",
    "sg:tags":[
        "inspection"
    ],
    "wof:name":"Western Home Inc",
    "wof:placetype":"venue"
},
  "geometry": {"coordinates":[-106.69896799999999,44.350855],"type":"Point"}
}