{
  "type": "Feature",
  "properties": {
    "addr:full":"425 Center St Douglas WY 82633",
    "addr:housenumber":"425",
    "addr:postcode":"82633",
    "addr:street":"Center St Douglas Wy",
    "iso:country":"US",
    "sg:address":"425 Center St",
    "sg:city":"Douglas",
    "sg:classifiers":[
        {
            "category":"Travel",
            "subcategory":"Hotels & Motels",
            "type":"Entertainment"
        }
    ],
    "sg:phone":"+1 307 358 2129",
    "sg:postcode":"82633",
    "sg:province":"WY",
    "sg:tags":[
        "operation"
    ],
    "wof:name":"Morton Mansion Bed & Breakfast",
    "wof:placetype":"venue"
},
  "geometry": {"coordinates":[-105.381637,42.759439],"type":"Point"}
}