{
  "type": "Feature",
  "properties": {
    "iso:country":"US",
    "sg:address":"937 W Main St",
    "sg:city":"Riverton",
    "sg:classifiers":[
        {
            "category":"Utilities",
            "subcategory":"Telephone",
            "type":"Services"
        }
    ],
    "sg:phone":"+1 307 733 7900",
    "sg:postcode":"82501",
    "sg:province":"WY",
    "sg:tags":[
        "communications",
        "retrieval",
        "information"
    ],
    "wof:name":"Onewestnet",
    "wof:placetype":"venue"
},
  "geometry": {"coordinates":[-108.40378,43.024511],"type":"Point"}
}