{
  "type": "Feature",
  "properties": {
    "iso:country":"US",
    "sg:address":"1310 N Garner Lake Rd",
    "sg:city":"Gillette",
    "sg:classifiers":[
        {
            "category":"Professional",
            "subcategory":"Business Services",
            "type":"Services"
        }
    ],
    "sg:phone":"+1 307 682 5583",
    "sg:postcode":"82716",
    "sg:province":"WY",
    "sg:tags":[
        "water",
        "treatment"
    ],
    "wof:name":"Western Water Conditioning Inc",
    "wof:placetype":"venue"
},
  "geometry": {"coordinates":[-105.450053,44.308257],"type":"Point"}
}