{
  "type": "Feature",
  "properties": {
    "addr:full":"752 Coffeen Ave Sheridan WY 82801",
    "addr:housenumber":"752",
    "addr:postcode":"82801",
    "addr:street":"Coffeen Ave",
    "iso:country":"US",
    "sg:address":"752 Coffeen Ave",
    "sg:city":"Sheridan",
    "sg:classifiers":[
        {
            "category":"Retail",
            "subcategory":"Auto Repair",
            "type":"Services"
        }
    ],
    "sg:phone":"+1 307 672 8006",
    "sg:postcode":"82801",
    "sg:province":"WY",
    "sg:tags":[
        "automobile",
        "lubrication"
    ],
    "wof:name":"Jiffy Lube",
    "wof:placetype":"venue"
},
  "geometry": {"coordinates":[-106.946758,44.789156],"type":"Point"}
}