{
  "type": "Feature",
  "properties": {
    "iso:country":"US",
    "sg:address":"2000 W Main St",
    "sg:city":"Newcastle",
    "sg:classifiers":[
        {
            "category":"Autos & Motor Vehicles",
            "subcategory":"Automobile Sales",
            "type":"Retail Goods"
        }
    ],
    "sg:phone":"+1 307 746 9500",
    "sg:postcode":"82701",
    "sg:province":"WY",
    "sg:tags":[
        "car",
        "dealer"
    ],
    "sg:website":"www.outlawmotors.com",
    "wof:name":"Outlaw Motors",
    "wof:placetype":"venue"
},
  "geometry": {"coordinates":[-104.227386,43.851145],"type":"Point"}
}