{
  "type": "Feature",
  "properties": {
    "addr:full":"103454 US Hwy 89 Freedom WY 83127",
    "addr:housenumber":"103454",
    "addr:postcode":"83127",
    "addr:street":"Us Hwy 89 Freedom Wy",
    "iso:country":"US",
    "sg:address":"103454 US Hwy 89",
    "sg:city":"Freedom",
    "sg:classifiers":[
        {
            "category":"Home & Garden",
            "subcategory":"Building Materials",
            "type":"Retail Goods"
        }
    ],
    "sg:phone":"+1 307 883 2215",
    "sg:postcode":"83127",
    "sg:province":"WY",
    "wof:name":"Freedom Lumber Co",
    "wof:placetype":"venue"
},
  "geometry": {"coordinates":[-111.01237,42.96845],"type":"Point"}
}