{
  "type": "Feature",
  "properties": {
    "iso:country":"US",
    "sg:address":"301 Thelma Dr",
    "sg:city":"Casper",
    "sg:classifiers":[
        {
            "category":"Building & Trades",
            "subcategory":"Construction",
            "type":"Services"
        }
    ],
    "sg:phone":"+1 307 472 1096",
    "sg:postcode":"82609",
    "sg:province":"WY",
    "sg:tags":[
        "general",
        "contractor"
    ],
    "wof:name":"Diamond L Construction Inc",
    "wof:placetype":"venue"
},
  "geometry": {"coordinates":[-106.274101,42.84781],"type":"Point"}
}