{
  "type": "Feature",
  "properties": {
    "iso:country":"US",
    "sg:address":"514 S Beech St",
    "sg:city":"Casper",
    "sg:classifiers":[
        {
            "category":"Organizations",
            "subcategory":"Religious Organization",
            "type":"Services"
        }
    ],
    "sg:phone":"+1 307 234 6946",
    "sg:postcode":"82601",
    "sg:province":"WY",
    "wof:name":"First Baptist Church",
    "wof:placetype":"venue"
},
  "geometry": {"coordinates":[-106.32100699999999,42.844805],"type":"Point"}
}