{
  "type": "Feature",
  "properties": {
    "iso:country":"US",
    "sg:address":"1407 Dewar Dr",
    "sg:city":"Rock Springs",
    "sg:classifiers":[
        {
            "category":"Professional",
            "subcategory":"Printing & Photocopies",
            "type":"Services"
        }
    ],
    "sg:phone":"+1 307 382 2679",
    "sg:postcode":"82901",
    "sg:province":"WY",
    "sg:tags":[
        "duplicating",
        "copying"
    ],
    "wof:name":"KOPY Korner",
    "wof:placetype":"venue"
},
  "geometry": {"coordinates":[-109.247518,41.574934],"type":"Point"}
}