{
  "type": "Feature",
  "properties": {
    "addr:full":"13 E Loucks St Sheridan WY 82801",
    "addr:housenumber":"13",
    "addr:postcode":"82801",
    "addr:street":"E Loucks St",
    "iso:country":"US",
    "sg:address":"13 E Loucks St",
    "sg:city":"Sheridan",
    "sg:classifiers":[
        {
            "category":"Restaurant",
            "type":"Food & Drink"
        }
    ],
    "sg:phone":"+1 307 674 9414",
    "sg:postcode":"82801",
    "sg:province":"WY",
    "sg:tags":[
        "eating"
    ],
    "wof:name":"Downtown Diner Takeout & Catrg",
    "wof:placetype":"venue"
},
  "geometry": {"coordinates":[-106.955692,44.797307],"type":"Point"}
}