{
  "type": "Feature",
  "properties": {
    "iso:country":"US",
    "sg:address":"3161 Omaha Rd",
    "sg:city":"Cheyenne",
    "sg:classifiers":[
        {
            "category":"Organizations",
            "subcategory":"Religious Organization",
            "type":"Services"
        }
    ],
    "sg:phone":"+1 307 778 8709",
    "sg:postcode":"82001",
    "sg:province":"WY",
    "sg:website":"www.meadowbrooke.org",
    "wof:name":"Meadowbrooke Baptist Church",
    "wof:placetype":"venue"
},
  "geometry": {"coordinates":[-104.771355,41.143712],"type":"Point"}
}