{
  "type": "Feature",
  "properties": {
    "iso:country":"US",
    "sg:address":"5 Choke Cherry Ln",
    "sg:city":"Story",
    "sg:classifiers":[
        {
            "category":"Insurance",
            "subcategory":"Hazard Insurance",
            "type":"Services"
        }
    ],
    "sg:phone":"+1 307 683 2765",
    "sg:postcode":"82842",
    "sg:province":"WY",
    "sg:tags":[
        "carrier"
    ],
    "wof:name":"Karwest Inc",
    "wof:placetype":"venue"
},
  "geometry": {"coordinates":[-106.89825399999999,44.574785],"type":"Point"}
}