{
  "type": "Feature",
  "properties": {
    "iso:country":"US",
    "sg:address":"229 US Hwy 89",
    "sg:city":"Thayne",
    "sg:classifiers":[
        {
            "category":"Personal",
            "subcategory":"Beauty Salon",
            "type":"Services"
        }
    ],
    "sg:phone":"+1 307 883 8377",
    "sg:postcode":"83127",
    "sg:province":"WY",
    "wof:name":"Main Attraction",
    "wof:placetype":"venue"
},
  "geometry": {"coordinates":[-111.000244,42.913479],"type":"Point"}
}