{
  "type": "Feature",
  "properties": {
    "addr:full":"50 E Simpson Ave Jackson WY 83001",
    "addr:housenumber":"50",
    "addr:postcode":"83001",
    "addr:street":"E Simpson Ave Jackson Wy",
    "iso:country":"US",
    "sg:address":"50 E Simpson Ave",
    "sg:city":"Jackson",
    "sg:classifiers":[
        {
            "category":"Real Estate",
            "subcategory":"Developer",
            "type":"Services"
        }
    ],
    "sg:phone":"+1 307 734 5860",
    "sg:postcode":"83001",
    "sg:province":"WY",
    "wof:name":"Caddis Development Group",
    "wof:placetype":"venue"
},
  "geometry": {"coordinates":[-110.761746,43.477392],"type":"Point"}
}