{
  "type": "Feature",
  "properties": {
    "iso:country":"US",
    "sg:address":"2400 Missile Dr",
    "sg:city":"Cheyenne",
    "sg:classifiers":[
        {
            "category":"Mining & Drilling",
            "type":"Manufacturing & Wholesale Goods"
        }
    ],
    "sg:phone":"+1 307 638 4910",
    "sg:postcode":"82001",
    "sg:province":"WY",
    "sg:tags":[
        "oil",
        "gas",
        "producer"
    ],
    "wof:name":"Tri State Oil Reclaimers",
    "wof:placetype":"venue"
},
  "geometry": {"coordinates":[-104.834997,41.134045],"type":"Point"}
}