{
  "type": "Feature",
  "properties": {
    "addr:full":"2211 Bluffs Ridge Dr Gillette WY 82718",
    "addr:housenumber":"2211",
    "addr:postcode":"82718",
    "addr:street":"Bluffs Ridge Dr",
    "iso:country":"US",
    "sg:address":"2211 Bluffs Ridge Dr",
    "sg:city":"Gillette",
    "sg:classifiers":[
        {
            "category":"Mining & Drilling",
            "type":"Manufacturing & Wholesale Goods"
        }
    ],
    "sg:phone":"+1 307 686 8292",
    "sg:postcode":"82718",
    "sg:province":"WY",
    "sg:tags":[
        "oil",
        "well"
    ],
    "wof:name":"Bison Acidizing & Fracturing",
    "wof:placetype":"venue"
},
  "geometry": {"coordinates":[-105.526887,44.275072],"type":"Point"}
}