{
  "type": "Feature",
  "properties": {
    "iso:country":"US",
    "sg:address":"132 N Bent St",
    "sg:city":"Powell",
    "sg:classifiers":[
        {
            "category":"Shopping",
            "subcategory":"Clothing, Apparel, & Fashions",
            "type":"Retail Goods"
        }
    ],
    "sg:phone":"+1 307 754 7244",
    "sg:postcode":"82435",
    "sg:province":"WY",
    "wof:name":"My Favorite Things",
    "wof:placetype":"venue"
},
  "geometry": {"coordinates":[-108.757666,44.753738],"type":"Point"}
}