{
  "type": "Feature",
  "properties": {
    "iso:country":"US",
    "sg:address":"144 W Yellowstone Ave",
    "sg:city":"Cody",
    "sg:classifiers":[
        {
            "category":"Personal",
            "subcategory":"Shoe Repair & Shine",
            "type":"Services"
        }
    ],
    "sg:phone":"+1 307 527 5939",
    "sg:postcode":"82414",
    "sg:province":"WY",
    "sg:tags":[
        "hat",
        "renovator"
    ],
    "wof:name":"Windriver Hat Co",
    "wof:placetype":"venue"
},
  "geometry": {"coordinates":[-109.095713,44.51533],"type":"Point"}
}