{
  "type": "Feature",
  "properties": {
    "iso:country":"US",
    "sg:address":"214 W Loucks St",
    "sg:city":"Sheridan",
    "sg:classifiers":[
        {
            "category":"Health Services",
            "subcategory":"Chiropractor",
            "type":"Services"
        }
    ],
    "sg:phone":"+1 307 674 9593",
    "sg:postcode":"82801",
    "sg:province":"WY",
    "wof:name":"Mitchell Chiropractic",
    "wof:placetype":"venue"
},
  "geometry": {"coordinates":[-106.959565,44.79722],"type":"Point"}
}