{
  "type": "Feature",
  "properties": {
    "iso:country":"US",
    "sg:address":"1507 E Ord St",
    "sg:city":"Laramie",
    "sg:classifiers":[
        {
            "category":"Building & Trades",
            "subcategory":"Construction",
            "type":"Services"
        }
    ],
    "sg:phone":"+1 307 742 7408",
    "sg:postcode":"82070",
    "sg:province":"WY",
    "sg:tags":[
        "house"
    ],
    "wof:name":"Leathers Ron Paint Contra",
    "wof:placetype":"venue"
},
  "geometry": {"coordinates":[-105.575259,41.303767],"type":"Point"}
}