{
  "type": "Feature",
  "properties": {
    "iso:country":"US",
    "sg:address":"3364 Squaw Creek Rd",
    "sg:city":"Casper",
    "sg:classifiers":[
        {
            "category":"Freight",
            "type":"Transportation"
        }
    ],
    "sg:phone":"+1 307 234 5103",
    "sg:postcode":"82604",
    "sg:province":"WY",
    "sg:tags":[
        "hauling",
        "trucking"
    ],
    "wof:name":"Jack R Whitlock Trucking",
    "wof:placetype":"venue"
},
  "geometry": {"coordinates":[-106.38391900000001,42.809725],"type":"Point"}
}