{
  "type": "Feature",
  "properties": {
    "addr:full":"975 Shoshone Ave Lovell WY 82431",
    "addr:housenumber":"975",
    "addr:postcode":"82431",
    "addr:street":"Shoshone Ave Lovell Wy",
    "iso:country":"US",
    "sg:address":"975 Shoshone Ave",
    "sg:city":"Lovell",
    "sg:classifiers":[
        {
            "category":"Professional",
            "type":"Services"
        }
    ],
    "sg:phone":"+1 307 548 7209",
    "sg:postcode":"82431",
    "sg:province":"WY",
    "sg:tags":[
        "establishment"
    ],
    "wof:name":"Mr KWIK",
    "wof:placetype":"venue"
},
  "geometry": {"coordinates":[-108.393413,44.828731],"type":"Point"}
}