{
  "type": "Feature",
  "properties": {
    "iso:country":"US",
    "sg:address":"124 N 8th St",
    "sg:city":"Worland",
    "sg:classifiers":[
        {
            "category":"Shopping",
            "subcategory":"Florist",
            "type":"Retail Goods"
        }
    ],
    "sg:phone":"+1 307 347 2474",
    "sg:postcode":"82401",
    "sg:province":"WY",
    "wof:name":"Rose Cottage",
    "wof:placetype":"venue"
},
  "geometry": {"coordinates":[-107.958405,44.017628],"type":"Point"}
}