{
  "type": "Feature",
  "properties": {
    "iso:country":"US",
    "sg:address":"67 el Rancho Rd",
    "sg:city":"Wheatland",
    "sg:classifiers":[
        {
            "category":"Restaurant",
            "type":"Food & Drink"
        }
    ],
    "sg:phone":"+1 307 322 5599",
    "sg:postcode":"82201",
    "sg:province":"WY",
    "wof:name":"El Rancho Steakhouse & Tavern",
    "wof:placetype":"venue"
},
  "geometry": {"coordinates":[-105.0496,42.272429],"type":"Point"}
}