{
  "type": "Feature",
  "properties": {
    "iso:country":"US",
    "sg:address":"152 N Durbin St",
    "sg:city":"Casper",
    "sg:classifiers":[
        {
            "category":"Education",
            "subcategory":"Vocational School",
            "type":"Public Place"
        }
    ],
    "sg:phone":"+1 307 234 8653",
    "sg:postcode":"82601",
    "sg:province":"WY",
    "sg:tags":[
        "real estate"
    ],
    "wof:name":"Steve Willoughby Seminars",
    "wof:placetype":"venue"
},
  "geometry": {"coordinates":[-106.322425,42.850737],"type":"Point"}
}