{
  "type": "Feature",
  "properties": {
    "iso:country":"US",
    "sg:address":"100 E Main St",
    "sg:city":"Lander",
    "sg:classifiers":[
        {
            "category":"Restaurant",
            "type":"Food & Drink"
        }
    ],
    "sg:phone":"+1 307 332 5143",
    "sg:postcode":"82520",
    "sg:province":"WY",
    "wof:name":"Atlantic City Mercantile",
    "wof:placetype":"venue"
},
  "geometry": {"coordinates":[-108.72731899999999,42.832322],"type":"Point"}
}