{
  "type": "Feature",
  "properties": {
    "iso:country":"US",
    "sg:address":"4210 S Poplar St",
    "sg:city":"Casper",
    "sg:classifiers":[
        {
            "category":"Travel",
            "subcategory":"Travel Agent",
            "type":"Entertainment"
        }
    ],
    "sg:phone":"+1 307 577 8747",
    "sg:postcode":"82601",
    "sg:province":"WY",
    "sg:tags":[
        "agency",
        "bureau"
    ],
    "sg:website":"www.alltravel.org",
    "wof:name":"All Travel",
    "wof:placetype":"venue"
},
  "geometry": {"coordinates":[-106.34369,42.810014],"type":"Point"}
}