{
  "type": "Feature",
  "properties": {
    "iso:country":"US",
    "sg:address":"1400 Uinta Dr",
    "sg:city":"Green River",
    "sg:classifiers":[
        {
            "category":"Health Services",
            "subcategory":"Doctor",
            "type":"Services"
        }
    ],
    "sg:phone":"+1 307 872 4500",
    "sg:postcode":"82935",
    "sg:province":"WY",
    "sg:tags":[
        "clinic"
    ],
    "wof:name":"Castle Rock Medical Ctr",
    "wof:placetype":"venue"
},
  "geometry": {"coordinates":[-109.47422,41.50982],"type":"Point"}
}