{
  "type": "Feature",
  "properties": {
    "addr:full":"900 Butler-Spaeth Rd Gillette WY 82716",
    "addr:housenumber":"900",
    "addr:postcode":"82716",
    "addr:street":"Butler-Spaeth Rd",
    "iso:country":"US",
    "sg:address":"900 Butler-Spaeth Rd",
    "sg:city":"Gillette",
    "sg:classifiers":[
        {
            "category":"Social Services",
            "type":"Services"
        }
    ],
    "sg:phone":"+1 307 682 7690",
    "sg:postcode":"82716",
    "sg:province":"WY",
    "sg:tags":[
        "pregnancy",
        "counseling",
        "information"
    ],
    "wof:name":"Gabriel's Angels",
    "wof:placetype":"venue"
},
  "geometry": {"coordinates":[-105.47906999999999,44.28644],"type":"Point"}
}