{
  "type": "Feature",
  "properties": {
    "iso:country":"US",
    "sg:address":"850 Maple St",
    "sg:city":"Wheatland",
    "sg:classifiers":[
        {
            "category":"Government",
            "subcategory":"Police Station",
            "type":"Public Place"
        }
    ],
    "sg:phone":"+1 307 322 2331",
    "sg:postcode":"82201",
    "sg:province":"WY",
    "sg:tags":[
        "sheriff"
    ],
    "wof:name":"Platte County Sheriff Dept",
    "wof:placetype":"venue"
},
  "geometry": {"coordinates":[-104.95326,42.055299],"type":"Point"}
}