{
  "type": "Feature",
  "properties": {
    "iso:country":"US",
    "sg:address":"1450 E Brundage Ln",
    "sg:city":"Sheridan",
    "sg:classifiers":[
        {
            "category":"Travel",
            "subcategory":"Hotels & Motels",
            "type":"Entertainment"
        }
    ],
    "sg:phone":"+1 307 672 5098",
    "sg:postcode":"82801",
    "sg:province":"WY",
    "wof:name":"Comfort Inn",
    "wof:placetype":"venue"
},
  "geometry": {"coordinates":[-106.93349600000001,44.773713],"type":"Point"}
}