{
  "type": "Feature",
  "properties": {
    "iso:country":"US",
    "sg:address":"708 S 17th St",
    "sg:city":"Worland",
    "sg:classifiers":[
        {
            "category":"Organizations",
            "subcategory":"Religious Organization",
            "type":"Services"
        }
    ],
    "sg:phone":"+1 307 347 6582",
    "sg:postcode":"82401",
    "sg:province":"WY",
    "wof:name":"Christian Victory Center",
    "wof:placetype":"venue"
},
  "geometry": {"coordinates":[-107.946063,44.01045],"type":"Point"}
}