{
  "type": "Feature",
  "properties": {
    "addr:full":"912 E Lincolnway Cheyenne WY 82001",
    "addr:housenumber":"912",
    "addr:postcode":"82001",
    "addr:street":"E Lincolnway;Wy",
    "iso:country":"US",
    "sg:address":"912 E Lincolnway",
    "sg:city":"Cheyenne",
    "sg:classifiers":[
        {
            "category":"Retail",
            "subcategory":"Self-service Laundry",
            "type":"Services"
        }
    ],
    "sg:phone":"+1 307 635 6881",
    "sg:postcode":"82001",
    "sg:province":"WY",
    "sg:tags":[
        "coin"
    ],
    "wof:name":"Sparkling Brites",
    "wof:placetype":"venue"
},
  "geometry": {"coordinates":[-104.804232,41.136931],"type":"Point"}
}