{
  "type": "Feature",
  "properties": {
    "iso:country":"US",
    "sg:address":"79 N Main St",
    "sg:city":"Driggs",
    "sg:classifiers":[
        {
            "category":"Utilities",
            "subcategory":"Telephone",
            "type":"Services"
        }
    ],
    "sg:phone":"+1 208 354 6269",
    "sg:postcode":"83422",
    "sg:province":"WY",
    "sg:tags":[
        "telecommunication"
    ],
    "wof:name":"Teton Telecom",
    "wof:placetype":"venue"
},
  "geometry": {"coordinates":[-111.11114999999999,43.723768],"type":"Point"}
}