{
  "type": "Feature",
  "properties": {
    "iso:country":"US",
    "sg:address":"754 Yellowstone Ave",
    "sg:city":"Cody",
    "sg:classifiers":[
        {
            "category":"Shopping",
            "subcategory":"Clothing, Apparel, & Fashions",
            "type":"Retail Goods"
        }
    ],
    "sg:phone":"+1 307 527 7398",
    "sg:postcode":"82414",
    "sg:province":"WY",
    "sg:tags":[
        "dance"
    ],
    "wof:name":"Cody Center For Performing Art",
    "wof:placetype":"venue"
},
  "geometry": {"coordinates":[-109.078311,44.516625],"type":"Point"}
}