{
  "type": "Feature",
  "properties": {
    "addr:full":"503 Jackson St Belle Fourche WY 57717",
    "addr:housenumber":"503",
    "addr:postcode":"57717",
    "addr:street":"Jackson St;Fourche Wy",
    "iso:country":"US",
    "sg:address":"503 Jackson St",
    "sg:city":"Belle Fourche",
    "sg:classifiers":[
        {
            "category":"Health Services",
            "subcategory":"Doctor",
            "type":"Services"
        }
    ],
    "sg:phone":"+1 605 892 6347",
    "sg:postcode":"57717",
    "sg:province":"WY",
    "wof:name":"Jackson Dental Clinic",
    "wof:placetype":"venue"
},
  "geometry": {"coordinates":[-103.85347299999999,44.66696],"type":"Point"}
}