{
  "type": "Feature",
  "properties": {
    "iso:country":"US",
    "sg:address":"1530 Kdc Ln",
    "sg:city":"Jackson",
    "sg:classifiers":[
        {
            "category":"Manufacturing",
            "subcategory":"Tools & Machinery",
            "type":"Manufacturing & Wholesale Goods"
        }
    ],
    "sg:phone":"+1 307 739 9150",
    "sg:postcode":"83001",
    "sg:province":"WY",
    "sg:tags":[
        "equipment",
        "refrigeration"
    ],
    "wof:name":"Rammell Refrigeration & Elec",
    "wof:placetype":"venue"
},
  "geometry": {"coordinates":[-110.731047,43.362788],"type":"Point"}
}