{
  "type": "Feature",
  "properties": {
    "addr:full":"5310 US Hwy 16 Newcastle WY 82701",
    "addr:housenumber":"5310",
    "addr:postcode":"82701",
    "addr:street":"Us Hwy 16 Newcastle Wy",
    "iso:country":"US",
    "sg:address":"5310 US Hwy 16",
    "sg:city":"Newcastle",
    "sg:classifiers":[
        {
            "category":"Building & Trades",
            "subcategory":"Construction",
            "type":"Services"
        }
    ],
    "sg:phone":"+1 307 746 2476",
    "sg:postcode":"82701",
    "sg:province":"WY",
    "sg:tags":[
        "residential"
    ],
    "wof:name":"Sundstrom Construction Inc",
    "wof:placetype":"venue"
},
  "geometry": {"coordinates":[-104.140231,43.820918],"type":"Point"}
}