{
  "type": "Feature",
  "properties": {
    "iso:country":"US",
    "sg:address":"74 State Hwy 352",
    "sg:city":"Pinedale",
    "sg:classifiers":[
        {
            "category":"Manufacturing",
            "subcategory":"Buildings",
            "type":"Manufacturing & Wholesale Goods"
        }
    ],
    "sg:phone":"+1 307 367 6388",
    "sg:postcode":"82925",
    "sg:province":"WY",
    "sg:tags":[
        "home",
        "log",
        "cabin"
    ],
    "wof:name":"Binning Mill Inc",
    "wof:placetype":"venue"
},
  "geometry": {"coordinates":[-109.98081500000001,42.902525],"type":"Point"}
}