{
  "type": "Feature",
  "properties": {
    "iso:country":"US",
    "sg:address":"1155 E Richards St",
    "sg:city":"Douglas",
    "sg:classifiers":[
        {
            "category":"Retail",
            "subcategory":"Car Wash",
            "type":"Services"
        }
    ],
    "sg:phone":"+1 307 358 9474",
    "sg:postcode":"82633",
    "sg:province":"WY",
    "sg:tags":[
        "carwash"
    ],
    "wof:name":"Raceway Lube & Wash",
    "wof:placetype":"venue"
},
  "geometry": {"coordinates":[-105.37302699999999,42.748375],"type":"Point"}
}