{
  "type": "Feature",
  "properties": {
    "iso:country":"US",
    "sg:address":"1320 S Oak St",
    "sg:city":"Casper",
    "sg:classifiers":[
        {
            "category":"Health Services",
            "subcategory":"Doctor",
            "type":"Services"
        }
    ],
    "sg:phone":"+1 307 472 3022",
    "sg:postcode":"82601",
    "sg:province":"WY",
    "sg:tags":[
        "medical"
    ],
    "wof:name":"Amador R Cantu DO LLC",
    "wof:placetype":"venue"
},
  "geometry": {"coordinates":[-106.33072300000001,42.836736],"type":"Point"}
}