{
  "type": "Feature",
  "properties": {
    "addr:full":"1424 Griffith Way Douglas WY 82633",
    "addr:housenumber":"1424",
    "addr:postcode":"82633",
    "addr:street":"Griffith Way Douglas Wy",
    "iso:country":"US",
    "sg:address":"1424 Griffith Way",
    "sg:city":"Douglas",
    "sg:classifiers":[
        {
            "category":"Organizations",
            "subcategory":"Religious Organization",
            "type":"Services"
        }
    ],
    "sg:phone":"+1 307 358 4815",
    "sg:postcode":"82633",
    "sg:province":"WY",
    "sg:tags":[
        "church"
    ],
    "wof:name":"Trinity Baptist Church",
    "wof:placetype":"venue"
},
  "geometry": {"coordinates":[-105.40595500000001,42.758127],"type":"Point"}
}