{
  "type": "Feature",
  "properties": {
    "iso:country":"US",
    "sg:address":"2901 Dogwood Ave",
    "sg:city":"Gillette",
    "sg:classifiers":[
        {
            "category":"Retail",
            "subcategory":"Auto Repair",
            "type":"Services"
        }
    ],
    "sg:phone":"+1 307 686 2259",
    "sg:postcode":"82718",
    "sg:province":"WY",
    "sg:tags":[
        "repairing",
        "automobile"
    ],
    "wof:name":"Ideal Auto Inc",
    "wof:placetype":"venue"
},
  "geometry": {"coordinates":[-105.503709,44.268373],"type":"Point"}
}