{
  "type": "Feature",
  "properties": {
    "iso:country":"US",
    "sg:address":"1712 Terra Ave",
    "sg:city":"Sheridan",
    "sg:classifiers":[
        {
            "category":"Building & Trades",
            "subcategory":"Construction",
            "type":"Services"
        }
    ],
    "sg:phone":"+1 307 673 4364",
    "sg:postcode":"82801",
    "sg:province":"WY",
    "sg:tags":[
        "contractor"
    ],
    "wof:name":"LLC Moore Glass",
    "wof:placetype":"venue"
},
  "geometry": {"coordinates":[-106.946161,44.778419],"type":"Point"}
}