{
  "type": "Feature",
  "properties": {
    "addr:full":"3348 Ridge Rd Cheyenne WY 82001",
    "addr:housenumber":"3348",
    "addr:postcode":"82001",
    "addr:street":"Ridge Rd",
    "iso:country":"US",
    "sg:address":"3348 Ridge Rd",
    "sg:city":"Cheyenne",
    "sg:classifiers":[
        {
            "category":"Insurance",
            "subcategory":"Insurance Agent",
            "type":"Services"
        }
    ],
    "sg:phone":"+1 307 638 0286",
    "sg:postcode":"82001",
    "sg:province":"WY",
    "wof:name":"State Farm Insurance",
    "wof:placetype":"venue"
},
  "geometry": {"coordinates":[-104.768539,41.146478],"type":"Point"}
}