{
  "type": "Feature",
  "properties": {
    "iso:country":"US",
    "sg:address":"3708 E Pershing Blvd",
    "sg:city":"Cheyenne",
    "sg:classifiers":[
        {
            "category":"Health Services",
            "subcategory":"Doctor",
            "type":"Services"
        }
    ],
    "sg:phone":"+1 307 634 9111",
    "sg:postcode":"82001",
    "sg:province":"WY",
    "wof:name":"Donahue Jerri Ann DDS",
    "wof:placetype":"venue"
},
  "geometry": {"coordinates":[-104.76468300000001,41.145655],"type":"Point"}
}