{
  "type": "Feature",
  "properties": {
    "iso:country":"US",
    "sg:address":"314 W 18th St",
    "sg:city":"Cheyenne",
    "sg:classifiers":[
        {
            "category":"Professional",
            "subcategory":"Management & Consulting",
            "type":"Services"
        }
    ],
    "sg:phone":"+1 307 638 6137",
    "sg:postcode":"82001",
    "sg:province":"WY",
    "sg:tags":[
        "fuel"
    ],
    "wof:name":"Micale Management",
    "wof:placetype":"venue"
},
  "geometry": {"coordinates":[-104.818077,41.133974],"type":"Point"}
}