{
  "type": "Feature",
  "properties": {
    "addr:full":"525 S 5th St Thermopolis WY 82443",
    "addr:housenumber":"525",
    "addr:postcode":"82443",
    "addr:street":"S 5Th St Thermopolis Wy",
    "iso:country":"US",
    "sg:address":"525 S 5th St",
    "sg:city":"Thermopolis",
    "sg:classifiers":[
        {
            "category":"Shopping",
            "subcategory":"Bicycles & Sporting Goods",
            "type":"Retail Goods"
        }
    ],
    "sg:phone":"+1 307 864 3602",
    "sg:postcode":"82443",
    "sg:province":"WY",
    "sg:tags":[
        "gun",
        "gunsmith"
    ],
    "wof:name":"Diamond R Gun Repair",
    "wof:placetype":"venue"
},
  "geometry": {"coordinates":[-108.210303,43.641334],"type":"Point"}
}