{
  "type": "Feature",
  "properties": {
    "iso:country":"US",
    "sg:address":"13 Pineview Ct",
    "sg:city":"Gillette",
    "sg:classifiers":[
        {
            "category":"Wholesale",
            "subcategory":"Construction Materials",
            "type":"Manufacturing & Wholesale Goods"
        },
        {
            "category":"Building & Trades",
            "subcategory":"Construction",
            "type":"Services"
        }
    ],
    "sg:phone":"+1 307 686 6459",
    "sg:postcode":"82716",
    "sg:province":"WY",
    "sg:tags":[
        "siding",
        "contractor"
    ],
    "wof:name":"Brook's Siding & Construction",
    "wof:placetype":"venue"
},
  "geometry": {"coordinates":[-105.58564,44.45398],"type":"Point"}
}