{
  "type": "Feature",
  "properties": {
    "iso:country":"US",
    "sg:address":"507 W 29th St",
    "sg:city":"Cheyenne",
    "sg:classifiers":[
        {
            "category":"Health Services",
            "subcategory":"Chiropractor",
            "type":"Services"
        }
    ],
    "sg:phone":"+1 307 433 8853",
    "sg:postcode":"82001",
    "sg:province":"WY",
    "wof:name":"29th Street Health Center PC",
    "wof:placetype":"venue"
},
  "geometry": {"coordinates":[-104.82719,41.142531],"type":"Point"}
}