{
  "type": "Feature",
  "properties": {
    "addr:full":"365 N 4th St Rock River WY 82083",
    "addr:housenumber":"365",
    "addr:postcode":"82083",
    "addr:street":"N 4Th St Rock River Wy",
    "iso:country":"US",
    "sg:address":"365 N 4th St",
    "sg:city":"Rock River",
    "sg:classifiers":[
        {
            "category":"Food & Beverages",
            "subcategory":"Groceries & Convenience Stores",
            "type":"Retail Goods"
        }
    ],
    "sg:phone":"+1 307 378 2555",
    "sg:postcode":"82083",
    "sg:province":"WY",
    "wof:name":"Shop",
    "wof:placetype":"venue"
},
  "geometry": {"coordinates":[-105.97541099999999,41.743606],"type":"Point"}
}