{
  "type": "Feature",
  "properties": {
    "iso:country":"US",
    "sg:address":"500 W Lott St",
    "sg:city":"Buffalo",
    "sg:classifiers":[
        {
            "category":"Wholesale",
            "subcategory":"Machinery & Supplies",
            "type":"Manufacturing & Wholesale Goods"
        }
    ],
    "sg:phone":"+1 307 684 8510",
    "sg:postcode":"82834",
    "sg:province":"WY",
    "sg:tags":[
        "equipment",
        "industrial"
    ],
    "wof:name":"Natural Gas Compression System",
    "wof:placetype":"venue"
},
  "geometry": {"coordinates":[-106.70733300000001,44.349739],"type":"Point"}
}