{
  "type": "Feature",
  "properties": {
    "iso:country":"US",
    "sg:address":"606 SW Wyoming Blvd",
    "sg:city":"Mills",
    "sg:classifiers":[
        {
            "category":"Home & Garden",
            "subcategory":"Building Materials",
            "type":"Retail Goods"
        }
    ],
    "sg:phone":"+1 307 237 9333",
    "sg:postcode":"82644",
    "sg:province":"WY",
    "sg:tags":[
        "mixed",
        "concrete"
    ],
    "wof:name":"Mobile Concrete Inc",
    "wof:placetype":"venue"
},
  "geometry": {"coordinates":[-106.375022,42.841482],"type":"Point"}
}