{
  "type": "Feature",
  "properties": {
    "iso:country":"US",
    "sg:address":"1901 Energy Ct",
    "sg:city":"Gillette",
    "sg:classifiers":[
        {
            "category":"Government",
            "subcategory":"Office",
            "type":"Public Place"
        }
    ],
    "sg:phone":"+1 307 682 1796",
    "sg:postcode":"82718",
    "sg:province":"WY",
    "wof:name":"Division Of Criminal Invest",
    "wof:placetype":"venue"
},
  "geometry": {"coordinates":[-105.49254000000001,44.27727],"type":"Point"}
}