{
  "type": "Feature",
  "properties": {
    "iso:country":"US",
    "sg:address":"3051 Ridgecrest Dr",
    "sg:city":"Gillette",
    "sg:classifiers":[
        {
            "category":"Real Estate",
            "subcategory":"Real Estate Operator",
            "type":"Services"
        }
    ],
    "sg:phone":"+1 307 682 5432",
    "sg:postcode":"82718",
    "sg:province":"WY",
    "sg:tags":[
        "building",
        "nonresidential"
    ],
    "wof:name":"Snead Properties LLC",
    "wof:placetype":"venue"
},
  "geometry": {"coordinates":[-105.521275,44.269056],"type":"Point"}
}