{
  "type": "Feature",
  "properties": {
    "addr:full":"225 N Cache Dr Jackson WY 83001",
    "addr:housenumber":"225",
    "addr:postcode":"83001",
    "addr:street":"N Cache Dr Jackson Wy",
    "iso:country":"US",
    "sg:address":"225 N Cache Dr",
    "sg:city":"Jackson",
    "sg:classifiers":[
        {
            "category":"Restaurant",
            "type":"Food & Drink"
        }
    ],
    "sg:phone":"+1 307 734 6490",
    "sg:postcode":"83001",
    "sg:province":"WY",
    "sg:tags":[
        "eating"
    ],
    "wof:name":"Nikai",
    "wof:placetype":"venue"
},
  "geometry": {"coordinates":[-110.762455,43.482292],"type":"Point"}
}