{
  "type": "Feature",
  "properties": {
    "iso:country":"US",
    "sg:address":"3633 Crook Dr",
    "sg:city":"Torrington",
    "sg:classifiers":[
        {
            "category":"Building & Trades",
            "subcategory":"Landscaping Services",
            "type":"Services"
        }
    ],
    "sg:phone":"+1 307 532 5798",
    "sg:postcode":"82240",
    "sg:province":"WY",
    "sg:tags":[
        "tree"
    ],
    "wof:name":"Barber Tree Svc",
    "wof:placetype":"venue"
},
  "geometry": {"coordinates":[-104.19162,42.085741],"type":"Point"}
}