{
  "type": "Feature",
  "properties": {
    "iso:country":"US",
    "sg:address":"289 Hunter Creek Rd",
    "sg:city":"Cody",
    "sg:classifiers":[
        {
            "category":"Farming",
            "subcategory":"Livestock Farm",
            "type":"Manufacturing & Wholesale Goods"
        }
    ],
    "sg:phone":"+1 307 587 3731",
    "sg:postcode":"82414",
    "sg:province":"WY",
    "sg:tags":[
        "beef",
        "feedlot",
        "cattle"
    ],
    "wof:name":"A 2 Z Ranch",
    "wof:placetype":"venue"
},
  "geometry": {"coordinates":[-109.57041,44.178979],"type":"Point"}
}