{
  "type": "Feature",
  "properties": {
    "addr:full":"65 S Glenwood St Jackson WY 83001",
    "addr:housenumber":"65",
    "addr:postcode":"83001",
    "addr:street":"S Glenwood St Jackson Wy",
    "iso:country":"US",
    "sg:address":"65 S Glenwood St",
    "sg:city":"Jackson",
    "sg:classifiers":[
        {
            "category":"Shopping",
            "type":"Retail Goods"
        }
    ],
    "sg:phone":"+1 307 732 2112",
    "sg:postcode":"83001",
    "sg:province":"WY",
    "sg:tags":[
        "art",
        "gallery",
        "dealer"
    ],
    "wof:name":"Game Trail Gathering",
    "wof:placetype":"venue"
},
  "geometry": {"coordinates":[-110.763791,43.478845],"type":"Point"}
}