{
  "type": "Feature",
  "properties": {
    "iso:country":"US",
    "sg:address":"1345 Monument St",
    "sg:city":"Cody",
    "sg:classifiers":[
        {
            "category":"Social Services",
            "subcategory":"Child Care",
            "type":"Services"
        }
    ],
    "sg:phone":"+1 307 587 2567",
    "sg:postcode":"82414",
    "sg:province":"WY",
    "sg:tags":[
        "organization",
        "religious",
        "day"
    ],
    "wof:name":"St Anthony Pre School",
    "wof:placetype":"venue"
},
  "geometry": {"coordinates":[-109.07647299999999,44.52469],"type":"Point"}
}