{
  "type": "Feature",
  "properties": {
    "iso:country":"US",
    "sg:address":"824 Ridge Ave",
    "sg:city":"Rock Springs",
    "sg:classifiers":[
        {
            "category":"Building & Trades",
            "subcategory":"Construction",
            "type":"Services"
        }
    ],
    "sg:phone":"+1 307 362 6091",
    "sg:postcode":"82901",
    "sg:province":"WY",
    "sg:tags":[
        "painter"
    ],
    "wof:name":"James Brothers",
    "wof:placetype":"venue"
},
  "geometry": {"coordinates":[-109.219255,41.596119],"type":"Point"}
}