{
  "type": "Feature",
  "properties": {
    "iso:country":"US",
    "sg:address":"1463 Cootes Ave",
    "sg:city":"Hillsdale",
    "sg:classifiers":[
        {
            "category":"Government",
            "subcategory":"Post Office",
            "type":"Public Place"
        }
    ],
    "sg:phone":"+1 307 547 9250",
    "sg:postcode":"82060",
    "sg:province":"WY",
    "wof:name":"US Post Office",
    "wof:placetype":"venue"
},
  "geometry": {"coordinates":[-104.478283,41.211108],"type":"Point"}
}