{
  "type": "Feature",
  "properties": {
    "addr:full":"130 Rio Vista Ave Cody WY 82414",
    "addr:housenumber":"130",
    "addr:postcode":"82414",
    "addr:street":"Rio Vista Ave",
    "iso:country":"US",
    "sg:address":"130 Rio Vista Ave",
    "sg:city":"Cody",
    "sg:classifiers":[
        {
            "category":"Wholesale",
            "subcategory":"Hardware",
            "type":"Manufacturing & Wholesale Goods"
        }
    ],
    "sg:phone":"+1 307 527 7813",
    "sg:postcode":"82414",
    "sg:province":"WY",
    "sg:tags":[
        "tool"
    ],
    "wof:name":"Reed Tool Co",
    "wof:placetype":"venue"
},
  "geometry": {"coordinates":[-109.10039999999999,44.51209],"type":"Point"}
}