{
  "type": "Feature",
  "properties": {
    "addr:full":"3716 Garman Rd Gillette WY 82716",
    "addr:housenumber":"3716",
    "addr:postcode":"82716",
    "addr:street":"Garman Rd",
    "iso:country":"US",
    "sg:address":"3716 Garman Rd",
    "sg:city":"Gillette",
    "sg:classifiers":[
        {
            "category":"Building & Trades",
            "subcategory":"Construction",
            "type":"Services"
        }
    ],
    "sg:phone":"+1 307 682 4877",
    "sg:postcode":"82716",
    "sg:province":"WY",
    "sg:tags":[
        "well",
        "drilling"
    ],
    "wof:name":"AMW Svc",
    "wof:placetype":"venue"
},
  "geometry": {"coordinates":[-105.521382,44.330504],"type":"Point"}
}