{
  "type": "Feature",
  "properties": {
    "iso:country":"US",
    "sg:address":"925 W Birch St",
    "sg:city":"Glenrock",
    "sg:classifiers":[
        {
            "category":"Health Services",
            "subcategory":"Hospital",
            "type":"Services"
        }
    ],
    "sg:phone":"+1 307 436 8335",
    "sg:postcode":"82637",
    "sg:province":"WY",
    "sg:tags":[
        "mental"
    ],
    "wof:name":"Eastern Wyoming Mental Health",
    "wof:placetype":"venue"
},
  "geometry": {"coordinates":[-105.88163299999999,42.861522],"type":"Point"}
}