{
  "type": "Feature",
  "properties": {
    "iso:country":"US",
    "sg:address":"4200 W Yellowstone Hwy",
    "sg:city":"Casper",
    "sg:classifiers":[
        {
            "category":"Personal",
            "subcategory":"Beauty Salon",
            "type":"Services"
        }
    ],
    "sg:phone":"+1 307 237 3441",
    "sg:postcode":"82604",
    "sg:province":"WY",
    "sg:tags":[
        "shop"
    ],
    "wof:name":"Country Cottage Salon",
    "wof:placetype":"venue"
},
  "geometry": {"coordinates":[-106.377815,42.849066],"type":"Point"}
}