{
  "type": "Feature",
  "properties": {
    "iso:country":"US",
    "sg:address":"2700 Commercial Way",
    "sg:city":"Rock Springs",
    "sg:classifiers":[
        {
            "category":"Manufacturing",
            "subcategory":"Tools & Machinery",
            "type":"Manufacturing & Wholesale Goods"
        }
    ],
    "sg:phone":"+1 307 362 6710",
    "sg:postcode":"82901",
    "sg:province":"WY",
    "sg:tags":[
        "machine",
        "shop"
    ],
    "wof:name":"Pioneer Engine Svc",
    "wof:placetype":"venue"
},
  "geometry": {"coordinates":[-109.254187,41.582451],"type":"Point"}
}