{
  "type": "Feature",
  "properties": {
    "addr:full":"160 S Main St Thayne WY 83127",
    "addr:housenumber":"160",
    "addr:postcode":"83127",
    "addr:street":"S Main St Thayne Wy",
    "iso:country":"US",
    "sg:address":"160 S Main St",
    "sg:city":"Thayne",
    "sg:classifiers":[
        {
            "category":"Food & Beverages",
            "subcategory":"Groceries & Convenience Stores",
            "type":"Retail Goods"
        }
    ],
    "sg:phone":"+1 307 883 2959",
    "sg:postcode":"83127",
    "sg:province":"WY",
    "wof:name":"Maverik Country Store",
    "wof:placetype":"venue"
},
  "geometry": {"coordinates":[-110.999984,42.913395],"type":"Point"}
}