{
  "type": "Feature",
  "properties": {
    "iso:country":"US",
    "sg:address":"205 Newton Rd",
    "sg:city":"Gillette",
    "sg:classifiers":[
        {
            "category":"Building & Trades",
            "subcategory":"Construction",
            "type":"Services"
        }
    ],
    "sg:phone":"+1 307 685 6465",
    "sg:postcode":"82716",
    "sg:province":"WY",
    "sg:tags":[
        "boring",
        "drilling",
        "contractor"
    ],
    "wof:name":"R & L Methane & Water Well Svc",
    "wof:placetype":"venue"
},
  "geometry": {"coordinates":[-105.532709,44.296169],"type":"Point"}
}