{
  "type": "Feature",
  "properties": {
    "iso:country":"US",
    "sg:address":"101 E Grand Ave",
    "sg:city":"Laramie",
    "sg:classifiers":[
        {
            "category":"Restaurant",
            "type":"Food & Drink"
        }
    ],
    "sg:phone":"+1 307 745 0141",
    "sg:postcode":"82070",
    "sg:province":"WY",
    "wof:name":"Lovejoy's Bar & Grill",
    "wof:placetype":"venue"
},
  "geometry": {"coordinates":[-105.596191,41.311175],"type":"Point"}
}