{
  "type": "Feature",
  "properties": {
    "addr:full":"5734 Old Yellowstone Hwy Casper WY 82644",
    "addr:housenumber":"5734",
    "addr:postcode":"82644",
    "addr:street":"Old Yellowstone Hwy",
    "iso:country":"US",
    "sg:address":"5734 Old Yellowstone Hwy",
    "sg:city":"Casper",
    "sg:classifiers":[
        {
            "category":"Wholesale",
            "subcategory":"Books, Periodicals, & Newspapers",
            "type":"Manufacturing & Wholesale Goods"
        }
    ],
    "sg:phone":"+1 307 266 5328",
    "sg:postcode":"82644",
    "sg:province":"WY",
    "wof:name":"Anderson News Company",
    "wof:placetype":"venue"
},
  "geometry": {"coordinates":[-106.406047,42.867305],"type":"Point"}
}