{
  "type": "Feature",
  "properties": {
    "iso:country":"US",
    "sg:address":"1032 Alger Ave",
    "sg:city":"Cody",
    "sg:classifiers":[
        {
            "category":"Organizations",
            "subcategory":"Non-profit Organization",
            "type":"Services"
        }
    ],
    "sg:phone":"+1 307 587 7881",
    "sg:postcode":"82414",
    "sg:province":"WY",
    "sg:tags":[
        "disability"
    ],
    "wof:name":"Wyoming Independent Living",
    "wof:placetype":"venue"
},
  "geometry": {"coordinates":[-109.067251,44.523832],"type":"Point"}
}