{
  "type": "Feature",
  "properties": {
    "addr:full":"516 Randall Ave Cheyenne WY 82001",
    "addr:housenumber":"516",
    "addr:postcode":"82001",
    "addr:street":"Randall Ave",
    "iso:country":"US",
    "sg:address":"516 Randall Ave",
    "sg:city":"Cheyenne",
    "sg:classifiers":[
        {
            "category":"Professional",
            "subcategory":"Computer Services",
            "type":"Services"
        }
    ],
    "sg:phone":"+1 307 638 7614",
    "sg:postcode":"82001",
    "sg:province":"WY",
    "sg:tags":[
        "consultant",
        "designer"
    ],
    "wof:name":"ERC Computing Svc",
    "wof:placetype":"venue"
},
  "geometry": {"coordinates":[-104.827029,41.142548],"type":"Point"}
}