{
  "type": "Feature",
  "properties": {
    "addr:full":"2208 E Fox Farm Rd Cheyenne WY 82007",
    "addr:housenumber":"2208",
    "addr:postcode":"82007",
    "addr:street":"E Fox Farm Rd",
    "iso:country":"US",
    "sg:address":"2208 E Fox Farm Rd",
    "sg:city":"Cheyenne",
    "sg:classifiers":[
        {
            "category":"Building & Trades",
            "subcategory":"Construction",
            "type":"Services"
        }
    ],
    "sg:phone":"+1 307 635 5460",
    "sg:postcode":"82007",
    "sg:province":"WY",
    "sg:tags":[
        "repairing",
        "remodeling",
        "contractor"
    ],
    "wof:name":"Valley Construction",
    "wof:placetype":"venue"
},
  "geometry": {"coordinates":[-104.77758,41.116742],"type":"Point"}
}