{
  "type": "Feature",
  "properties": {
    "addr:full":"152 N 5th St Laramie WY 82072",
    "addr:housenumber":"152",
    "addr:postcode":"82072",
    "addr:street":"N 5Th St",
    "iso:country":"US",
    "sg:address":"152 N 5th St",
    "sg:city":"Laramie",
    "sg:classifiers":[
        {
            "category":"Government",
            "subcategory":"Post Office",
            "type":"Public Place"
        }
    ],
    "sg:phone":"+1 307 721 8837",
    "sg:postcode":"82072",
    "sg:province":"WY",
    "wof:name":"US Post Office",
    "wof:placetype":"venue"
},
  "geometry": {"coordinates":[-105.59079300000001,41.313185],"type":"Point"}
}