{
  "type": "Feature",
  "properties": {
    "iso:country":"US",
    "sg:address":"57 Tweed Ln",
    "sg:city":"Lander",
    "sg:classifiers":[
        {
            "category":"Building & Trades",
            "subcategory":"Construction",
            "type":"Services"
        }
    ],
    "sg:phone":"+1 307 332 9493",
    "sg:postcode":"82520",
    "sg:province":"WY",
    "sg:tags":[
        "general",
        "contractor"
    ],
    "wof:name":"Artery Construction",
    "wof:placetype":"venue"
},
  "geometry": {"coordinates":[-108.746876,42.844194],"type":"Point"}
}