{
  "type": "Feature",
  "properties": {
    "iso:country":"US",
    "sg:address":"4524 E Yellowstone Hwy",
    "sg:city":"Evansville",
    "sg:classifiers":[
        {
            "category":"Personal",
            "subcategory":"Beauty Salon",
            "type":"Services"
        }
    ],
    "sg:phone":"+1 307 265 3210",
    "sg:postcode":"82604",
    "sg:province":"WY",
    "wof:name":"Shear Wonders",
    "wof:placetype":"venue"
},
  "geometry": {"coordinates":[-106.2672,42.85792],"type":"Point"}
}