{
  "type": "Feature",
  "properties": {
    "addr:full":"1605 Capitol Ave Cheyenne WY 82001",
    "addr:housenumber":"1605",
    "addr:postcode":"82001",
    "addr:street":"Capitol Ave",
    "iso:country":"US",
    "sg:address":"1605 Capitol Ave",
    "sg:city":"Cheyenne",
    "sg:classifiers":[
        {
            "category":"Shopping",
            "subcategory":"Clothing, Apparel, & Fashions",
            "type":"Retail Goods"
        }
    ],
    "sg:phone":"+1 307 632 1173",
    "sg:postcode":"82001",
    "sg:province":"WY",
    "wof:name":"Emporium The",
    "wof:placetype":"venue"
},
  "geometry": {"coordinates":[-104.815764,41.133617],"type":"Point"}
}