{
  "type": "Feature",
  "properties": {
    "iso:country":"US",
    "sg:address":"217 W 3rd St",
    "sg:city":"Pine Bluffs",
    "sg:classifiers":[
        {
            "category":"Recreation",
            "type":"Entertainment"
        }
    ],
    "sg:phone":"+1 307 245 3301",
    "sg:postcode":"82082",
    "sg:province":"WY",
    "sg:tags":[
        "parks"
    ],
    "wof:name":"Pine Bluff Recreation Director",
    "wof:placetype":"venue"
},
  "geometry": {"coordinates":[-104.071028,41.182005],"type":"Point"}
}