{
  "type": "Feature",
  "properties": {
    "iso:country":"US",
    "sg:address":"21 W 3rd Ave",
    "sg:city":"Afton",
    "sg:classifiers":[
        {
            "category":"Shopping",
            "subcategory":"Bicycles & Sporting Goods",
            "type":"Retail Goods"
        }
    ],
    "sg:phone":"+1 307 885 3672",
    "sg:postcode":"83110",
    "sg:province":"WY",
    "sg:tags":[
        "saddlery",
        "harness"
    ],
    "wof:name":"Western Wyoming Horsemen Co",
    "wof:placetype":"venue"
},
  "geometry": {"coordinates":[-110.936055,42.727542],"type":"Point"}
}