{
  "type": "Feature",
  "properties": {
    "addr:full":"1911 Big Horn Ave Worland WY 82401",
    "addr:housenumber":"1911",
    "addr:postcode":"82401",
    "addr:street":"Big Horn Ave",
    "iso:country":"US",
    "sg:address":"1911 Big Horn Ave",
    "sg:city":"Worland",
    "sg:classifiers":[
        {
            "category":"Retail",
            "subcategory":"Repair Shop",
            "type":"Services"
        }
    ],
    "sg:phone":"+1 307 347 8119",
    "sg:postcode":"82401",
    "sg:province":"WY",
    "sg:tags":[
        "industrial",
        "merchandise"
    ],
    "wof:name":"Mowers Plus",
    "wof:placetype":"venue"
},
  "geometry": {"coordinates":[-107.943258,44.016902],"type":"Point"}
}