{
  "type": "Feature",
  "properties": {
    "addr:full":"1810 S Douglas Hwy Gillette WY 82718",
    "addr:housenumber":"1810",
    "addr:postcode":"82718",
    "addr:street":"S Douglas Hwy",
    "iso:country":"US",
    "sg:address":"1810 S Douglas Hwy",
    "sg:city":"Gillette",
    "sg:classifiers":[
        {
            "category":"Autos & Motor Vehicles",
            "subcategory":"Fuel & Gas Station",
            "type":"Retail Goods"
        }
    ],
    "sg:phone":"+1 307 682 3562",
    "sg:postcode":"82718",
    "sg:province":"WY",
    "sg:tags":[
        "plaza",
        "truck",
        "stops"
    ],
    "wof:name":"Flying J Travel Plaza",
    "wof:placetype":"venue"
},
  "geometry": {"coordinates":[-105.494046,44.27803],"type":"Point"}
}