{
  "type": "Feature",
  "properties": {
    "addr:full":"202 N 7th St Worland WY 82401",
    "addr:housenumber":"202",
    "addr:postcode":"82401",
    "addr:street":"N 7Th St Worland Wy",
    "iso:country":"US",
    "sg:address":"202 N 7th St",
    "sg:city":"Worland",
    "sg:classifiers":[
        {
            "category":"Manufacturing",
            "subcategory":"Printing",
            "type":"Manufacturing & Wholesale Goods"
        }
    ],
    "sg:phone":"+1 307 347 9211",
    "sg:postcode":"82401",
    "sg:province":"WY",
    "sg:tags":[
        "printer"
    ],
    "wof:name":"Hi Country Printing",
    "wof:placetype":"venue"
},
  "geometry": {"coordinates":[-107.95979699999999,44.018886],"type":"Point"}
}