{
  "type": "Feature",
  "properties": {
    "iso:country":"US",
    "sg:address":"3729 E Lincolnway",
    "sg:city":"Cheyenne",
    "sg:classifiers":[
        {
            "category":"Personal",
            "subcategory":"Shoe Repair & Shine",
            "type":"Services"
        }
    ],
    "sg:phone":"+1 307 638 9751",
    "sg:postcode":"82001",
    "sg:province":"WY",
    "sg:tags":[
        "parlor"
    ],
    "wof:name":"Georges Shoe Repair",
    "wof:placetype":"venue"
},
  "geometry": {"coordinates":[-104.763488,41.140767],"type":"Point"}
}