{
  "type": "Feature",
  "properties": {
    "addr:full":"500 N 6th St Greybull WY 82426",
    "addr:housenumber":"500",
    "addr:postcode":"82426",
    "addr:street":"N 6Th St Greybull Wy",
    "iso:country":"US",
    "sg:address":"500 N 6th St",
    "sg:city":"Greybull",
    "sg:classifiers":[
        {
            "category":"Food & Beverages",
            "subcategory":"Groceries & Convenience Stores",
            "type":"Retail Goods"
        }
    ],
    "sg:phone":"+1 307 765 2162",
    "sg:postcode":"82426",
    "sg:province":"WY",
    "wof:name":"Express Mart",
    "wof:placetype":"venue"
},
  "geometry": {"coordinates":[-108.05529799999999,44.494485],"type":"Point"}
}