{
  "type": "Feature",
  "properties": {
    "iso:country":"US",
    "sg:address":"1275 N 15th St",
    "sg:city":"Laramie",
    "sg:classifiers":[
        {
            "category":"Mining & Drilling",
            "type":"Manufacturing & Wholesale Goods"
        }
    ],
    "sg:phone":"+1 307 745 4464",
    "sg:postcode":"82072",
    "sg:province":"WY",
    "sg:tags":[
        "development",
        "gas",
        "oil",
        "exploration",
        "research"
    ],
    "wof:name":"Innovative Discovery Tech LLC",
    "wof:placetype":"venue"
},
  "geometry": {"coordinates":[-105.57679400000001,41.324238],"type":"Point"}
}