{
  "type": "Feature",
  "properties": {
    "iso:country":"US",
    "sg:address":"231 2nd St E",
    "sg:city":"Powell",
    "sg:classifiers":[
        {
            "category":"Government",
            "subcategory":"Office",
            "type":"Public Place"
        }
    ],
    "sg:phone":"+1 307 754 6685",
    "sg:postcode":"82435",
    "sg:province":"WY",
    "sg:tags":[
        "agricultural",
        "regulation",
        "marketing"
    ],
    "wof:name":"Agriculture Wyoming Department",
    "wof:placetype":"venue"
},
  "geometry": {"coordinates":[-108.465777,44.885119],"type":"Point"}
}