{
  "type": "Feature",
  "properties": {
    "iso:country":"US",
    "sg:address":"188 Ivy Creek Rd",
    "sg:city":"Arvada",
    "sg:phone":"+1 307 736 2441",
    "sg:postcode":"82831",
    "sg:province":"WY",
    "sg:tags":[
        "farm",
        "wheat"
    ],
    "wof:name":"Ivy Creek Ranch",
    "wof:placetype":"venue"
},
  "geometry": {"coordinates":[-105.9645,44.735969],"type":"Point"}
}