{
  "type": "Feature",
  "properties": {
    "iso:country":"US",
    "sg:address":"1608 Big Horn Ave",
    "sg:city":"Worland",
    "sg:classifiers":[
        {
            "category":"Restaurant",
            "type":"Food & Drink"
        }
    ],
    "sg:phone":"+1 307 347 4222",
    "sg:postcode":"82401",
    "sg:province":"WY",
    "wof:name":"Habanero Mexican Grill",
    "wof:placetype":"venue"
},
  "geometry": {"coordinates":[-107.94699199999999,44.016754],"type":"Point"}
}