{
  "type": "Feature",
  "properties": {
    "iso:country":"US",
    "sg:address":"1901 4th Ave",
    "sg:city":"Gillette",
    "sg:classifiers":[
        {
            "category":"Building & Trades",
            "subcategory":"Construction",
            "type":"Services"
        }
    ],
    "sg:phone":"+1 307 682 2104",
    "sg:postcode":"82716",
    "sg:province":"WY",
    "sg:tags":[
        "general",
        "contractor"
    ],
    "wof:name":"Home Specialists Inc",
    "wof:placetype":"venue"
},
  "geometry": {"coordinates":[-105.52885999999999,44.303609],"type":"Point"}
}