{
  "type": "Feature",
  "properties": {
    "addr:full":"695 Jensen St Green River WY 82935",
    "addr:housenumber":"695",
    "addr:postcode":"82935",
    "addr:street":"Jensen St Green River Wy",
    "iso:country":"US",
    "sg:address":"695 Jensen St",
    "sg:city":"Green River",
    "sg:classifiers":[
        {
            "category":"Manufacturing",
            "subcategory":"Metals",
            "type":"Manufacturing & Wholesale Goods"
        }
    ],
    "sg:phone":"+1 307 875 6709",
    "sg:postcode":"82935",
    "sg:province":"WY",
    "sg:tags":[
        "ornamental",
        "work"
    ],
    "wof:name":"3 J's Fab",
    "wof:placetype":"venue"
},
  "geometry": {"coordinates":[-109.46966999999999,41.51252],"type":"Point"}
}