{
  "type": "Feature",
  "properties": {
    "addr:full":"2101 O Neil Ave Cheyenne WY 82001",
    "addr:housenumber":"2101",
    "addr:postcode":"82001",
    "addr:street":"O Neil Ave",
    "iso:country":"US",
    "sg:address":"2101 O Neil Ave",
    "sg:city":"Cheyenne",
    "sg:classifiers":[
        {
            "category":"Government",
            "subcategory":"Office",
            "type":"Public Place"
        }
    ],
    "sg:phone":"+1 307 637 6458",
    "sg:postcode":"82001",
    "sg:province":"WY",
    "sg:tags":[
        "botanic",
        "support",
        "garden"
    ],
    "wof:name":"Friends of Chynne Btanic Grdns",
    "wof:placetype":"venue"
},
  "geometry": {"coordinates":[-104.805761,41.095454],"type":"Point"}
}