{
  "type": "Feature",
  "properties": {
    "addr:full":"3401 E 2nd St Gillette WY 82718",
    "addr:housenumber":"3401",
    "addr:postcode":"82718",
    "addr:street":"E 2Nd St",
    "iso:country":"US",
    "sg:address":"3401 E 2nd St",
    "sg:city":"Gillette",
    "sg:classifiers":[
        {
            "category":"Manufacturing",
            "subcategory":"Food",
            "type":"Manufacturing & Wholesale Goods"
        }
    ],
    "sg:phone":"+1 307 682 3377",
    "sg:postcode":"82718",
    "sg:province":"WY",
    "sg:tags":[
        "processing",
        "milk"
    ],
    "wof:name":"Gillette Dairy",
    "wof:placetype":"venue"
},
  "geometry": {"coordinates":[-105.451173,44.292753],"type":"Point"}
}