{
  "type": "Feature",
  "properties": {
    "iso:country":"US",
    "sg:address":"313 N Main St",
    "sg:city":"Buffalo",
    "sg:classifiers":[
        {
            "category":"Travel",
            "subcategory":"Hotels & Motels",
            "type":"Entertainment"
        }
    ],
    "sg:phone":"+1 307 684 2218",
    "sg:postcode":"82834",
    "sg:province":"WY",
    "sg:tags":[
        "operation"
    ],
    "sg:website":"www.mansionhouseinn.com",
    "wof:name":"Mansion House Inn",
    "wof:placetype":"venue"
},
  "geometry": {"coordinates":[-106.698953,44.351652],"type":"Point"}
}