{
  "type": "Feature",
  "properties": {
    "iso:country":"US",
    "sg:address":"1945 Schoonover St",
    "sg:city":"Gillette",
    "sg:classifiers":[
        {
            "category":"Professional",
            "subcategory":"Engineering",
            "type":"Services"
        }
    ],
    "sg:phone":"+1 307 686 6409",
    "sg:postcode":"82718",
    "sg:province":"WY",
    "sg:tags":[
        "engineer"
    ],
    "sg:website":"www.cemt.biz",
    "wof:name":"C E & Mt Inc",
    "wof:placetype":"venue"
},
  "geometry": {"coordinates":[-105.472272,44.237158],"type":"Point"}
}