{
  "type": "Feature",
  "properties": {
    "iso:country":"US",
    "sg:address":"411 S Walsh Dr",
    "sg:city":"Casper",
    "sg:classifiers":[
        {
            "category":"Organizations",
            "subcategory":"Religious Organization",
            "type":"Services"
        }
    ],
    "sg:phone":"+1 307 265 4073",
    "sg:postcode":"82609",
    "sg:province":"WY",
    "sg:website":"www.hpcc.cc",
    "wof:name":"Highland Park Community Church",
    "wof:placetype":"venue"
},
  "geometry": {"coordinates":[-106.276445,42.845137],"type":"Point"}
}