{
  "type": "Feature",
  "properties": {
    "iso:country":"US",
    "sg:address":"600 National St",
    "sg:city":"Belle Fourche",
    "sg:classifiers":[
        {
            "category":"Shopping",
            "subcategory":"Pharmacy",
            "type":"Retail Goods"
        }
    ],
    "sg:phone":"+1 605 892 2666",
    "sg:postcode":"57717",
    "sg:province":"WY",
    "wof:name":"Ron's FTC Pharmacy",
    "wof:placetype":"venue"
},
  "geometry": {"coordinates":[-103.850899,44.662586],"type":"Point"}
}