{
  "type": "Feature",
  "properties": {
    "iso:country":"US",
    "sg:address":"123 W 1st St",
    "sg:city":"Casper",
    "sg:classifiers":[
        {
            "category":"Banks & Credit Unions",
            "subcategory":"Investment Brokerage",
            "type":"Services"
        }
    ],
    "sg:phone":"+1 307 266 3500",
    "sg:postcode":"82601",
    "sg:province":"WY",
    "sg:tags":[
        "stock",
        "bond"
    ],
    "wof:name":"Smith Barney",
    "wof:placetype":"venue"
},
  "geometry": {"coordinates":[-106.325625,42.850005],"type":"Point"}
}