{
  "type": "Feature",
  "properties": {
    "addr:full":"3544 Wolf Creek Rd Casper WY 82604",
    "addr:housenumber":"3544",
    "addr:postcode":"82604",
    "addr:street":"Wolf Creek Rd",
    "iso:country":"US",
    "sg:address":"3544 Wolf Creek Rd",
    "sg:city":"Casper",
    "sg:classifiers":[
        {
            "category":"Professional",
            "type":"Services"
        }
    ],
    "sg:phone":"+1 307 235 5166",
    "sg:postcode":"82604",
    "sg:province":"WY",
    "wof:name":"DK Luers LLC",
    "wof:placetype":"venue"
},
  "geometry": {"coordinates":[-106.376544,42.811122],"type":"Point"}
}