{
  "type": "Feature",
  "properties": {
    "iso:country":"US",
    "sg:address":"426 Nevada Ave",
    "sg:city":"Lovell",
    "sg:classifiers":[
        {
            "category":"Health Services",
            "subcategory":"Optometrist",
            "type":"Services"
        }
    ],
    "sg:phone":"+1 307 548 7450",
    "sg:postcode":"82431",
    "sg:province":"WY",
    "wof:name":"Family Vision Clinic",
    "wof:placetype":"venue"
},
  "geometry": {"coordinates":[-108.389364,44.837112],"type":"Point"}
}