{
  "type": "Feature",
  "properties": {
    "iso:country":"US",
    "sg:address":"510 SW Wyoming Blvd",
    "sg:city":"Mills",
    "sg:classifiers":[
        {
            "category":"Shopping",
            "type":"Retail Goods"
        }
    ],
    "sg:phone":"+1 307 472 2982",
    "sg:postcode":"82644",
    "sg:province":"WY",
    "sg:tags":[
        "art",
        "gallery",
        "dealer"
    ],
    "wof:name":"Oui Bee Art",
    "wof:placetype":"venue"
},
  "geometry": {"coordinates":[-106.37395600000001,42.84106],"type":"Point"}
}