{
  "type": "Feature",
  "properties": {
    "iso:country":"US",
    "sg:address":"1537 Beck Ave",
    "sg:city":"Cody",
    "sg:classifiers":[
        {
            "category":"Shopping",
            "subcategory":"Used Merchandise",
            "type":"Retail Goods"
        }
    ],
    "sg:phone":"+1 307 587 6333",
    "sg:postcode":"82414",
    "sg:province":"WY",
    "wof:name":"Bargain Box Furniture Store",
    "wof:placetype":"venue"
},
  "geometry": {"coordinates":[-109.05694,44.525025],"type":"Point"}
}