{
  "type": "Feature",
  "properties": {
    "addr:full":"3307 E 2nd St Gillette WY 82718",
    "addr:housenumber":"3307",
    "addr:postcode":"82718",
    "addr:street":"E 2Nd St",
    "iso:country":"US",
    "sg:address":"3307 E 2nd St",
    "sg:city":"Gillette",
    "sg:classifiers":[
        {
            "category":"Mining & Drilling",
            "type":"Manufacturing & Wholesale Goods"
        }
    ],
    "sg:phone":"+1 307 682 2413",
    "sg:postcode":"82718",
    "sg:province":"WY",
    "sg:tags":[
        "field",
        "c",
        "industrial",
        "equipment"
    ],
    "wof:name":"Weatherford Artfl Lift Systems",
    "wof:placetype":"venue"
},
  "geometry": {"coordinates":[-105.457829,44.292633],"type":"Point"}
}