{
  "type": "Feature",
  "properties": {
    "iso:country":"US",
    "sg:address":"1911 S Chestnut St",
    "sg:city":"Casper",
    "sg:classifiers":[
        {
            "category":"Manufacturing",
            "subcategory":"Tools & Machinery",
            "type":"Manufacturing & Wholesale Goods"
        }
    ],
    "sg:phone":"+1 307 234 8754",
    "sg:postcode":"82601",
    "sg:province":"WY",
    "sg:tags":[
        "equipment",
        "lighting",
        "mfg"
    ],
    "wof:name":"Segment Systems Inc",
    "wof:placetype":"venue"
},
  "geometry": {"coordinates":[-106.33445500000001,42.830168],"type":"Point"}
}