{
  "type": "Feature",
  "properties": {
    "addr:full":"749 Hightower Rd Wheatland WY 82201",
    "addr:housenumber":"749",
    "addr:postcode":"82201",
    "addr:street":"Hightower Rd Wheatland Wy",
    "iso:country":"US",
    "sg:address":"749 Hightower Rd",
    "sg:city":"Wheatland",
    "sg:phone":"+1 307 322 3730",
    "sg:postcode":"82201",
    "sg:province":"WY",
    "sg:tags":[
        "farm",
        "corn",
        "beet"
    ],
    "wof:name":"Lauck & Lauck Farms",
    "wof:placetype":"venue"
},
  "geometry": {"coordinates":[-105.04069,42.016929],"type":"Point"}
}