{
  "type": "Feature",
  "properties": {
    "iso:country":"US",
    "sg:address":"1520 Logan Ave",
    "sg:city":"Cheyenne",
    "sg:classifiers":[
        {
            "category":"Real Estate",
            "subcategory":"Real Estate Agent",
            "type":"Services"
        }
    ],
    "sg:phone":"+1 307 632 0174",
    "sg:postcode":"82001",
    "sg:province":"WY",
    "wof:name":"Homes By Owner Store",
    "wof:placetype":"venue"
},
  "geometry": {"coordinates":[-104.79619700000001,41.139602],"type":"Point"}
}