{
  "type": "Feature",
  "properties": {
    "iso:country":"US",
    "sg:address":"714 S 11th St",
    "sg:city":"Worland",
    "sg:classifiers":[
        {
            "category":"Building & Trades",
            "subcategory":"Electrical",
            "type":"Services"
        }
    ],
    "sg:phone":"+1 307 347 4215",
    "sg:postcode":"82401",
    "sg:province":"WY",
    "sg:tags":[
        "electric",
        "contractor"
    ],
    "wof:name":"Washakie Electric",
    "wof:placetype":"venue"
},
  "geometry": {"coordinates":[-107.95411,44.009703],"type":"Point"}
}