{
  "type": "Feature",
  "properties": {
    "iso:country":"US",
    "sg:address":"615 Dallas Rd",
    "sg:city":"Cheyenne",
    "sg:classifiers":[
        {
            "category":"Professional",
            "subcategory":"Business Services",
            "type":"Services"
        }
    ],
    "sg:phone":"+1 307 635 2148",
    "sg:postcode":"82007",
    "sg:province":"WY",
    "wof:name":"Tri State Design",
    "wof:placetype":"venue"
},
  "geometry": {"coordinates":[-104.806695,41.081029],"type":"Point"}
}