{
  "type": "Feature",
  "properties": {
    "addr:full":"750 E Broadway Jackson WY 83002",
    "addr:housenumber":"750",
    "addr:postcode":"83002",
    "addr:street":"E Broadway Jackson Wy",
    "iso:country":"US",
    "sg:address":"750 E Broadway",
    "sg:city":"Jackson",
    "sg:classifiers":[
        {
            "category":"Travel",
            "subcategory":"Campground",
            "type":"Entertainment"
        }
    ],
    "sg:phone":"+1 307 733 7189",
    "sg:postcode":"83002",
    "sg:province":"WY",
    "sg:tags":[
        "trailer"
    ],
    "wof:name":"Virginia R V Park",
    "wof:placetype":"venue"
},
  "geometry": {"coordinates":[-110.746292,43.479606],"type":"Point"}
}