{
  "type": "Feature",
  "properties": {
    "iso:country":"US",
    "sg:address":"428 S Elm St",
    "sg:city":"Casper",
    "sg:classifiers":[
        {
            "category":"Shopping",
            "subcategory":"Used Merchandise",
            "type":"Retail Goods"
        }
    ],
    "sg:phone":"+1 307 235 0831",
    "sg:postcode":"82601",
    "sg:province":"WY",
    "wof:name":"Casper Value Villa",
    "wof:placetype":"venue"
},
  "geometry": {"coordinates":[-106.329397,42.847039],"type":"Point"}
}