{
  "type": "Feature",
  "properties": {
    "iso:country":"US",
    "sg:address":"257 S Main St",
    "sg:city":"La Barge",
    "sg:classifiers":[
        {
            "category":"Home & Garden",
            "subcategory":"Household Appliances",
            "type":"Retail Goods"
        }
    ],
    "sg:phone":"+1 307 386 6622",
    "sg:postcode":"83123",
    "sg:province":"WY",
    "sg:tags":[
        "pump"
    ],
    "wof:name":"Millenium Pump Repair",
    "wof:placetype":"venue"
},
  "geometry": {"coordinates":[-110.194315,42.261115],"type":"Point"}
}