{
  "type": "Feature",
  "properties": {
    "iso:country":"US",
    "sg:address":"450 N 2 St",
    "sg:city":"Lander",
    "sg:classifiers":[
        {
            "category":"Social Services",
            "type":"Services"
        }
    ],
    "sg:phone":"+1 307 856 7212",
    "sg:postcode":"82520",
    "sg:province":"WY",
    "sg:tags":[
        "information",
        "planning",
        "center",
        "family"
    ],
    "wof:name":"Western Wyoming Family Planng",
    "wof:placetype":"venue"
},
  "geometry": {"coordinates":[-108.73453600000001,42.829806],"type":"Point"}
}