{
  "type": "Feature",
  "properties": {
    "addr:full":"1120 Arapahoe St Thermopolis WY 82443",
    "addr:housenumber":"1120",
    "addr:postcode":"82443",
    "addr:street":"Arapahoe St Thermopolis Wy",
    "iso:country":"US",
    "sg:address":"1120 Arapahoe St",
    "sg:city":"Thermopolis",
    "sg:classifiers":[
        {
            "category":"Museum",
            "type":"Entertainment"
        }
    ],
    "sg:phone":"+1 307 864 9396",
    "sg:postcode":"82443",
    "sg:province":"WY",
    "wof:name":"Old West Wax Museum",
    "wof:placetype":"venue"
},
  "geometry": {"coordinates":[-108.221986,43.647528],"type":"Point"}
}