{
  "type": "Feature",
  "properties": {
    "iso:country":"US",
    "sg:address":"60 Valley View Rd",
    "sg:city":"Newcastle",
    "sg:classifiers":[
        {
            "category":"Shopping",
            "subcategory":"Crafts & Fabrics",
            "type":"Retail Goods"
        }
    ],
    "sg:phone":"+1 307 746 3645",
    "sg:postcode":"82701",
    "sg:province":"WY",
    "sg:tags":[
        "sewing"
    ],
    "wof:name":"In Stitches",
    "wof:placetype":"venue"
},
  "geometry": {"coordinates":[-104.15083799999999,43.896961],"type":"Point"}
}