{
  "type": "Feature",
  "properties": {
    "addr:full":"336 S Jackson St Casper WY 82601",
    "addr:housenumber":"336",
    "addr:postcode":"82601",
    "addr:street":"S Jackson St",
    "iso:country":"US",
    "sg:address":"336 S Jackson St",
    "sg:city":"Casper",
    "sg:classifiers":[
        {
            "category":"Social Services",
            "type":"Services"
        }
    ],
    "sg:phone":"+1 307 265 2555",
    "sg:postcode":"82601",
    "sg:province":"WY",
    "wof:name":"Transitions Family Counseling",
    "wof:placetype":"venue"
},
  "geometry": {"coordinates":[-106.31110200000001,42.846096],"type":"Point"}
}