{
  "type": "Feature",
  "properties": {
    "addr:full":"23 Snowmobile Ln Cora WY 82925",
    "addr:housenumber":"23",
    "addr:postcode":"82925",
    "addr:street":"Snowmobile Ln Cora Wy",
    "iso:country":"US",
    "sg:address":"23 Snowmobile Ln",
    "sg:city":"Cora",
    "sg:classifiers":[
        {
            "category":"Home & Garden",
            "subcategory":"Building Materials",
            "type":"Retail Goods"
        }
    ],
    "sg:phone":"+1 307 859 8619",
    "sg:postcode":"82925",
    "sg:province":"WY",
    "sg:tags":[
        "glass",
        "window",
        "plate"
    ],
    "wof:name":"No Hassle Auto Glass LLC",
    "wof:placetype":"venue"
},
  "geometry": {"coordinates":[-110.02884,42.989467],"type":"Point"}
}