{
  "type": "Feature",
  "properties": {
    "addr:full":"2655 E 7th St Casper WY 82609",
    "addr:housenumber":"2655",
    "addr:postcode":"82609",
    "addr:street":"E 7Th St",
    "iso:country":"US",
    "sg:address":"2655 E 7th St",
    "sg:city":"Casper",
    "sg:classifiers":[
        {
            "category":"Building & Trades",
            "subcategory":"Construction",
            "type":"Services"
        }
    ],
    "sg:phone":"+1 307 235 0285",
    "sg:postcode":"82609",
    "sg:province":"WY",
    "sg:tags":[
        "hanging",
        "contractor"
    ],
    "wof:name":"Bruce Heberlein Painting",
    "wof:placetype":"venue"
},
  "geometry": {"coordinates":[-106.291059,42.843245],"type":"Point"}
}