{
  "type": "Feature",
  "properties": {
    "addr:full":"2310 E 8th St Cheyenne WY 82001",
    "addr:housenumber":"2310",
    "addr:postcode":"82001",
    "addr:street":"E 8Th St",
    "iso:country":"US",
    "sg:address":"2310 E 8th St",
    "sg:city":"Cheyenne",
    "sg:classifiers":[
        {
            "category":"Health Services",
            "subcategory":"Hospital",
            "type":"Services"
        }
    ],
    "sg:phone":"+1 307 632 6433",
    "sg:postcode":"82001",
    "sg:province":"WY",
    "sg:tags":[
        "mental"
    ],
    "wof:name":"Alcohol Receiving Ctr",
    "wof:placetype":"venue"
},
  "geometry": {"coordinates":[-104.789169,41.13294],"type":"Point"}
}