{
  "type": "Feature",
  "properties": {
    "addr:full":"424 N 6th St Greybull WY 82426",
    "addr:housenumber":"424",
    "addr:postcode":"82426",
    "addr:street":"N 6Th St Greybull Wy",
    "iso:country":"US",
    "sg:address":"424 N 6th St",
    "sg:city":"Greybull",
    "sg:classifiers":[
        {
            "category":"Personal",
            "subcategory":"Beauty Salon",
            "type":"Services"
        }
    ],
    "sg:phone":"+1 307 765 9316",
    "sg:postcode":"82426",
    "sg:province":"WY",
    "wof:name":"Hers & Sirs",
    "wof:placetype":"venue"
},
  "geometry": {"coordinates":[-108.05538900000001,44.493223],"type":"Point"}
}