{
  "type": "Feature",
  "properties": {
    "iso:country":"US",
    "sg:address":"42 E Little Ave",
    "sg:city":"Driggs",
    "sg:classifiers":[
        {
            "category":"Restaurant",
            "type":"Food & Drink"
        }
    ],
    "sg:phone":"+1 208 354 8115",
    "sg:postcode":"83422",
    "sg:province":"WY",
    "wof:name":"O'Rourkes Fine Food & Beer",
    "wof:placetype":"venue"
},
  "geometry": {"coordinates":[-111.11045799999999,43.723022],"type":"Point"}
}