{
  "type": "Feature",
  "properties": {
    "addr:full":"41 S Franklin Ave Pinedale WY 82941",
    "addr:housenumber":"41",
    "addr:postcode":"82941",
    "addr:street":"S Franklin Ave",
    "iso:country":"US",
    "sg:address":"41 S Franklin Ave",
    "sg:city":"Pinedale",
    "sg:classifiers":[
        {
            "category":"Professional",
            "subcategory":"Computer Services",
            "type":"Services"
        }
    ],
    "sg:phone":"+1 307 367 7331",
    "sg:postcode":"82941",
    "sg:province":"WY",
    "sg:tags":[
        "internet"
    ],
    "wof:name":"ACS Networks Inc",
    "wof:placetype":"venue"
},
  "geometry": {"coordinates":[-109.86366099999999,42.866249],"type":"Point"}
}