{
  "type": "Feature",
  "properties": {
    "iso:country":"US",
    "sg:address":"875 Rd 10",
    "sg:city":"Ten Sleep",
    "sg:classifiers":[
        {
            "category":"Professional",
            "type":"Services"
        }
    ],
    "sg:phone":"+1 307 366 2305",
    "sg:postcode":"82435",
    "sg:province":"WY",
    "wof:name":"Kenneth Tanner",
    "wof:placetype":"venue"
},
  "geometry": {"coordinates":[-108.779991,44.757556],"type":"Point"}
}