{
  "type": "Feature",
  "properties": {
    "iso:country":"US",
    "sg:address":"736 Arlington Blvd",
    "sg:city":"Sheridan",
    "sg:classifiers":[
        {
            "category":"Building & Trades",
            "subcategory":"Construction",
            "type":"Services"
        }
    ],
    "sg:phone":"+1 307 673 5274",
    "sg:postcode":"82801",
    "sg:province":"WY",
    "wof:name":"Hofer Building",
    "wof:placetype":"venue"
},
  "geometry": {"coordinates":[-106.96156999999999,44.80401],"type":"Point"}
}