{
  "type": "Feature",
  "properties": {
    "iso:country":"US",
    "sg:address":"520 US Hwy 89",
    "sg:city":"Jackson",
    "sg:classifiers":[
        {
            "category":"Food & Beverages",
            "subcategory":"Liquor & Beverages",
            "type":"Retail Goods"
        }
    ],
    "sg:phone":"+1 307 739 1122",
    "sg:postcode":"83001",
    "sg:province":"WY",
    "wof:name":"Teton Liquors",
    "wof:placetype":"venue"
},
  "geometry": {"coordinates":[-110.762218,43.488712],"type":"Point"}
}