{
  "type": "Feature",
  "properties": {
    "iso:country":"US",
    "sg:address":"1705 Oregon St",
    "sg:city":"Rawlins",
    "sg:classifiers":[
        {
            "category":"Shopping",
            "subcategory":"Bicycles & Sporting Goods",
            "type":"Retail Goods"
        }
    ],
    "sg:phone":"+1 307 324 3605",
    "sg:postcode":"82301",
    "sg:province":"WY",
    "wof:name":"Self Service Drug Inc",
    "wof:placetype":"venue"
},
  "geometry": {"coordinates":[-107.24216,41.80479],"type":"Point"}
}