{
  "type": "Feature",
  "properties": {
    "iso:country":"US",
    "sg:address":"10495 Prugh",
    "sg:city":"Casper",
    "sg:classifiers":[
        {
            "category":"Building & Trades",
            "subcategory":"Construction",
            "type":"Services"
        }
    ],
    "sg:phone":"+1 307 577 6407",
    "sg:postcode":"82604",
    "sg:province":"WY",
    "sg:tags":[
        "downspouts",
        "gutter"
    ],
    "wof:name":"Pat's Seamless Rain Gutters",
    "wof:placetype":"venue"
},
  "geometry": {"coordinates":[-106.30947500000001,42.71914],"type":"Point"}
}