{
  "type": "Feature",
  "properties": {
    "addr:full":"132 N Adams Ave Buffalo WY 82834",
    "addr:housenumber":"132",
    "addr:postcode":"82834",
    "addr:street":"N Adams Ave Buffalo Wy",
    "iso:country":"US",
    "sg:address":"132 N Adams Ave",
    "sg:city":"Buffalo",
    "sg:classifiers":[
        {
            "category":"Organizations",
            "subcategory":"Religious Organization",
            "type":"Services"
        }
    ],
    "sg:phone":"+1 307 684 7109",
    "sg:postcode":"82834",
    "sg:province":"WY",
    "sg:tags":[
        "church"
    ],
    "wof:name":"Parsonage",
    "wof:placetype":"venue"
},
  "geometry": {"coordinates":[-106.70060100000001,44.349098],"type":"Point"}
}