{
  "type": "Feature",
  "properties": {
    "addr:full":"350 City View Dr Evanston WY 82930",
    "addr:housenumber":"350",
    "addr:postcode":"82930",
    "addr:street":"City View Dr",
    "iso:country":"US",
    "sg:address":"350 City View Dr",
    "sg:city":"Evanston",
    "sg:classifiers":[
        {
            "category":"Social Services",
            "subcategory":"Child Care",
            "type":"Services"
        },
        {
            "category":"Education",
            "subcategory":"School",
            "type":"Public Place"
        }
    ],
    "sg:phone":"+1 307 789 7384",
    "sg:postcode":"82930",
    "sg:province":"WY",
    "sg:tags":[
        "academic",
        "day",
        "special"
    ],
    "wof:name":"Lincoln Uinta Child Dev Assoc",
    "wof:placetype":"venue"
},
  "geometry": {"coordinates":[-110.955296,41.248141],"type":"Point"}
}