{
  "type": "Feature",
  "properties": {
    "iso:country":"US",
    "sg:address":"317 E Main St",
    "sg:city":"Lovell",
    "sg:classifiers":[
        {
            "category":"Wholesale",
            "subcategory":"Petroleum",
            "type":"Manufacturing & Wholesale Goods"
        }
    ],
    "sg:phone":"+1 307 548 7277",
    "sg:postcode":"82431",
    "sg:province":"WY",
    "sg:tags":[
        "bulk",
        "station",
        "gasoline"
    ],
    "wof:name":"Sinclair Gas & Oil Products",
    "wof:placetype":"venue"
},
  "geometry": {"coordinates":[-108.386945,44.837607],"type":"Point"}
}