{
  "type": "Feature",
  "properties": {
    "iso:country":"US",
    "sg:address":"2000 E 20th Ave",
    "sg:city":"Torrington",
    "sg:classifiers":[
        {
            "category":"Airport",
            "type":"Transportation"
        }
    ],
    "sg:phone":"+1 307 532 8551",
    "sg:postcode":"82240",
    "sg:province":"WY",
    "wof:name":"Torrington Airport",
    "wof:placetype":"venue"
},
  "geometry": {"coordinates":[-104.16074,42.06343],"type":"Point"}
}