{
  "type": "Feature",
  "properties": {
    "addr:full":"1418 Campbell Ave Cheyenne WY 82001",
    "addr:housenumber":"1418",
    "addr:postcode":"82001",
    "addr:street":"Campbell Ave",
    "iso:country":"US",
    "sg:address":"1418 Campbell Ave",
    "sg:city":"Cheyenne",
    "sg:classifiers":[
        {
            "category":"Insurance",
            "subcategory":"Insurance Agent",
            "type":"Services"
        }
    ],
    "sg:phone":"+1 307 635 6266",
    "sg:postcode":"82001",
    "sg:province":"WY",
    "wof:name":"Allstate Insurance",
    "wof:placetype":"venue"
},
  "geometry": {"coordinates":[-104.792748,41.139062],"type":"Point"}
}