{
  "type": "Feature",
  "properties": {
    "addr:full":"420 C St Basin WY 82410",
    "addr:housenumber":"420",
    "addr:postcode":"82410",
    "addr:street":"C St Basin Wy",
    "iso:country":"US",
    "sg:address":"420 C St",
    "sg:city":"Basin",
    "sg:classifiers":[
        {
            "category":"Government",
            "subcategory":"Court House",
            "type":"Public Place"
        }
    ],
    "sg:phone":"+1 307 568 2381",
    "sg:postcode":"82410",
    "sg:province":"WY",
    "sg:tags":[
        "county"
    ],
    "wof:name":"Big Horn District Court Clerk",
    "wof:placetype":"venue"
},
  "geometry": {"coordinates":[-108.039237,44.381176],"type":"Point"}
}