{
  "type": "Feature",
  "properties": {
    "addr:full":"410 E 5th St Sheridan WY 82801",
    "addr:housenumber":"410",
    "addr:postcode":"82801",
    "addr:street":"E 5Th St",
    "iso:country":"US",
    "sg:address":"410 E 5th St",
    "sg:city":"Sheridan",
    "sg:classifiers":[
        {
            "category":"Retail",
            "subcategory":"Auto Repair",
            "type":"Services"
        }
    ],
    "sg:phone":"+1 307 674 4773",
    "sg:postcode":"82801",
    "sg:province":"WY",
    "sg:tags":[
        "repairing",
        "automobile",
        "radiator"
    ],
    "wof:name":"Ace Radiator Svc",
    "wof:placetype":"venue"
},
  "geometry": {"coordinates":[-106.950091,44.806747],"type":"Point"}
}