{
  "type": "Feature",
  "properties": {
    "iso:country":"US",
    "sg:address":"1002 Sheridan Ave",
    "sg:city":"Cody",
    "sg:classifiers":[
        {
            "category":"Building & Trades",
            "subcategory":"Construction",
            "type":"Services"
        }
    ],
    "sg:phone":"+1 307 527 8520",
    "sg:postcode":"82414",
    "sg:province":"WY",
    "sg:tags":[
        "grading",
        "contractor"
    ],
    "wof:name":"Park County Public Works",
    "wof:placetype":"venue"
},
  "geometry": {"coordinates":[-109.067789,44.525965],"type":"Point"}
}