{
  "type": "Feature",
  "properties": {
    "iso:country":"US",
    "sg:address":"12118 Deike Ct",
    "sg:city":"Cheyenne",
    "sg:classifiers":[
        {
            "category":"Restaurant",
            "type":"Food & Drink"
        }
    ],
    "sg:phone":"+1 307 632 9300",
    "sg:postcode":"82009",
    "sg:province":"WY",
    "sg:tags":[
        "eating"
    ],
    "wof:name":"Great American Real Food Fast",
    "wof:placetype":"venue"
},
  "geometry": {"coordinates":[-104.66214100000001,41.156743],"type":"Point"}
}