{
  "type": "Feature",
  "properties": {
    "iso:country":"US",
    "sg:address":"355 W 5th St",
    "sg:city":"Powell",
    "sg:classifiers":[
        {
            "category":"Wholesale",
            "subcategory":"Plants",
            "type":"Manufacturing & Wholesale Goods"
        }
    ],
    "sg:phone":"+1 307 754 3762",
    "sg:postcode":"82435",
    "sg:province":"WY",
    "sg:tags":[
        "shop",
        "beauty",
        "supply"
    ],
    "wof:name":"Classic Touch",
    "wof:placetype":"venue"
},
  "geometry": {"coordinates":[-108.763486,44.758214],"type":"Point"}
}