{
  "type": "Feature",
  "properties": {
    "iso:country":"US",
    "sg:address":"225 N Bent St",
    "sg:city":"Powell",
    "sg:classifiers":[
        {
            "category":"Shopping",
            "subcategory":"Beauty & Cosmetics",
            "type":"Retail Goods"
        }
    ],
    "sg:phone":"+1 307 754 3686",
    "sg:postcode":"82435",
    "sg:province":"WY",
    "sg:tags":[
        "merchandise"
    ],
    "wof:name":"Little Luxuries",
    "wof:placetype":"venue"
},
  "geometry": {"coordinates":[-108.757516,44.755168],"type":"Point"}
}