{
  "type": "Feature",
  "properties": {
    "iso:country":"US",
    "sg:address":"804 Rd 2",
    "sg:city":"Powell",
    "sg:classifiers":[
        {
            "category":"Organizations",
            "subcategory":"Religious Organization",
            "type":"Services"
        }
    ],
    "sg:phone":"+1 307 754 0424",
    "sg:postcode":"82435",
    "sg:province":"WY",
    "sg:tags":[
        "church"
    ],
    "wof:name":"New Life Christian Fellowship",
    "wof:placetype":"venue"
},
  "geometry": {"coordinates":[-108.576618,44.739712],"type":"Point"}
}