{
  "type": "Feature",
  "properties": {
    "iso:country":"US",
    "sg:address":"8 Tonamp Ln",
    "sg:city":"Lander",
    "sg:classifiers":[
        {
            "category":"Building & Trades",
            "subcategory":"Construction",
            "type":"Services"
        }
    ],
    "sg:phone":"+1 307 332 6488",
    "sg:postcode":"82520",
    "sg:province":"WY",
    "sg:tags":[
        "painter"
    ],
    "wof:name":"New World Painting",
    "wof:placetype":"venue"
},
  "geometry": {"coordinates":[-108.793492,42.899154],"type":"Point"}
}