{
  "type": "Feature",
  "properties": {
    "addr:full":"285 W Main St Lander WY 82520",
    "addr:housenumber":"285",
    "addr:postcode":"wy 82520",
    "addr:street":"W Main St",
    "iso:country":"US",
    "sg:address":"285 W Main St",
    "sg:city":"Lander",
    "sg:classifiers":[
        {
            "category":"Travel",
            "subcategory":"Travel Agent",
            "type":"Entertainment"
        }
    ],
    "sg:phone":"+1 307 332 4882",
    "sg:postcode":"82520",
    "sg:province":"WY",
    "sg:tags":[
        "agency",
        "bureau"
    ],
    "wof:name":"Noble Travel Agency",
    "wof:placetype":"venue"
},
  "geometry": {"coordinates":[-108.744868,42.837265],"type":"Point"}
}