{
  "type": "Feature",
  "properties": {
    "iso:country":"US",
    "sg:address":"886 State Hwy 11",
    "sg:city":"Laramie",
    "sg:classifiers":[
        {
            "category":"Banks & Credit Unions",
            "subcategory":"Bank",
            "type":"Services"
        }
    ],
    "sg:phone":"+1 307 742 6048",
    "sg:postcode":"82070",
    "sg:province":"WY",
    "sg:tags":[
        "national",
        "commercial"
    ],
    "wof:name":"Ahhoona Ranch",
    "wof:placetype":"venue"
},
  "geometry": {"coordinates":[-106.09263300000001,41.193001],"type":"Point"}
}