{
  "type": "Feature",
  "properties": {
    "addr:full":"7006 N College Dr Cheyenne WY 82009",
    "addr:housenumber":"7006",
    "addr:postcode":"82009",
    "addr:street":"N College Dr",
    "iso:country":"US",
    "sg:address":"7006 N College Dr",
    "sg:city":"Cheyenne",
    "sg:classifiers":[
        {
            "category":"Organizations",
            "subcategory":"Religious Organization",
            "type":"Services"
        }
    ],
    "sg:phone":"+1 307 637 3733",
    "sg:postcode":"82009",
    "sg:province":"WY",
    "sg:tags":[
        "church"
    ],
    "wof:name":"Cheyenne Evangelical Free Chr",
    "wof:placetype":"venue"
},
  "geometry": {"coordinates":[-104.76107,41.182584],"type":"Point"}
}