{
  "type": "Feature",
  "properties": {
    "iso:country":"US",
    "sg:address":"216 W Washington Ave",
    "sg:city":"Riverton",
    "sg:classifiers":[
        {
            "category":"Shopping",
            "subcategory":"Bicycles & Sporting Goods",
            "type":"Retail Goods"
        }
    ],
    "sg:phone":"+1 307 857 1091",
    "sg:postcode":"82501",
    "sg:province":"WY",
    "wof:name":"Mustang Amusements",
    "wof:placetype":"venue"
},
  "geometry": {"coordinates":[-108.394211,43.023541],"type":"Point"}
}