{
  "type": "Feature",
  "properties": {
    "iso:country":"US",
    "sg:address":"553 N Front St",
    "sg:city":"Rock Springs",
    "sg:classifiers":[
        {
            "category":"Home & Garden",
            "subcategory":"Furniture",
            "type":"Retail Goods"
        }
    ],
    "sg:phone":"+1 307 362 6330",
    "sg:postcode":"82901",
    "sg:province":"WY",
    "wof:name":"Fanelli Appliance & Furniture",
    "wof:placetype":"venue"
},
  "geometry": {"coordinates":[-109.219835,41.58767],"type":"Point"}
}