{
  "type": "Feature",
  "properties": {
    "iso:country":"US",
    "sg:address":"2508 E Fox Farm Rd",
    "sg:city":"Cheyenne",
    "sg:classifiers":[
        {
            "category":"Shopping",
            "type":"Retail Goods"
        }
    ],
    "sg:phone":"+1 307 637 8870",
    "sg:postcode":"82007",
    "sg:province":"WY",
    "sg:tags":[
        "pet",
        "food",
        "supply"
    ],
    "wof:name":"Oasis Market Country Store",
    "wof:placetype":"venue"
},
  "geometry": {"coordinates":[-104.76839099999999,41.116679],"type":"Point"}
}