{
  "type": "Feature",
  "properties": {
    "iso:country":"US",
    "sg:address":"1704 N Main St",
    "sg:city":"Sheridan",
    "sg:classifiers":[
        {
            "category":"Local Transit",
            "type":"Transportation"
        }
    ],
    "sg:phone":"+1 307 672 8812",
    "sg:postcode":"82801",
    "sg:province":"WY",
    "sg:tags":[
        "passenger"
    ],
    "wof:name":"Aladdin Limousines",
    "wof:placetype":"venue"
},
  "geometry": {"coordinates":[-106.95556500000001,44.817139],"type":"Point"}
}