{
  "type": "Feature",
  "properties": {
    "iso:country":"US",
    "sg:address":"1125 E 2nd St",
    "sg:city":"Casper",
    "sg:classifiers":[
        {
            "category":"Health Services",
            "subcategory":"Doctor",
            "type":"Services"
        }
    ],
    "sg:phone":"+1 307 577 4225",
    "sg:postcode":"82601",
    "sg:province":"WY",
    "sg:tags":[
        "physician",
        "surgeon"
    ],
    "wof:name":"Womens Health Assoc-Wyoming",
    "wof:placetype":"venue"
},
  "geometry": {"coordinates":[-106.31057800000001,42.848694],"type":"Point"}
}