{
  "type": "Feature",
  "properties": {
    "iso:country":"US",
    "sg:address":"305 N Park St",
    "sg:city":"Casper",
    "sg:classifiers":[
        {
            "category":"Wholesale",
            "subcategory":"Toys & Hobbies",
            "type":"Manufacturing & Wholesale Goods"
        },
        {
            "category":"Shopping",
            "subcategory":"Hobbies, Toys, & Games",
            "type":"Retail Goods"
        }
    ],
    "sg:phone":"+1 307 577 4107",
    "sg:postcode":"82601",
    "sg:province":"WY",
    "sg:tags":[
        "bingo",
        "supply"
    ],
    "wof:name":"High Country Amusement & Bingo",
    "wof:placetype":"venue"
},
  "geometry": {"coordinates":[-106.318037,42.853611],"type":"Point"}
}