{
  "type": "Feature",
  "properties": {
    "iso:country":"US",
    "sg:address":"6707 Highland Rd",
    "sg:city":"Cheyenne",
    "sg:classifiers":[
        {
            "category":"Retail",
            "subcategory":"Repair Shop",
            "type":"Services"
        }
    ],
    "sg:phone":"+1 307 637 4466",
    "sg:postcode":"82009",
    "sg:province":"WY",
    "sg:tags":[
        "equipment"
    ],
    "wof:name":"Marlow Music Instrument Repair",
    "wof:placetype":"venue"
},
  "geometry": {"coordinates":[-104.751426,41.179776],"type":"Point"}
}