{
  "type": "Feature",
  "properties": {
    "iso:country":"US",
    "sg:address":"229 E 2nd St",
    "sg:city":"Casper",
    "sg:classifiers":[
        {
            "category":"Professional",
            "subcategory":"Management & Consulting",
            "type":"Services"
        }
    ],
    "sg:phone":"+1 307 234 5110",
    "sg:postcode":"82601",
    "sg:province":"WY",
    "sg:tags":[
        "employee",
        "consultant",
        "benefit"
    ],
    "wof:name":"Service First",
    "wof:placetype":"venue"
},
  "geometry": {"coordinates":[-106.322704,42.848637],"type":"Point"}
}