{
  "type": "Feature",
  "properties": {
    "iso:country":"US",
    "sg:address":"1448 Main St",
    "sg:city":"Reliance",
    "sg:classifiers":[
        {
            "category":"Building & Trades",
            "subcategory":"Construction",
            "type":"Services"
        }
    ],
    "sg:phone":"+1 307 362 7298",
    "sg:postcode":"82943",
    "sg:province":"WY",
    "sg:tags":[
        "general",
        "contractor"
    ],
    "wof:name":"Four Square Builders",
    "wof:placetype":"venue"
},
  "geometry": {"coordinates":[-109.18864600000001,41.670318],"type":"Point"}
}