{
  "type": "Feature",
  "properties": {
    "iso:country":"US",
    "sg:address":"322 W 17th St",
    "sg:city":"Cheyenne",
    "sg:classifiers":[
        {
            "category":"Health Services",
            "subcategory":"Medical Lab",
            "type":"Services"
        }
    ],
    "sg:phone":"+1 307 632 9096",
    "sg:postcode":"82001",
    "sg:province":"WY",
    "sg:tags":[
        "detection",
        "equipment",
        "drug"
    ],
    "sg:website":"www.fcs-inc.net",
    "wof:name":"Frontier Correctional Systems",
    "wof:placetype":"venue"
},
  "geometry": {"coordinates":[-104.817868,41.132956],"type":"Point"}
}