{
  "type": "Feature",
  "properties": {
    "iso:country":"US",
    "sg:address":"1801 E 4th St",
    "sg:city":"Casper",
    "sg:classifiers":[
        {
            "category":"Shopping",
            "subcategory":"Bicycles & Sporting Goods",
            "type":"Retail Goods"
        }
    ],
    "sg:phone":"+1 307 473 1385",
    "sg:postcode":"82609",
    "sg:province":"WY",
    "sg:tags":[
        "equipment",
        "hockey"
    ],
    "wof:name":"Bush-Wells Skate Shop",
    "wof:placetype":"venue"
},
  "geometry": {"coordinates":[-106.30038999999999,42.84635],"type":"Point"}
}