{
  "type": "Feature",
  "properties": {
    "addr:full":"234 E Main St Lovell WY 82431",
    "addr:housenumber":"234",
    "addr:postcode":"82431",
    "addr:street":"E Main St Lovell Wy",
    "iso:country":"US",
    "sg:address":"234 E Main St",
    "sg:city":"Lovell",
    "sg:classifiers":[
        {
            "category":"Manufacturing",
            "subcategory":"Printing",
            "type":"Manufacturing & Wholesale Goods"
        }
    ],
    "sg:phone":"+1 307 548 2217",
    "sg:postcode":"82431",
    "sg:province":"WY",
    "sg:tags":[
        "newspaper"
    ],
    "sg:website":"www.lovellchronicle.com",
    "wof:name":"Lovell Chronicle",
    "wof:placetype":"venue"
},
  "geometry": {"coordinates":[-108.388704,44.837452],"type":"Point"}
}