{
  "type": "Feature",
  "properties": {
    "iso:country":"US",
    "sg:address":"1071 Cy Ave",
    "sg:city":"Casper",
    "sg:classifiers":[
        {
            "category":"Shopping",
            "subcategory":"Pharmacy",
            "type":"Retail Goods"
        }
    ],
    "sg:phone":"+1 307 234 4416",
    "sg:postcode":"82604",
    "sg:province":"WY",
    "sg:website":"www.walgreens.com",
    "wof:name":"Walgreens",
    "wof:placetype":"venue"
},
  "geometry": {"coordinates":[-106.337124,42.83504],"type":"Point"}
}