{
  "type": "Feature",
  "properties": {
    "iso:country":"US",
    "sg:address":"5231 Squaw Creek Rd",
    "sg:city":"Casper",
    "sg:classifiers":[
        {
            "category":"Museum",
            "type":"Entertainment"
        }
    ],
    "sg:phone":"+1 307 234 5547",
    "sg:postcode":"82604",
    "sg:province":"WY",
    "sg:tags":[
        "gallery"
    ],
    "wof:name":"Navarro Gallery",
    "wof:placetype":"venue"
},
  "geometry": {"coordinates":[-106.385375,42.795306],"type":"Point"}
}