{
  "type": "Feature",
  "properties": {
    "addr:full":"355 S Millward St Jackson WY 83001",
    "addr:housenumber":"355",
    "addr:postcode":"83001",
    "addr:street":"S Millward St Jackson Wy",
    "iso:country":"US",
    "sg:address":"355 S Millward St",
    "sg:city":"Jackson",
    "sg:classifiers":[
        {
            "category":"Real Estate",
            "subcategory":"Architect",
            "type":"Services"
        }
    ],
    "sg:phone":"+1 307 733 8637",
    "sg:postcode":"83001",
    "sg:province":"WY",
    "wof:name":"Stiles Architects",
    "wof:placetype":"venue"
},
  "geometry": {"coordinates":[-110.765176,43.475732],"type":"Point"}
}