{
  "type": "Feature",
  "properties": {
    "iso:country":"US",
    "sg:address":"189 US Hwy 20 N",
    "sg:city":"Thermopolis",
    "sg:classifiers":[
        {
            "category":"Wholesale",
            "subcategory":"Petroleum",
            "type":"Manufacturing & Wholesale Goods"
        }
    ],
    "sg:phone":"+1 307 864 5593",
    "sg:postcode":"82443",
    "sg:province":"WY",
    "sg:tags":[
        "pipe",
        "line",
        "company"
    ],
    "wof:name":"Rocky Mountain Pipeline System",
    "wof:placetype":"venue"
},
  "geometry": {"coordinates":[-108.202348,43.664863],"type":"Point"}
}