{
  "type": "Feature",
  "properties": {
    "iso:country":"US",
    "sg:address":"1210 Co Ln 10",
    "sg:city":"Worland",
    "sg:classifiers":[
        {
            "category":"Freight",
            "type":"Transportation"
        }
    ],
    "sg:phone":"+1 307 347 4161",
    "sg:postcode":"82401",
    "sg:province":"WY",
    "sg:tags":[
        "field",
        "oil",
        "hauling"
    ],
    "wof:name":"Swing's Trucking Co & Svc",
    "wof:placetype":"venue"
},
  "geometry": {"coordinates":[-107.938627,44.03708],"type":"Point"}
}