{
  "type": "Feature",
  "properties": {
    "addr:full":"808 E 6th St Gillette WY 82716",
    "addr:housenumber":"808",
    "addr:postcode":"82716",
    "addr:street":"E 6Th St",
    "iso:country":"US",
    "sg:address":"808 E 6th St",
    "sg:city":"Gillette",
    "sg:classifiers":[
        {
            "category":"Building & Trades",
            "subcategory":"Construction",
            "type":"Services"
        }
    ],
    "sg:phone":"+1 307 686 7200",
    "sg:postcode":"82716",
    "sg:province":"WY",
    "sg:tags":[
        "siding",
        "contractor"
    ],
    "wof:name":"ABC Seamless Siding",
    "wof:placetype":"venue"
},
  "geometry": {"coordinates":[-105.49394100000001,44.289254],"type":"Point"}
}