{
  "type": "Feature",
  "properties": {
    "iso:country":"US",
    "sg:address":"260 N 9th St",
    "sg:city":"Laramie",
    "sg:classifiers":[
        {
            "category":"Real Estate",
            "subcategory":"Real Estate Operator",
            "type":"Services"
        }
    ],
    "sg:phone":"+1 307 745 7203",
    "sg:postcode":"82072",
    "sg:province":"WY",
    "sg:tags":[
        "building",
        "apartment"
    ],
    "wof:name":"Teton Apts",
    "wof:placetype":"venue"
},
  "geometry": {"coordinates":[-105.58547299999999,41.313751],"type":"Point"}
}