{
  "type": "Feature",
  "properties": {
    "iso:country":"US",
    "sg:address":"839 S Walnut St",
    "sg:city":"Casper",
    "sg:classifiers":[
        {
            "category":"Shopping",
            "subcategory":"Books",
            "type":"Retail Goods"
        }
    ],
    "sg:phone":"+1 307 266 0987",
    "sg:postcode":"82601",
    "sg:province":"WY",
    "wof:name":"Cisneros Cycle Co",
    "wof:placetype":"venue"
},
  "geometry": {"coordinates":[-106.333208,42.842303],"type":"Point"}
}