{
  "type": "Feature",
  "properties": {
    "addr:full":"301 2nd St Rock Springs WY 82901",
    "addr:housenumber":"301",
    "addr:postcode":"82901",
    "addr:street":"2Nd St Rock Springs Wy",
    "iso:country":"US",
    "sg:address":"301 2nd St",
    "sg:city":"Rock Springs",
    "sg:classifiers":[
        {
            "category":"Banks & Credit Unions",
            "subcategory":"Bank",
            "type":"Services"
        }
    ],
    "sg:phone":"+1 307 382 2227",
    "sg:postcode":"82901",
    "sg:province":"WY",
    "sg:tags":[
        "federal"
    ],
    "wof:name":"Sweetwater Federal Credit",
    "wof:placetype":"venue"
},
  "geometry": {"coordinates":[-109.2196,41.58463],"type":"Point"}
}