{
  "type": "Feature",
  "properties": {
    "addr:full":"226 2nd Ave N Greybull WY 82426",
    "addr:housenumber":"226",
    "addr:postcode":"82426",
    "addr:street":"2Nd Ave N Greybull Wy",
    "iso:country":"US",
    "sg:address":"226 2nd Ave N",
    "sg:city":"Greybull",
    "sg:classifiers":[
        {
            "category":"Shopping",
            "subcategory":"Discount & Variety Stores",
            "type":"Retail Goods"
        }
    ],
    "sg:phone":"+1 307 765 2124",
    "sg:postcode":"82426",
    "sg:province":"WY",
    "sg:tags":[
        "clothing",
        "merchandise",
        "family"
    ],
    "wof:name":"Town & Country Department Str",
    "wof:placetype":"venue"
},
  "geometry": {"coordinates":[-108.050134,44.491028],"type":"Point"}
}