{
  "type": "Feature",
  "properties": {
    "iso:country":"US",
    "sg:address":"71 E Ridge Rd",
    "sg:city":"Sheridan",
    "sg:classifiers":[
        {
            "category":"Retail",
            "subcategory":"Auto Repair",
            "type":"Services"
        }
    ],
    "sg:phone":"+1 307 674 9764",
    "sg:postcode":"82801",
    "sg:province":"WY",
    "sg:tags":[
        "wrecker"
    ],
    "wof:name":"A-Plus Towing",
    "wof:placetype":"venue"
},
  "geometry": {"coordinates":[-106.92722000000001,44.798326],"type":"Point"}
}