{
  "type": "Feature",
  "properties": {
    "iso:country":"US",
    "sg:address":"1700 W Lincolnway",
    "sg:city":"Cheyenne",
    "sg:classifiers":[
        {
            "category":"Shopping",
            "subcategory":"Clothing, Apparel, & Fashions",
            "type":"Retail Goods"
        }
    ],
    "sg:phone":"+1 307 778 7821",
    "sg:postcode":"82001",
    "sg:province":"WY",
    "sg:tags":[
        "furnishing"
    ],
    "wof:name":"Fred Baggs LTD",
    "wof:placetype":"venue"
},
  "geometry": {"coordinates":[-104.834941,41.124798],"type":"Point"}
}