{
  "type": "Feature",
  "properties": {
    "iso:country":"US",
    "sg:address":"413 E Center St",
    "sg:city":"Douglas",
    "sg:classifiers":[
        {
            "category":"Government",
            "subcategory":"Office",
            "type":"Public Place"
        }
    ],
    "sg:phone":"+1 307 358 3046",
    "sg:postcode":"82633",
    "sg:province":"WY",
    "sg:tags":[
        "state",
        "program"
    ],
    "wof:name":"Transportation Dept-Traffic",
    "wof:placetype":"venue"
},
  "geometry": {"coordinates":[-105.381405,42.759442],"type":"Point"}
}