{
  "type": "Feature",
  "properties": {
    "iso:country":"US",
    "sg:address":"18 Fairgrounds Rd",
    "sg:city":"Buffalo",
    "sg:classifiers":[
        {
            "category":"Government",
            "subcategory":"Office",
            "type":"Public Place"
        }
    ],
    "sg:phone":"+1 307 684 7357",
    "sg:postcode":"82834",
    "sg:province":"WY",
    "wof:name":"Johnson County Fairboard Ofc",
    "wof:placetype":"venue"
},
  "geometry": {"coordinates":[-106.69427399999999,44.362761],"type":"Point"}
}