{
  "type": "Feature",
  "properties": {
    "iso:country":"US",
    "sg:address":"219 E 18th St",
    "sg:city":"Cheyenne",
    "sg:classifiers":[
        {
            "category":"Travel",
            "subcategory":"Hotels & Motels",
            "type":"Entertainment"
        }
    ],
    "sg:phone":"+1 307 638 2337",
    "sg:postcode":"82001",
    "sg:province":"WY",
    "sg:tags":[
        "operation"
    ],
    "wof:name":"Rainsford Inn Bed & Breakfast",
    "wof:placetype":"venue"
},
  "geometry": {"coordinates":[-104.81321699999999,41.135627],"type":"Point"}
}