{
  "type": "Feature",
  "properties": {
    "addr:full":"202 S 3rd St E Riverton WY 82501",
    "addr:housenumber":"202",
    "addr:postcode":"82501",
    "addr:street":"S 3Rd St",
    "iso:country":"US",
    "sg:address":"202 S 3rd St E",
    "sg:city":"Riverton",
    "sg:classifiers":[
        {
            "category":"Restaurant",
            "type":"Food & Drink"
        }
    ],
    "sg:phone":"+1 307 856 8003",
    "sg:postcode":"82501",
    "sg:province":"WY",
    "wof:name":"Oriental Palace",
    "wof:placetype":"venue"
},
  "geometry": {"coordinates":[-108.387826,43.023551],"type":"Point"}
}