{
  "type": "Feature",
  "properties": {
    "addr:full":"242 E 2nd St Powell WY 82435",
    "addr:housenumber":"242",
    "addr:postcode":"82435",
    "addr:street":"E 2Nd St Powell Wy",
    "iso:country":"US",
    "sg:address":"242 E 2nd St",
    "sg:city":"Powell",
    "sg:classifiers":[
        {
            "category":"Professional",
            "subcategory":"Business Services",
            "type":"Services"
        }
    ],
    "sg:phone":"+1 307 754 5122",
    "sg:postcode":"82435",
    "sg:province":"WY",
    "sg:tags":[
        "interior",
        "consultant",
        "design",
        "decorator"
    ],
    "wof:name":"Decorating Ideas",
    "wof:placetype":"venue"
},
  "geometry": {"coordinates":[-108.757046,44.754105],"type":"Point"}
}