{
  "type": "Feature",
  "properties": {
    "addr:full":"6660 Henderson Creek Pl Casper WY 82604",
    "addr:housenumber":"6660",
    "addr:postcode":"82604",
    "addr:street":"Henderson Creek Pl",
    "iso:country":"US",
    "sg:address":"6660 Henderson Creek Pl",
    "sg:city":"Casper",
    "sg:classifiers":[
        {
            "category":"Building & Trades",
            "subcategory":"Construction",
            "type":"Services"
        }
    ],
    "sg:phone":"+1 307 266 1859",
    "sg:postcode":"82604",
    "sg:province":"WY",
    "sg:tags":[
        "residential"
    ],
    "wof:name":"RMR Construction",
    "wof:placetype":"venue"
},
  "geometry": {"coordinates":[-106.42235599999999,42.821013],"type":"Point"}
}