{
  "type": "Feature",
  "properties": {
    "iso:country":"US",
    "sg:address":"709 S 3rd St",
    "sg:city":"Laramie",
    "sg:classifiers":[
        {
            "category":"Autos & Motor Vehicles",
            "subcategory":"Fuel & Gas Station",
            "type":"Retail Goods"
        }
    ],
    "sg:phone":"+1 307 742 5229",
    "sg:postcode":"82070",
    "sg:province":"WY",
    "sg:tags":[
        "station"
    ],
    "wof:name":"Gasamat Inc",
    "wof:placetype":"venue"
},
  "geometry": {"coordinates":[-105.593943,41.30721],"type":"Point"}
}