{
  "type": "Feature",
  "properties": {
    "iso:country":"US",
    "sg:address":"1511 Mydland Rd",
    "sg:city":"Sheridan",
    "sg:classifiers":[
        {
            "category":"Real Estate",
            "subcategory":"Developer",
            "type":"Services"
        },
        {
            "category":"Real Estate",
            "subcategory":"Real Estate Operator",
            "type":"Services"
        }
    ],
    "sg:phone":"+1 307 674 4503",
    "sg:postcode":"82801",
    "sg:province":"WY",
    "sg:tags":[
        "mobile",
        "site",
        "home",
        "rental",
        "trailer",
        "utility"
    ],
    "wof:name":"West Park Mobile Home Cmnty",
    "wof:placetype":"venue"
},
  "geometry": {"coordinates":[-106.98755199999999,44.814417],"type":"Point"}
}