{
  "type": "Feature",
  "properties": {
    "addr:full":"3066 Cabin Creek Pl Casper WY 82604",
    "addr:housenumber":"3066",
    "addr:postcode":"82604",
    "addr:street":"Cabin Creek Pl",
    "iso:country":"US",
    "sg:address":"3066 Cabin Creek Pl",
    "sg:city":"Casper",
    "sg:classifiers":[
        {
            "category":"Manufacturing",
            "subcategory":"Toys & Sporting Goods",
            "type":"Manufacturing & Wholesale Goods"
        }
    ],
    "sg:phone":"+1 307 472 5765",
    "sg:postcode":"82604",
    "sg:province":"WY",
    "sg:tags":[
        "stuffed",
        "doll"
    ],
    "wof:name":"Gray's Crafts",
    "wof:placetype":"venue"
},
  "geometry": {"coordinates":[-106.416122,42.818676],"type":"Point"}
}