{
  "type": "Feature",
  "properties": {
    "iso:country":"US",
    "sg:address":"610 Lakota Ln",
    "sg:city":"Jackson",
    "sg:phone":"+1 307 734 4432",
    "sg:postcode":"83001",
    "sg:province":"WY",
    "sg:tags":[
        "hydrologist"
    ],
    "wof:name":"Legette Brashears & Graham Inc",
    "wof:placetype":"venue"
},
  "geometry": {"coordinates":[-110.80394200000001,43.470776],"type":"Point"}
}