{
  "type": "Feature",
  "properties": {
    "iso:country":"US",
    "sg:address":"1509 Bent Ave",
    "sg:city":"Cheyenne",
    "sg:classifiers":[
        {
            "category":"Wholesale",
            "subcategory":"Electrical",
            "type":"Manufacturing & Wholesale Goods"
        }
    ],
    "sg:phone":"+1 307 635 4966",
    "sg:postcode":"82001",
    "sg:province":"WY",
    "sg:tags":[
        "equipment",
        "electric",
        "supply"
    ],
    "wof:name":"Cheyenne Winlectric Co Inc",
    "wof:placetype":"venue"
},
  "geometry": {"coordinates":[-104.82078,41.130635],"type":"Point"}
}