{
  "type": "Feature",
  "properties": {
    "iso:country":"US",
    "sg:address":"875 Gilchrist St",
    "sg:city":"Wheatland",
    "sg:classifiers":[
        {
            "category":"Shopping",
            "subcategory":"Books",
            "type":"Retail Goods"
        }
    ],
    "sg:phone":"+1 307 322 1725",
    "sg:postcode":"82201",
    "sg:province":"WY",
    "sg:tags":[
        "needlework",
        "quilting",
        "custom"
    ],
    "wof:name":"Wheatland Mercantile",
    "wof:placetype":"venue"
},
  "geometry": {"coordinates":[-104.952187,42.054304],"type":"Point"}
}