{
  "type": "Feature",
  "properties": {
    "addr:full":"429 State Hwy 230 Laramie WY 82070",
    "addr:housenumber":"429",
    "addr:postcode":"82070",
    "addr:street":"State Hwy 230",
    "iso:country":"US",
    "sg:address":"429 State Hwy 230",
    "sg:city":"Laramie",
    "sg:classifiers":[
        {
            "category":"Real Estate",
            "subcategory":"Developer",
            "type":"Services"
        }
    ],
    "sg:phone":"+1 307 742 6553",
    "sg:postcode":"82070",
    "sg:province":"WY",
    "sg:tags":[
        "mobile",
        "home"
    ],
    "wof:name":"Westgate Mobile Home Park",
    "wof:placetype":"venue"
},
  "geometry": {"coordinates":[-105.604617,41.315167],"type":"Point"}
}