{
  "type": "Feature",
  "properties": {
    "iso:country":"US",
    "sg:address":"1068 Vali Rd",
    "sg:city":"Powell",
    "sg:classifiers":[
        {
            "category":"Building & Trades",
            "subcategory":"Construction",
            "type":"Services"
        }
    ],
    "sg:phone":"+1 307 754 5518",
    "sg:postcode":"82435",
    "sg:province":"WY",
    "sg:tags":[
        "house"
    ],
    "wof:name":"Metzler Construction Inc",
    "wof:placetype":"venue"
},
  "geometry": {"coordinates":[-108.762404,44.728797],"type":"Point"}
}