{
  "type": "Feature",
  "properties": {
    "iso:country":"US",
    "sg:address":"509 Swift St",
    "sg:city":"Buffalo",
    "sg:classifiers":[
        {
            "category":"Social Services",
            "type":"Services"
        }
    ],
    "sg:phone":"+1 307 684 2234",
    "sg:postcode":"82834",
    "sg:province":"WY",
    "sg:tags":[
        "youth",
        "organization",
        "center"
    ],
    "wof:name":"Johnson-Sheridan Youth Home",
    "wof:placetype":"venue"
},
  "geometry": {"coordinates":[-106.706366,44.358098],"type":"Point"}
}