{
  "type": "Feature",
  "properties": {
    "iso:country":"US",
    "sg:address":"285 Main St",
    "sg:city":"Lander",
    "sg:classifiers":[
        {
            "category":"Real Estate",
            "subcategory":"Real Estate Operator",
            "type":"Services"
        }
    ],
    "sg:phone":"+1 307 332 4882",
    "sg:postcode":"82520",
    "sg:province":"WY",
    "sg:tags":[
        "building",
        "nonresidential"
    ],
    "wof:name":"Noble Travel Agency",
    "wof:placetype":"venue"
},
  "geometry": {"coordinates":[-108.729438,42.832685],"type":"Point"}
}