{
  "type": "Feature",
  "properties": {
    "addr:full":"524 N 6 St Riverton WY 82501",
    "addr:housenumber":"524;6",
    "addr:postcode":"82501",
    "addr:street":"N;St Riverton Wy",
    "iso:country":"US",
    "sg:address":"524 N 6 St",
    "sg:city":"Riverton",
    "sg:classifiers":[
        {
            "category":"Real Estate",
            "subcategory":"Real Estate Operator",
            "type":"Services"
        }
    ],
    "sg:phone":"+1 307 856 7117",
    "sg:postcode":"82501",
    "sg:province":"WY",
    "sg:tags":[
        "apartment"
    ],
    "wof:name":"Sertoma Senior Housing",
    "wof:placetype":"venue"
},
  "geometry": {"coordinates":[-108.383522,43.029564],"type":"Point"}
}