{
  "type": "Feature",
  "properties": {
    "iso:country":"US",
    "sg:address":"218 S Greeley Hwy",
    "sg:city":"Cheyenne",
    "sg:classifiers":[
        {
            "category":"Banks & Credit Unions",
            "subcategory":"Bank",
            "type":"Services"
        }
    ],
    "sg:phone":"+1 307 772 0020",
    "sg:postcode":"82007",
    "sg:province":"WY",
    "sg:tags":[
        "depository",
        "banking"
    ],
    "wof:name":"B & R Check Holders",
    "wof:placetype":"venue"
},
  "geometry": {"coordinates":[-104.803325,41.116538],"type":"Point"}
}