{
  "type": "Feature",
  "properties": {
    "iso:country":"US",
    "sg:address":"494 Main St",
    "sg:city":"Lander",
    "sg:classifiers":[
        {
            "category":"Retail",
            "subcategory":"Laundry & Dry Cleaning",
            "type":"Services"
        }
    ],
    "sg:phone":"+1 307 332 5454",
    "sg:postcode":"82520",
    "sg:province":"WY",
    "wof:name":"American Dry Cleaning-Laundry",
    "wof:placetype":"venue"
},
  "geometry": {"coordinates":[-108.734675,42.833948],"type":"Point"}
}