{
  "type": "Feature",
  "properties": {
    "addr:full":"1001 E 2nd St Casper WY 82601",
    "addr:housenumber":"1001",
    "addr:postcode":"82601",
    "addr:street":"E 2Nd St",
    "iso:country":"US",
    "sg:address":"1001 E 2nd St",
    "sg:city":"Casper",
    "sg:classifiers":[
        {
            "category":"Food & Beverages",
            "subcategory":"Groceries & Convenience Stores",
            "type":"Retail Goods"
        }
    ],
    "sg:phone":"+1 307 234 6490",
    "sg:postcode":"82601",
    "sg:province":"WY",
    "wof:name":"Homax",
    "wof:placetype":"venue"
},
  "geometry": {"coordinates":[-106.31101,42.848769],"type":"Point"}
}