{
  "type": "Feature",
  "properties": {
    "iso:country":"US",
    "sg:address":"601 SE Wyoming Blvd",
    "sg:city":"Casper",
    "sg:classifiers":[
        {
            "category":"Real Estate",
            "subcategory":"Real Estate Agent",
            "type":"Services"
        }
    ],
    "sg:phone":"+1 307 234 3324",
    "sg:postcode":"82601",
    "sg:province":"WY",
    "wof:name":"Reid Debbie Real Estate",
    "wof:placetype":"venue"
},
  "geometry": {"coordinates":[-106.26674,42.844139],"type":"Point"}
}