{
  "type": "Feature",
  "properties": {
    "iso:country":"US",
    "sg:address":"624 W Fetterman St",
    "sg:city":"Buffalo",
    "sg:classifiers":[
        {
            "category":"Government",
            "subcategory":"Office",
            "type":"Public Place"
        }
    ],
    "sg:phone":"+1 307 684 2757",
    "sg:postcode":"82834",
    "sg:province":"WY",
    "sg:tags":[
        "organization",
        "membership",
        "executive"
    ],
    "wof:name":"City of Buffalo Dog Pound",
    "wof:placetype":"venue"
},
  "geometry": {"coordinates":[-106.708271,44.346689],"type":"Point"}
}