{
  "type": "Feature",
  "properties": {
    "addr:full":"3710 Ostdiek Ct Cheyenne WY 82001",
    "addr:housenumber":"3710",
    "addr:postcode":"82001",
    "addr:street":"Ostdiek Ct",
    "iso:country":"US",
    "sg:address":"3710 Ostdiek Ct",
    "sg:city":"Cheyenne",
    "sg:classifiers":[
        {
            "category":"Building & Trades",
            "subcategory":"Construction",
            "type":"Services"
        }
    ],
    "sg:phone":"+1 307 632 0982",
    "sg:postcode":"82001",
    "sg:province":"WY",
    "sg:tags":[
        "excavation",
        "park",
        "contractor",
        "mobile",
        "operator",
        "home"
    ],
    "wof:name":"Ostdiek Private MBL HM Subdv",
    "wof:placetype":"venue"
},
  "geometry": {"coordinates":[-104.765306,41.148456],"type":"Point"}
}