{
  "type": "Feature",
  "properties": {
    "iso:country":"US",
    "sg:address":"125 N 7th St",
    "sg:city":"Glenrock",
    "sg:classifiers":[
        {
            "category":"Organizations",
            "subcategory":"Religious Organization",
            "type":"Services"
        }
    ],
    "sg:phone":"+1 307 436 9565",
    "sg:postcode":"82637",
    "sg:province":"WY",
    "wof:name":"Glenrock Fndmntal Bptst Church",
    "wof:placetype":"venue"
},
  "geometry": {"coordinates":[-105.876698,42.864053],"type":"Point"}
}