{
  "type": "Feature",
  "properties": {
    "addr:full":"381 Bocage Dr Cheyenne WY 82009",
    "addr:housenumber":"381",
    "addr:postcode":"82009",
    "addr:street":"Bocage Dr",
    "iso:country":"US",
    "sg:address":"381 Bocage Dr",
    "sg:city":"Cheyenne",
    "sg:classifiers":[
        {
            "category":"Professional",
            "subcategory":"Business Services",
            "type":"Services"
        }
    ],
    "sg:phone":"+1 307 634 8410",
    "sg:postcode":"82009",
    "sg:province":"WY",
    "wof:name":"Db Systems LLC",
    "wof:placetype":"venue"
},
  "geometry": {"coordinates":[-104.824506,41.177152],"type":"Point"}
}