{
  "type": "Feature",
  "properties": {
    "iso:country":"US",
    "sg:address":"955 N 4 St",
    "sg:city":"Lander",
    "sg:classifiers":[
        {
            "category":"Restaurant",
            "type":"Food & Drink"
        }
    ],
    "sg:phone":"+1 307 332 2115",
    "sg:postcode":"82520",
    "sg:province":"WY",
    "sg:tags":[
        "shower",
        "operation",
        "catering"
    ],
    "wof:name":"Nu-Way Catering Service",
    "wof:placetype":"venue"
},
  "geometry": {"coordinates":[-108.734511,42.824649],"type":"Point"}
}