{
  "type": "Feature",
  "properties": {
    "addr:full":"104 E Pershing Blvd Cheyenne WY 82001",
    "addr:housenumber":"104",
    "addr:postcode":"82001",
    "addr:street":"E Pershing Blvd",
    "iso:country":"US",
    "sg:address":"104 E Pershing Blvd",
    "sg:city":"Cheyenne",
    "sg:classifiers":[
        {
            "category":"Manufacturing",
            "subcategory":"Tools & Machinery",
            "type":"Manufacturing & Wholesale Goods"
        }
    ],
    "sg:phone":"+1 307 632 1806",
    "sg:postcode":"82001",
    "sg:province":"WY",
    "sg:tags":[
        "inverter"
    ],
    "wof:name":"Integrated Investigations Inc",
    "wof:placetype":"venue"
},
  "geometry": {"coordinates":[-104.821136,41.145966],"type":"Point"}
}