{
  "type": "Feature",
  "properties": {
    "iso:country":"US",
    "sg:address":"111 S Riverbend Dr",
    "sg:city":"Douglas",
    "sg:classifiers":[
        {
            "category":"Real Estate",
            "subcategory":"Real Estate Operator",
            "type":"Services"
        }
    ],
    "sg:phone":"+1 307 358 1889",
    "sg:postcode":"82633",
    "sg:province":"WY",
    "sg:tags":[
        "building",
        "apartment"
    ],
    "wof:name":"Conestoga Village Apartments",
    "wof:placetype":"venue"
},
  "geometry": {"coordinates":[-105.406447,42.759186],"type":"Point"}
}