{
  "type": "Feature",
  "properties": {
    "iso:country":"US",
    "sg:address":"91 Gateway Blvd",
    "sg:city":"Rock Springs",
    "sg:classifiers":[
        {
            "category":"Restaurant",
            "type":"Food & Drink"
        }
    ],
    "sg:menulink":"http://www.allmenus.com/wy/rock-springs-north/135377-subway/menu/",
    "sg:phone":"+1 307 382 2822",
    "sg:postcode":"82901",
    "sg:province":"WY",
    "sg:tags":[
        "american",
        "sandwich"
    ],
    "wof:name":"Subway",
    "wof:placetype":"venue"
},
  "geometry": {"coordinates":[-109.249571,41.578241],"type":"Point"}
}