{
  "type": "Feature",
  "properties": {
    "iso:country":"US",
    "sg:address":"1641 Esterbrook Rd",
    "sg:city":"Douglas",
    "sg:classifiers":[
        {
            "category":"Education",
            "subcategory":"School",
            "type":"Public Place"
        }
    ],
    "sg:phone":"+1 307 358 0842",
    "sg:postcode":"82633",
    "sg:province":"WY",
    "wof:name":"White School",
    "wof:placetype":"venue"
},
  "geometry": {"coordinates":[-105.42462,42.540734],"type":"Point"}
}