{
  "type": "Feature",
  "properties": {
    "iso:country":"US",
    "sg:address":"1002 W Hill Rd",
    "sg:city":"Laramie",
    "sg:classifiers":[
        {
            "category":"Professional",
            "subcategory":"Business Services",
            "type":"Services"
        }
    ],
    "sg:phone":"+1 307 742 3857",
    "sg:postcode":"82072",
    "sg:province":"WY",
    "wof:name":"Gerald L Crites",
    "wof:placetype":"venue"
},
  "geometry": {"coordinates":[-105.582477,41.327761],"type":"Point"}
}