{
  "type": "Feature",
  "properties": {
    "addr:full":"225 S 4th St Thermopolis WY 82443",
    "addr:housenumber":"225",
    "addr:postcode":"82443",
    "addr:street":"S 4Th St Thermopolis Wy",
    "iso:country":"US",
    "sg:address":"225 S 4th St",
    "sg:city":"Thermopolis",
    "sg:classifiers":[
        {
            "category":"Food & Beverages",
            "subcategory":"Groceries & Convenience Stores",
            "type":"Retail Goods"
        }
    ],
    "sg:phone":"+1 307 864 5576",
    "sg:postcode":"82443",
    "sg:province":"WY",
    "sg:tags":[
        "independent",
        "grocer"
    ],
    "wof:name":"Don's IGA",
    "wof:placetype":"venue"
},
  "geometry": {"coordinates":[-108.20845199999999,43.644627],"type":"Point"}
}