{
  "type": "Feature",
  "properties": {
    "iso:country":"US",
    "sg:address":"100 Pou Rd",
    "sg:city":"Evansville",
    "sg:classifiers":[
        {
            "category":"Professional",
            "type":"Services"
        }
    ],
    "sg:phone":"+1 307 237 2522",
    "sg:postcode":"82636",
    "sg:province":"WY",
    "sg:tags":[
        "establishment"
    ],
    "wof:name":"Taylor & Taylor",
    "wof:placetype":"venue"
},
  "geometry": {"coordinates":[-106.15772,42.84521],"type":"Point"}
}