{
  "type": "Feature",
  "properties": {
    "addr:full":"170 Aspen Dr Buffalo WY 82834",
    "addr:housenumber":"170",
    "addr:postcode":"82834",
    "addr:street":"Aspen Dr Buffalo Wy",
    "iso:country":"US",
    "sg:address":"170 Aspen Dr",
    "sg:city":"Buffalo",
    "sg:classifiers":[
        {
            "category":"Building & Trades",
            "subcategory":"Construction",
            "type":"Services"
        }
    ],
    "sg:phone":"+1 307 684 9024",
    "sg:postcode":"82834",
    "sg:province":"WY",
    "sg:tags":[
        "residential"
    ],
    "wof:name":"Wildeman Contract Service Llc",
    "wof:placetype":"venue"
},
  "geometry": {"coordinates":[-106.74063099999999,44.339633],"type":"Point"}
}