{
  "type": "Feature",
  "properties": {
    "iso:country":"US",
    "sg:address":"900 Butler-Spaeth Rd",
    "sg:city":"Gillette",
    "sg:classifiers":[
        {
            "category":"Organizations",
            "subcategory":"Religious Organization",
            "type":"Services"
        }
    ],
    "sg:phone":"+1 307 682 3319",
    "sg:postcode":"82716",
    "sg:province":"WY",
    "sg:tags":[
        "church"
    ],
    "sg:website":"www.stmatthews.vcn.com",
    "wof:name":"Saint Matthews Catholic Church",
    "wof:placetype":"venue"
},
  "geometry": {"coordinates":[-105.47906999999999,44.28644],"type":"Point"}
}