{
  "type": "Feature",
  "properties": {
    "iso:country":"US",
    "sg:address":"3193 State Hwy 89 N",
    "sg:city":"Evanston",
    "sg:classifiers":[
        {
            "category":"Freight",
            "type":"Transportation"
        }
    ],
    "sg:phone":"+1 307 789 4358",
    "sg:postcode":"82930",
    "sg:province":"WY",
    "sg:tags":[
        "hauling",
        "trucking"
    ],
    "wof:name":"Schwitzer's Night & Day Trckng",
    "wof:placetype":"venue"
},
  "geometry": {"coordinates":[-110.996814,41.319669],"type":"Point"}
}