{
  "type": "Feature",
  "properties": {
    "iso:country":"US",
    "sg:address":"460 N 6th St",
    "sg:city":"Greybull",
    "sg:classifiers":[
        {
            "category":"Retail",
            "subcategory":"Auto Repair",
            "type":"Services"
        }
    ],
    "sg:phone":"+1 307 765 9220",
    "sg:postcode":"82426",
    "sg:province":"WY",
    "sg:tags":[
        "general"
    ],
    "wof:name":"Greybull Tire & Oil",
    "wof:placetype":"venue"
},
  "geometry": {"coordinates":[-108.05538,44.493873],"type":"Point"}
}