{
  "type": "Feature",
  "properties": {
    "addr:full":"28 N Piney Rd Story WY 82842",
    "addr:housenumber":"28",
    "addr:postcode":"82842",
    "addr:street":"N Piney Rd",
    "iso:country":"US",
    "sg:address":"28 N Piney Rd",
    "sg:city":"Story",
    "sg:classifiers":[
        {
            "category":"Organizations",
            "subcategory":"Membership Organization",
            "type":"Services"
        }
    ],
    "sg:phone":"+1 307 683 2109",
    "sg:postcode":"82842",
    "sg:province":"WY",
    "wof:name":"Story Women's Club",
    "wof:placetype":"venue"
},
  "geometry": {"coordinates":[-106.88706999999999,44.574799],"type":"Point"}
}