{
  "type": "Feature",
  "properties": {
    "iso:country":"US",
    "sg:address":"1616 E 19th St",
    "sg:city":"Cheyenne",
    "sg:classifiers":[
        {
            "category":"Health Services",
            "subcategory":"Doctor",
            "type":"Services"
        }
    ],
    "sg:phone":"+1 307 433 1110",
    "sg:postcode":"82001",
    "sg:province":"WY",
    "sg:tags":[
        "medical"
    ],
    "wof:name":"Cheyenne Hblttion Thrptic Cent",
    "wof:placetype":"venue"
},
  "geometry": {"coordinates":[-104.798036,41.14241],"type":"Point"}
}