{
  "type": "Feature",
  "properties": {
    "iso:country":"US",
    "sg:address":"105 Heap Dr",
    "sg:city":"Thayne",
    "sg:classifiers":[
        {
            "category":"Real Estate",
            "subcategory":"Real Estate Operator",
            "type":"Services"
        }
    ],
    "sg:phone":"+1 307 883 2265",
    "sg:postcode":"83127",
    "sg:province":"WY",
    "sg:tags":[
        "mobile",
        "home",
        "community"
    ],
    "wof:name":"Three Pines Trailer Court",
    "wof:placetype":"venue"
},
  "geometry": {"coordinates":[-111.00782,42.919419],"type":"Point"}
}