{
  "type": "Feature",
  "properties": {
    "iso:country":"US",
    "sg:address":"205 2nd St",
    "sg:city":"Ten Sleep",
    "sg:classifiers":[
        {
            "category":"Banks & Credit Unions",
            "subcategory":"Bank",
            "type":"Services"
        }
    ],
    "sg:phone":"+1 307 366 2551",
    "sg:postcode":"82442",
    "sg:province":"WY",
    "wof:name":"Ten Sleep National Bank",
    "wof:placetype":"venue"
},
  "geometry": {"coordinates":[-107.449764,44.034104],"type":"Point"}
}