{
  "type": "Feature",
  "properties": {
    "iso:country":"US",
    "sg:address":"701 Wind River Ave",
    "sg:city":"Casper",
    "sg:classifiers":[
        {
            "category":"Building & Trades",
            "subcategory":"Construction",
            "type":"Services"
        }
    ],
    "sg:phone":"+1 307 235 0735",
    "sg:postcode":"82609",
    "sg:province":"WY",
    "sg:tags":[
        "general",
        "contractor"
    ],
    "wof:name":"Bird Contracting",
    "wof:placetype":"venue"
},
  "geometry": {"coordinates":[-106.27858000000001,42.842639],"type":"Point"}
}