{
  "type": "Feature",
  "properties": {
    "addr:full":"17 Wagon Hammer Ln Lander WY 82520",
    "addr:housenumber":"17",
    "addr:postcode":"wy 82520",
    "addr:street":"Wagon Hammer Ln",
    "iso:country":"US",
    "sg:address":"17 Wagon Hammer Ln",
    "sg:city":"Lander",
    "sg:classifiers":[
        {
            "category":"Professional",
            "subcategory":"Management & Consulting",
            "type":"Services"
        }
    ],
    "sg:phone":"+1 307 335 8666",
    "sg:postcode":"82520",
    "sg:province":"WY",
    "sg:tags":[
        "business"
    ],
    "wof:name":"Fremont Energy Company",
    "wof:placetype":"venue"
},
  "geometry": {"coordinates":[-108.655376,42.762222],"type":"Point"}
}