{
  "type": "Feature",
  "properties": {
    "iso:country":"US",
    "sg:address":"5097 US Hwy 16",
    "sg:city":"Newcastle",
    "sg:classifiers":[
        {
            "category":"Manufacturing",
            "subcategory":"Lumber",
            "type":"Manufacturing & Wholesale Goods"
        }
    ],
    "sg:phone":"+1 307 746 9656",
    "sg:postcode":"82701",
    "sg:province":"WY",
    "sg:tags":[
        "construction",
        "logging"
    ],
    "wof:name":"A-1 Lumber Co",
    "wof:placetype":"venue"
},
  "geometry": {"coordinates":[-104.167368,43.84076],"type":"Point"}
}