{
  "type": "Feature",
  "properties": {
    "iso:country":"US",
    "sg:address":"206 W 1st St",
    "sg:city":"Gillette",
    "sg:classifiers":[
        {
            "category":"Wholesale",
            "subcategory":"Machinery & Supplies",
            "type":"Manufacturing & Wholesale Goods"
        }
    ],
    "sg:phone":"+1 307 682 4154",
    "sg:postcode":"82716",
    "sg:province":"WY",
    "sg:tags":[
        "equipment",
        "industrial"
    ],
    "wof:name":"Valley Welders & Indus Sup",
    "wof:placetype":"venue"
},
  "geometry": {"coordinates":[-105.506865,44.294494],"type":"Point"}
}