{
  "type": "Feature",
  "properties": {
    "iso:country":"US",
    "sg:address":"102 Foothill Blvd",
    "sg:city":"Rock Springs",
    "sg:classifiers":[
        {
            "category":"Wholesale",
            "subcategory":"Machinery & Supplies",
            "type":"Manufacturing & Wholesale Goods"
        }
    ],
    "sg:phone":"+1 307 382 3134",
    "sg:postcode":"82901",
    "sg:province":"WY",
    "sg:tags":[
        "equipment",
        "field"
    ],
    "sg:website":"www.coopercameron.com",
    "wof:name":"Cameron",
    "wof:placetype":"venue"
},
  "geometry": {"coordinates":[-109.292,41.565999],"type":"Point"}
}