{
  "type": "Feature",
  "properties": {
    "iso:country":"US",
    "sg:address":"1400 W Warlow Dr",
    "sg:city":"Gillette",
    "sg:classifiers":[
        {
            "category":"Utilities",
            "subcategory":"Mobile Phone",
            "type":"Services"
        }
    ],
    "sg:phone":"+1 307 682 0113",
    "sg:postcode":"82716",
    "sg:province":"WY",
    "sg:tags":[
        "telephone",
        "cellular"
    ],
    "wof:name":"Action Page",
    "wof:placetype":"venue"
},
  "geometry": {"coordinates":[-105.52310900000001,44.299766],"type":"Point"}
}