{
  "type": "Feature",
  "properties": {
    "iso:country":"US",
    "sg:address":"307 E 17th St",
    "sg:city":"Cheyenne",
    "sg:classifiers":[
        {
            "category":"Shopping",
            "subcategory":"Clothing, Apparel, & Fashions",
            "type":"Retail Goods"
        }
    ],
    "sg:phone":"+1 307 772 4430",
    "sg:postcode":"82001",
    "sg:province":"WY",
    "wof:name":"A Unique Boutique",
    "wof:placetype":"venue"
},
  "geometry": {"coordinates":[-104.811392,41.135187],"type":"Point"}
}