{
  "type": "Feature",
  "properties": {
    "iso:country":"US",
    "sg:address":"155 Cedar St",
    "sg:city":"Green River",
    "sg:classifiers":[
        {
            "category":"Building & Trades",
            "subcategory":"Electrical",
            "type":"Services"
        }
    ],
    "sg:phone":"+1 307 875 3347",
    "sg:postcode":"82935",
    "sg:province":"WY",
    "sg:tags":[
        "electrical",
        "contractor"
    ],
    "wof:name":"Able Electric",
    "wof:placetype":"venue"
},
  "geometry": {"coordinates":[-109.472037,41.520661],"type":"Point"}
}