{
  "type": "Feature",
  "properties": {
    "iso:country":"US",
    "sg:address":"1051 N Bonita Dr",
    "sg:city":"Laramie",
    "sg:classifiers":[
        {
            "category":"Real Estate",
            "subcategory":"Real Estate Operator",
            "type":"Services"
        }
    ],
    "sg:phone":"+1 307 745 3338",
    "sg:postcode":"82072",
    "sg:province":"WY",
    "sg:tags":[
        "building",
        "apartment"
    ],
    "wof:name":"Chisholm Trail Investment",
    "wof:placetype":"venue"
},
  "geometry": {"coordinates":[-105.555756,41.32174],"type":"Point"}
}