{
  "type": "Feature",
  "properties": {
    "addr:full":"5825 Eastland Ct Cheyenne WY 82001",
    "addr:housenumber":"5825",
    "addr:postcode":"82001",
    "addr:street":"Eastland Ct",
    "iso:country":"US",
    "sg:address":"5825 Eastland Ct",
    "sg:city":"Cheyenne",
    "sg:classifiers":[
        {
            "category":"Real Estate",
            "subcategory":"Real Estate Operator",
            "type":"Services"
        }
    ],
    "sg:phone":"+1 307 632 3112",
    "sg:postcode":"82001",
    "sg:province":"WY",
    "sg:tags":[
        "building",
        "apartment"
    ],
    "wof:name":"Prairie View Apartments",
    "wof:placetype":"venue"
},
  "geometry": {"coordinates":[-104.73879599999999,41.154964],"type":"Point"}
}