{
  "type": "Feature",
  "properties": {
    "iso:country":"US",
    "sg:address":"1001 Buckskin Dr",
    "sg:city":"Gillette",
    "sg:classifiers":[
        {
            "category":"Mining & Drilling",
            "type":"Manufacturing & Wholesale Goods"
        }
    ],
    "sg:phone":"+1 307 682 8452",
    "sg:postcode":"82716",
    "sg:province":"WY",
    "sg:tags":[
        "field",
        "oil"
    ],
    "wof:name":"Bill's Hydraulic Specialists",
    "wof:placetype":"venue"
},
  "geometry": {"coordinates":[-105.48435000000001,44.30907],"type":"Point"}
}