{
  "type": "Feature",
  "properties": {
    "iso:country":"US",
    "sg:address":"46 W 3rd Ave",
    "sg:city":"Afton",
    "sg:classifiers":[
        {
            "category":"Real Estate",
            "subcategory":"Surveying",
            "type":"Services"
        }
    ],
    "sg:phone":"+1 307 885 9319",
    "sg:postcode":"83110",
    "sg:province":"WY",
    "sg:tags":[
        "surveyor"
    ],
    "wof:name":"Surveyor Schervel LTD",
    "wof:placetype":"venue"
},
  "geometry": {"coordinates":[-110.935935,42.727388],"type":"Point"}
}