{
  "type": "Feature",
  "properties": {
    "iso:country":"US",
    "sg:address":"319 S New York Ave",
    "sg:city":"Hudson",
    "sg:classifiers":[
        {
            "category":"Organizations",
            "subcategory":"Religious Organization",
            "type":"Services"
        }
    ],
    "sg:phone":"+1 307 332 2609",
    "sg:postcode":"82515",
    "sg:province":"WY",
    "sg:tags":[
        "church"
    ],
    "wof:name":"Hudson Community Church",
    "wof:placetype":"venue"
},
  "geometry": {"coordinates":[-108.578855,42.901958],"type":"Point"}
}