{
  "type": "Feature",
  "properties": {
    "iso:country":"US",
    "sg:address":"4308 E Grand Ave",
    "sg:city":"Laramie",
    "sg:classifiers":[
        {
            "category":"Banks & Credit Unions",
            "subcategory":"Bank",
            "type":"Services"
        }
    ],
    "sg:phone":"+1 307 721 4600",
    "sg:postcode":"82070",
    "sg:province":"WY",
    "wof:name":"First Interstate Bank",
    "wof:placetype":"venue"
},
  "geometry": {"coordinates":[-105.539541,41.304066],"type":"Point"}
}