{
  "type": "Feature",
  "properties": {
    "iso:country":"US",
    "sg:address":"109 Jonquil St",
    "sg:city":"Casper",
    "sg:classifiers":[
        {
            "category":"Food & Beverages",
            "subcategory":"Specialty",
            "type":"Retail Goods"
        }
    ],
    "sg:phone":"+1 307 261 4942",
    "sg:postcode":"82604",
    "sg:province":"WY",
    "wof:name":"Water Store",
    "wof:placetype":"venue"
},
  "geometry": {"coordinates":[-106.40112999999999,42.826599],"type":"Point"}
}