{
  "type": "Feature",
  "properties": {
    "iso:country":"US",
    "sg:address":"19 Bowker Rd",
    "sg:city":"Rock Springs",
    "sg:classifiers":[
        {
            "category":"Retail",
            "subcategory":"Auto Repair",
            "type":"Services"
        }
    ],
    "sg:phone":"+1 307 382 5050",
    "sg:postcode":"82901",
    "sg:province":"WY",
    "sg:tags":[
        "truck"
    ],
    "wof:name":"Peterbilt",
    "wof:placetype":"venue"
},
  "geometry": {"coordinates":[-109.272147,41.570397],"type":"Point"}
}