{
  "type": "Feature",
  "properties": {
    "addr:full":"2425 Mountain View Dr Cody WY 82414",
    "addr:housenumber":"2425",
    "addr:postcode":"82414",
    "addr:street":"Mountain View Dr",
    "iso:country":"US",
    "sg:address":"2425 Mountain View Dr",
    "sg:city":"Cody",
    "sg:classifiers":[
        {
            "category":"Manufacturing",
            "subcategory":"Metals",
            "type":"Manufacturing & Wholesale Goods"
        }
    ],
    "sg:phone":"+1 307 587 4373",
    "sg:postcode":"82414",
    "sg:province":"WY",
    "sg:tags":[
        "plumbing",
        "fixture",
        "supply"
    ],
    "wof:name":"Cody Winnelson Co",
    "wof:placetype":"venue"
},
  "geometry": {"coordinates":[-109.04047799999999,44.515264],"type":"Point"}
}