{
  "type": "Feature",
  "properties": {
    "addr:full":"842 E South St Powell WY 82435",
    "addr:housenumber":"842 e",
    "addr:postcode":"82435",
    "addr:street":"South St Powell Wy",
    "iso:country":"US",
    "sg:address":"842 E South St",
    "sg:city":"Powell",
    "sg:classifiers":[
        {
            "category":"Retail",
            "subcategory":"Auto Repair",
            "type":"Services"
        }
    ],
    "sg:phone":"+1 307 754 7289",
    "sg:postcode":"82435",
    "sg:province":"WY",
    "sg:tags":[
        "repairing",
        "automobile",
        "boat",
        "general"
    ],
    "wof:name":"Dorm's Automotive & Marine",
    "wof:placetype":"venue"
},
  "geometry": {"coordinates":[-108.748637,44.751958],"type":"Point"}
}