{
  "type": "Feature",
  "properties": {
    "iso:country":"US",
    "sg:address":"3307 Watsabaugh Dr",
    "sg:city":"Gillette",
    "sg:classifiers":[
        {
            "category":"Mining & Drilling",
            "type":"Manufacturing & Wholesale Goods"
        }
    ],
    "sg:phone":"+1 307 682 4511",
    "sg:postcode":"82718",
    "sg:province":"WY",
    "sg:tags":[
        "field",
        "oil"
    ],
    "wof:name":"J-Bird Well Svc",
    "wof:placetype":"venue"
},
  "geometry": {"coordinates":[-105.51419799999999,44.262785],"type":"Point"}
}