{
  "type": "Feature",
  "properties": {
    "iso:country":"US",
    "sg:address":"2010 W 4-J Rd",
    "sg:city":"Gillette",
    "sg:classifiers":[
        {
            "category":"Organizations",
            "subcategory":"Religious Organization",
            "type":"Services"
        }
    ],
    "sg:phone":"+1 307 685 2272",
    "sg:postcode":"82718",
    "sg:province":"WY",
    "sg:tags":[
        "church"
    ],
    "wof:name":"Mike Morrison Ministries",
    "wof:placetype":"venue"
},
  "geometry": {"coordinates":[-105.50977899999999,44.27594],"type":"Point"}
}