{
  "type": "Feature",
  "properties": {
    "addr:full":"120 W Pearl Ave Jackson WY 83001",
    "addr:housenumber":"120",
    "addr:postcode":"83001",
    "addr:street":"W Pearl Ave Jackson Wy",
    "iso:country":"US",
    "sg:address":"120 W Pearl Ave",
    "sg:city":"Jackson",
    "sg:classifiers":[
        {
            "category":"Wholesale",
            "subcategory":"Apparel",
            "type":"Manufacturing & Wholesale Goods"
        }
    ],
    "sg:phone":"+1 307 734 3880",
    "sg:postcode":"83001",
    "sg:province":"WY",
    "sg:tags":[
        "clothing"
    ],
    "sg:website":"www.cloudveil.com",
    "wof:name":"Cloudveil Mountain Works",
    "wof:placetype":"venue"
},
  "geometry": {"coordinates":[-110.764867,43.478449],"type":"Point"}
}