{
  "type": "Feature",
  "properties": {
    "addr:full":"310 E Broadway Jackson WY 83001",
    "addr:housenumber":"310",
    "addr:postcode":"83001",
    "addr:street":"E Broadway Jackson Wy",
    "iso:country":"US",
    "sg:address":"310 E Broadway",
    "sg:city":"Jackson",
    "sg:classifiers":[
        {
            "category":"Health Services",
            "subcategory":"Clinic",
            "type":"Services"
        }
    ],
    "sg:phone":"+1 307 734 2877",
    "sg:postcode":"83001",
    "sg:province":"WY",
    "sg:tags":[
        "therapy",
        "hand"
    ],
    "wof:name":"Teton Hand Therapy",
    "wof:placetype":"venue"
},
  "geometry": {"coordinates":[-110.756129,43.479544],"type":"Point"}
}