{
  "type": "Feature",
  "properties": {
    "addr:full":"307 W 3rd St Gillette WY 82716",
    "addr:housenumber":"307",
    "addr:postcode":"82716",
    "addr:street":"W 3Rd St",
    "iso:country":"US",
    "sg:address":"307 W 3rd St",
    "sg:city":"Gillette",
    "sg:classifiers":[
        {
            "category":"Health Services",
            "subcategory":"Medical Lab",
            "type":"Services"
        }
    ],
    "sg:phone":"+1 307 685 1501",
    "sg:postcode":"82716",
    "sg:province":"WY",
    "sg:tags":[
        "laboratory",
        "dental"
    ],
    "wof:name":"Sawtooth Dental Lab",
    "wof:placetype":"venue"
},
  "geometry": {"coordinates":[-105.508295,44.292106],"type":"Point"}
}