{
  "type": "Feature",
  "properties": {
    "iso:country":"US",
    "sg:address":"107675 US Hwy 89",
    "sg:city":"Etna",
    "sg:classifiers":[
        {
            "category":"Professional",
            "subcategory":"Engineering",
            "type":"Services"
        }
    ],
    "sg:phone":"+1 307 883 2906",
    "sg:postcode":"83118",
    "sg:province":"WY",
    "sg:tags":[
        "engineer"
    ],
    "wof:name":"Star Valley Engineering",
    "wof:placetype":"venue"
},
  "geometry": {"coordinates":[-111.01215999999999,43.031459],"type":"Point"}
}