{
  "type": "Feature",
  "properties": {
    "addr:full":"601 Oak St Douglas WY 82633",
    "addr:housenumber":"601",
    "addr:postcode":"82633",
    "addr:street":"Oak St Douglas Wy",
    "iso:country":"US",
    "sg:address":"601 Oak St",
    "sg:city":"Douglas",
    "sg:classifiers":[
        {
            "category":"Health Services",
            "subcategory":"Nursing And Care Facility",
            "type":"Services"
        }
    ],
    "sg:phone":"+1 307 358 6790",
    "sg:postcode":"82633",
    "sg:province":"WY",
    "sg:tags":[
        "home",
        "retirement",
        "community"
    ],
    "wof:name":"Mc Comb Retirement Ctr",
    "wof:placetype":"venue"
},
  "geometry": {"coordinates":[-105.379964,42.75803],"type":"Point"}
}