{
  "type": "Feature",
  "properties": {
    "iso:country":"US",
    "sg:address":"1620 E Yellowstone Hwy",
    "sg:city":"Casper",
    "sg:classifiers":[
        {
            "category":"Restaurant",
            "type":"Food & Drink"
        }
    ],
    "sg:phone":"+1 307 234 6962",
    "sg:postcode":"82601",
    "sg:province":"WY",
    "sg:tags":[
        "motel"
    ],
    "wof:name":"Red & White Cafe",
    "wof:placetype":"venue"
},
  "geometry": {"coordinates":[-106.30287,42.853709],"type":"Point"}
}