{
  "type": "Feature",
  "properties": {
    "iso:country":"US",
    "sg:address":"622 W Main St",
    "sg:city":"Newcastle",
    "sg:classifiers":[
        {
            "category":"Food & Beverages",
            "subcategory":"Groceries & Convenience Stores",
            "type":"Retail Goods"
        }
    ],
    "sg:phone":"+1 307 746 3511",
    "sg:postcode":"82701",
    "sg:province":"WY",
    "sg:tags":[
        "grocer"
    ],
    "wof:name":"Woody's Food Ctr",
    "wof:placetype":"venue"
},
  "geometry": {"coordinates":[-104.212233,43.85177],"type":"Point"}
}