{
  "type": "Feature",
  "properties": {
    "iso:country":"US",
    "sg:address":"1755 W Sunset Dr",
    "sg:city":"Riverton",
    "sg:classifiers":[
        {
            "category":"Education",
            "subcategory":"School",
            "type":"Public Place"
        }
    ],
    "sg:phone":"+1 307 856 6526",
    "sg:postcode":"82501",
    "sg:province":"WY",
    "wof:name":"Alternative School",
    "wof:placetype":"venue"
},
  "geometry": {"coordinates":[-108.41360299999999,43.033582],"type":"Point"}
}