{
  "type": "Feature",
  "properties": {
    "addr:full":"104 E Hart St Buffalo WY 82834",
    "addr:housenumber":"104",
    "addr:postcode":"82834",
    "addr:street":"E Hart St Buffalo Wy",
    "iso:country":"US",
    "sg:address":"104 E Hart St",
    "sg:city":"Buffalo",
    "sg:classifiers":[
        {
            "category":"Restaurant",
            "type":"Food & Drink"
        }
    ],
    "sg:menulink":"http://www.allmenus.com/wy/buffalo/155296-hardees/menu/",
    "sg:phone":"+1 307 684 7971",
    "sg:postcode":"82834",
    "sg:province":"WY",
    "sg:tags":[
        "burger",
        "american"
    ],
    "wof:name":"Hardee's",
    "wof:placetype":"venue"
},
  "geometry": {"coordinates":[-106.69739800000001,44.35423],"type":"Point"}
}