{
  "type": "Feature",
  "properties": {
    "iso:country":"US",
    "sg:address":"400 Broadway St",
    "sg:city":"Sheridan",
    "sg:classifiers":[
        {
            "category":"Shopping",
            "subcategory":"Gifts & Souvenirs",
            "type":"Retail Goods"
        }
    ],
    "sg:phone":"+1 307 674 7945",
    "sg:postcode":"82801",
    "sg:province":"WY",
    "wof:name":"Carls Corner Cards & Gifts",
    "wof:placetype":"venue"
},
  "geometry": {"coordinates":[-106.953369,44.80251],"type":"Point"}
}