{
  "type": "Feature",
  "properties": {
    "iso:country":"US",
    "sg:address":"2212 Dunblane Dr",
    "sg:city":"Rawlins",
    "sg:classifiers":[
        {
            "category":"Wholesale",
            "subcategory":"Chemicals & Plastics",
            "type":"Manufacturing & Wholesale Goods"
        }
    ],
    "sg:phone":"+1 307 324 9041",
    "sg:postcode":"82301",
    "sg:province":"WY",
    "sg:tags":[
        "oxygen"
    ],
    "wof:name":"Pam's Oxygen Therapy Inc",
    "wof:placetype":"venue"
},
  "geometry": {"coordinates":[-107.219729,41.809961],"type":"Point"}
}