{
  "type": "Feature",
  "properties": {
    "iso:country":"US",
    "sg:address":"18566 US Hwy 14",
    "sg:city":"Sundance",
    "sg:classifiers":[
        {
            "category":"Farming",
            "subcategory":"Livestock Farm",
            "type":"Manufacturing & Wholesale Goods"
        }
    ],
    "sg:phone":"+1 307 283 2066",
    "sg:postcode":"82729",
    "sg:province":"WY",
    "sg:tags":[
        "beef",
        "equine",
        "feedlot",
        "cattle"
    ],
    "wof:name":"Harold Adema",
    "wof:placetype":"venue"
},
  "geometry": {"coordinates":[-104.388091,44.395064],"type":"Point"}
}