{
  "type": "Feature",
  "properties": {
    "addr:full":"801 E 4th St Gillette WY 82716",
    "addr:housenumber":"801",
    "addr:postcode":"82716",
    "addr:street":"E 4Th St",
    "iso:country":"US",
    "sg:address":"801 E 4th St",
    "sg:city":"Gillette",
    "sg:classifiers":[
        {
            "category":"Government",
            "subcategory":"Office",
            "type":"Public Place"
        }
    ],
    "sg:phone":"+1 307 686 6440",
    "sg:postcode":"82716",
    "sg:province":"WY",
    "sg:tags":[
        "armed",
        "force",
        "recruiting"
    ],
    "wof:name":"US Army Recruiting",
    "wof:placetype":"venue"
},
  "geometry": {"coordinates":[-105.49311,44.291299],"type":"Point"}
}