{
  "type": "Feature",
  "properties": {
    "iso:country":"US",
    "sg:address":"614 E 8th St",
    "sg:city":"Cheyenne",
    "sg:classifiers":[
        {
            "category":"Shopping",
            "subcategory":"Hobbies, Toys, & Games",
            "type":"Retail Goods"
        }
    ],
    "sg:phone":"+1 307 635 7899",
    "sg:postcode":"82007",
    "sg:province":"WY",
    "wof:name":"Custom Pnted Dsigns On Clothes",
    "wof:placetype":"venue"
},
  "geometry": {"coordinates":[-104.802976,41.128568],"type":"Point"}
}