{
  "type": "Feature",
  "properties": {
    "iso:country":"US",
    "sg:address":"2 Story Brooke Ln",
    "sg:city":"Story",
    "sg:classifiers":[
        {
            "category":"Retail",
            "subcategory":"Repair Shop",
            "type":"Services"
        },
        {
            "category":"Home & Garden",
            "subcategory":"Home Furnishings",
            "type":"Retail Goods"
        }
    ],
    "sg:phone":"+1 307 672 3283",
    "sg:postcode":"82842",
    "sg:province":"WY",
    "sg:tags":[
        "upholsterer"
    ],
    "wof:name":"Barbula's Upholstery & Sewing",
    "wof:placetype":"venue"
},
  "geometry": {"coordinates":[-106.8927,44.572279],"type":"Point"}
}