{
  "type": "Feature",
  "properties": {
    "addr:full":"29 Sand Cliff Rd Meeteetse WY 82433",
    "addr:housenumber":"29",
    "addr:postcode":"82433",
    "addr:street":"Sand Cliff Rd Meeteetse Wy",
    "iso:country":"US",
    "sg:address":"29 Sand Cliff Rd",
    "sg:city":"Meeteetse",
    "sg:classifiers":[
        {
            "category":"Manufacturing",
            "subcategory":"Buildings",
            "type":"Manufacturing & Wholesale Goods"
        }
    ],
    "sg:phone":"+1 307 868 2223",
    "sg:postcode":"82433",
    "sg:province":"WY",
    "sg:tags":[
        "home",
        "log",
        "cabin"
    ],
    "wof:name":"Yellowstone Woodcare",
    "wof:placetype":"venue"
},
  "geometry": {"coordinates":[-108.882341,44.168089],"type":"Point"}
}