{
  "type": "Feature",
  "properties": {
    "iso:country":"US",
    "sg:address":"47 State Hwy 28",
    "sg:city":"Farson",
    "sg:classifiers":[
        {
            "category":"Organizations",
            "subcategory":"Religious Organization",
            "type":"Services"
        }
    ],
    "sg:phone":"+1 307 273 9767",
    "sg:postcode":"82932",
    "sg:province":"WY",
    "sg:tags":[
        "church"
    ],
    "wof:name":"Eden Valley Baptist Church",
    "wof:placetype":"venue"
},
  "geometry": {"coordinates":[-109.43533100000001,42.114834],"type":"Point"}
}