{
  "type": "Feature",
  "properties": {
    "iso:country":"US",
    "sg:address":"327 C St",
    "sg:city":"Rock Springs",
    "sg:classifiers":[
        {
            "category":"Sports & Exercise",
            "subcategory":"Bowling",
            "type":"Entertainment"
        }
    ],
    "sg:phone":"+1 307 362 5235",
    "sg:postcode":"82901",
    "sg:province":"WY",
    "sg:tags":[
        "center"
    ],
    "wof:name":"Plamor Lanes",
    "wof:placetype":"venue"
},
  "geometry": {"coordinates":[-109.219318,41.584432],"type":"Point"}
}