{
  "type": "Feature",
  "properties": {
    "iso:country":"US",
    "sg:address":"1409 Woodworth St",
    "sg:city":"Sheridan",
    "sg:classifiers":[
        {
            "category":"Professional",
            "subcategory":"Research",
            "type":"Services"
        },
        {
            "category":"Professional",
            "subcategory":"Management & Consulting",
            "type":"Services"
        }
    ],
    "sg:phone":"+1 307 672 5752",
    "sg:postcode":"82801",
    "sg:province":"WY",
    "sg:tags":[
        "environmental",
        "ecological",
        "business"
    ],
    "wof:name":"Aquatic Assessments Inc",
    "wof:placetype":"venue"
},
  "geometry": {"coordinates":[-106.978191,44.800211],"type":"Point"}
}