{
  "type": "Feature",
  "properties": {
    "iso:country":"US",
    "sg:address":"63 Rd 2Abn",
    "sg:city":"Cody",
    "sg:classifiers":[
        {
            "category":"Building & Trades",
            "subcategory":"Construction",
            "type":"Services"
        }
    ],
    "sg:phone":"+1 307 527 7166",
    "sg:postcode":"82414",
    "sg:province":"WY",
    "sg:tags":[
        "general",
        "contractor"
    ],
    "wof:name":"Moltz Constructors Inc",
    "wof:placetype":"venue"
},
  "geometry": {"coordinates":[-109.07461600000001,44.555568],"type":"Point"}
}