{
  "type": "Feature",
  "properties": {
    "addr:full":"447 N Front St Rock Springs WY 82901",
    "addr:housenumber":"447",
    "addr:postcode":"82901",
    "addr:street":"N Front St",
    "iso:country":"US",
    "sg:address":"447 N Front St",
    "sg:city":"Rock Springs",
    "sg:classifiers":[
        {
            "category":"Shopping",
            "subcategory":"Shoes",
            "type":"Retail Goods"
        }
    ],
    "sg:phone":"+1 307 362 6777",
    "sg:postcode":"82901",
    "sg:province":"WY",
    "sg:tags":[
        "boot"
    ],
    "wof:name":"Kelley's Shoes Inc",
    "wof:placetype":"venue"
},
  "geometry": {"coordinates":[-109.22110600000001,41.587014],"type":"Point"}
}