{
  "type": "Feature",
  "properties": {
    "iso:country":"US",
    "sg:address":"39 Bohica Ln",
    "sg:city":"Cody",
    "sg:classifiers":[
        {
            "category":"Professional",
            "subcategory":"Secretarial Services",
            "type":"Services"
        }
    ],
    "sg:phone":"+1 307 587 9334",
    "sg:postcode":"82414",
    "sg:province":"WY",
    "sg:tags":[
        "reporting"
    ],
    "wof:name":"Medical Transcription Services",
    "wof:placetype":"venue"
},
  "geometry": {"coordinates":[-109.061896,44.555426],"type":"Point"}
}