{
  "type": "Feature",
  "properties": {
    "iso:country":"US",
    "sg:address":"546 Main St",
    "sg:city":"Lander",
    "sg:classifiers":[
        {
            "category":"Shopping",
            "subcategory":"Gifts & Souvenirs",
            "type":"Retail Goods"
        }
    ],
    "sg:phone":"+1 307 332 6943",
    "sg:postcode":"82520",
    "sg:province":"WY",
    "wof:name":"Ceramics Unlimited",
    "wof:placetype":"venue"
},
  "geometry": {"coordinates":[-108.73638800000001,42.834282],"type":"Point"}
}