{
  "type": "Feature",
  "properties": {
    "addr:full":"206 W Lincolnway Cheyenne WY 82001",
    "addr:housenumber":"206",
    "addr:postcode":"82001",
    "addr:street":"W Lincolnway;Wy",
    "iso:country":"US",
    "sg:address":"206 W Lincolnway",
    "sg:city":"Cheyenne",
    "sg:classifiers":[
        {
            "category":"Shopping",
            "type":"Retail Goods"
        },
        {
            "category":"Food & Beverages",
            "subcategory":"Bakery",
            "type":"Retail Goods"
        }
    ],
    "sg:phone":"+1 307 635 6279",
    "sg:postcode":"82001",
    "sg:province":"WY",
    "sg:tags":[
        "baker",
        "wedding",
        "supply"
    ],
    "wof:name":"Mary's Bake Shoppe",
    "wof:placetype":"venue"
},
  "geometry": {"coordinates":[-104.816361,41.132416],"type":"Point"}
}