{
  "type": "Feature",
  "properties": {
    "iso:country":"US",
    "sg:address":"502 E Allison Rd",
    "sg:city":"Cheyenne",
    "sg:classifiers":[
        {
            "category":"Building & Trades",
            "subcategory":"Construction",
            "type":"Services"
        }
    ],
    "sg:phone":"+1 307 638 3856",
    "sg:postcode":"82007",
    "sg:province":"WY",
    "sg:tags":[
        "house"
    ],
    "wof:name":"Quinns Icf Construction LLC",
    "wof:placetype":"venue"
},
  "geometry": {"coordinates":[-104.795646,41.10957],"type":"Point"}
}