{
  "type": "Feature",
  "properties": {
    "iso:country":"US",
    "sg:address":"140 N Cache Dr",
    "sg:city":"Jackson",
    "sg:classifiers":[
        {
            "category":"Professional",
            "subcategory":"Art Services",
            "type":"Services"
        }
    ],
    "sg:phone":"+1 307 733 7015",
    "sg:postcode":"83001",
    "sg:province":"WY",
    "sg:tags":[
        "photographer"
    ],
    "wof:name":"Whitewater Photos & Videos",
    "wof:placetype":"venue"
},
  "geometry": {"coordinates":[-110.76230200000001,43.481538],"type":"Point"}
}