{
  "type": "Feature",
  "properties": {
    "iso:country":"US",
    "sg:address":"110 W Karns Ave",
    "sg:city":"Jackson",
    "sg:classifiers":[
        {
            "category":"Personal",
            "type":"Services"
        }
    ],
    "sg:phone":"+1 307 733 7355",
    "sg:postcode":"83001",
    "sg:province":"WY",
    "sg:tags":[
        "therapist",
        "massage"
    ],
    "wof:name":"Alpine Mobile Massage",
    "wof:placetype":"venue"
},
  "geometry": {"coordinates":[-110.765112,43.474439],"type":"Point"}
}