{
  "type": "Feature",
  "properties": {
    "addr:full":"804 E 2nd St Gillette WY 82716",
    "addr:housenumber":"804",
    "addr:postcode":"82716",
    "addr:street":"E 2Nd St",
    "iso:country":"US",
    "sg:address":"804 E 2nd St",
    "sg:city":"Gillette",
    "sg:classifiers":[
        {
            "category":"Building & Trades",
            "subcategory":"Equipment Rental",
            "type":"Services"
        }
    ],
    "sg:phone":"+1 307 686 3113",
    "sg:postcode":"82716",
    "sg:province":"WY",
    "wof:name":"Gizmos Rental",
    "wof:placetype":"venue"
},
  "geometry": {"coordinates":[-105.49414,44.293091],"type":"Point"}
}