{
  "type": "Feature",
  "properties": {
    "iso:country":"US",
    "sg:address":"116 Front St",
    "sg:city":"Big Piney",
    "sg:classifiers":[
        {
            "category":"Food & Beverages",
            "subcategory":"Liquor & Beverages",
            "type":"Retail Goods"
        }
    ],
    "sg:phone":"+1 307 276 3592",
    "sg:postcode":"83113",
    "sg:province":"WY",
    "wof:name":"Wheel-In Liquors & Bar",
    "wof:placetype":"venue"
},
  "geometry": {"coordinates":[-110.10980000000001,42.53637],"type":"Point"}
}