{
  "type": "Feature",
  "properties": {
    "addr:full":"1949 Sugarland Dr Sheridan WY 82801",
    "addr:housenumber":"1949",
    "addr:postcode":"82801",
    "addr:street":"Sugarland Dr",
    "iso:country":"US",
    "sg:address":"1949 Sugarland Dr",
    "sg:city":"Sheridan",
    "sg:classifiers":[
        {
            "category":"Government",
            "subcategory":"Office",
            "type":"Public Place"
        }
    ],
    "sg:phone":"+1 307 672 2788",
    "sg:postcode":"82801",
    "sg:province":"WY",
    "sg:tags":[
        "policy"
    ],
    "wof:name":"Internal Revenue Service",
    "wof:placetype":"venue"
},
  "geometry": {"coordinates":[-106.93949000000001,44.777426],"type":"Point"}
}