{
  "type": "Feature",
  "properties": {
    "iso:country":"US",
    "sg:address":"1457 South St",
    "sg:city":"Wheatland",
    "sg:classifiers":[
        {
            "category":"Restaurant",
            "type":"Food & Drink"
        }
    ],
    "sg:menulink":"http://www.allmenus.com/wy/wheatland/96495-taco-johns/menu/",
    "sg:phone":"+1 307 322 4058",
    "sg:postcode":"82201",
    "sg:province":"WY",
    "sg:tags":[
        "american",
        "mexican"
    ],
    "wof:name":"Taco John's",
    "wof:placetype":"venue"
},
  "geometry": {"coordinates":[-104.9602,42.051603],"type":"Point"}
}