{
  "type": "Feature",
  "properties": {
    "addr:full":"1162 Pass Creek Rd Parkman WY 82838",
    "addr:housenumber":"1162",
    "addr:postcode":"82838",
    "addr:street":"Pass Creek Rd Parkman Wy",
    "iso:country":"US",
    "sg:address":"1162 Pass Creek Rd",
    "sg:city":"Parkman",
    "sg:classifiers":[
        {
            "category":"Travel",
            "subcategory":"Campground",
            "type":"Entertainment"
        }
    ],
    "sg:phone":"+1 307 655 9760",
    "sg:postcode":"82838",
    "sg:province":"WY",
    "sg:tags":[
        "camp"
    ],
    "wof:name":"Bauen Camp Inc",
    "wof:placetype":"venue"
},
  "geometry": {"coordinates":[-107.55368,44.963265],"type":"Point"}
}