{
  "type": "Feature",
  "properties": {
    "iso:country":"US",
    "sg:address":"1919 E A St",
    "sg:city":"Torrington",
    "sg:classifiers":[
        {
            "category":"Manufacturing",
            "subcategory":"Chemicals & Compounds",
            "type":"Manufacturing & Wholesale Goods"
        }
    ],
    "sg:phone":"+1 307 532 2449",
    "sg:postcode":"82240",
    "sg:province":"WY",
    "sg:tags":[
        "industrial",
        "organic"
    ],
    "wof:name":"Wyoming Ethanol",
    "wof:placetype":"venue"
},
  "geometry": {"coordinates":[-104.182911,42.063853],"type":"Point"}
}