{
  "type": "Feature",
  "properties": {
    "iso:country":"US",
    "sg:address":"204 Elk St",
    "sg:city":"Rock Springs",
    "sg:classifiers":[
        {
            "category":"Recreation",
            "type":"Entertainment"
        }
    ],
    "sg:phone":"+1 307 382 8488",
    "sg:postcode":"82901",
    "sg:province":"WY",
    "sg:tags":[
        "astrologer"
    ],
    "wof:name":"Earth Impressions",
    "wof:placetype":"venue"
},
  "geometry": {"coordinates":[-109.223259,41.590079],"type":"Point"}
}