{
  "type": "Feature",
  "properties": {
    "addr:full":"2905 Reed Ave Cheyenne WY 82001",
    "addr:housenumber":"2905",
    "addr:postcode":"82001",
    "addr:street":"Reed Ave",
    "iso:country":"US",
    "sg:address":"2905 Reed Ave",
    "sg:city":"Cheyenne",
    "sg:classifiers":[
        {
            "category":"Shopping",
            "subcategory":"Computers & Home Electronics",
            "type":"Retail Goods"
        }
    ],
    "sg:phone":"+1 307 635 9155",
    "sg:postcode":"82001",
    "sg:province":"WY",
    "sg:tags":[
        "mobile",
        "radio"
    ],
    "wof:name":"Communications Systems Service",
    "wof:placetype":"venue"
},
  "geometry": {"coordinates":[-104.829967,41.142608],"type":"Point"}
}