{
  "type": "Feature",
  "properties": {
    "iso:country":"US",
    "sg:address":"117 Cole Shopping Center",
    "sg:city":"Cheyenne",
    "sg:classifiers":[
        {
            "category":"Shopping",
            "subcategory":"Shoes",
            "type":"Retail Goods"
        }
    ],
    "sg:phone":"+1 307 634 4012",
    "sg:postcode":"82001",
    "sg:province":"WY",
    "wof:name":"Dick's Bootery",
    "wof:placetype":"venue"
},
  "geometry": {"coordinates":[-104.788712,41.14455],"type":"Point"}
}