{
  "type": "Feature",
  "properties": {
    "iso:country":"US",
    "sg:address":"1807 Capitol Ave",
    "sg:city":"Cheyenne",
    "sg:classifiers":[
        {
            "category":"Professional",
            "subcategory":"Lawyer & Legal Services",
            "type":"Services"
        }
    ],
    "sg:phone":"+1 307 632 0536",
    "sg:postcode":"82001",
    "sg:province":"WY",
    "sg:tags":[
        "attorney"
    ],
    "wof:name":"Dennis M Grant",
    "wof:placetype":"venue"
},
  "geometry": {"coordinates":[-104.816923,41.135372],"type":"Point"}
}