{
  "type": "Feature",
  "properties": {
    "addr:full":"6907 W Yellowstone Hwy Casper WY 82604",
    "addr:housenumber":"6907",
    "addr:postcode":"82604",
    "addr:street":"W Yellowstone Hwy",
    "iso:country":"US",
    "sg:address":"6907 W Yellowstone Hwy",
    "sg:city":"Casper",
    "sg:classifiers":[
        {
            "category":"Wholesale",
            "subcategory":"Chemicals & Plastics",
            "type":"Manufacturing & Wholesale Goods"
        }
    ],
    "sg:phone":"+1 307 237 4921",
    "sg:postcode":"82604",
    "sg:province":"WY",
    "wof:name":"Baker Petrolite",
    "wof:placetype":"venue"
},
  "geometry": {"coordinates":[-106.426351,42.875363],"type":"Point"}
}