{
  "type": "Feature",
  "properties": {
    "iso:country":"US",
    "sg:address":"617 S 4th St",
    "sg:city":"Basin",
    "sg:classifiers":[
        {
            "category":"Shopping",
            "type":"Retail Goods"
        }
    ],
    "sg:phone":"+1 307 568 2838",
    "sg:postcode":"82410",
    "sg:province":"WY",
    "sg:tags":[
        "candle"
    ],
    "wof:name":"Dragonfire Candles & Crafts",
    "wof:placetype":"venue"
},
  "geometry": {"coordinates":[-108.03885099999999,44.376304],"type":"Point"}
}