{
  "type": "Feature",
  "properties": {
    "iso:country":"US",
    "sg:address":"58 N Lobban Ave",
    "sg:city":"Buffalo",
    "sg:classifiers":[
        {
            "category":"Manufacturing",
            "subcategory":"Printing",
            "type":"Manufacturing & Wholesale Goods"
        }
    ],
    "sg:phone":"+1 307 684 2223",
    "sg:postcode":"82834",
    "sg:province":"WY",
    "sg:tags":[
        "newspaper"
    ],
    "wof:name":"Buffalo Bulletin",
    "wof:placetype":"venue"
},
  "geometry": {"coordinates":[-106.69761099999999,44.34776],"type":"Point"}
}