{
  "type": "Feature",
  "properties": {
    "iso:country":"US",
    "sg:address":"778 Circle Dr",
    "sg:city":"Casper",
    "sg:classifiers":[
        {
            "category":"Mining & Drilling",
            "type":"Manufacturing & Wholesale Goods"
        }
    ],
    "sg:phone":"+1 307 237 3100",
    "sg:postcode":"82601",
    "sg:province":"WY",
    "sg:tags":[
        "field",
        "oil"
    ],
    "sg:website":"www.nationoil.com",
    "wof:name":"National-Oilwell Varco",
    "wof:placetype":"venue"
},
  "geometry": {"coordinates":[-106.340524,42.85673],"type":"Point"}
}