{
  "type": "Feature",
  "properties": {
    "iso:country":"US",
    "sg:address":"828 Kingsbury St",
    "sg:city":"Belle Fourche",
    "sg:classifiers":[
        {
            "category":"Social Services",
            "type":"Services"
        }
    ],
    "sg:phone":"+1 605 892 6285",
    "sg:postcode":"57717",
    "sg:province":"WY",
    "sg:tags":[
        "senior",
        "citizen"
    ],
    "wof:name":"Belle Fourche Senior Citizens",
    "wof:placetype":"venue"
},
  "geometry": {"coordinates":[-103.848765,44.66568],"type":"Point"}
}