{
  "type": "Feature",
  "properties": {
    "addr:full":"1211 S Douglas Hwy Gillette WY 82716",
    "addr:housenumber":"1211",
    "addr:postcode":"82716",
    "addr:street":"S Douglas Hwy",
    "iso:country":"US",
    "sg:address":"1211 S Douglas Hwy",
    "sg:city":"Gillette",
    "sg:classifiers":[
        {
            "category":"Social Services",
            "type":"Services"
        }
    ],
    "sg:phone":"+1 307 685 0450",
    "sg:postcode":"82716",
    "sg:province":"WY",
    "sg:tags":[
        "organization",
        "welfare"
    ],
    "wof:name":"Our Families Our Future",
    "wof:placetype":"venue"
},
  "geometry": {"coordinates":[-105.49402499999999,44.283804],"type":"Point"}
}