{
  "type": "Feature",
  "properties": {
    "addr:full":"71 Main St Superior WY 82945",
    "addr:housenumber":"71",
    "addr:postcode":"82945",
    "addr:street":"Main St",
    "iso:country":"US",
    "sg:address":"71 Main St",
    "sg:city":"Superior",
    "sg:classifiers":[
        {
            "category":"Bars & Pubs",
            "type":"Food & Drink"
        }
    ],
    "sg:phone":"+1 307 362 1398",
    "sg:postcode":"82945",
    "sg:province":"WY",
    "sg:tags":[
        "drinking"
    ],
    "wof:name":"Horse Thief Saloon",
    "wof:placetype":"venue"
},
  "geometry": {"coordinates":[-108.967735,41.76472],"type":"Point"}
}