{
  "type": "Feature",
  "properties": {
    "iso:country":"US",
    "sg:address":"1285 Sheridan Ave",
    "sg:city":"Cody",
    "sg:classifiers":[
        {
            "category":"Organizations",
            "subcategory":"Non-profit Organization",
            "type":"Services"
        }
    ],
    "sg:phone":"+1 307 527 6233",
    "sg:postcode":"82414",
    "sg:province":"WY",
    "wof:name":"Greater Yellowstone Coalition",
    "wof:placetype":"venue"
},
  "geometry": {"coordinates":[-109.062389,44.526116],"type":"Point"}
}