{
  "type": "Feature",
  "properties": {
    "iso:country":"US",
    "sg:address":"222 E 2nd St",
    "sg:city":"Powell",
    "sg:classifiers":[
        {
            "category":"Banks & Credit Unions",
            "subcategory":"Bank",
            "type":"Services"
        }
    ],
    "sg:phone":"+1 307 754 2774",
    "sg:postcode":"82435",
    "sg:province":"WY",
    "wof:name":"Bank Of Lovell",
    "wof:placetype":"venue"
},
  "geometry": {"coordinates":[-108.757267,44.754105],"type":"Point"}
}