{
  "type": "Feature",
  "properties": {
    "iso:country":"US",
    "sg:address":"1793 E Riding Club Rd",
    "sg:city":"Cheyenne",
    "sg:classifiers":[
        {
            "category":"Retail",
            "subcategory":"Auto Repair",
            "type":"Services"
        }
    ],
    "sg:phone":"+1 307 637 8388",
    "sg:postcode":"82009",
    "sg:province":"WY",
    "sg:tags":[
        "automotive"
    ],
    "wof:name":"Full Bore Inc",
    "wof:placetype":"venue"
},
  "geometry": {"coordinates":[-104.80501700000001,41.203689],"type":"Point"}
}