{
  "type": "Feature",
  "properties": {
    "iso:country":"US",
    "sg:address":"80 US Hwy 89",
    "sg:city":"Alpine",
    "sg:classifiers":[
        {
            "category":"Personal",
            "subcategory":"Beauty Salon",
            "type":"Services"
        }
    ],
    "sg:phone":"+1 307 654 4247",
    "sg:postcode":"83128",
    "sg:province":"WY",
    "wof:name":"Greys River Hair Studio",
    "wof:placetype":"venue"
},
  "geometry": {"coordinates":[-111.036513,43.155638],"type":"Point"}
}