{
  "type": "Feature",
  "properties": {
    "iso:country":"US",
    "sg:address":"2165 W Polk St",
    "sg:city":"Laramie",
    "sg:classifiers":[
        {
            "category":"Professional",
            "type":"Services"
        }
    ],
    "sg:phone":"+1 307 742 0605",
    "sg:postcode":"82070",
    "sg:province":"WY",
    "wof:name":"Family Monitoring Services LLC",
    "wof:placetype":"venue"
},
  "geometry": {"coordinates":[-105.625479,41.314813],"type":"Point"}
}