{
  "type": "Feature",
  "properties": {
    "iso:country":"US",
    "sg:address":"120 S 3rd St E",
    "sg:city":"Riverton",
    "sg:classifiers":[
        {
            "category":"Shopping",
            "subcategory":"Department Store",
            "type":"Retail Goods"
        }
    ],
    "sg:phone":"+1 307 856 2291",
    "sg:postcode":"82501",
    "sg:province":"WY",
    "wof:name":"J C Penney Co",
    "wof:placetype":"venue"
},
  "geometry": {"coordinates":[-108.387899,43.024417],"type":"Point"}
}