{
  "type": "Feature",
  "properties": {
    "iso:country":"US",
    "sg:address":"569 N 3rd St",
    "sg:city":"Laramie",
    "sg:classifiers":[
        {
            "category":"Food & Beverages",
            "subcategory":"Groceries & Convenience Stores",
            "type":"Retail Goods"
        }
    ],
    "sg:phone":"+1 307 742 2198",
    "sg:postcode":"82072",
    "sg:province":"WY",
    "wof:name":"Kum & Go Convenience Stores",
    "wof:placetype":"venue"
},
  "geometry": {"coordinates":[-105.592911,41.317597],"type":"Point"}
}