{
  "type": "Feature",
  "properties": {
    "iso:country":"US",
    "sg:address":"58 N Lobban Ave",
    "sg:city":"Buffalo",
    "sg:classifiers":[
        {
            "category":"Professional",
            "type":"Services"
        }
    ],
    "sg:phone":"+1 307 684 8790",
    "sg:postcode":"82834",
    "sg:province":"WY",
    "sg:tags":[
        "establishment"
    ],
    "wof:name":"Wercs Comm Tribcsr",
    "wof:placetype":"venue"
},
  "geometry": {"coordinates":[-106.69761099999999,44.34776],"type":"Point"}
}