{
  "type": "Feature",
  "properties": {
    "iso:country":"US",
    "sg:address":"910 Ponderosa Rd",
    "sg:city":"Cheyenne",
    "sg:classifiers":[
        {
            "category":"Manufacturing",
            "subcategory":"Retail Goods",
            "type":"Manufacturing & Wholesale Goods"
        }
    ],
    "sg:phone":"+1 307 635 5169",
    "sg:postcode":"82009",
    "sg:province":"WY",
    "sg:tags":[
        "product",
        "mfg"
    ],
    "wof:name":"Wysocki Brothers LLC",
    "wof:placetype":"venue"
},
  "geometry": {"coordinates":[-104.846947,41.181596],"type":"Point"}
}