{
  "type": "Feature",
  "properties": {
    "addr:full":"339 E 1st St Powell WY 82435",
    "addr:housenumber":"339",
    "addr:postcode":"82435",
    "addr:street":"E 1St St Powell Wy",
    "iso:country":"US",
    "sg:address":"339 E 1st St",
    "sg:city":"Powell",
    "sg:classifiers":[
        {
            "category":"Professional",
            "subcategory":"Accounting & Tax Preparation",
            "type":"Services"
        }
    ],
    "sg:phone":"+1 307 754 5126",
    "sg:postcode":"82435",
    "sg:province":"WY",
    "sg:tags":[
        "accountant"
    ],
    "wof:name":"Robirds & Assoc",
    "wof:placetype":"venue"
},
  "geometry": {"coordinates":[-108.755568,44.752906],"type":"Point"}
}