{
  "type": "Feature",
  "properties": {
    "iso:country":"US",
    "sg:address":"119 S Center St",
    "sg:city":"Casper",
    "sg:classifiers":[
        {
            "category":"Cinema",
            "subcategory":"Movie Theater",
            "type":"Entertainment"
        }
    ],
    "sg:phone":"+1 307 235 5440",
    "sg:postcode":"82601",
    "sg:province":"WY",
    "wof:name":"American Theatre",
    "wof:placetype":"venue"
},
  "geometry": {"coordinates":[-106.32508799999999,42.848971],"type":"Point"}
}