{
  "type": "Feature",
  "properties": {
    "addr:full":"1 Bear River Dr Evanston WY 82930",
    "addr:housenumber":"1",
    "addr:postcode":"82930",
    "addr:street":"Bear River Dr",
    "iso:country":"US",
    "sg:address":"1 Bear River Dr",
    "sg:city":"Evanston",
    "sg:phone":"+1 307 789 0562",
    "sg:postcode":"82930",
    "sg:province":"WY",
    "sg:tags":[
        "oil"
    ],
    "wof:name":"Kellerstrass Oil Co",
    "wof:placetype":"venue"
},
  "geometry": {"coordinates":[-110.96340499999999,41.26835],"type":"Point"}
}