{
  "type": "Feature",
  "properties": {
    "addr:full":"525 S 6th St Thermopolis WY 82443",
    "addr:housenumber":"525",
    "addr:postcode":"82443",
    "addr:street":"S 6Th St Thermopolis Wy",
    "iso:country":"US",
    "sg:address":"525 S 6th St",
    "sg:city":"Thermopolis",
    "sg:classifiers":[
        {
            "category":"Restaurant",
            "type":"Food & Drink"
        }
    ],
    "sg:menulink":"http://www.allmenus.com/wy/thermopolis-west/135382-subway/menu/",
    "sg:phone":"+1 307 864 9404",
    "sg:postcode":"82443",
    "sg:province":"WY",
    "sg:tags":[
        "american",
        "sandwich"
    ],
    "wof:name":"Subway",
    "wof:placetype":"venue"
},
  "geometry": {"coordinates":[-108.212081,43.641306],"type":"Point"}
}