{
  "type": "Feature",
  "properties": {
    "iso:country":"US",
    "sg:address":"1702 Robertson Ave",
    "sg:city":"Worland",
    "sg:classifiers":[
        {
            "category":"Social Services",
            "subcategory":"Job Training",
            "type":"Services"
        }
    ],
    "sg:phone":"+1 307 347 3396",
    "sg:postcode":"82401",
    "sg:province":"WY",
    "sg:tags":[
        "program",
        "administrative"
    ],
    "wof:name":"Employment Wyoming Department",
    "wof:placetype":"venue"
},
  "geometry": {"coordinates":[-107.945607,44.01785],"type":"Point"}
}