{
  "type": "Feature",
  "properties": {
    "addr:full":"2500 Cy Ave Casper WY 82604",
    "addr:postcode":"2500;82604",
    "addr:street":"Cy Ave",
    "iso:country":"US",
    "sg:address":"2500 Cy Ave",
    "sg:city":"Casper",
    "sg:classifiers":[
        {
            "category":"Recreation",
            "type":"Entertainment"
        }
    ],
    "sg:phone":"+1 307 234 4386",
    "sg:postcode":"82604",
    "sg:province":"WY",
    "wof:name":"Kids Works",
    "wof:placetype":"venue"
},
  "geometry": {"coordinates":[-106.347718,42.830617],"type":"Point"}
}