{
  "type": "Feature",
  "properties": {
    "iso:country":"US",
    "sg:address":"1442 W B St",
    "sg:city":"Torrington",
    "sg:classifiers":[
        {
            "category":"Building & Trades",
            "subcategory":"Construction",
            "type":"Services"
        }
    ],
    "sg:phone":"+1 307 532 2264",
    "sg:postcode":"82240",
    "sg:province":"WY",
    "sg:tags":[
        "roofing",
        "contractor"
    ],
    "wof:name":"Bob's Roofing & Repair",
    "wof:placetype":"venue"
},
  "geometry": {"coordinates":[-104.18715400000001,42.059534],"type":"Point"}
}