{
  "type": "Feature",
  "properties": {
    "iso:country":"US",
    "sg:address":"318 N 6th St",
    "sg:city":"Thermopolis",
    "sg:classifiers":[
        {
            "category":"Government",
            "subcategory":"Office",
            "type":"Public Place"
        }
    ],
    "sg:phone":"+1 307 864 3488",
    "sg:postcode":"82443",
    "sg:province":"WY",
    "sg:tags":[
        "conservation"
    ],
    "wof:name":"Natural Rsrces Cnservation Svc",
    "wof:placetype":"venue"
},
  "geometry": {"coordinates":[-108.21198200000001,43.648751],"type":"Point"}
}