{
  "type": "Feature",
  "properties": {
    "iso:country":"US",
    "sg:address":"400 Broadway St",
    "sg:city":"Sheridan",
    "sg:classifiers":[
        {
            "category":"Shopping",
            "subcategory":"Pharmacy",
            "type":"Retail Goods"
        }
    ],
    "sg:phone":"+1 307 672 2620",
    "sg:postcode":"82801",
    "sg:province":"WY",
    "sg:tags":[
        "shop",
        "gift",
        "package",
        "liquor",
        "drug",
        "cafe",
        "store"
    ],
    "wof:name":"Brown Drug",
    "wof:placetype":"venue"
},
  "geometry": {"coordinates":[-106.953369,44.80251],"type":"Point"}
}