{
  "type": "Feature",
  "properties": {
    "iso:country":"US",
    "sg:address":"130 Uinta Dr",
    "sg:city":"Green River",
    "sg:classifiers":[
        {
            "category":"Restaurant",
            "type":"Food & Drink"
        }
    ],
    "sg:phone":"+1 307 875 7007",
    "sg:postcode":"82935",
    "sg:province":"WY",
    "wof:name":"Mama's Pizza",
    "wof:placetype":"venue"
},
  "geometry": {"coordinates":[-109.466903,41.518756],"type":"Point"}
}