{
  "type": "Feature",
  "properties": {
    "iso:country":"US",
    "sg:address":"510 5th Ave",
    "sg:city":"Belle Fourche",
    "sg:classifiers":[
        {
            "category":"Food & Beverages",
            "subcategory":"Groceries & Convenience Stores",
            "type":"Retail Goods"
        }
    ],
    "sg:phone":"+1 605 892 4564",
    "sg:postcode":"57717",
    "sg:province":"WY",
    "sg:tags":[
        "gasoline",
        "variety"
    ],
    "wof:name":"Mason's 5th Ave",
    "wof:placetype":"venue"
},
  "geometry": {"coordinates":[-103.85363599999999,44.673415],"type":"Point"}
}