{
  "type": "Feature",
  "properties": {
    "addr:full":"1501 E 2nd St Casper WY 82601",
    "addr:housenumber":"1501",
    "addr:postcode":"82601",
    "addr:street":"E 2Nd St",
    "iso:country":"US",
    "sg:address":"1501 E 2nd St",
    "sg:city":"Casper",
    "sg:classifiers":[
        {
            "category":"Restaurant",
            "type":"Food & Drink"
        }
    ],
    "sg:menulink":"http://www.allmenus.com/wy/casper/81184-papa-johns-pizza/menu/",
    "sg:phone":"+1 307 234 2121",
    "sg:postcode":"82601",
    "sg:province":"WY",
    "sg:tags":[
        "american",
        "pizza"
    ],
    "wof:name":"Papa John's Pizza",
    "wof:placetype":"venue"
},
  "geometry": {"coordinates":[-106.30531999999999,42.848717],"type":"Point"}
}