{
  "type": "Feature",
  "properties": {
    "iso:country":"US",
    "sg:address":"5547 Co Rd 222",
    "sg:city":"Pine Bluffs",
    "sg:classifiers":[
        {
            "category":"Farming",
            "subcategory":"Livestock Farm",
            "type":"Manufacturing & Wholesale Goods"
        }
    ],
    "sg:phone":"+1 307 245 3350",
    "sg:postcode":"82082",
    "sg:province":"WY",
    "sg:tags":[
        "beef",
        "feedlot",
        "cattle"
    ],
    "wof:name":"Justin Miller",
    "wof:placetype":"venue"
},
  "geometry": {"coordinates":[-104.249132,41.316841],"type":"Point"}
}