{
  "type": "Feature",
  "properties": {
    "iso:country":"US",
    "sg:address":"103 Hillside Dr",
    "sg:city":"Evanston",
    "sg:classifiers":[
        {
            "category":"Freight",
            "type":"Transportation"
        }
    ],
    "sg:phone":"+1 307 789 1164",
    "sg:postcode":"82930",
    "sg:province":"WY",
    "sg:tags":[
        "field",
        "oil",
        "hauling"
    ],
    "wof:name":"Mountain States Water Svc",
    "wof:placetype":"venue"
},
  "geometry": {"coordinates":[-110.950957,41.282288],"type":"Point"}
}