{
  "type": "Feature",
  "properties": {
    "iso:country":"US",
    "sg:address":"2401 Daley St",
    "sg:city":"Rawlins",
    "sg:classifiers":[
        {
            "category":"Wholesale",
            "subcategory":"Petroleum",
            "type":"Manufacturing & Wholesale Goods"
        }
    ],
    "sg:phone":"+1 307 324 6631",
    "sg:postcode":"82301",
    "sg:province":"WY",
    "sg:tags":[
        "pipe",
        "line",
        "company"
    ],
    "wof:name":"Rocky Mountain Pipeline Syst",
    "wof:placetype":"venue"
},
  "geometry": {"coordinates":[-107.210239,41.796252],"type":"Point"}
}