{
  "type": "Feature",
  "properties": {
    "iso:country":"US",
    "sg:address":"80 E Flaming Gorge Way",
    "sg:city":"Green River",
    "sg:classifiers":[
        {
            "category":"Government",
            "subcategory":"Office",
            "type":"Public Place"
        }
    ],
    "sg:phone":"+1 307 872 6485",
    "sg:postcode":"82935",
    "sg:province":"WY",
    "sg:tags":[
        "general"
    ],
    "wof:name":"Engineering Office",
    "wof:placetype":"venue"
},
  "geometry": {"coordinates":[-109.466618,41.528572],"type":"Point"}
}