{
  "type": "Feature",
  "properties": {
    "iso:country":"US",
    "sg:address":"1953 US Hwy 310",
    "sg:city":"Lovell",
    "sg:classifiers":[
        {
            "category":"Building & Trades",
            "subcategory":"Cleaning & Sanitation",
            "type":"Services"
        }
    ],
    "sg:phone":"+1 307 548 7463",
    "sg:postcode":"82431",
    "sg:province":"WY",
    "sg:tags":[
        "janitor"
    ],
    "wof:name":"A G Shop",
    "wof:placetype":"venue"
},
  "geometry": {"coordinates":[-108.41882200000001,44.837334],"type":"Point"}
}