{
  "type": "Feature",
  "properties": {
    "iso:country":"US",
    "sg:address":"738 Big Horn Ave",
    "sg:city":"Worland",
    "sg:classifiers":[
        {
            "category":"Shopping",
            "subcategory":"Florist",
            "type":"Retail Goods"
        }
    ],
    "sg:phone":"+1 307 347 2225",
    "sg:postcode":"82401",
    "sg:province":"WY",
    "sg:tags":[
        "floral",
        "book",
        "gift"
    ],
    "wof:name":"Petals & Pages",
    "wof:placetype":"venue"
},
  "geometry": {"coordinates":[-107.959467,44.016746],"type":"Point"}
}