{
  "type": "Feature",
  "properties": {
    "iso:country":"US",
    "sg:address":"1924 Rustic Dr",
    "sg:city":"Casper",
    "sg:classifiers":[
        {
            "category":"Farming",
            "subcategory":"Livestock Farm",
            "type":"Manufacturing & Wholesale Goods"
        }
    ],
    "sg:phone":"+1 307 234 8558",
    "sg:postcode":"82609",
    "sg:province":"WY",
    "sg:tags":[
        "beef",
        "feedlot",
        "cattle"
    ],
    "wof:name":"Richard Lisco",
    "wof:placetype":"venue"
},
  "geometry": {"coordinates":[-106.28296,42.831399],"type":"Point"}
}