{
  "type": "Feature",
  "properties": {
    "addr:full":"1104 Wilson Dr Worland WY 82401",
    "addr:housenumber":"1104",
    "addr:postcode":"82401",
    "addr:street":"Wilson Dr",
    "iso:country":"US",
    "sg:address":"1104 Wilson Dr",
    "sg:city":"Worland",
    "sg:classifiers":[
        {
            "category":"Retail",
            "subcategory":"Portrait Studio",
            "type":"Services"
        }
    ],
    "sg:phone":"+1 307 347 6304",
    "sg:postcode":"82401",
    "sg:province":"WY",
    "sg:tags":[
        "photo"
    ],
    "sg:website":"www.huberphoto.com",
    "wof:name":"David Huber Photography",
    "wof:placetype":"venue"
},
  "geometry": {"coordinates":[-107.94098,44.001789],"type":"Point"}
}