{
  "type": "Feature",
  "properties": {
    "addr:full":"2335 Kerzell Ln Casper WY 82601",
    "addr:housenumber":"2335",
    "addr:postcode":"82601",
    "addr:street":"Kerzell Ln",
    "iso:country":"US",
    "sg:address":"2335 Kerzell Ln",
    "sg:city":"Casper",
    "sg:classifiers":[
        {
            "category":"Professional",
            "type":"Services"
        }
    ],
    "sg:phone":"+1 307 577 5775",
    "sg:postcode":"82601",
    "sg:province":"WY",
    "sg:tags":[
        "consulting",
        "chemist"
    ],
    "wof:name":"Colorado Biotechnology Assoc",
    "wof:placetype":"venue"
},
  "geometry": {"coordinates":[-106.350167,42.881347],"type":"Point"}
}