{
  "type": "Feature",
  "properties": {
    "iso:country":"US",
    "sg:address":"1312 Sigma Dr",
    "sg:city":"Rawlins",
    "sg:classifiers":[
        {
            "category":"Building & Trades",
            "subcategory":"Construction",
            "type":"Services"
        }
    ],
    "sg:phone":"+1 307 324 8485",
    "sg:postcode":"82301",
    "sg:province":"WY",
    "sg:tags":[
        "house"
    ],
    "wof:name":"Lu Morse Construction",
    "wof:placetype":"venue"
},
  "geometry": {"coordinates":[-107.22643600000001,41.799349],"type":"Point"}
}