{
  "type": "Feature",
  "properties": {
    "addr:full":"720 Winfield St Newcastle WY 82701",
    "addr:housenumber":"720",
    "addr:postcode":"82701",
    "addr:street":"Winfield St Newcastle Wy",
    "iso:country":"US",
    "sg:address":"720 Winfield St",
    "sg:city":"Newcastle",
    "sg:classifiers":[
        {
            "category":"Retail",
            "subcategory":"Auto Repair",
            "type":"Services"
        }
    ],
    "sg:phone":"+1 307 746 9338",
    "sg:postcode":"82701",
    "sg:province":"WY",
    "sg:tags":[
        "repairing",
        "automobile",
        "automotive"
    ],
    "wof:name":"Rich's Automotive",
    "wof:placetype":"venue"
},
  "geometry": {"coordinates":[-104.197587,43.848124],"type":"Point"}
}