{
  "type": "Feature",
  "properties": {
    "iso:country":"US",
    "sg:address":"907 N Poplar St",
    "sg:city":"Casper",
    "sg:classifiers":[
        {
            "category":"Professional",
            "subcategory":"Employment Agencies",
            "type":"Services"
        }
    ],
    "sg:phone":"+1 307 237 2523",
    "sg:postcode":"82601",
    "sg:province":"WY",
    "sg:tags":[
        "help",
        "contractor"
    ],
    "wof:name":"Manpower Inc",
    "wof:placetype":"venue"
},
  "geometry": {"coordinates":[-106.33258499999999,42.860373],"type":"Point"}
}