{
  "type": "Feature",
  "properties": {
    "addr:full":"825 W Fir St Glenrock WY 82637",
    "addr:housenumber":"825",
    "addr:postcode":"82637",
    "addr:street":"W Fir St Glenrock Wy",
    "iso:country":"US",
    "sg:address":"825 W Fir St",
    "sg:city":"Glenrock",
    "sg:classifiers":[
        {
            "category":"Personal",
            "type":"Services"
        }
    ],
    "sg:phone":"+1 307 436 9266",
    "sg:postcode":"82637",
    "sg:province":"WY",
    "sg:tags":[
        "consultant",
        "program",
        "health",
        "fitness"
    ],
    "wof:name":"Abundant Health Ctr",
    "wof:placetype":"venue"
},
  "geometry": {"coordinates":[-105.875421,42.856887],"type":"Point"}
}