{
  "type": "Feature",
  "properties": {
    "addr:full":"108 Tweed Ln Lander WY 82520",
    "addr:housenumber":"108",
    "addr:postcode":"wy 82520",
    "addr:street":"Tweed Ln",
    "iso:country":"US",
    "sg:address":"108 Tweed Ln",
    "sg:city":"Lander",
    "sg:classifiers":[
        {
            "category":"Retail",
            "subcategory":"Veterinary Services",
            "type":"Services"
        }
    ],
    "sg:phone":"+1 307 332 5512",
    "sg:postcode":"82520",
    "sg:province":"WY",
    "sg:tags":[
        "veterinarian"
    ],
    "wof:name":"Wind River Veterinary Services",
    "wof:placetype":"venue"
},
  "geometry": {"coordinates":[-108.74485300000001,42.847626],"type":"Point"}
}