{
  "type": "Feature",
  "properties": {
    "addr:full":"1915 E Murray St Rawlins WY 82301",
    "addr:housenumber":"1915",
    "addr:postcode":"82301",
    "addr:street":"E Murray St",
    "iso:country":"US",
    "sg:address":"1915 E Murray St",
    "sg:city":"Rawlins",
    "sg:classifiers":[
        {
            "category":"Restaurant",
            "type":"Food & Drink"
        }
    ],
    "sg:phone":"+1 307 324 3636",
    "sg:postcode":"82301",
    "sg:province":"WY",
    "wof:name":"China House",
    "wof:placetype":"venue"
},
  "geometry": {"coordinates":[-107.21622499999999,41.798825],"type":"Point"}
}