{
  "type": "Feature",
  "properties": {
    "iso:country":"US",
    "sg:address":"114 Washington St",
    "sg:city":"Pinedale",
    "sg:classifiers":[
        {
            "category":"Retail",
            "subcategory":"Repair Shop",
            "type":"Services"
        }
    ],
    "sg:phone":"+1 307 367 2452",
    "sg:postcode":"82941",
    "sg:province":"WY",
    "sg:tags":[
        "taxidermist"
    ],
    "wof:name":"Faler Brothers' Taxidermy",
    "wof:placetype":"venue"
},
  "geometry": {"coordinates":[-109.859657,42.863855],"type":"Point"}
}