{
  "type": "Feature",
  "properties": {
    "iso:country":"US",
    "sg:address":"2629 E 2nd St",
    "sg:city":"Casper",
    "sg:classifiers":[
        {
            "category":"Building & Trades",
            "subcategory":"Equipment Rental",
            "type":"Services"
        }
    ],
    "sg:phone":"+1 307 265 6721",
    "sg:postcode":"82609",
    "sg:province":"WY",
    "wof:name":"Appliance & Furniture Rentall",
    "wof:placetype":"venue"
},
  "geometry": {"coordinates":[-106.29289,42.84878],"type":"Point"}
}