{
  "type": "Feature",
  "properties": {
    "iso:country":"US",
    "sg:address":"74 US Hwy 16",
    "sg:city":"Buffalo",
    "sg:classifiers":[
        {
            "category":"Food & Beverages",
            "subcategory":"Groceries & Convenience Stores",
            "type":"Retail Goods"
        }
    ],
    "sg:phone":"+1 307 684 7786",
    "sg:postcode":"82834",
    "sg:province":"WY",
    "wof:name":"Short Stop",
    "wof:placetype":"venue"
},
  "geometry": {"coordinates":[-106.698115,44.354293],"type":"Point"}
}