{
  "type": "Feature",
  "properties": {
    "addr:full":"11234 Coonrod Rd Cheyenne WY 82009",
    "addr:postcode":"11234;82009",
    "addr:street":"Coonrod Rd",
    "iso:country":"US",
    "sg:address":"11234 Coonrod Rd",
    "sg:city":"Cheyenne",
    "sg:classifiers":[
        {
            "category":"Building & Trades",
            "subcategory":"Construction",
            "type":"Services"
        }
    ],
    "sg:phone":"+1 307 638 0707",
    "sg:postcode":"82009",
    "sg:province":"WY",
    "sg:tags":[
        "general",
        "contractor"
    ],
    "wof:name":"Johnson Construction",
    "wof:placetype":"venue"
},
  "geometry": {"coordinates":[-104.824398,41.223654],"type":"Point"}
}