{
  "type": "Feature",
  "properties": {
    "iso:country":"US",
    "sg:address":"9614 State Hwy 410",
    "sg:city":"Mountain View",
    "sg:classifiers":[
        {
            "category":"Museum",
            "type":"Entertainment"
        }
    ],
    "sg:phone":"+1 307 782 7512",
    "sg:postcode":"82939",
    "sg:province":"WY",
    "sg:tags":[
        "society",
        "historic"
    ],
    "wof:name":"Fort Bridger Rendezvous Assn",
    "wof:placetype":"venue"
},
  "geometry": {"coordinates":[-110.336293,41.311002],"type":"Point"}
}