{
  "type": "Feature",
  "properties": {
    "addr:full":"2741 Main St Torrington WY 82240",
    "addr:housenumber":"2741",
    "addr:postcode":"82240",
    "addr:street":"Main St",
    "iso:country":"US",
    "sg:address":"2741 Main St",
    "sg:city":"Torrington",
    "sg:classifiers":[
        {
            "category":"Organizations",
            "subcategory":"Religious Organization",
            "type":"Services"
        }
    ],
    "sg:phone":"+1 307 532 2824",
    "sg:postcode":"82240",
    "sg:province":"WY",
    "wof:name":"Church of Nazarene",
    "wof:placetype":"venue"
},
  "geometry": {"coordinates":[-104.18432900000001,42.071122],"type":"Point"}
}