{
  "type": "Feature",
  "properties": {
    "iso:country":"US",
    "sg:address":"301 Thelma Dr",
    "sg:city":"Casper",
    "sg:classifiers":[
        {
            "category":"Utilities",
            "subcategory":"Telephone",
            "type":"Services"
        }
    ],
    "sg:phone":"+1 307 473 2323",
    "sg:postcode":"82609",
    "sg:province":"WY",
    "sg:tags":[
        "internet",
        "provider"
    ],
    "wof:name":"W Y O Beamcom",
    "wof:placetype":"venue"
},
  "geometry": {"coordinates":[-106.274101,42.84781],"type":"Point"}
}