{
  "type": "Feature",
  "properties": {
    "addr:full":"2000 E 1st St Casper WY 82609",
    "addr:housenumber":"2000",
    "addr:postcode":"82609",
    "addr:street":"E 1St St",
    "iso:country":"US",
    "sg:address":"2000 E 1st St",
    "sg:city":"Casper",
    "sg:classifiers":[
        {
            "category":"Real Estate",
            "subcategory":"Developer",
            "type":"Services"
        }
    ],
    "sg:phone":"+1 307 237 7128",
    "sg:postcode":"82609",
    "sg:province":"WY",
    "sg:tags":[
        "mobile",
        "home"
    ],
    "wof:name":"A & First St Mobile Home Court",
    "wof:placetype":"venue"
},
  "geometry": {"coordinates":[-106.29761000000001,42.85001],"type":"Point"}
}