{
  "type": "Feature",
  "properties": {
    "iso:country":"US",
    "sg:address":"851 Werner Ct",
    "sg:city":"Casper",
    "sg:classifiers":[
        {
            "category":"Professional",
            "subcategory":"Secretarial Services",
            "type":"Services"
        }
    ],
    "sg:phone":"+1 307 235 9009",
    "sg:postcode":"82601",
    "sg:province":"WY",
    "sg:tags":[
        "reporting",
        "business"
    ],
    "wof:name":"Choice Secretarial Services",
    "wof:placetype":"venue"
},
  "geometry": {"coordinates":[-106.33316499999999,42.859689],"type":"Point"}
}