{
  "type": "Feature",
  "properties": {
    "addr:full":"625 S Millward St Jackson WY 83001",
    "addr:housenumber":"625",
    "addr:postcode":"83001",
    "addr:street":"S Millward St Jackson Wy",
    "iso:country":"US",
    "sg:address":"625 S Millward St",
    "sg:city":"Jackson",
    "sg:classifiers":[
        {
            "category":"Professional",
            "subcategory":"Art Services",
            "type":"Services"
        }
    ],
    "sg:phone":"+1 307 739 2281",
    "sg:postcode":"83001",
    "sg:province":"WY",
    "sg:tags":[
        "photographer"
    ],
    "wof:name":"Garth Dowling Photography",
    "wof:placetype":"venue"
},
  "geometry": {"coordinates":[-110.765192,43.473045],"type":"Point"}
}