{
  "type": "Feature",
  "properties": {
    "iso:country":"US",
    "sg:address":"431 Washington St",
    "sg:city":"Afton",
    "sg:classifiers":[
        {
            "category":"Shopping",
            "subcategory":"Clothing, Apparel, & Fashions",
            "type":"Retail Goods"
        }
    ],
    "sg:phone":"+1 307 885 5622",
    "sg:postcode":"83110",
    "sg:province":"WY",
    "wof:name":"Swift Creek Trading Co",
    "wof:placetype":"venue"
},
  "geometry": {"coordinates":[-110.933437,42.724684],"type":"Point"}
}