{
  "type": "Feature",
  "properties": {
    "addr:full":"3186 State Hwy 450 Newcastle WY 82701",
    "addr:housenumber":"3186",
    "addr:postcode":"82701",
    "addr:street":"State Hwy 450 Newcastle Wy",
    "iso:country":"US",
    "sg:address":"3186 State Hwy 450",
    "sg:city":"Newcastle",
    "sg:classifiers":[
        {
            "category":"Farming",
            "subcategory":"Livestock Farm",
            "type":"Manufacturing & Wholesale Goods"
        }
    ],
    "sg:phone":"+1 307 746 2074",
    "sg:postcode":"82701",
    "sg:province":"WY",
    "sg:tags":[
        "beef",
        "feedlot",
        "cattle"
    ],
    "wof:name":"Bryan Stroh Inc",
    "wof:placetype":"venue"
},
  "geometry": {"coordinates":[-104.84402,43.691967],"type":"Point"}
}