{
  "type": "Feature",
  "properties": {
    "addr:full":"550 N Custer St Sheridan WY 82801",
    "addr:housenumber":"550",
    "addr:postcode":"82801",
    "addr:street":"N Custer St",
    "iso:country":"US",
    "sg:address":"550 N Custer St",
    "sg:city":"Sheridan",
    "sg:classifiers":[
        {
            "category":"Manufacturing",
            "subcategory":"Lumber",
            "type":"Manufacturing & Wholesale Goods"
        }
    ],
    "sg:phone":"+1 307 673 1535",
    "sg:postcode":"82801",
    "sg:province":"WY",
    "sg:tags":[
        "logging"
    ],
    "wof:name":"TNT Logging Inc",
    "wof:placetype":"venue"
},
  "geometry": {"coordinates":[-106.950299,44.803235],"type":"Point"}
}