{
  "type": "Feature",
  "properties": {
    "iso:country":"US",
    "sg:address":"180 W Hansen Ave",
    "sg:city":"Jackson",
    "sg:classifiers":[
        {
            "category":"Professional",
            "type":"Services"
        }
    ],
    "sg:phone":"+1 307 734 7674",
    "sg:postcode":"83001",
    "sg:province":"WY",
    "sg:tags":[
        "establishment"
    ],
    "wof:name":"Jeff Hogan Productions",
    "wof:placetype":"venue"
},
  "geometry": {"coordinates":[-110.764298,43.476357],"type":"Point"}
}