{
  "type": "Feature",
  "properties": {
    "addr:full":"33 N Pineview Dr Gillette WY 82716",
    "addr:housenumber":"33",
    "addr:postcode":"82716",
    "addr:street":"N Pineview Dr",
    "iso:country":"US",
    "sg:address":"33 N Pineview Dr",
    "sg:city":"Gillette",
    "sg:classifiers":[
        {
            "category":"Professional",
            "subcategory":"Computer Services",
            "type":"Services"
        }
    ],
    "sg:phone":"+1 307 685 2440",
    "sg:postcode":"82716",
    "sg:province":"WY",
    "sg:tags":[
        "development",
        "software"
    ],
    "wof:name":"Telemetry Control Systems LLC",
    "wof:placetype":"venue"
},
  "geometry": {"coordinates":[-105.58707,44.46139],"type":"Point"}
}