{
  "type": "Feature",
  "properties": {
    "addr:full":"48 E 5th St Sheridan WY 82801",
    "addr:housenumber":"48",
    "addr:postcode":"82801",
    "addr:street":"E 5Th St",
    "iso:country":"US",
    "sg:address":"48 E 5th St",
    "sg:city":"Sheridan",
    "sg:classifiers":[
        {
            "category":"Building & Trades",
            "subcategory":"Plumbing",
            "type":"Services"
        }
    ],
    "sg:phone":"+1 307 674 7061",
    "sg:postcode":"82801",
    "sg:province":"WY",
    "sg:tags":[
        "plumbing",
        "heating",
        "contractor"
    ],
    "wof:name":"Roush Plumbing & Heating Inc",
    "wof:placetype":"venue"
},
  "geometry": {"coordinates":[-106.955144,44.806766],"type":"Point"}
}