{
  "type": "Feature",
  "properties": {
    "addr:full":"1035 Jackson St Rock Springs WY 82901",
    "addr:housenumber":"1035",
    "addr:postcode":"82901",
    "addr:street":"Jackson St Rock Springs Wy",
    "iso:country":"US",
    "sg:address":"1035 Jackson St",
    "sg:city":"Rock Springs",
    "sg:classifiers":[
        {
            "category":"Social Services",
            "subcategory":"Child Care",
            "type":"Services"
        }
    ],
    "sg:phone":"+1 307 352 6639",
    "sg:postcode":"82901",
    "sg:province":"WY",
    "wof:name":"YWCA",
    "wof:placetype":"venue"
},
  "geometry": {"coordinates":[-109.250811,41.588726],"type":"Point"}
}