{
  "type": "Feature",
  "properties": {
    "iso:country":"US",
    "sg:address":"701 Dallas Rd",
    "sg:city":"Cheyenne",
    "sg:classifiers":[
        {
            "category":"Real Estate",
            "subcategory":"Real Estate Agent",
            "type":"Services"
        }
    ],
    "sg:phone":"+1 307 637 5509",
    "sg:postcode":"82007",
    "sg:province":"WY",
    "sg:tags":[
        "inspection"
    ],
    "wof:name":"Top Shelf Enterprises LLC",
    "wof:placetype":"venue"
},
  "geometry": {"coordinates":[-104.807312,41.081041],"type":"Point"}
}