{
  "type": "Feature",
  "properties": {
    "addr:full":"160 S Cache Dr Jackson WY 83001",
    "addr:housenumber":"160",
    "addr:postcode":"83001",
    "addr:street":"S Cache Dr Jackson Wy",
    "iso:country":"US",
    "sg:address":"160 S Cache Dr",
    "sg:city":"Jackson",
    "sg:classifiers":[
        {
            "category":"Education",
            "subcategory":"College",
            "type":"Public Place"
        }
    ],
    "sg:phone":"+1 307 733 7425",
    "sg:postcode":"83001",
    "sg:province":"WY",
    "sg:tags":[
        "academic",
        "school"
    ],
    "wof:name":"Community Education Svc",
    "wof:placetype":"venue"
},
  "geometry": {"coordinates":[-110.76229600000001,43.477855],"type":"Point"}
}