{
  "type": "Feature",
  "properties": {
    "iso:country":"US",
    "sg:address":"1122 12th St",
    "sg:city":"Cody",
    "sg:classifiers":[
        {
            "category":"Organizations",
            "subcategory":"Professional Association",
            "type":"Services"
        }
    ],
    "sg:phone":"+1 307 587 2339",
    "sg:postcode":"82414",
    "sg:province":"WY",
    "sg:website":"www.duderanch.org",
    "wof:name":"Dude Ranchers Assn",
    "wof:placetype":"venue"
},
  "geometry": {"coordinates":[-109.063929,44.52579],"type":"Point"}
}