{
  "type": "Feature",
  "properties": {
    "iso:country":"US",
    "sg:address":"212 Freimuth Ave",
    "sg:city":"Lingle",
    "sg:classifiers":[
        {
            "category":"Wholesale",
            "subcategory":"Machinery & Supplies",
            "type":"Manufacturing & Wholesale Goods"
        }
    ],
    "sg:phone":"+1 307 837 2368",
    "sg:postcode":"82223",
    "sg:province":"WY",
    "sg:tags":[
        "equipment",
        "irrigation",
        "system"
    ],
    "wof:name":"Lanphier Inc",
    "wof:placetype":"venue"
},
  "geometry": {"coordinates":[-104.347555,42.135874],"type":"Point"}
}