{
  "type": "Feature",
  "properties": {
    "iso:country":"US",
    "sg:address":"24 Granite Ln",
    "sg:city":"Pinedale",
    "sg:classifiers":[
        {
            "category":"Building & Trades",
            "subcategory":"Construction",
            "type":"Services"
        }
    ],
    "sg:phone":"+1 307 367 2699",
    "sg:postcode":"82941",
    "sg:province":"WY",
    "sg:tags":[
        "contractor"
    ],
    "wof:name":"Green Frontier",
    "wof:placetype":"venue"
},
  "geometry": {"coordinates":[-109.86525,42.852019],"type":"Point"}
}