{
  "type": "Feature",
  "properties": {
    "iso:country":"US",
    "sg:address":"831 Outlook Ct",
    "sg:city":"Cody",
    "sg:classifiers":[
        {
            "category":"Social Services",
            "subcategory":"Child Care",
            "type":"Services"
        }
    ],
    "sg:phone":"+1 307 587 1284",
    "sg:postcode":"82414",
    "sg:province":"WY",
    "wof:name":"A Step Ahead Daycare",
    "wof:placetype":"venue"
},
  "geometry": {"coordinates":[-109.036491,44.52922],"type":"Point"}
}