{
  "type": "Feature",
  "properties": {
    "iso:country":"US",
    "sg:address":"565 E Simpson Ave",
    "sg:city":"Jackson",
    "sg:classifiers":[
        {
            "category":"Professional",
            "subcategory":"Management & Consulting",
            "type":"Services"
        }
    ],
    "sg:phone":"+1 307 733 6639",
    "sg:postcode":"83001",
    "sg:province":"WY",
    "sg:tags":[
        "selling",
        "establishment",
        "direct"
    ],
    "wof:name":"Shaklee Distributor",
    "wof:placetype":"venue"
},
  "geometry": {"coordinates":[-110.75090899999999,43.477445],"type":"Point"}
}