{
  "type": "Feature",
  "properties": {
    "iso:country":"US",
    "sg:address":"1731 Commercial Ave",
    "sg:city":"Sheridan",
    "sg:classifiers":[
        {
            "category":"Retail",
            "subcategory":"Auto Repair",
            "type":"Services"
        }
    ],
    "sg:phone":"+1 307 672 3420",
    "sg:postcode":"82801",
    "sg:province":"WY",
    "sg:tags":[
        "shop",
        "automobile",
        "machine",
        "automotive",
        "general"
    ],
    "wof:name":"Top End Auto Machine T E A M",
    "wof:placetype":"venue"
},
  "geometry": {"coordinates":[-106.933829,44.779189],"type":"Point"}
}