{
  "type": "Feature",
  "properties": {
    "addr:full":"309 E Flint St Laramie WY 82072",
    "addr:housenumber":"309",
    "addr:postcode":"82072",
    "addr:street":"E Flint St",
    "iso:country":"US",
    "sg:address":"309 E Flint St",
    "sg:city":"Laramie",
    "sg:classifiers":[
        {
            "category":"Restaurant",
            "type":"Food & Drink"
        }
    ],
    "sg:menulink":"http://www.allmenus.com/wy/laramie/78194-dominos-pizza/menu/",
    "sg:phone":"+1 307 742 0030",
    "sg:postcode":"82072",
    "sg:province":"WY",
    "sg:tags":[
        "american",
        "wing",
        "pizza"
    ],
    "wof:name":"Domino's Pizza",
    "wof:placetype":"venue"
},
  "geometry": {"coordinates":[-105.592766,41.317629],"type":"Point"}
}