{
  "type": "Feature",
  "properties": {
    "iso:country":"US",
    "sg:address":"627 Willow Ridge",
    "sg:city":"Riverton",
    "sg:classifiers":[
        {
            "category":"Professional",
            "subcategory":"Advertising",
            "type":"Services"
        }
    ],
    "sg:phone":"+1 307 857 0929",
    "sg:postcode":"82501",
    "sg:province":"WY",
    "sg:tags":[
        "distribution"
    ],
    "wof:name":"Walton Distributing",
    "wof:placetype":"venue"
},
  "geometry": {"coordinates":[-108.414401,43.03092],"type":"Point"}
}