{
  "type": "Feature",
  "properties": {
    "iso:country":"US",
    "sg:address":"912 W 2nd St",
    "sg:city":"Gillette",
    "sg:classifiers":[
        {
            "category":"Museum",
            "type":"Entertainment"
        }
    ],
    "sg:phone":"+1 307 682 5723",
    "sg:postcode":"82716",
    "sg:province":"WY",
    "wof:name":"Campbell Cnty Rockpile Museum",
    "wof:placetype":"venue"
},
  "geometry": {"coordinates":[-105.516318,44.293174],"type":"Point"}
}