{
  "type": "Feature",
  "properties": {
    "addr:full":"1618 E Park Ave Riverton WY 82501",
    "addr:housenumber":"1618",
    "addr:postcode":"82501",
    "addr:street":"E Park Ave",
    "iso:country":"US",
    "sg:address":"1618 E Park Ave",
    "sg:city":"Riverton",
    "sg:classifiers":[
        {
            "category":"Travel",
            "subcategory":"Campground",
            "type":"Entertainment"
        }
    ],
    "sg:phone":"+1 307 857 3000",
    "sg:postcode":"82501",
    "sg:province":"WY",
    "sg:tags":[
        "recreational",
        "parks",
        "vehicle"
    ],
    "wof:name":"Wind River Good Sam RV Park",
    "wof:placetype":"venue"
},
  "geometry": {"coordinates":[-108.371302,43.02686],"type":"Point"}
}