{
  "type": "Feature",
  "properties": {
    "iso:country":"US",
    "sg:address":"1728 5th Ave",
    "sg:city":"Belle Fourche",
    "sg:classifiers":[
        {
            "category":"Home & Garden",
            "subcategory":"Garden Supply",
            "type":"Retail Goods"
        }
    ],
    "sg:phone":"+1 605 892 2846",
    "sg:postcode":"57717",
    "sg:province":"WY",
    "sg:tags":[
        "nursery"
    ],
    "wof:name":"Homestead Nursery",
    "wof:placetype":"venue"
},
  "geometry": {"coordinates":[-103.85521900000001,44.66019],"type":"Point"}
}