{
  "type": "Feature",
  "properties": {
    "iso:country":"US",
    "sg:address":"4250 E Hoback River Rd",
    "sg:city":"Jackson",
    "sg:classifiers":[
        {
            "category":"Travel",
            "subcategory":"Hotels & Motels",
            "type":"Entertainment"
        }
    ],
    "sg:phone":"+1 307 733 1168",
    "sg:postcode":"83001",
    "sg:province":"WY",
    "sg:tags":[
        "operation"
    ],
    "wof:name":"Twin Mountain River Ranch Inc",
    "wof:placetype":"venue"
},
  "geometry": {"coordinates":[-110.679821,43.306442],"type":"Point"}
}