{
  "type": "Feature",
  "properties": {
    "iso:country":"US",
    "sg:address":"544 E Yellowstone Hwy",
    "sg:city":"Casper",
    "sg:classifiers":[
        {
            "category":"Manufacturing",
            "subcategory":"Printing",
            "type":"Manufacturing & Wholesale Goods"
        }
    ],
    "sg:phone":"+1 307 234 1030",
    "sg:postcode":"82601",
    "sg:province":"WY",
    "sg:tags":[
        "commercial"
    ],
    "wof:name":"Oil City Printers",
    "wof:placetype":"venue"
},
  "geometry": {"coordinates":[-106.319013,42.849174],"type":"Point"}
}