{
  "type": "Feature",
  "properties": {
    "iso:country":"US",
    "sg:address":"111 Washakie Ave",
    "sg:city":"Lovell",
    "sg:classifiers":[
        {
            "category":"Recreation",
            "type":"Entertainment"
        }
    ],
    "sg:phone":"+1 307 548 9339",
    "sg:postcode":"82431",
    "sg:province":"WY",
    "wof:name":"Meeteetse Creek Horse Co",
    "wof:placetype":"venue"
},
  "geometry": {"coordinates":[-108.39747699999999,44.835285],"type":"Point"}
}