{
  "type": "Feature",
  "properties": {
    "iso:country":"US",
    "sg:address":"5815 Sunset Dr",
    "sg:city":"Cheyenne",
    "sg:classifiers":[
        {
            "category":"Building & Trades",
            "subcategory":"Construction",
            "type":"Services"
        }
    ],
    "sg:phone":"+1 307 778 3103",
    "sg:postcode":"82009",
    "sg:province":"WY",
    "sg:tags":[
        "general",
        "contractor"
    ],
    "wof:name":"Custom Development",
    "wof:placetype":"venue"
},
  "geometry": {"coordinates":[-104.825909,41.172602],"type":"Point"}
}