{
  "type": "Feature",
  "properties": {
    "iso:country":"US",
    "sg:address":"85 Reliance Rd",
    "sg:city":"Rock Springs",
    "sg:classifiers":[
        {
            "category":"Retail",
            "subcategory":"Repair Shop",
            "type":"Services"
        }
    ],
    "sg:phone":"+1 307 362 2879",
    "sg:postcode":"82943",
    "sg:province":"WY",
    "sg:tags":[
        "welding"
    ],
    "wof:name":"Bittercreek Industrial Repair",
    "wof:placetype":"venue"
},
  "geometry": {"coordinates":[-109.220894,41.660058],"type":"Point"}
}