{
  "type": "Feature",
  "properties": {
    "iso:country":"US",
    "sg:address":"1800 Carey Ave",
    "sg:city":"Cheyenne",
    "sg:classifiers":[
        {
            "category":"Professional",
            "subcategory":"Accounting & Tax Preparation",
            "type":"Services"
        }
    ],
    "sg:phone":"+1 307 742 2411",
    "sg:postcode":"82001",
    "sg:province":"WY",
    "wof:name":"Jane D Weskamp CPA",
    "wof:placetype":"venue"
},
  "geometry": {"coordinates":[-104.818134,41.134979],"type":"Point"}
}