{
  "type": "Feature",
  "properties": {
    "iso:country":"US",
    "sg:address":"1016 W Spruce St",
    "sg:city":"Rawlins",
    "sg:classifiers":[
        {
            "category":"Cinema",
            "subcategory":"Movie Rental",
            "type":"Entertainment"
        }
    ],
    "sg:phone":"+1 307 324 4200",
    "sg:postcode":"82301",
    "sg:province":"WY",
    "sg:tags":[
        "leasing",
        "video",
        "disc",
        "tape"
    ],
    "wof:name":"Blockbuster Video",
    "wof:placetype":"venue"
},
  "geometry": {"coordinates":[-107.247345,41.789051],"type":"Point"}
}