{
  "type": "Feature",
  "properties": {
    "iso:country":"US",
    "sg:address":"401 E Ivinson Ave",
    "sg:city":"Laramie",
    "sg:classifiers":[
        {
            "category":"Organizations",
            "subcategory":"Community Association",
            "type":"Services"
        }
    ],
    "sg:phone":"+1 307 745 4400",
    "sg:postcode":"82070",
    "sg:province":"WY",
    "sg:tags":[
        "fraternal"
    ],
    "wof:name":"Masonic Lodge",
    "wof:placetype":"venue"
},
  "geometry": {"coordinates":[-105.592159,41.311878],"type":"Point"}
}