{
  "type": "Feature",
  "properties": {
    "iso:country":"US",
    "sg:address":"2407 Mountain View Dr",
    "sg:city":"Cody",
    "sg:classifiers":[
        {
            "category":"Building & Trades",
            "subcategory":"Plumbing",
            "type":"Services"
        }
    ],
    "sg:phone":"+1 307 587 2910",
    "sg:postcode":"82414",
    "sg:province":"WY",
    "sg:tags":[
        "plumbing",
        "contractor"
    ],
    "wof:name":"Nielsen Plumbing & Heating",
    "wof:placetype":"venue"
},
  "geometry": {"coordinates":[-109.04022399999999,44.515269],"type":"Point"}
}