{
  "type": "Feature",
  "properties": {
    "iso:country":"US",
    "sg:address":"245 N Millward St",
    "sg:city":"Jackson",
    "sg:classifiers":[
        {
            "category":"Real Estate",
            "subcategory":"Real Estate Agent",
            "type":"Services"
        }
    ],
    "sg:phone":"+1 307 732 3400",
    "sg:postcode":"83001",
    "sg:province":"WY",
    "sg:tags":[
        "management"
    ],
    "wof:name":"Clear Creek Group",
    "wof:placetype":"venue"
},
  "geometry": {"coordinates":[-110.765164,43.482703],"type":"Point"}
}