{
  "type": "Feature",
  "properties": {
    "iso:country":"US",
    "sg:address":"4181 US Hwy 191",
    "sg:city":"Farson",
    "sg:classifiers":[
        {
            "category":"Building & Trades",
            "subcategory":"Equipment Rental",
            "type":"Services"
        }
    ],
    "sg:phone":"+1 307 273 9591",
    "sg:postcode":"82932",
    "sg:province":"WY",
    "sg:tags":[
        "generator"
    ],
    "wof:name":"Premier Powerplants & Pumps",
    "wof:placetype":"venue"
},
  "geometry": {"coordinates":[-109.45509199999999,42.125496],"type":"Point"}
}