{
  "type": "Feature",
  "properties": {
    "iso:country":"US",
    "sg:address":"1615 Lynwood Pl",
    "sg:city":"Casper",
    "sg:classifiers":[
        {
            "category":"Wholesale",
            "subcategory":"Farm Supplies",
            "type":"Manufacturing & Wholesale Goods"
        }
    ],
    "sg:phone":"+1 307 234 8204",
    "sg:postcode":"82604",
    "sg:province":"WY",
    "sg:tags":[
        "livestock"
    ],
    "wof:name":"Yz Ltd Partnership",
    "wof:placetype":"venue"
},
  "geometry": {"coordinates":[-106.350174,42.832245],"type":"Point"}
}