{
  "type": "Feature",
  "properties": {
    "iso:country":"US",
    "sg:address":"451 Piney Dr",
    "sg:city":"Big Piney",
    "sg:classifiers":[
        {
            "category":"Government",
            "subcategory":"Office",
            "type":"Public Place"
        }
    ],
    "sg:phone":"+1 307 276 3359",
    "sg:postcode":"83113",
    "sg:province":"WY",
    "wof:name":"Game Warden",
    "wof:placetype":"venue"
},
  "geometry": {"coordinates":[-110.11569,42.54035],"type":"Point"}
}