{
  "type": "Feature",
  "properties": {
    "iso:country":"US",
    "sg:address":"3810 Dell Range Blvd",
    "sg:city":"Cheyenne",
    "sg:classifiers":[
        {
            "category":"Banks & Credit Unions",
            "subcategory":"Bank",
            "type":"Services"
        }
    ],
    "sg:phone":"+1 307 432 5400",
    "sg:postcode":"82009",
    "sg:province":"WY",
    "wof:name":"Warren Federal Credit Union",
    "wof:placetype":"venue"
},
  "geometry": {"coordinates":[-104.763745,41.160137],"type":"Point"}
}