{
  "type": "Feature",
  "properties": {
    "iso:country":"US",
    "sg:address":"222 S Gillette Ave",
    "sg:city":"Gillette",
    "sg:classifiers":[
        {
            "category":"Mining & Drilling",
            "type":"Manufacturing & Wholesale Goods"
        }
    ],
    "sg:phone":"+1 307 686 2082",
    "sg:postcode":"82716",
    "sg:province":"WY",
    "sg:tags":[
        "crude",
        "well",
        "gas"
    ],
    "wof:name":"Coleman Oil & Gas Inc",
    "wof:placetype":"venue"
},
  "geometry": {"coordinates":[-105.504077,44.292965],"type":"Point"}
}