{
  "type": "Feature",
  "properties": {
    "addr:full":"149 Co Rd 143 Carpenter WY 82054",
    "addr:housenumber":"149",
    "addr:postcode":"82054",
    "addr:street":"Co Rd 143 Carpenter Wy",
    "iso:country":"US",
    "sg:address":"149 Co Rd 143",
    "sg:city":"Carpenter",
    "sg:classifiers":[
        {
            "category":"Building & Trades",
            "subcategory":"Construction",
            "type":"Services"
        }
    ],
    "sg:phone":"+1 307 649 2275",
    "sg:postcode":"82054",
    "sg:province":"WY",
    "sg:tags":[
        "house"
    ],
    "wof:name":"Porter Creek Construction",
    "wof:placetype":"venue"
},
  "geometry": {"coordinates":[-104.46612500000001,41.032004],"type":"Point"}
}