{
  "type": "Feature",
  "properties": {
    "addr:full":"330 W 28th Ave Torrington WY 82240",
    "addr:housenumber":"330",
    "addr:postcode":"82240",
    "addr:street":"W 28Th Ave",
    "iso:country":"US",
    "sg:address":"330 W 28th Ave",
    "sg:city":"Torrington",
    "sg:classifiers":[
        {
            "category":"Shopping",
            "subcategory":"Used Merchandise",
            "type":"Retail Goods"
        }
    ],
    "sg:phone":"+1 307 532 7800",
    "sg:postcode":"82240",
    "sg:province":"WY",
    "sg:tags":[
        "shop",
        "consignment"
    ],
    "wof:name":"Encore",
    "wof:placetype":"venue"
},
  "geometry": {"coordinates":[-104.187382,42.071998],"type":"Point"}
}