{
  "type": "Feature",
  "properties": {
    "addr:full":"1902 E 23rd St Casper WY 82601",
    "addr:housenumber":"1902",
    "addr:postcode":"82601",
    "addr:street":"E 23Rd St",
    "iso:country":"US",
    "sg:address":"1902 E 23rd St",
    "sg:city":"Casper",
    "sg:classifiers":[
        {
            "category":"Freight",
            "type":"Transportation"
        }
    ],
    "sg:phone":"+1 307 472 5510",
    "sg:postcode":"82601",
    "sg:province":"WY",
    "sg:tags":[
        "operator",
        "local",
        "special",
        "trucking"
    ],
    "wof:name":"Moving & Storage Connection",
    "wof:placetype":"venue"
},
  "geometry": {"coordinates":[-106.301861,42.826774],"type":"Point"}
}