{
  "type": "Feature",
  "properties": {
    "addr:full":"2500 Big Horn Ave Worland WY 82401",
    "addr:housenumber":"2500",
    "addr:postcode":"82401",
    "addr:street":"Big Horn Ave",
    "iso:country":"US",
    "sg:address":"2500 Big Horn Ave",
    "sg:city":"Worland",
    "sg:classifiers":[
        {
            "category":"Travel",
            "subcategory":"Hotels & Motels",
            "type":"Entertainment"
        }
    ],
    "sg:phone":"+1 307 347 9236",
    "sg:postcode":"82401",
    "sg:province":"WY",
    "sg:tags":[
        "operation"
    ],
    "wof:name":"Super 8 Motel",
    "wof:placetype":"venue"
},
  "geometry": {"coordinates":[-107.932428,44.018888],"type":"Point"}
}