{
  "type": "Feature",
  "properties": {
    "iso:country":"US",
    "sg:address":"255 Shoshoni St",
    "sg:city":"Cheyenne",
    "sg:classifiers":[
        {
            "category":"Professional",
            "type":"Services"
        }
    ],
    "sg:phone":"+1 307 635 5174",
    "sg:postcode":"82009",
    "sg:province":"WY",
    "wof:name":"Pj Services LLC",
    "wof:placetype":"venue"
},
  "geometry": {"coordinates":[-104.824181,41.169392],"type":"Point"}
}