{
  "type": "Feature",
  "properties": {
    "iso:country":"US",
    "sg:address":"805 Cindy Cir",
    "sg:city":"Riverton",
    "sg:classifiers":[
        {
            "category":"Building & Trades",
            "subcategory":"Cleaning & Sanitation",
            "type":"Services"
        }
    ],
    "sg:phone":"+1 307 857 2589",
    "sg:postcode":"82501",
    "sg:province":"WY",
    "sg:tags":[
        "fireplace",
        "chimney"
    ],
    "wof:name":"Soot & Ashes Chimney Sweep",
    "wof:placetype":"venue"
},
  "geometry": {"coordinates":[-108.37368600000001,43.031869],"type":"Point"}
}