{
  "type": "Feature",
  "properties": {
    "iso:country":"US",
    "sg:address":"514 E Main St",
    "sg:city":"Riverton",
    "sg:classifiers":[
        {
            "category":"Home & Garden",
            "subcategory":"Carpets & Floor Coverings",
            "type":"Retail Goods"
        }
    ],
    "sg:phone":"+1 307 856 9071",
    "sg:postcode":"82501",
    "sg:province":"WY",
    "sg:tags":[
        "material"
    ],
    "wof:name":"Plains Floor & Window Cvrngs",
    "wof:placetype":"venue"
},
  "geometry": {"coordinates":[-108.384725,43.024732],"type":"Point"}
}