{
  "type": "Feature",
  "properties": {
    "addr:full":"79 Rd 2Ac Cody WY 82414",
    "addr:housenumber":"79;2ac",
    "addr:postcode":"82414",
    "addr:street":"Rd;Cody Wy",
    "iso:country":"US",
    "sg:address":"79 Rd 2Ac",
    "sg:city":"Cody",
    "sg:classifiers":[
        {
            "category":"Building & Trades",
            "subcategory":"Plumbing",
            "type":"Services"
        }
    ],
    "sg:phone":"+1 307 587 3713",
    "sg:postcode":"82414",
    "sg:province":"WY",
    "sg:tags":[
        "plumbing",
        "contractor"
    ],
    "wof:name":"Wrangler Plumbing & Heating",
    "wof:placetype":"venue"
},
  "geometry": {"coordinates":[-109.05789300000001,44.555715],"type":"Point"}
}