{
  "type": "Feature",
  "properties": {
    "addr:full":"778 Sybille Creek Rd Wheatland WY 82201",
    "addr:housenumber":"778",
    "addr:postcode":"82201",
    "addr:street":"Sybille Creek Rd",
    "iso:country":"US",
    "sg:address":"778 Sybille Creek Rd",
    "sg:city":"Wheatland",
    "sg:classifiers":[
        {
            "category":"Retail",
            "subcategory":"Veterinary Services",
            "type":"Services"
        }
    ],
    "sg:phone":"+1 307 322 9045",
    "sg:postcode":"82201",
    "sg:province":"WY",
    "wof:name":"Randy Hunter Dvm",
    "wof:placetype":"venue"
},
  "geometry": {"coordinates":[-105.060095,41.976566],"type":"Point"}
}