{
  "type": "Feature",
  "properties": {
    "iso:country":"US",
    "sg:address":"600 Persons Rd",
    "sg:city":"Pine Bluffs",
    "sg:classifiers":[
        {
            "category":"Restaurant",
            "type":"Food & Drink"
        }
    ],
    "sg:phone":"+1 307 245 9365",
    "sg:postcode":"82007",
    "sg:province":"WY",
    "wof:name":"Rodeo Pit Stops",
    "wof:placetype":"venue"
},
  "geometry": {"coordinates":[-104.795597,41.11865],"type":"Point"}
}