{
  "type": "Feature",
  "properties": {
    "addr:full":"520 W Broadway Jackson WY 83001",
    "addr:housenumber":"520",
    "addr:postcode":"83001",
    "addr:street":"W Broadway Jackson Wy",
    "iso:country":"US",
    "sg:address":"520 W Broadway",
    "sg:city":"Jackson",
    "sg:classifiers":[
        {
            "category":"Shopping",
            "subcategory":"Stationery & Office Supplies",
            "type":"Retail Goods"
        }
    ],
    "sg:phone":"+1 307 734 6148",
    "sg:postcode":"83001",
    "sg:province":"WY",
    "wof:name":"Staples The Office Superstore",
    "wof:placetype":"venue"
},
  "geometry": {"coordinates":[-110.770348,43.478137],"type":"Point"}
}