{
  "type": "Feature",
  "properties": {
    "iso:country":"US",
    "sg:address":"824 E Prosser Rd",
    "sg:city":"Cheyenne",
    "sg:classifiers":[
        {
            "category":"Professional",
            "type":"Services"
        }
    ],
    "sg:phone":"+1 307 634 8474",
    "sg:postcode":"82007",
    "sg:province":"WY",
    "sg:tags":[
        "lithograph",
        "artist"
    ],
    "wof:name":"Broken Arrow Art Works",
    "wof:placetype":"venue"
},
  "geometry": {"coordinates":[-104.790705,41.105947],"type":"Point"}
}