{
  "type": "Feature",
  "properties": {
    "addr:full":"2401 Foothill Blvd Rock Springs WY 82901",
    "addr:housenumber":"2401",
    "addr:postcode":"82901",
    "addr:street":"Foothill Blvd;Springs Wy",
    "iso:country":"US",
    "sg:address":"2401 Foothill Blvd",
    "sg:city":"Rock Springs",
    "sg:classifiers":[
        {
            "category":"Autos & Motor Vehicles",
            "subcategory":"Motorcycle Sales",
            "type":"Retail Goods"
        },
        {
            "category":"Shopping",
            "subcategory":"Clothing, Apparel, & Fashions",
            "type":"Retail Goods"
        }
    ],
    "sg:phone":"+1 307 382 9099",
    "sg:postcode":"82901",
    "sg:province":"WY",
    "sg:tags":[
        "leather"
    ],
    "sg:website":"www.flamingharley.com",
    "wof:name":"Flaming Gorge Harley-Davidson",
    "wof:placetype":"venue"
},
  "geometry": {"coordinates":[-109.26372000000001,41.57927],"type":"Point"}
}