{
  "type": "Feature",
  "properties": {
    "iso:country":"US",
    "sg:address":"325 Roundup St",
    "sg:city":"Belle Fourche",
    "sg:classifiers":[
        {
            "category":"Freight",
            "type":"Transportation"
        }
    ],
    "sg:phone":"+1 605 892 3313",
    "sg:postcode":"57717",
    "sg:province":"WY",
    "sg:tags":[
        "warehouse",
        "self",
        "storage",
        "general"
    ],
    "wof:name":"Baroide Idp Bpm Warehouse",
    "wof:placetype":"venue"
},
  "geometry": {"coordinates":[-103.85375999999999,44.67049],"type":"Point"}
}