{
  "type": "Feature",
  "properties": {
    "iso:country":"US",
    "sg:address":"1169 Co Rd 154",
    "sg:city":"Burns",
    "sg:classifiers":[
        {
            "category":"Freight",
            "type":"Transportation"
        }
    ],
    "sg:phone":"+1 307 547 3682",
    "sg:postcode":"82053",
    "sg:province":"WY",
    "sg:tags":[
        "arrangement"
    ],
    "wof:name":"I 80 Industrial Rail Park",
    "wof:placetype":"venue"
},
  "geometry": {"coordinates":[-104.253657,41.171267],"type":"Point"}
}