{
  "type": "Feature",
  "properties": {
    "iso:country":"US",
    "sg:address":"230 N 4th St",
    "sg:city":"Glenrock",
    "sg:classifiers":[
        {
            "category":"Building & Trades",
            "subcategory":"Construction",
            "type":"Services"
        }
    ],
    "sg:phone":"+1 307 436 9063",
    "sg:postcode":"82637",
    "sg:province":"WY",
    "sg:tags":[
        "general",
        "contractor"
    ],
    "wof:name":"Amcon Inc",
    "wof:placetype":"venue"
},
  "geometry": {"coordinates":[-105.872072,42.865554],"type":"Point"}
}