{
  "type": "Feature",
  "properties": {
    "addr:full":"149 Davis Ln Riverton WY 82501",
    "addr:housenumber":"149",
    "addr:postcode":"82501",
    "addr:street":"Davis Ln",
    "iso:country":"US",
    "sg:address":"149 Davis Ln",
    "sg:city":"Riverton",
    "sg:classifiers":[
        {
            "category":"Shopping",
            "type":"Retail Goods"
        }
    ],
    "sg:phone":"+1 307 856 7534",
    "sg:postcode":"82501",
    "sg:province":"WY",
    "sg:tags":[
        "merchandise"
    ],
    "wof:name":"Wyoming Hearing Aid Service",
    "wof:placetype":"venue"
},
  "geometry": {"coordinates":[-108.418046,43.024244],"type":"Point"}
}