{
  "type": "Feature",
  "properties": {
    "iso:country":"US",
    "sg:address":"990 Montana Dr",
    "sg:city":"Jackson",
    "sg:classifiers":[
        {
            "category":"Building & Trades",
            "subcategory":"Construction",
            "type":"Services"
        }
    ],
    "sg:phone":"+1 307 739 1232",
    "sg:postcode":"83001",
    "sg:province":"WY",
    "sg:tags":[
        "general",
        "contractor"
    ],
    "wof:name":"MKD Construction",
    "wof:placetype":"venue"
},
  "geometry": {"coordinates":[-110.806237,43.465357],"type":"Point"}
}