{
  "type": "Feature",
  "properties": {
    "iso:country":"US",
    "sg:address":"4659 Powell Hwy",
    "sg:city":"Cody",
    "sg:phone":"+1 307 587 3922",
    "sg:postcode":"82414",
    "sg:province":"WY",
    "sg:tags":[
        "farm",
        "beet"
    ],
    "wof:name":"Merle Dutton",
    "wof:placetype":"venue"
},
  "geometry": {"coordinates":[-108.982322,44.548748],"type":"Point"}
}