{
  "type": "Feature",
  "properties": {
    "iso:country":"US",
    "sg:address":"402 N Beverly St",
    "sg:city":"Casper",
    "sg:classifiers":[
        {
            "category":"Building & Trades",
            "subcategory":"Construction",
            "type":"Services"
        }
    ],
    "sg:phone":"+1 307 235 4547",
    "sg:postcode":"82609",
    "sg:province":"WY",
    "sg:tags":[
        "home",
        "flooring"
    ],
    "wof:name":"Casper Home Center",
    "wof:placetype":"venue"
},
  "geometry": {"coordinates":[-106.297775,42.854267],"type":"Point"}
}