{
  "type": "Feature",
  "properties": {
    "iso:country":"US",
    "sg:address":"171 N 3rd St",
    "sg:city":"Laramie",
    "sg:classifiers":[
        {
            "category":"Bars & Pubs",
            "type":"Food & Drink"
        }
    ],
    "sg:phone":"+1 970 231 5536",
    "sg:postcode":"82072",
    "sg:province":"WY",
    "sg:tags":[
        "drinking"
    ],
    "wof:name":"Grounds Intrnet Cof Lounge LLC",
    "wof:placetype":"venue"
},
  "geometry": {"coordinates":[-105.59329700000001,41.313157],"type":"Point"}
}