{
  "type": "Feature",
  "properties": {
    "iso:country":"US",
    "sg:address":"14871 State Hwy 387",
    "sg:city":"Wright",
    "sg:classifiers":[
        {
            "category":"Home & Garden",
            "subcategory":"Hardware",
            "type":"Retail Goods"
        }
    ],
    "sg:phone":"+1 307 464 0200",
    "sg:postcode":"82732",
    "sg:province":"WY",
    "wof:name":"Wright True Value Hardware",
    "wof:placetype":"venue"
},
  "geometry": {"coordinates":[-105.527854,43.742394],"type":"Point"}
}