{
  "type": "Feature",
  "properties": {
    "iso:country":"US",
    "sg:address":"701 E Ord St",
    "sg:city":"Laramie",
    "sg:classifiers":[
        {
            "category":"Education",
            "subcategory":"Dance Studio",
            "type":"Public Place"
        }
    ],
    "sg:phone":"+1 307 745 8959",
    "sg:postcode":"82070",
    "sg:province":"WY",
    "wof:name":"Dancing Woman Ventures",
    "wof:placetype":"venue"
},
  "geometry": {"coordinates":[-105.589078,41.304124],"type":"Point"}
}