{
  "type": "Feature",
  "properties": {
    "addr:full":"513 Date St Cody WY 82414",
    "addr:housenumber":"513",
    "addr:postcode":"82414",
    "addr:street":"Date St",
    "iso:country":"US",
    "sg:address":"513 Date St",
    "sg:city":"Cody",
    "sg:classifiers":[
        {
            "category":"Retail",
            "subcategory":"Auto Repair",
            "type":"Services"
        }
    ],
    "sg:phone":"+1 307 587 3248",
    "sg:postcode":"82414",
    "sg:province":"WY",
    "sg:tags":[
        "repairing",
        "automobile"
    ],
    "wof:name":"Joe's Auto Repair",
    "wof:placetype":"venue"
},
  "geometry": {"coordinates":[-109.022796,44.532351],"type":"Point"}
}