{
  "type": "Feature",
  "properties": {
    "addr:full":"217 E 21st Ave Torrington WY 82240",
    "addr:housenumber":"217",
    "addr:postcode":"82240",
    "addr:street":"E 21St Ave",
    "iso:country":"US",
    "sg:address":"217 E 21st Ave",
    "sg:city":"Torrington",
    "sg:classifiers":[
        {
            "category":"Insurance",
            "subcategory":"Insurance Agent",
            "type":"Services"
        }
    ],
    "sg:phone":"+1 307 532 3197",
    "sg:postcode":"82240",
    "sg:province":"WY",
    "wof:name":"Farm Bureau Insurance",
    "wof:placetype":"venue"
},
  "geometry": {"coordinates":[-104.182832,42.064962],"type":"Point"}
}