{
  "type": "Feature",
  "properties": {
    "iso:country":"US",
    "sg:address":"187 E Main St",
    "sg:city":"Lovell",
    "sg:classifiers":[
        {
            "category":"Freight",
            "type":"Transportation"
        }
    ],
    "sg:phone":"+1 307 548 6786",
    "sg:postcode":"82431",
    "sg:province":"WY",
    "sg:tags":[
        "trucking"
    ],
    "wof:name":"Shoshone Trucking",
    "wof:placetype":"venue"
},
  "geometry": {"coordinates":[-108.390001,44.837598],"type":"Point"}
}