{
  "type": "Feature",
  "properties": {
    "addr:full":"19 N Main St Buffalo WY 82834",
    "addr:housenumber":"19",
    "addr:postcode":"82834",
    "addr:street":"N Main St",
    "iso:country":"US",
    "sg:address":"19 N Main St",
    "sg:city":"Buffalo",
    "sg:classifiers":[
        {
            "category":"Retail",
            "subcategory":"Portrait Studio",
            "type":"Services"
        }
    ],
    "sg:phone":"+1 307 684 9190",
    "sg:postcode":"82834",
    "sg:province":"WY",
    "sg:tags":[
        "photography",
        "commercial"
    ],
    "sg:website":"www.cooleyimages.com",
    "wof:name":"Cooley Images Studio",
    "wof:placetype":"venue"
},
  "geometry": {"coordinates":[-106.698971,44.347967],"type":"Point"}
}