{
  "type": "Feature",
  "properties": {
    "iso:country":"US",
    "sg:address":"211 W Flaming Gorge Way",
    "sg:city":"Green River",
    "sg:classifiers":[
        {
            "category":"Restaurant",
            "type":"Food & Drink"
        }
    ],
    "sg:phone":"+1 307 875 5124",
    "sg:postcode":"82935",
    "sg:province":"WY",
    "wof:name":"Krazy Moose",
    "wof:placetype":"venue"
},
  "geometry": {"coordinates":[-109.47078,41.530917],"type":"Point"}
}