{
  "type": "Feature",
  "properties": {
    "iso:country":"US",
    "sg:address":"4700 Airport Rd",
    "sg:city":"Riverton",
    "sg:classifiers":[
        {
            "category":"Airline",
            "type":"Transportation"
        }
    ],
    "sg:phone":"+1 307 856 6671",
    "sg:postcode":"82501",
    "sg:province":"WY",
    "sg:tags":[
        "charter",
        "fueling",
        "air"
    ],
    "wof:name":"Carriage Corral",
    "wof:placetype":"venue"
},
  "geometry": {"coordinates":[-108.45546899999999,43.057811],"type":"Point"}
}