{
  "type": "Feature",
  "properties": {
    "iso:country":"US",
    "sg:address":"23 Timm St",
    "sg:city":"Sheridan",
    "sg:classifiers":[
        {
            "category":"Shopping",
            "subcategory":"Gifts & Souvenirs",
            "type":"Retail Goods"
        }
    ],
    "sg:phone":"+1 307 672 7296",
    "sg:postcode":"82801",
    "sg:province":"WY",
    "sg:tags":[
        "basket",
        "parcel"
    ],
    "wof:name":"Buckaroo Baskets & Gifts",
    "wof:placetype":"venue"
},
  "geometry": {"coordinates":[-107.088302,44.761016],"type":"Point"}
}