{
  "type": "Feature",
  "properties": {
    "iso:country":"US",
    "sg:address":"2881 Heights Blvd",
    "sg:city":"Casper",
    "sg:classifiers":[
        {
            "category":"Building & Trades",
            "subcategory":"Construction",
            "type":"Services"
        }
    ],
    "sg:phone":"+1 307 473 3068",
    "sg:postcode":"82604",
    "sg:province":"WY",
    "sg:tags":[
        "downspouts",
        "gutter"
    ],
    "wof:name":"Gutter Guy's",
    "wof:placetype":"venue"
},
  "geometry": {"coordinates":[-106.356876,42.854724],"type":"Point"}
}