{
  "type": "Feature",
  "properties": {
    "addr:full":"161 S Fenway St Casper WY 82601",
    "addr:housenumber":"161",
    "addr:postcode":"82601",
    "addr:street":"S Fenway St",
    "iso:country":"US",
    "sg:address":"161 S Fenway St",
    "sg:city":"Casper",
    "sg:classifiers":[
        {
            "category":"Personal",
            "subcategory":"Barber",
            "type":"Services"
        }
    ],
    "sg:phone":"+1 307 265 9181",
    "sg:postcode":"82601",
    "sg:province":"WY",
    "sg:tags":[
        "shop"
    ],
    "wof:name":"Milo's Barbershop",
    "wof:placetype":"venue"
},
  "geometry": {"coordinates":[-106.30527499999999,42.849584],"type":"Point"}
}