{
  "type": "Feature",
  "properties": {
    "iso:country":"US",
    "sg:address":"4252 Cabin Creek Rd",
    "sg:city":"Casper",
    "sg:classifiers":[
        {
            "category":"Real Estate",
            "subcategory":"Real Estate Operator",
            "type":"Services"
        }
    ],
    "sg:phone":"+1 307 234 1710",
    "sg:postcode":"82604",
    "sg:province":"WY",
    "sg:tags":[
        "building",
        "nonresidential"
    ],
    "wof:name":"Nelson Cv Properties LLC",
    "wof:placetype":"venue"
},
  "geometry": {"coordinates":[-106.415918,42.80733],"type":"Point"}
}