{
  "type": "Feature",
  "properties": {
    "addr:full":"1550 N Federal Blvd Riverton WY 82501",
    "addr:housenumber":"1550",
    "addr:postcode":"82501",
    "addr:street":"N Federal Blvd",
    "iso:country":"US",
    "sg:address":"1550 N Federal Blvd",
    "sg:city":"Riverton",
    "sg:classifiers":[
        {
            "category":"Travel",
            "subcategory":"Hotels & Motels",
            "type":"Entertainment"
        }
    ],
    "sg:phone":"+1 307 856 9238",
    "sg:postcode":"82501",
    "sg:province":"WY",
    "wof:name":"Paintbrush Motel",
    "wof:placetype":"venue"
},
  "geometry": {"coordinates":[-108.38071100000001,43.04018],"type":"Point"}
}