{
  "type": "Feature",
  "properties": {
    "iso:country":"US",
    "sg:address":"527 1st Ave S",
    "sg:city":"Greybull",
    "sg:classifiers":[
        {
            "category":"Recreation",
            "type":"Entertainment"
        }
    ],
    "sg:phone":"+1 307 765 9575",
    "sg:postcode":"82426",
    "sg:province":"WY",
    "sg:tags":[
        "center"
    ],
    "wof:name":"Greybull Recreation District",
    "wof:placetype":"venue"
},
  "geometry": {"coordinates":[-108.05425099999999,44.487721],"type":"Point"}
}