{
  "type": "Feature",
  "properties": {
    "addr:full":"160 Fir St Buffalo WY 82834",
    "addr:housenumber":"160",
    "addr:postcode":"82834",
    "addr:street":"Fir St Buffalo Wy",
    "iso:country":"US",
    "sg:address":"160 Fir St",
    "sg:city":"Buffalo",
    "sg:classifiers":[
        {
            "category":"Building & Trades",
            "subcategory":"Construction",
            "type":"Services"
        }
    ],
    "sg:phone":"+1 307 684 7421",
    "sg:postcode":"82834",
    "sg:province":"WY",
    "sg:tags":[
        "water",
        "well",
        "drilling"
    ],
    "wof:name":"Clear Creek Well Service Inc",
    "wof:placetype":"venue"
},
  "geometry": {"coordinates":[-106.74748200000001,44.339788],"type":"Point"}
}