{
  "type": "Feature",
  "properties": {
    "iso:country":"US",
    "sg:address":"1701 S Greeley Hwy",
    "sg:city":"Cheyenne",
    "sg:classifiers":[
        {
            "category":"Wholesale",
            "subcategory":"Auto Parts",
            "type":"Manufacturing & Wholesale Goods"
        }
    ],
    "sg:phone":"+1 307 634 3377",
    "sg:postcode":"82007",
    "sg:province":"WY",
    "sg:tags":[
        "automobile",
        "rebuilt"
    ],
    "wof:name":"Action Automotive Inc",
    "wof:placetype":"venue"
},
  "geometry": {"coordinates":[-104.80049099999999,41.101366],"type":"Point"}
}