{
  "type": "Feature",
  "properties": {
    "addr:full":"237 Coffeen Ave Sheridan WY 82801",
    "addr:housenumber":"237",
    "addr:postcode":"82801",
    "addr:street":"Coffeen Ave",
    "iso:country":"US",
    "sg:address":"237 Coffeen Ave",
    "sg:city":"Sheridan",
    "sg:classifiers":[
        {
            "category":"Social Services",
            "subcategory":"Adult Care",
            "type":"Services"
        }
    ],
    "sg:phone":"+1 307 673 1920",
    "sg:postcode":"82801",
    "sg:province":"WY",
    "sg:tags":[
        "foster"
    ],
    "wof:name":"Hill Top",
    "wof:placetype":"venue"
},
  "geometry": {"coordinates":[-106.952332,44.79354],"type":"Point"}
}