{
  "type": "Feature",
  "properties": {
    "addr:full":"3101 Oakcrest Dr Gillette WY 82718",
    "addr:housenumber":"3101",
    "addr:postcode":"82718",
    "addr:street":"Oakcrest Dr",
    "iso:country":"US",
    "sg:address":"3101 Oakcrest Dr",
    "sg:city":"Gillette",
    "sg:classifiers":[
        {
            "category":"Home & Garden",
            "subcategory":"Garden Supply",
            "type":"Retail Goods"
        }
    ],
    "sg:phone":"+1 307 686 7246",
    "sg:postcode":"82718",
    "sg:province":"WY",
    "sg:tags":[
        "sprinkler"
    ],
    "wof:name":"Midwest Landscaping",
    "wof:placetype":"venue"
},
  "geometry": {"coordinates":[-105.529855,44.264895],"type":"Point"}
}