{
  "type": "Feature",
  "properties": {
    "iso:country":"US",
    "sg:address":"356 Granite Dr",
    "sg:city":"Rock Springs",
    "sg:classifiers":[
        {
            "category":"Retail",
            "subcategory":"Repair Shop",
            "type":"Services"
        }
    ],
    "sg:phone":"+1 307 382 4440",
    "sg:postcode":"82901",
    "sg:province":"WY",
    "sg:tags":[
        "welding"
    ],
    "wof:name":"Slags Welding Inc",
    "wof:placetype":"venue"
},
  "geometry": {"coordinates":[-109.26723,41.638023],"type":"Point"}
}