{
  "type": "Feature",
  "properties": {
    "iso:country":"US",
    "sg:address":"2304 E 13th St",
    "sg:city":"Cheyenne",
    "sg:classifiers":[
        {
            "category":"Organizations",
            "subcategory":"Community Association",
            "type":"Services"
        }
    ],
    "sg:phone":"+1 307 632 5716",
    "sg:postcode":"82001",
    "sg:province":"WY",
    "sg:tags":[
        "environmental",
        "protection"
    ],
    "wof:name":"Wyoming Assn Conservation Dist",
    "wof:placetype":"venue"
},
  "geometry": {"coordinates":[-104.788805,41.137587],"type":"Point"}
}