{
  "type": "Feature",
  "properties": {
    "addr:full":"1008 Baldwin Dr Cheyenne WY 82001",
    "addr:housenumber":"1008",
    "addr:postcode":"82001",
    "addr:street":"Baldwin Dr",
    "iso:country":"US",
    "sg:address":"1008 Baldwin Dr",
    "sg:city":"Cheyenne",
    "sg:classifiers":[
        {
            "category":"Personal",
            "subcategory":"Beauty Salon",
            "type":"Services"
        }
    ],
    "sg:phone":"+1 307 632 1121",
    "sg:postcode":"82001",
    "sg:province":"WY",
    "sg:tags":[
        "body",
        "art"
    ],
    "wof:name":"Extreme Point Body Shoppe LLC",
    "wof:placetype":"venue"
},
  "geometry": {"coordinates":[-104.762646,41.134975],"type":"Point"}
}