{
  "type": "Feature",
  "properties": {
    "iso:country":"US",
    "sg:address":"76 Gateway Blvd",
    "sg:city":"Rock Springs",
    "sg:classifiers":[
        {
            "category":"Restaurant",
            "type":"Food & Drink"
        }
    ],
    "sg:phone":"+1 307 382 4690",
    "sg:postcode":"82901",
    "sg:province":"WY",
    "wof:name":"Popeye's Chicken & Biscuit",
    "wof:placetype":"venue"
},
  "geometry": {"coordinates":[-109.24977800000001,41.576405],"type":"Point"}
}