{
  "type": "Feature",
  "properties": {
    "iso:country":"US",
    "sg:address":"1652 Begonia St",
    "sg:city":"Casper",
    "sg:classifiers":[
        {
            "category":"Wholesale",
            "subcategory":"Machinery & Supplies",
            "type":"Manufacturing & Wholesale Goods"
        }
    ],
    "sg:phone":"+1 307 577 9219",
    "sg:postcode":"82604",
    "sg:province":"WY",
    "sg:tags":[
        "car"
    ],
    "wof:name":"Car Wash Supply",
    "wof:placetype":"venue"
},
  "geometry": {"coordinates":[-106.40419,42.830459],"type":"Point"}
}