{
  "type": "Feature",
  "properties": {
    "iso:country":"US",
    "sg:address":"310 E Main St",
    "sg:city":"Riverton",
    "sg:classifiers":[
        {
            "category":"Retail",
            "subcategory":"Repair Shop",
            "type":"Services"
        }
    ],
    "sg:phone":"+1 307 856 1402",
    "sg:postcode":"82501",
    "sg:province":"WY",
    "wof:name":"Wind River Gallery & Framing",
    "wof:placetype":"venue"
},
  "geometry": {"coordinates":[-108.386473,43.024719],"type":"Point"}
}