{
  "type": "Feature",
  "properties": {
    "iso:country":"US",
    "sg:address":"75 N Main St",
    "sg:city":"Buffalo",
    "sg:classifiers":[
        {
            "category":"Real Estate",
            "subcategory":"Real Estate Agent",
            "type":"Services"
        }
    ],
    "sg:phone":"+1 307 684 5563",
    "sg:postcode":"82834",
    "sg:province":"WY",
    "wof:name":"Smith Brokerage",
    "wof:placetype":"venue"
},
  "geometry": {"coordinates":[-106.698795,44.347201],"type":"Point"}
}