{
  "type": "Feature",
  "properties": {
    "addr:full":"626 Washington St Lander WY 82520",
    "addr:housenumber":"626",
    "addr:postcode":"82520",
    "addr:street":"Washington St Lander Wy",
    "iso:country":"US",
    "sg:address":"626 Washington St",
    "sg:city":"Lander",
    "sg:classifiers":[
        {
            "category":"Education",
            "subcategory":"School",
            "type":"Public Place"
        }
    ],
    "sg:phone":"+1 307 332 5943",
    "sg:postcode":"82520",
    "sg:province":"WY",
    "wof:name":"Northside School",
    "wof:placetype":"venue"
},
  "geometry": {"coordinates":[-108.73514,42.841759],"type":"Point"}
}