{
  "type": "Feature",
  "properties": {
    "addr:full":"260 W 1st St Casper WY 82601",
    "addr:housenumber":"260",
    "addr:postcode":"82601",
    "addr:street":"W 1St St",
    "iso:country":"US",
    "sg:address":"260 W 1st St",
    "sg:city":"Casper",
    "sg:classifiers":[
        {
            "category":"Food & Beverages",
            "subcategory":"Bakery",
            "type":"Retail Goods"
        }
    ],
    "sg:phone":"+1 307 472 0255",
    "sg:postcode":"82601",
    "sg:province":"WY",
    "sg:tags":[
        "baker"
    ],
    "wof:name":"First Street Bakers Inc",
    "wof:placetype":"venue"
},
  "geometry": {"coordinates":[-106.328351,42.850172],"type":"Point"}
}