{
  "type": "Feature",
  "properties": {
    "iso:country":"US",
    "sg:address":"1200 E 20th St",
    "sg:city":"Cheyenne",
    "sg:classifiers":[
        {
            "category":"Insurance",
            "subcategory":"Health Insurance",
            "type":"Services"
        },
        {
            "category":"Insurance",
            "subcategory":"Insurance Agent",
            "type":"Services"
        }
    ],
    "sg:phone":"+1 307 638 7700",
    "sg:postcode":"82001",
    "sg:province":"WY",
    "sg:tags":[
        "medical",
        "plan"
    ],
    "wof:name":"Win Health Partners",
    "wof:placetype":"venue"
},
  "geometry": {"coordinates":[-104.803032,41.141698],"type":"Point"}
}