{
  "type": "Feature",
  "properties": {
    "addr:full":"400 Greybull Ave Greybull WY 82426",
    "addr:housenumber":"400",
    "addr:postcode":"82426",
    "addr:street":"Greybull Ave Greybull Wy",
    "iso:country":"US",
    "sg:address":"400 Greybull Ave",
    "sg:city":"Greybull",
    "sg:classifiers":[
        {
            "category":"Autos & Motor Vehicles",
            "subcategory":"Fuel & Gas Station",
            "type":"Retail Goods"
        }
    ],
    "sg:phone":"+1 307 765 2051",
    "sg:postcode":"82426",
    "sg:province":"WY",
    "sg:tags":[
        "station",
        "gasoline"
    ],
    "wof:name":"Big Horn Co-Op Service Station",
    "wof:placetype":"venue"
},
  "geometry": {"coordinates":[-108.053917,44.488859],"type":"Point"}
}