{
  "type": "Feature",
  "properties": {
    "addr:full":"130 Lake Rd Pinedale WY 82941",
    "addr:housenumber":"130",
    "addr:postcode":"82941",
    "addr:street":"Lake Rd",
    "iso:country":"US",
    "sg:address":"130 Lake Rd",
    "sg:city":"Pinedale",
    "sg:classifiers":[
        {
            "category":"Freight",
            "type":"Transportation"
        }
    ],
    "sg:phone":"+1 307 367 6216",
    "sg:postcode":"82941",
    "sg:province":"WY",
    "sg:tags":[
        "trucking"
    ],
    "wof:name":"DMS Inc",
    "wof:placetype":"venue"
},
  "geometry": {"coordinates":[-109.86562000000001,42.87611],"type":"Point"}
}