{
  "type": "Feature",
  "properties": {
    "iso:country":"US",
    "sg:address":"3220 Reesy Rd",
    "sg:city":"Cody",
    "sg:classifiers":[
        {
            "category":"Building & Trades",
            "subcategory":"Construction",
            "type":"Services"
        }
    ],
    "sg:phone":"+1 307 587 4570",
    "sg:postcode":"82414",
    "sg:province":"WY",
    "sg:tags":[
        "excavating",
        "contractor"
    ],
    "wof:name":"Morris Excavation",
    "wof:placetype":"venue"
},
  "geometry": {"coordinates":[-109.025369,44.495415],"type":"Point"}
}