{
  "type": "Feature",
  "properties": {
    "iso:country":"US",
    "sg:address":"676 Ln 9",
    "sg:city":"Powell",
    "sg:classifiers":[
        {
            "category":"Real Estate",
            "subcategory":"Developer",
            "type":"Services"
        }
    ],
    "sg:phone":"+1 307 754 4313",
    "sg:postcode":"82435",
    "sg:province":"WY",
    "sg:tags":[
        "cemetery"
    ],
    "wof:name":"Powell Crown Hill Cemetery",
    "wof:placetype":"venue"
},
  "geometry": {"coordinates":[-108.712529,44.753588],"type":"Point"}
}