{
  "type": "Feature",
  "properties": {
    "iso:country":"US",
    "sg:address":"202 Iroquois Ln",
    "sg:city":"Gillette",
    "sg:classifiers":[
        {
            "category":"Social Services",
            "subcategory":"Child Care",
            "type":"Services"
        }
    ],
    "sg:phone":"+1 307 686 9389",
    "sg:postcode":"82716",
    "sg:province":"WY",
    "sg:tags":[
        "day"
    ],
    "wof:name":"A & T Daycare",
    "wof:placetype":"venue"
},
  "geometry": {"coordinates":[-105.53637500000001,44.299938],"type":"Point"}
}