{
  "type": "Feature",
  "properties": {
    "iso:country":"US",
    "sg:address":"442 N Hamilton St",
    "sg:city":"Powell",
    "sg:classifiers":[
        {
            "category":"Bars & Pubs",
            "type":"Food & Drink"
        }
    ],
    "sg:phone":"+1 307 754 4810",
    "sg:postcode":"82435",
    "sg:province":"WY",
    "sg:tags":[
        "drinking",
        "product",
        "mfg"
    ],
    "wof:name":"Breath of West",
    "wof:placetype":"venue"
},
  "geometry": {"coordinates":[-108.74839900000001,44.757421],"type":"Point"}
}