{
  "type": "Feature",
  "properties": {
    "addr:full":"816 N Federal Blvd Riverton WY 82501",
    "addr:housenumber":"816",
    "addr:postcode":"82501",
    "addr:street":"N Federal Blvd",
    "iso:country":"US",
    "sg:address":"816 N Federal Blvd",
    "sg:city":"Riverton",
    "sg:classifiers":[
        {
            "category":"Government",
            "subcategory":"Court House",
            "type":"Public Place"
        }
    ],
    "sg:phone":"+1 307 856 0918",
    "sg:postcode":"82501",
    "sg:province":"WY",
    "sg:tags":[
        "state",
        "counsel"
    ],
    "wof:name":"Attorney General",
    "wof:placetype":"venue"
},
  "geometry": {"coordinates":[-108.38065899999999,43.033665],"type":"Point"}
}