{
  "type": "Feature",
  "properties": {
    "iso:country":"US",
    "sg:address":"1001 E 9th St",
    "sg:city":"Gillette",
    "sg:classifiers":[
        {
            "category":"Social Services",
            "subcategory":"Child Care",
            "type":"Services"
        }
    ],
    "sg:phone":"+1 307 682 5126",
    "sg:postcode":"82716",
    "sg:province":"WY",
    "sg:tags":[
        "kindergarten",
        "academic",
        "school"
    ],
    "wof:name":"Trinity Lutheran Preschool",
    "wof:placetype":"venue"
},
  "geometry": {"coordinates":[-105.48748999999999,44.28639],"type":"Point"}
}