{
  "type": "Feature",
  "properties": {
    "addr:full":"319 4th St Rawlins WY 82301",
    "addr:housenumber":"319",
    "addr:postcode":"82301",
    "addr:street":"4Th St",
    "iso:country":"US",
    "sg:address":"319 4th St",
    "sg:city":"Rawlins",
    "sg:classifiers":[
        {
            "category":"Organizations",
            "subcategory":"Community Association",
            "type":"Services"
        }
    ],
    "sg:phone":"+1 307 324 5292",
    "sg:postcode":"82301",
    "sg:province":"WY",
    "sg:tags":[
        "fraternal"
    ],
    "wof:name":"Fraternal Order Of Eagles",
    "wof:placetype":"venue"
},
  "geometry": {"coordinates":[-107.239305,41.789167],"type":"Point"}
}