{
  "type": "Feature",
  "properties": {
    "addr:full":"405 E Main St Sundance WY 82729",
    "addr:housenumber":"405",
    "addr:postcode":"82729",
    "addr:street":"E Main St Sundance Wy",
    "iso:country":"US",
    "sg:address":"405 E Main St",
    "sg:city":"Sundance",
    "sg:classifiers":[
        {
            "category":"Education",
            "subcategory":"School",
            "type":"Public Place"
        }
    ],
    "sg:phone":"+1 307 283 2144",
    "sg:postcode":"82729",
    "sg:province":"WY",
    "wof:name":"Bear Lodge High School",
    "wof:placetype":"venue"
},
  "geometry": {"coordinates":[-104.38203900000001,44.40488],"type":"Point"}
}