{
  "type": "Feature",
  "properties": {
    "addr:full":"205 High St Belle Fourche WY 57717",
    "addr:housenumber":"205",
    "addr:postcode":"57717",
    "addr:street":"High St",
    "iso:country":"US",
    "sg:address":"205 High St",
    "sg:city":"Belle Fourche",
    "sg:classifiers":[
        {
            "category":"Shopping",
            "subcategory":"Catalog Store",
            "type":"Retail Goods"
        }
    ],
    "sg:phone":"+1 605 892 0154",
    "sg:postcode":"57717",
    "sg:province":"WY",
    "sg:tags":[
        "mail",
        "retailer",
        "order"
    ],
    "wof:name":"Distrbtor Tr-Ctch Animal Traps",
    "wof:placetype":"venue"
},
  "geometry": {"coordinates":[-103.69713400000001,44.669688],"type":"Point"}
}