{
  "type": "Feature",
  "properties": {
    "iso:country":"US",
    "sg:address":"425 Morgan Ave",
    "sg:city":"Mills",
    "sg:classifiers":[
        {
            "category":"Education",
            "subcategory":"Library",
            "type":"Public Place"
        }
    ],
    "sg:phone":"+1 307 265 6017",
    "sg:postcode":"82644",
    "sg:province":"WY",
    "wof:name":"Mills Library",
    "wof:placetype":"venue"
},
  "geometry": {"coordinates":[-106.371707,42.84119],"type":"Point"}
}