{
  "type": "Feature",
  "properties": {
    "addr:full":"2207 S Douglas Hwy Gillette WY 82718",
    "addr:housenumber":"2207",
    "addr:postcode":"82718",
    "addr:street":"S Douglas Hwy",
    "iso:country":"US",
    "sg:address":"2207 S Douglas Hwy",
    "sg:city":"Gillette",
    "sg:classifiers":[
        {
            "category":"Professional",
            "subcategory":"Business Services",
            "type":"Services"
        },
        {
            "category":"Wholesale",
            "subcategory":"Non-durable Goods",
            "type":"Manufacturing & Wholesale Goods"
        }
    ],
    "sg:phone":"+1 307 682 3474",
    "sg:postcode":"82718",
    "sg:province":"WY",
    "sg:tags":[
        "embroidery"
    ],
    "wof:name":"Fuzzy Feet Monogramming",
    "wof:placetype":"venue"
},
  "geometry": {"coordinates":[-105.493953,44.274409],"type":"Point"}
}