{
  "type": "Feature",
  "properties": {
    "iso:country":"US",
    "sg:address":"1500 Circle Rd",
    "sg:city":"Worland",
    "sg:classifiers":[
        {
            "category":"Organizations",
            "subcategory":"Religious Organization",
            "type":"Services"
        }
    ],
    "sg:phone":"+1 307 347 2266",
    "sg:postcode":"82401",
    "sg:province":"WY",
    "sg:tags":[
        "church"
    ],
    "wof:name":"Zion Lutheran Church",
    "wof:placetype":"venue"
},
  "geometry": {"coordinates":[-107.94511,44.020269],"type":"Point"}
}