{
  "type": "Feature",
  "properties": {
    "iso:country":"US",
    "sg:address":"209 Cherokee Ct",
    "sg:city":"Evanston",
    "sg:classifiers":[
        {
            "category":"Mining & Drilling",
            "type":"Manufacturing & Wholesale Goods"
        }
    ],
    "sg:phone":"+1 307 789 0927",
    "sg:postcode":"82930",
    "sg:province":"WY",
    "sg:tags":[
        "field"
    ],
    "wof:name":"Pro Wireline Inc",
    "wof:placetype":"venue"
},
  "geometry": {"coordinates":[-110.96485800000001,41.255317],"type":"Point"}
}