{
  "type": "Feature",
  "properties": {
    "addr:full":"1856 E Brundage Ln Sheridan WY 82801",
    "addr:housenumber":"1856",
    "addr:postcode":"82801",
    "addr:street":"E Brundage Ln",
    "iso:country":"US",
    "sg:address":"1856 E Brundage Ln",
    "sg:city":"Sheridan",
    "sg:classifiers":[
        {
            "category":"Social Services",
            "subcategory":"Child Care",
            "type":"Services"
        }
    ],
    "sg:phone":"+1 307 673 0688",
    "sg:postcode":"82801",
    "sg:province":"WY",
    "sg:tags":[
        "day"
    ],
    "wof:name":"Monkey House Day Care",
    "wof:placetype":"venue"
},
  "geometry": {"coordinates":[-106.928521,44.772815],"type":"Point"}
}