{
  "type": "Feature",
  "properties": {
    "iso:country":"US",
    "sg:address":"303 S Main St",
    "sg:city":"Sheridan",
    "sg:classifiers":[
        {
            "category":"Social Services",
            "type":"Services"
        }
    ],
    "sg:phone":"+1 307 674 1520",
    "sg:postcode":"82801",
    "sg:province":"WY",
    "sg:tags":[
        "counselor",
        "marriage",
        "family"
    ],
    "wof:name":"Sharyn Siler",
    "wof:placetype":"venue"
},
  "geometry": {"coordinates":[-106.955845,44.794553],"type":"Point"}
}