{
  "type": "Feature",
  "properties": {
    "iso:country":"US",
    "sg:address":"2820 Dillon Ave",
    "sg:city":"Cheyenne",
    "sg:classifiers":[
        {
            "category":"Social Services",
            "subcategory":"Child Care",
            "type":"Services"
        }
    ],
    "sg:phone":"+1 307 638 1342",
    "sg:postcode":"82001",
    "sg:province":"WY",
    "sg:tags":[
        "day"
    ],
    "wof:name":"Grandmas Day Care",
    "wof:placetype":"venue"
},
  "geometry": {"coordinates":[-104.831721,41.140689],"type":"Point"}
}