{
  "type": "Feature",
  "properties": {
    "iso:country":"US",
    "sg:address":"234 E 1st St",
    "sg:city":"Powell",
    "sg:classifiers":[
        {
            "category":"Travel",
            "subcategory":"Hotels & Motels",
            "type":"Entertainment"
        },
        {
            "category":"Restaurant",
            "type":"Food & Drink"
        }
    ],
    "sg:phone":"+1 307 754 2226",
    "sg:postcode":"82435",
    "sg:province":"WY",
    "sg:tags":[
        "drinking",
        "eating",
        "operation"
    ],
    "wof:name":"Lamplighter Inn The",
    "wof:placetype":"venue"
},
  "geometry": {"coordinates":[-108.757104,44.752769],"type":"Point"}
}