{
  "type": "Feature",
  "properties": {
    "iso:country":"US",
    "sg:address":"10929 Hwy 26",
    "sg:city":"Kinnear",
    "sg:classifiers":[
        {
            "category":"Manufacturing",
            "subcategory":"Leather Goods",
            "type":"Manufacturing & Wholesale Goods"
        }
    ],
    "sg:phone":"+1 307 856 6725",
    "sg:postcode":"82516",
    "sg:province":"WY",
    "sg:tags":[
        "harness",
        "buggy",
        "mfg"
    ],
    "wof:name":"Morton Harness & Buggy",
    "wof:placetype":"venue"
},
  "geometry": {"coordinates":[-108.791416,43.207681],"type":"Point"}
}