{
  "type": "Feature",
  "properties": {
    "addr:full":"177 US Hwy 16 Buffalo WY 82834",
    "addr:housenumber":"177",
    "addr:postcode":"82834",
    "addr:street":"Us Hwy 16 Buffalo Wy",
    "iso:country":"US",
    "sg:address":"177 US Hwy 16",
    "sg:city":"Buffalo",
    "sg:classifiers":[
        {
            "category":"Bars & Pubs",
            "type":"Food & Drink"
        }
    ],
    "sg:phone":"+1 307 684 5200",
    "sg:postcode":"82834",
    "sg:province":"WY",
    "wof:name":"Cowboy Saloon",
    "wof:placetype":"venue"
},
  "geometry": {"coordinates":[-106.696534,44.354124],"type":"Point"}
}