{
  "type": "Feature",
  "properties": {
    "iso:country":"US",
    "sg:address":"309 W Lincolnway",
    "sg:city":"Cheyenne",
    "sg:classifiers":[
        {
            "category":"Shopping",
            "subcategory":"Crafts & Fabrics",
            "type":"Retail Goods"
        }
    ],
    "sg:phone":"+1 307 638 2002",
    "sg:postcode":"82001",
    "sg:province":"WY",
    "sg:tags":[
        "sewing",
        "used",
        "merchandise"
    ],
    "sg:website":"www.wyomingquilting.com",
    "wof:name":"Quilted Corner",
    "wof:placetype":"venue"
},
  "geometry": {"coordinates":[-104.817408,41.131875],"type":"Point"}
}