{
  "type": "Feature",
  "properties": {
    "addr:full":"219 Taylor Ave Marbleton WY 83113",
    "addr:housenumber":"219",
    "addr:postcode":"83113",
    "addr:street":"Taylor Ave Marbleton Wy",
    "iso:country":"US",
    "sg:address":"219 Taylor Ave",
    "sg:city":"Marbleton",
    "sg:classifiers":[
        {
            "category":"Building & Trades",
            "subcategory":"Construction",
            "type":"Services"
        }
    ],
    "sg:phone":"+1 307 276 3413",
    "sg:postcode":"83113",
    "sg:province":"WY",
    "sg:tags":[
        "general",
        "contractor"
    ],
    "wof:name":"Eiden Construction LLC",
    "wof:placetype":"venue"
},
  "geometry": {"coordinates":[-110.112551,42.55454],"type":"Point"}
}