{
  "type": "Feature",
  "properties": {
    "addr:full":"237 N Main St Sheridan WY 82801",
    "addr:housenumber":"237",
    "addr:postcode":"82801",
    "addr:street":"N Main St",
    "iso:country":"US",
    "sg:address":"237 N Main St",
    "sg:city":"Sheridan",
    "sg:classifiers":[
        {
            "category":"Insurance",
            "subcategory":"Insurance Agent",
            "type":"Services"
        }
    ],
    "sg:phone":"+1 307 674 6495",
    "sg:postcode":"82801",
    "sg:province":"WY",
    "wof:name":"Allstate",
    "wof:placetype":"venue"
},
  "geometry": {"coordinates":[-106.95568900000001,44.80026],"type":"Point"}
}