{
  "type": "Feature",
  "properties": {
    "iso:country":"US",
    "sg:address":"526 N 16th St E",
    "sg:city":"Riverton",
    "sg:classifiers":[
        {
            "category":"Government",
            "subcategory":"Office",
            "type":"Public Place"
        }
    ],
    "sg:phone":"+1 307 856 9005",
    "sg:postcode":"82501",
    "sg:province":"WY",
    "wof:name":"Game Warden-North Riverton",
    "wof:placetype":"venue"
},
  "geometry": {"coordinates":[-108.371464,43.030077],"type":"Point"}
}