{
  "type": "Feature",
  "properties": {
    "iso:country":"US",
    "sg:address":"45 E Loucks St",
    "sg:city":"Sheridan",
    "sg:classifiers":[
        {
            "category":"Professional",
            "subcategory":"Management & Consulting",
            "type":"Services"
        }
    ],
    "sg:phone":"+1 307 675 1009",
    "sg:postcode":"82801",
    "sg:province":"WY",
    "sg:tags":[
        "consultant",
        "educational"
    ],
    "wof:name":"Mountain States Mathematics",
    "wof:placetype":"venue"
},
  "geometry": {"coordinates":[-106.955327,44.797313],"type":"Point"}
}