{
  "type": "Feature",
  "properties": {
    "iso:country":"US",
    "sg:address":"23 Robinson Ln",
    "sg:city":"Buffalo",
    "sg:classifiers":[
        {
            "category":"Wholesale",
            "subcategory":"Chemicals & Plastics",
            "type":"Manufacturing & Wholesale Goods"
        }
    ],
    "sg:phone":"+1 307 684 9324",
    "sg:postcode":"82834",
    "sg:province":"WY",
    "sg:tags":[
        "oxygen"
    ],
    "wof:name":"Healthco Medical",
    "wof:placetype":"venue"
},
  "geometry": {"coordinates":[-106.707003,44.371286],"type":"Point"}
}