{
  "type": "Feature",
  "properties": {
    "iso:country":"US",
    "sg:address":"87 Meade Creek Rd",
    "sg:city":"Sheridan",
    "sg:classifiers":[
        {
            "category":"Building & Trades",
            "subcategory":"Construction",
            "type":"Services"
        }
    ],
    "sg:phone":"+1 307 673 1242",
    "sg:postcode":"82801",
    "sg:province":"WY",
    "sg:tags":[
        "house"
    ],
    "wof:name":"Hutson Construction",
    "wof:placetype":"venue"
},
  "geometry": {"coordinates":[-106.88493800000001,44.665417],"type":"Point"}
}