{
  "type": "Feature",
  "properties": {
    "iso:country":"US",
    "sg:address":"824 E Cedar St",
    "sg:city":"Rawlins",
    "sg:classifiers":[
        {
            "category":"Mining & Drilling",
            "type":"Manufacturing & Wholesale Goods"
        }
    ],
    "sg:phone":"+1 307 324 5608",
    "sg:postcode":"82301",
    "sg:province":"WY",
    "sg:tags":[
        "oil",
        "gas",
        "producer"
    ],
    "wof:name":"J H Kaspar Oil Co",
    "wof:placetype":"venue"
},
  "geometry": {"coordinates":[-107.227047,41.790454],"type":"Point"}
}