{
  "type": "Feature",
  "properties": {
    "iso:country":"US",
    "sg:address":"1975 E Monroe Ave",
    "sg:city":"Riverton",
    "sg:classifiers":[
        {
            "category":"Retail",
            "subcategory":"Veterinary Services",
            "type":"Services"
        },
        {
            "category":"Retail",
            "subcategory":"Animal Services",
            "type":"Services"
        }
    ],
    "sg:phone":"+1 307 857 1996",
    "sg:postcode":"82501",
    "sg:province":"WY",
    "sg:tags":[
        "veterinarian"
    ],
    "wof:name":"G Bar G Veterinary Services",
    "wof:placetype":"venue"
},
  "geometry": {"coordinates":[-108.36677,43.019438],"type":"Point"}
}