{
  "type": "Feature",
  "properties": {
    "iso:country":"US",
    "sg:address":"9 Juniper Ln",
    "sg:city":"Cody",
    "sg:classifiers":[
        {
            "category":"Professional",
            "subcategory":"Research",
            "type":"Services"
        }
    ],
    "sg:phone":"+1 307 587 1231",
    "sg:postcode":"82414",
    "sg:province":"WY",
    "sg:tags":[
        "development",
        "marketing",
        "product"
    ],
    "wof:name":"Pioneering Concepts Inc",
    "wof:placetype":"venue"
},
  "geometry": {"coordinates":[-109.498963,44.465945],"type":"Point"}
}