{
  "type": "Feature",
  "properties": {
    "iso:country":"US",
    "sg:address":"106 E 2 St",
    "sg:city":"Shoshoni",
    "sg:classifiers":[
        {
            "category":"Government",
            "subcategory":"Fire Station",
            "type":"Public Place"
        }
    ],
    "sg:phone":"+1 307 876 2442",
    "sg:postcode":"82649",
    "sg:province":"WY",
    "sg:tags":[
        "department"
    ],
    "wof:name":"Shoshoni Fire Dept",
    "wof:placetype":"venue"
},
  "geometry": {"coordinates":[-108.10995,43.235447],"type":"Point"}
}