{
  "type": "Feature",
  "properties": {
    "iso:country":"US",
    "sg:address":"1053 McDonald Rd",
    "sg:city":"Cheyenne",
    "sg:classifiers":[
        {
            "category":"Health Services",
            "subcategory":"Health Practitioner",
            "type":"Services"
        }
    ],
    "sg:phone":"+1 307 635 8247",
    "sg:postcode":"82009",
    "sg:province":"WY",
    "wof:name":"Med Care Contracts Inc",
    "wof:placetype":"venue"
},
  "geometry": {"coordinates":[-105.06381399999999,41.149975],"type":"Point"}
}