{
  "type": "Feature",
  "properties": {
    "addr:full":"4058 E Boxelder Rd Gillette WY 82718",
    "addr:housenumber":"4058",
    "addr:postcode":"82718",
    "addr:street":"E Boxelder Rd",
    "iso:country":"US",
    "sg:address":"4058 E Boxelder Rd",
    "sg:city":"Gillette",
    "sg:classifiers":[
        {
            "category":"Shopping",
            "subcategory":"Gifts & Souvenirs",
            "type":"Retail Goods"
        }
    ],
    "sg:phone":"+1 307 685 8251",
    "sg:postcode":"82718",
    "sg:province":"WY",
    "sg:tags":[
        "shop"
    ],
    "wof:name":"Way Out West",
    "wof:placetype":"venue"
},
  "geometry": {"coordinates":[-105.444301,44.27654],"type":"Point"}
}