{
  "type": "Feature",
  "properties": {
    "addr:full":"125 Yellowstone Ave Cody WY 82414",
    "addr:housenumber":"125",
    "addr:postcode":"82414",
    "addr:street":"Yellowstone Ave",
    "iso:country":"US",
    "sg:address":"125 Yellowstone Ave",
    "sg:city":"Cody",
    "sg:classifiers":[
        {
            "category":"Shopping",
            "subcategory":"Bicycles & Sporting Goods",
            "type":"Retail Goods"
        }
    ],
    "sg:phone":"+1 307 527 5470",
    "sg:postcode":"82414",
    "sg:province":"WY",
    "sg:tags":[
        "equipment",
        "outdoor",
        "accessory"
    ],
    "sg:website":"www.hiddencr.com",
    "wof:name":"Hidden Creek Outfitters",
    "wof:placetype":"venue"
},
  "geometry": {"coordinates":[-109.09426000000001,44.515789],"type":"Point"}
}