{
  "type": "Feature",
  "properties": {
    "addr:full":"3291 Alta Vista Rd Torrington WY 82240",
    "addr:housenumber":"3291",
    "addr:postcode":"82240",
    "addr:street":"Alta Vista Rd",
    "iso:country":"US",
    "sg:address":"3291 Alta Vista Rd",
    "sg:city":"Torrington",
    "sg:classifiers":[
        {
            "category":"Farming",
            "subcategory":"Farm & Veterinary Services",
            "type":"Manufacturing & Wholesale Goods"
        }
    ],
    "sg:phone":"+1 307 532 3291",
    "sg:postcode":"82240",
    "sg:province":"WY",
    "sg:tags":[
        "harvesting",
        "crop",
        "beef",
        "feedlot",
        "cattle"
    ],
    "wof:name":"Larry Harvey",
    "wof:placetype":"venue"
},
  "geometry": {"coordinates":[-104.185592,42.078374],"type":"Point"}
}