{
  "type": "Feature",
  "properties": {
    "iso:country":"US",
    "sg:address":"470 Montana Ave",
    "sg:city":"Lovell",
    "sg:classifiers":[
        {
            "category":"Travel",
            "subcategory":"Hotels & Motels",
            "type":"Entertainment"
        }
    ],
    "sg:phone":"+1 307 548 2296",
    "sg:postcode":"82431",
    "sg:province":"WY",
    "wof:name":"Cattlemen Motel",
    "wof:placetype":"venue"
},
  "geometry": {"coordinates":[-108.39146100000001,44.836464],"type":"Point"}
}