{
  "type": "Feature",
  "properties": {
    "iso:country":"US",
    "sg:address":"606 E Collins Dr",
    "sg:city":"Casper",
    "sg:classifiers":[
        {
            "category":"Building & Trades",
            "subcategory":"Plumbing",
            "type":"Services"
        }
    ],
    "sg:phone":"+1 307 261 9985",
    "sg:postcode":"82601",
    "sg:province":"WY",
    "sg:tags":[
        "conditioning",
        "air",
        "system",
        "contractor"
    ],
    "wof:name":"Emerald Tower HVAC",
    "wof:placetype":"venue"
},
  "geometry": {"coordinates":[-106.316785,42.849467],"type":"Point"}
}