{
  "type": "Feature",
  "properties": {
    "iso:country":"US",
    "sg:address":"7880 State Hwy 789",
    "sg:city":"Lander",
    "sg:classifiers":[
        {
            "category":"Building & Trades",
            "subcategory":"Construction",
            "type":"Services"
        }
    ],
    "sg:phone":"+1 307 332 9420",
    "sg:postcode":"82520",
    "sg:province":"WY",
    "sg:tags":[
        "general",
        "contractor"
    ],
    "wof:name":"Federer Brothers Construction",
    "wof:placetype":"venue"
},
  "geometry": {"coordinates":[-108.699793,42.807438],"type":"Point"}
}