{
  "type": "Feature",
  "properties": {
    "addr:full":"635 Broadway St Sheridan WY 82801",
    "addr:housenumber":"635",
    "addr:postcode":"82801",
    "addr:street":"Broadway St",
    "iso:country":"US",
    "sg:address":"635 Broadway St",
    "sg:city":"Sheridan",
    "sg:classifiers":[
        {
            "category":"Home & Garden",
            "subcategory":"Carpets & Floor Coverings",
            "type":"Retail Goods"
        }
    ],
    "sg:phone":"+1 307 673 4833",
    "sg:postcode":"82801",
    "sg:province":"WY",
    "sg:tags":[
        "dealer",
        "rug"
    ],
    "wof:name":"Abbey Carpet Co",
    "wof:placetype":"venue"
},
  "geometry": {"coordinates":[-106.953288,44.804436],"type":"Point"}
}