{
  "type": "Feature",
  "properties": {
    "iso:country":"US",
    "sg:address":"6118 Yellowstone Rd",
    "sg:city":"Cheyenne",
    "sg:classifiers":[
        {
            "category":"Food & Beverages",
            "subcategory":"Groceries & Convenience Stores",
            "type":"Retail Goods"
        }
    ],
    "sg:phone":"+1 307 635 3882",
    "sg:postcode":"82009",
    "sg:province":"WY",
    "sg:tags":[
        "grocer"
    ],
    "wof:name":"Safeway",
    "wof:placetype":"venue"
},
  "geometry": {"coordinates":[-104.828654,41.177111],"type":"Point"}
}