{
  "type": "Feature",
  "properties": {
    "iso:country":"US",
    "sg:address":"11105 US Hwy 20 - 26",
    "sg:city":"Casper",
    "sg:classifiers":[
        {
            "category":"Manufacturing",
            "subcategory":"Metals",
            "type":"Manufacturing & Wholesale Goods"
        }
    ],
    "sg:phone":"+1 307 237 9707",
    "sg:postcode":"82636",
    "sg:province":"WY",
    "sg:tags":[
        "coating"
    ],
    "wof:name":"Miracle Coating & Painting Svc",
    "wof:placetype":"venue"
},
  "geometry": {"coordinates":[-106.116151,42.854282],"type":"Point"}
}