{
  "type": "Feature",
  "properties": {
    "addr:full":"5506 Weaver Rd Cheyenne WY 82009",
    "addr:housenumber":"5506",
    "addr:postcode":"82009",
    "addr:street":"Weaver Rd",
    "iso:country":"US",
    "sg:address":"5506 Weaver Rd",
    "sg:city":"Cheyenne",
    "sg:classifiers":[
        {
            "category":"Recreation",
            "type":"Entertainment"
        }
    ],
    "sg:phone":"+1 307 634 7291",
    "sg:postcode":"82009",
    "sg:province":"WY",
    "sg:tags":[
        "skating",
        "rink"
    ],
    "wof:name":"Roller City Inc",
    "wof:placetype":"venue"
},
  "geometry": {"coordinates":[-104.818628,41.170305],"type":"Point"}
}