{
  "type": "Feature",
  "properties": {
    "iso:country":"US",
    "sg:address":"104 N 1st St",
    "sg:city":"Dubois",
    "sg:classifiers":[
        {
            "category":"Professional",
            "type":"Services"
        }
    ],
    "sg:phone":"+1 307 455 2088",
    "sg:postcode":"82513",
    "sg:province":"WY",
    "sg:tags":[
        "establishment"
    ],
    "wof:name":"Saddle Tramps",
    "wof:placetype":"venue"
},
  "geometry": {"coordinates":[-109.630899,43.534801],"type":"Point"}
}