{
  "type": "Feature",
  "properties": {
    "addr:full":"295 Garfield St Lander WY 82520",
    "addr:housenumber":"295",
    "addr:postcode":"82520",
    "addr:street":"Garfield St Lander Wy",
    "iso:country":"US",
    "sg:address":"295 Garfield St",
    "sg:city":"Lander",
    "sg:classifiers":[
        {
            "category":"Health Services",
            "subcategory":"Doctor",
            "type":"Services"
        }
    ],
    "sg:phone":"+1 307 332 5886",
    "sg:postcode":"82520",
    "sg:province":"WY",
    "sg:tags":[
        "physician",
        "surgeon",
        "medical"
    ],
    "wof:name":"Peter Crane MD",
    "wof:placetype":"venue"
},
  "geometry": {"coordinates":[-108.729697,42.831574],"type":"Point"}
}