{
  "type": "Feature",
  "properties": {
    "iso:country":"US",
    "sg:address":"8212 Blue Sky Dr",
    "sg:city":"Cheyenne",
    "sg:classifiers":[
        {
            "category":"Professional",
            "subcategory":"Management & Consulting",
            "type":"Services"
        }
    ],
    "sg:phone":"+1 307 635 0839",
    "sg:postcode":"82009",
    "sg:province":"WY",
    "wof:name":"Healing Arts Center",
    "wof:placetype":"venue"
},
  "geometry": {"coordinates":[-104.80668300000001,41.193076],"type":"Point"}
}