{
  "type": "Feature",
  "properties": {
    "iso:country":"US",
    "sg:address":"4990 Co Rd 216",
    "sg:city":"Burns",
    "sg:classifiers":[
        {
            "category":"Utilities",
            "subcategory":"Refuse",
            "type":"Services"
        }
    ],
    "sg:phone":"+1 307 547 3791",
    "sg:postcode":"82050",
    "sg:province":"WY",
    "sg:tags":[
        "disposal",
        "waste"
    ],
    "wof:name":"East Laramie County Waste",
    "wof:placetype":"venue"
},
  "geometry": {"coordinates":[-104.331879,41.230569],"type":"Point"}
}