{
  "type": "Feature",
  "properties": {
    "iso:country":"US",
    "sg:address":"530 S Center St",
    "sg:city":"Casper",
    "sg:classifiers":[
        {
            "category":"Insurance",
            "subcategory":"Insurance Agent",
            "type":"Services"
        }
    ],
    "sg:phone":"+1 307 235 4894",
    "sg:postcode":"82601",
    "sg:province":"WY",
    "wof:name":"Insurance-Marketing Assoc",
    "wof:placetype":"venue"
},
  "geometry": {"coordinates":[-106.325255,42.844935],"type":"Point"}
}