{
  "type": "Feature",
  "properties": {
    "addr:full":"1310 Ziebach St Belle Fourche WY 57717",
    "addr:housenumber":"1310",
    "addr:postcode":"57717",
    "addr:street":"Ziebach St;Fourche Wy",
    "iso:country":"US",
    "sg:address":"1310 Ziebach St",
    "sg:city":"Belle Fourche",
    "sg:classifiers":[
        {
            "category":"Health Services",
            "subcategory":"Chiropractor",
            "type":"Services"
        }
    ],
    "sg:phone":"+1 605 892 4845",
    "sg:postcode":"57717",
    "sg:province":"WY",
    "wof:name":"Tri State Chiropractic Center",
    "wof:placetype":"venue"
},
  "geometry": {"coordinates":[-103.845923,44.648126],"type":"Point"}
}