{
  "type": "Feature",
  "properties": {
    "addr:full":"1507 8th St Cody WY 82414",
    "addr:housenumber":"1507",
    "addr:postcode":"82414",
    "addr:street":"8Th St",
    "iso:country":"US",
    "sg:address":"1507 8th St",
    "sg:city":"Cody",
    "sg:classifiers":[
        {
            "category":"Banks & Credit Unions",
            "subcategory":"Investment Brokerage",
            "type":"Services"
        }
    ],
    "sg:phone":"+1 307 587 4748",
    "sg:postcode":"82414",
    "sg:province":"WY",
    "sg:tags":[
        "security"
    ],
    "wof:name":"Raymond James Financial Svc",
    "wof:placetype":"venue"
},
  "geometry": {"coordinates":[-109.071974,44.5216],"type":"Point"}
}