{
  "type": "Feature",
  "properties": {
    "iso:country":"US",
    "sg:address":"812 N 6 St",
    "sg:city":"Lander",
    "sg:classifiers":[
        {
            "category":"Professional",
            "subcategory":"Computer Services",
            "type":"Services"
        }
    ],
    "sg:phone":"+1 307 332 9600",
    "sg:postcode":"82520",
    "sg:province":"WY",
    "sg:tags":[
        "consulting"
    ],
    "wof:name":"Copper Mountain Consulting",
    "wof:placetype":"venue"
},
  "geometry": {"coordinates":[-108.743954,42.827955],"type":"Point"}
}