{
  "type": "Feature",
  "properties": {
    "iso:country":"US",
    "sg:address":"511 E 4th St",
    "sg:city":"Gillette",
    "sg:classifiers":[
        {
            "category":"Banks & Credit Unions",
            "subcategory":"Bank",
            "type":"Services"
        }
    ],
    "sg:phone":"+1 307 682 3112",
    "sg:postcode":"82716",
    "sg:province":"WY",
    "sg:tags":[
        "institution",
        "business"
    ],
    "wof:name":"Cowboy State Bank",
    "wof:placetype":"venue"
},
  "geometry": {"coordinates":[-105.49806,44.291343],"type":"Point"}
}