{
  "type": "Feature",
  "properties": {
    "iso:country":"US",
    "sg:address":"1701 E E St",
    "sg:city":"Casper",
    "sg:classifiers":[
        {
            "category":"Government",
            "subcategory":"Office",
            "type":"Public Place"
        }
    ],
    "sg:phone":"+1 307 261 7600",
    "sg:postcode":"82601",
    "sg:province":"WY",
    "sg:tags":[
        "federal"
    ],
    "wof:name":"US Interior Dept",
    "wof:placetype":"venue"
},
  "geometry": {"coordinates":[-106.304214,42.856986],"type":"Point"}
}