{
  "type": "Feature",
  "properties": {
    "iso:country":"US",
    "sg:address":"11221 US Hwy 30",
    "sg:city":"Cheyenne",
    "sg:classifiers":[
        {
            "category":"Government",
            "subcategory":"Office",
            "type":"Public Place"
        }
    ],
    "sg:phone":"+1 307 772 2314",
    "sg:postcode":"82009",
    "sg:province":"WY",
    "sg:tags":[
        "federal",
        "program"
    ],
    "wof:name":"US Agricultural Dept",
    "wof:placetype":"venue"
},
  "geometry": {"coordinates":[-104.67242299999999,41.159305],"type":"Point"}
}