{
  "type": "Feature",
  "properties": {
    "iso:country":"US",
    "sg:address":"240 S Center St",
    "sg:city":"Casper",
    "sg:classifiers":[
        {
            "category":"Shopping",
            "subcategory":"Bicycles & Sporting Goods",
            "type":"Retail Goods"
        }
    ],
    "sg:phone":"+1 307 234 6905",
    "sg:postcode":"82601",
    "sg:province":"WY",
    "wof:name":"Ugly Bug Fly Shop",
    "wof:placetype":"venue"
},
  "geometry": {"coordinates":[-106.32524100000001,42.847897],"type":"Point"}
}