{
  "type": "Feature",
  "properties": {
    "iso:country":"US",
    "sg:address":"1403 Columbine Ct",
    "sg:city":"Cheyenne",
    "sg:classifiers":[
        {
            "category":"Professional",
            "subcategory":"Business Services",
            "type":"Services"
        }
    ],
    "sg:phone":"+1 307 635 8647",
    "sg:postcode":"82001",
    "sg:province":"WY",
    "wof:name":"Landstrom Enterprises",
    "wof:placetype":"venue"
},
  "geometry": {"coordinates":[-104.75223,41.140414],"type":"Point"}
}