{
  "type": "Feature",
  "properties": {
    "iso:country":"US",
    "sg:address":"105 S 4th St",
    "sg:city":"Laramie",
    "sg:classifiers":[
        {
            "category":"Government",
            "subcategory":"Court House",
            "type":"Public Place"
        }
    ],
    "sg:phone":"+1 307 721 2552",
    "sg:postcode":"82070",
    "sg:province":"WY",
    "sg:tags":[
        "legal"
    ],
    "wof:name":"County Attorney Office",
    "wof:placetype":"venue"
},
  "geometry": {"coordinates":[-105.59202999999999,41.312761],"type":"Point"}
}