{
  "type": "Feature",
  "properties": {
    "addr:full":"51 Coffeen Ave Sheridan WY 82801",
    "addr:housenumber":"51",
    "addr:postcode":"82801",
    "addr:street":"Coffeen Ave",
    "iso:country":"US",
    "sg:address":"51 Coffeen Ave",
    "sg:city":"Sheridan",
    "sg:classifiers":[
        {
            "category":"Insurance",
            "subcategory":"Insurance Agent",
            "type":"Services"
        }
    ],
    "sg:phone":"+1 307 672 9738",
    "sg:postcode":"82801",
    "sg:province":"WY",
    "wof:name":"Equitable Life Assurance",
    "wof:placetype":"venue"
},
  "geometry": {"coordinates":[-106.954837,44.79521],"type":"Point"}
}