{
  "type": "Feature",
  "properties": {
    "iso:country":"US",
    "sg:address":"1116 N Federal Blvd",
    "sg:city":"Riverton",
    "sg:classifiers":[
        {
            "category":"Home & Garden",
            "subcategory":"Garden Supply",
            "type":"Retail Goods"
        }
    ],
    "sg:phone":"+1 307 857 7447",
    "sg:postcode":"82501",
    "sg:province":"WY",
    "wof:name":"Be On Tract",
    "wof:placetype":"venue"
},
  "geometry": {"coordinates":[-108.380661,43.03612],"type":"Point"}
}