{
  "type": "Feature",
  "properties": {
    "iso:country":"US",
    "sg:address":"825 W Snow King Ave",
    "sg:city":"Jackson",
    "sg:classifiers":[
        {
            "category":"Building & Trades",
            "subcategory":"Landscaping Services",
            "type":"Services"
        }
    ],
    "sg:phone":"+1 307 754 9140",
    "sg:postcode":"83001",
    "sg:province":"WY",
    "sg:tags":[
        "tree"
    ],
    "wof:name":"Pineco Tree Svc",
    "wof:placetype":"venue"
},
  "geometry": {"coordinates":[-110.779899,43.470974],"type":"Point"}
}