{
  "type": "Feature",
  "properties": {
    "addr:full":"600 S 12th St Worland WY 82401",
    "addr:housenumber":"600",
    "addr:postcode":"82401",
    "addr:street":"S 12Th St Worland Wy",
    "iso:country":"US",
    "sg:address":"600 S 12th St",
    "sg:city":"Worland",
    "sg:classifiers":[
        {
            "category":"Restaurant",
            "type":"Food & Drink"
        }
    ],
    "sg:phone":"+1 307 347 3436",
    "sg:postcode":"82401",
    "sg:province":"WY",
    "wof:name":"Martinez Mexican Food",
    "wof:placetype":"venue"
},
  "geometry": {"coordinates":[-107.95416299999999,44.011572],"type":"Point"}
}