{
  "type": "Feature",
  "properties": {
    "addr:full":"220 E College Dr Cheyenne WY 82007",
    "addr:housenumber":"220",
    "addr:postcode":"82007",
    "addr:street":"E College Dr",
    "iso:country":"US",
    "sg:address":"220 E College Dr",
    "sg:city":"Cheyenne",
    "sg:classifiers":[
        {
            "category":"Government",
            "subcategory":"Office",
            "type":"Public Place"
        }
    ],
    "sg:phone":"+1 307 637 6440",
    "sg:postcode":"82007",
    "sg:province":"WY",
    "sg:tags":[
        "sanitation"
    ],
    "wof:name":"Dept of Sanitation",
    "wof:placetype":"venue"
},
  "geometry": {"coordinates":[-104.79668599999999,41.102384],"type":"Point"}
}