{
  "type": "Feature",
  "properties": {
    "addr:full":"847 US Hwy 16 Worland WY 82401",
    "addr:housenumber":"847",
    "addr:postcode":"82401",
    "addr:street":"Us Hwy 16 Worland Wy",
    "iso:country":"US",
    "sg:address":"847 US Hwy 16",
    "sg:city":"Worland",
    "sg:classifiers":[
        {
            "category":"Mining & Drilling",
            "type":"Manufacturing & Wholesale Goods"
        }
    ],
    "sg:phone":"+1 307 347 2429",
    "sg:postcode":"82401",
    "sg:province":"WY",
    "sg:tags":[
        "field",
        "oil"
    ],
    "wof:name":"Welchem Inc",
    "wof:placetype":"venue"
},
  "geometry": {"coordinates":[-107.93159,44.06094],"type":"Point"}
}