{
  "type": "Feature",
  "properties": {
    "iso:country":"US",
    "sg:address":"1835 5th Ave",
    "sg:city":"Belle Fourche",
    "sg:classifiers":[
        {
            "category":"Government",
            "subcategory":"Office",
            "type":"Public Place"
        }
    ],
    "sg:phone":"+1 605 892 3368",
    "sg:postcode":"57717",
    "sg:province":"WY",
    "sg:tags":[
        "conservation"
    ],
    "wof:name":"Belle Fourche Field Office",
    "wof:placetype":"venue"
},
  "geometry": {"coordinates":[-103.85539300000001,44.659691],"type":"Point"}
}