{
  "type": "Feature",
  "properties": {
    "iso:country":"US",
    "sg:address":"1131 Collins Dr",
    "sg:city":"Casper",
    "sg:classifiers":[
        {
            "category":"Personal",
            "subcategory":"Beauty Salon",
            "type":"Services"
        }
    ],
    "sg:phone":"+1 307 265 1004",
    "sg:postcode":"82604",
    "sg:province":"WY",
    "sg:tags":[
        "shop"
    ],
    "wof:name":"Main Attraction",
    "wof:placetype":"venue"
},
  "geometry": {"coordinates":[-106.344038,42.838611],"type":"Point"}
}